Workbook

Sheet Income Statement
A1: Avery Dennison Corp (AVY US) - BBG Adjusted | B1: FY 2018 | C1: FY 2019 | D1: FY 2020 | E1: FY 2021 | F1: FY 2022 | G1: FY 2023 | H1: FY 2024
A2: In Millions of USD except Per Share
A3: 12 Months Ending | B3: 12/29/2018 | C3: 12/28/2019 | D3: 12/31/2020 | E3: 12/31/2021 | F3: 12/31/2022 | G3: 12/30/2023 | H3: 12/28/2024
A4: Revenue | B4: 7159 | C4: 7070.1 | D4: 6971.5 | E4: 8408.3 | F4: 9039.3 | G4: 8364.3 | H4: 8755.7
A5: Revenue Growth (%) | C5: =C4/B4-1 -> -0.012417935 | D5: =D4/C4-1 -> -0.013946055 | E5: =E4/D4-1 -> 0.20609625 | F5: =F4/E4-1 -> 0.075044896 | G5: =G4/F4-1 -> -0.074673924 | H5: =H4/G4-1 -> 0.046794113
A6: + Sales & Services Revenue | B6: 7159 | C6: 7070.1 | D6: 6971.5 | E6: 8408.3 | F6: 9039.3 | G6: 8364.3 | H6: 8755.7
A7: - Cost of Revenue | B7: 5243.5 | C7: 5166 | D7: 5048.2 | E7: 6095.5 | F7: 6635.1 | G7: 6086.8 | H7: 6225
A8: + Cost of Goods & Services | B8: 5243.5 | C8: 5166 | D8: 5048.2 | E8: 6095.5 | F8: 6635.1 | G8: 6086.8 | H8: 6225 | J8: Growth Rates & Margins | K8: =B1 -> FY 2018 | L8: =C1 -> FY 2019 | M8: =D1 -> FY 2020 | N8: =E1 -> FY 2021 | O8: =F1 -> FY 2022 | P8: =G1 -> FY 2023 | Q8: =H1 -> FY 2024 | R8: Average
A9: Gross Profit | B9: 1915.5 | C9: 1904.1 | D9: 1923.3 | E9: 2312.8 | F9: 2404.2 | G9: 2277.5 | H9: 2530.7 | J9: =A5 -> Revenue Growth (%) | L9: =C5 -> -0.012417935 | M9: =D5 -> -0.013946055 | N9: =E5 -> 0.20609625 | O9: =F5 -> 0.075044896 | P9: =G5 -> -0.074673924 | Q9: =H5 -> 0.046794113 | R9: =AVERAGE(Table8[[#This Row],[Column3]:[Column8]]) -> 0.037816224
A10: Gross Profit Margin (%) | B10: =B9/B4 -> 0.2675653 | C10: =C9/C4 -> 0.26931727 | D10: =D9/D4 -> 0.27588037 | E10: =E9/E4 -> 0.27506155 | F10: =F9/F4 -> 0.26597192 | G10: =G9/G4 -> 0.27228818 | H10: =H9/H4 -> 0.28903457 | J10: =A47 -> Net Profit Margin (%) | K10: =B47 -> 0.065288448 | L10: =C47 -> 0.042941401 | M10: =D47 -> 0.079738937 | N10: =E47 -> 0.088020171 | O10: =F47 -> 0.083756486 | P10: =G47 -> 0.060136533 | Q10: =H47 -> 0.080507555 | R10: =AVERAGE(Table8[[#This Row],[Column2]:[Column8]]) -> 0.071484219
A11: + Other Operating Income | B11: 0 | C11: 0 | D11: 0 | E11: 0 | F11: 0 | G11: 0 | H11: 0 | J11: =A69 -> EBITDA Margin (%) | K11: =B69 -> 0.135354 | L11: =C69 -> 0.151073 | M11: =D69 -> 0.163107 | N11: =E69 -> 0.166764 | O11: =F69 -> 0.160234 | P11: =G69 -> 0.155948 | Q11: =H69 -> 0.170198 | R11: =AVERAGE(Table8[[#This Row],[Column2]:[Column8]]) -> 0.15752543
A12: - Operating Expenses | B12: 1127.5 | C12: 1080.4 | D12: 1054.6 | E12: 1223.5 | F12: 1317.3 | G12: 1345.1 | H12: 1427.8 | J12: EBIT Margin (%) | K12: =B72 -> 0.11007124 | L12: =C72 -> 0.11650472 | M12: =D72 -> 0.12460733 | N12: =E72 -> 0.12955056 | O12: =F72 -> 0.12024161 | P12: =G72 -> 0.11147376 | Q12: =H72 -> 0.12596366 | R12: =AVERAGE(Table8[[#This Row],[Column2]:[Column8]]) -> 0.11977327
A13: + Selling, General & Admin | B13: 1029.3 | C13: 987.8 | D13: 947.7 | E13: 1111.9 | F13: 1194.7 | G13: 1177.9 | H13: 1277.5 | J13: Depreciation (% of Revenue) | K13: =B81 -> 0.01976533 | L13: =C81 -> 0.019844132 | M13: =D81 -> 0.022118626 | N13: =E81 -> 0.019897007 | O13: =F81 -> 0.019625413 | P13: =G81 -> 0.022404744 | Q13: =H81 -> 0.02251105 | R13: =AVERAGE(Table8[[#This Row],[Column6]:[Column8]]) -> 0.021513736
A14: + Research & Development | B14: 98.2 | C14: 92.6 | D14: 112.8 | E14: 136.6 | F14: 136.1 | G14: 135.8 | H14: 137.8
A15: + Other Operating Expense | B15: 0 | C15: 0 | D15: -5.9 | E15: -25 | F15: -13.5 | G15: 31.4 | H15: 12.5
A16: Operating Income (Loss) | B16: 788 | C16: 823.7 | D16: 868.7 | E16: 1089.3 | F16: 1086.9 | G16: 932.4 | H16: 1102.9
A17: - Non-Operating (Income) Loss | B17: 69.6 | C17: 76.9 | D17: 77.3 | E17: 89.1 | F17: 88.2 | G17: 88.2 | H17: 71.1
A18: + Interest Expense, Net | B18: 58.5 | C18: 75.8 | D18: 70 | E18: 70.2 | F18: 84.1 | G18: 119 | H18: 117
A19: + Interest Expense | B19: 58.5 | C19: 75.8 | D19: 70 | E19: 70.2 | F19: 84.1 | G19: 119 | H19: 117
A20: - Interest Income | B20: 0 | C20: 0 | D20: 0 | E20: 0 | F20: 0 | G20: 0 | H20: 0
A21: + Foreign Exch (Gain) Loss | B21: 0 | C21: 0 | D21: 0 | E21: 0 | F21: 0 | G21: 0 | H21: 0
A22: + Other Non-Op (Income) Loss | B22: 11.1 | C22: 1.1 | D22: 7.3 | E22: 18.9 | F22: 4.1 | G22: -30.8 | H22: -45.9
A23: Pretax Income (Loss), Adjusted | B23: 718.4 | C23: 746.8 | D23: 791.4 | E23: 1000.2 | F23: 998.7 | G23: 844.2 | H23: 1031.8
A24: - Abnormal Losses (Gains) | B24: 163.6 | C24: 497.3 | D24: 54.1 | E24: 7.6 | F24: -0.6 | G24: 149.5 | H24: 78.3
A25: + Merger/Acquisition Expense | B25: -1.6 | C25: 2.6 | D25: 4.2 | E25: 20.9 | F25: 0.3 | G25: 5.3 | H25: 0.3
A26: + Abnormal Derivatives | B26: — | C26: — | D26: — | E26: — | F26: — | G26: — | H26: 16.4
A27: + Disposal of Assets | B27: -2.7 | C27: -3.2 | D27: -0.5 | E27: 0.2 | F27: -1.4 | G27: 0.5 | H27: —
A28: + Asset Write-Down | B28: 10.7 | C28: — | D28: — | E28: — | F28: — | G28: 8.6 | H28: 6.5
A29: + Impairment of Intangibles | B29: — | C29: — | D29: — | E29: — | F29: — | G29: — | H29: —
A30: + Gain/Loss on Sale/Acquisition of Business | B30: — | C30: — | D30: — | E30: -5.7 | F30: — | G30: — | H30: —
A31: + Legal Settlement | B31: — | C31: 3.4 | D31: — | E31: — | F31: 6.3 | G31: 64.3 | H31: 0.5
A32: + Restructuring | B32: 63.5 | C32: 45.3 | D32: 49.1 | E32: 10.5 | F32: 7.6 | G32: 70.8 | H32: 35.4
A33: + Sale of Investments | B33: — | C33: — | D33: -5.4 | E33: -23 | F33: -13.5 | G33: — | H33: 19.2
A34: + Other Abnormal Items | B34: 104.4 | C34: 449.2 | D34: 6.7 | E34: 4.7 | F34: 0.1 | G34: — | H34: —
A35: Pretax Income (Loss), GAAP | B35: 554.8 | C35: 249.5 | D35: 737.3 | E35: 992.6 | F35: 999.3 | G35: 694.7 | H35: 953.5
A36: - Income Tax Expense (Benefit) | B36: 85.4 | C36: -56.7 | D36: 177.7 | E36: 248.6 | F36: 242.2 | G36: 191.7 | H36: 248.6
A37: + Current Income Tax | B37: 115.4 | C37: 159.6 | D37: 171.5 | E37: 242.5 | F37: 215.9 | G37: 212.3 | H37: 261.5
A38: + Deferred Income Tax | B38: -30 | C38: -216.3 | D38: 6.2 | E38: 6.1 | F38: 26.3 | G38: -20.6 | H38: -12.9
A39: - (Income) Loss from Affiliates | B39: 2 | C39: 2.6 | D39: 3.7 | E39: 3.9 | F39: 0 | G39: 0 | H39: 0
A40: Income (Loss) from Cont Ops | B40: 467.4 | C40: 303.6 | D40: 555.9 | E40: 740.1 | F40: 757.1 | G40: 503 | H40: 704.9
A41: - Net Extraordinary Losses (Gains) | B41: 0 | C41: 0 | D41: 0 | E41: 0 | F41: 0 | G41: 0 | H41: 0
A42: + Discontinued Operations | B42: 0 | C42: 0 | D42: 0 | E42: 0 | F42: 0 | G42: 0 | H42: 0
A43: + XO & Accounting Changes | B43: 0 | C43: 0 | D43: 0 | E43: 0 | F43: 0 | G43: 0 | H43: 0
A44: Income (Loss) Incl. MI | B44: 467.4 | C44: 303.6 | D44: 555.9 | E44: 740.1 | F44: 757.1 | G44: 503 | H44: 704.9
A45: - Minority Interest | B45: 0 | C45: 0 | D45: 0 | E45: 0 | F45: 0 | G45: 0 | H45: 0
A46: Net Income, GAAP | B46: 467.4 | C46: 303.6 | D46: 555.9 | E46: 740.1 | F46: 757.1 | G46: 503 | H46: 704.9
A47: Net Profit Margin (%) | B47: =B46/B4 -> 0.065288448 | C47: =C46/C4 -> 0.042941401 | D47: =D46/D4 -> 0.079738937 | E47: =E46/E4 -> 0.088020171 | F47: =F46/F4 -> 0.083756486 | G47: =G46/G4 -> 0.060136533 | H47: =H46/H4 -> 0.080507555
A48: - Preferred Dividends | B48: 0 | C48: 0 | D48: 0 | E48: 0 | F48: 0 | G48: 0 | H48: 0
A49: - Other Adjustments | B49: 0 | C49: 0 | D49: 0 | E49: 0 | F49: 0 | G49: 0 | H49: 0
A50: Net Income Avail to Common, GAAP | B50: 467.4 | C50: 303.6 | D50: 555.9 | E50: 740.1 | F50: 757.1 | G50: 503 | H50: 704.9
A52: Net Income Avail to Common, Adj | B52: 522.868 | C52: 648.567 | D52: 592.207 | E52: 745.584 | F52: 752.4 | G52: 590.005 | H52: 749.057
A53: Net Abnormal Losses (Gains) | B53: 55.468 | C53: 344.967 | D53: 36.307 | E53: 5.484 | F53: -4.7 | G53: 87.005 | H53: 44.157
A54: Net Extraordinary Losses (Gains) | B54: 0 | C54: 0 | D54: 0 | E54: 0 | F54: 0 | G54: 0 | H54: 0
A56: Basic Weighted Avg Shares | B56: 87.3 | C56: 84 | D56: 83.4 | E56: 82.9 | F56: 81.6 | G56: 80.7 | H56: 80.4
A57: Basic EPS, GAAP | B57: 5.35 | C57: 3.61 | D57: 6.67 | E57: 8.93 | F57: 9.28 | G57: 6.23 | H57: 8.77
A58: Basic EPS from Cont Ops, GAAP | B58: 5.35 | C58: 3.61 | D58: 6.67 | E58: 8.93 | F58: 9.28 | G58: 6.23 | H58: 8.77
A59: Basic EPS from Cont Ops, Adjusted | B59: 5.9893 | C59: 7.721 | D59: 7.1008 | E59: 8.9938 | F59: 9.2206 | G59: 7.3111 | H59: 9.3166
A61: Diluted Weighted Avg Shares | B61: 88.6 | C61: 85 | D61: 84.1 | E61: 83.8 | F61: 82.2 | G61: 81.1 | H61: 80.7
A62: Diluted EPS, GAAP | B62: 5.28 | C62: 3.57 | D62: 6.61 | E62: 8.83 | F62: 9.21 | G62: 6.2 | H62: 8.73
... A64: Diluted EPS from Cont Ops, Adjusted | B64: 5.906 | C64: 7.6284 | D64: 7.0417 | E64: 8.8954 | F64: 9.1528 | G64: 7.2728 | H64: 9.2772
A66: Reference Items
A67: Accounting Standard | B67: US GAAP | C67: US GAAP | D67: US GAAP | E67: US GAAP | F67: US GAAP | G67: US GAAP | H67: US GAAP
A68: EBITDA | B68: 969 | C68: 1068.1 | D68: 1137.1 | E68: 1402.2 | F68: 1448.4 | G68: 1304.4 | H68: 1490.2
A69: EBITDA Margin (%) | B69: 0.135354 | C69: 0.151073 | D69: 0.163107 | E69: 0.166764 | F69: 0.160234 | G69: 0.155948 | H69: 0.170198
A70: EBITA | B70: 827.5 | C70: 927.8 | D70: 982.9 | E70: 1234.9 | F70: 1271 | G70: 1117 | H70: 1293.1
A71: EBIT | B71: 788 | C71: 823.7 | D71: 868.7 | E71: 1089.3 | F71: 1086.9 | G71: 932.4 | H71: 1102.9
A72: EBIT Margin (%) (Operating Margin) | B72: =B71/B4 -> 0.11007124 | C72: =C71/C4 -> 0.11650472 | D72: =D71/D4 -> 0.12460733 | E72: =E71/E4 -> 0.12955056 | F72: =F71/F4 -> 0.12024161 | G72: =G71/G4 -> 0.11147376 | H72: =H71/H4 -> 0.12596366
A73: Gross Margin | B73: 26.7565 | C73: 26.9317 | D73: 27.588 | E73: 27.5062 | F73: 26.5972 | G73: 27.2288 | H73: 28.9035
A74: Operating Margin | B74: 11.0071 | C74: 11.6505 | D74: 12.4607 | E74: 12.9551 | F74: 12.0242 | G74: 11.1474 | H74: 12.5964
A75: Profit Margin | B75: 7.3036 | C75: 9.1734 | D75: 8.4947 | E75: 8.8672 | F75: 8.3237 | G75: 7.0538 | H75: 8.5551
A76: Sales per Employee | B76: 223718.75 | C76: 220940.62 | D76: 217859.38 | E76: 233563.89 | F76: 251091.67 | G76: 238980 | H76: 250162.86
A77: Dividends per Share | B77: 2.01 | C77: 2.26 | D77: 2.36 | E77: 2.66 | F77: 2.93 | G77: 3.18 | H77: 3.45
A78: Total Cash Common Dividends | B78: 175.473 | C78: 189.84 | D78: 196.824 | E78: 220.514 | F78: 239.088 | G78: 256.626 | H78: 277.38
A79: Capitalized Interest Expense | B79: — | C79: — | D79: — | E79: — | F79: — | G79: — | H79: —
A80: Depreciation Expense | B80: 141.5 | C80: 140.3 | D80: 154.2 | E80: 167.3 | F80: 177.4 | G80: 187.4 | H80: 197.1
A81: Depreciation (% of Revenue) | B81: =B80/B4 -> 0.01976533 | C81: =C80/C4 -> 0.019844132 | D81: =D80/D4 -> 0.022118626 | E81: =E80/E4 -> 0.019897007 | F81: =F80/F4 -> 0.019625413 | G81: =G80/G4 -> 0.022404744 | H81: =H80/H4 -> 0.02251105
A82: Rental Expense | B82: 66 | C82: 65.4 | D82: 63.1 | E82: 68.8 | F82: 70.8 | G82: 73.6 | H82: 75.1

Sheet Balance Sheet
A1: Avery Dennison Corp (AVY US) - Standardized | C1: FY 2015 | D1: FY 2016 | E1: FY 2017 | F1: FY 2018 | G1: FY 2019 | H1: FY 2020 | I1: FY 2021 | J1: FY 2022 | K1: FY 2023 | L1: FY 2024
A2: In Millions of USD except Per Share
A3: 12 Months Ending | C3: 01/02/2016 | D3: 12/31/2016 | E3: 12/30/2017 | F3: 12/29/2018 | G3: 12/28/2019 | H3: 12/31/2020 | I3: 12/31/2021 | J3: 12/31/2022 | K3: 12/30/2023 | L3: 12/28/2024
A5: Total Assets
A6: + Cash, Cash Equivalents & STI | B6: CASH_CASH_EQTY_STI_DETAILED | C6: 158.8 | D6: 195.1 | E6: 224.4 | F6: 232 | G6: 253.7 | H6: 252.3 | I6: 162.7 | J6: 167.2 | K6: 215 | L6: 329.1 | N6: Working Capital Efficiency Analysis | O6: FY 2018 | P6: FY 2019 | Q6: FY 2020 | R6: FY 2021 | S6: FY 2022 | T6: FY 2023 | U6: FY 2024
A7: + Cash & Cash Equivalents | B7: BS_CASH_NEAR_CASH_ITEM | C7: 158.8 | D7: 195.1 | E7: 224.4 | F7: 232 | G7: 253.7 | H7: 252.3 | I7: 162.7 | J7: 167.2 | K7: 215 | L7: 329.1 | N7: Days Sales Outstanding (DSO) (How Quickly Avery Collects Cash) | O7: =F14/'Income Statement'!B9*365 -> 37.481336 | P7: =G14/'Income Statement'!C9*365 -> 38.530014 | Q7: =H14/'Income Statement'!D9*365 -> 39.91031 | R7: =I14/'Income Statement'!E9*365 -> 36.787228 | S7: =J14/'Income Statement'!F9*365 -> 38.728683 | T7: =K14/'Income Statement'!G9*365 -> 38.174753 | U7: =L14/'Income Statement'!H9*365 -> 32.437073
A8: + ST Investments | B8: BS_MKT_SEC_OTHER_ST_INVEST | C8: 0 | D8: 0 | E8: 0 | F8: 0 | G8: 0 | H8: 0 | I8: 0 | J8: 0 | K8: 0 | L8: 0 | N8: Days Payable Outstanding (DPO) (How long does Avery takes to pay suppliers) | O8: =F46/'Income Statement'!B13*365 -> 2.0921986 | P8: =G46/'Income Statement'!C13*365 -> 16.960417 | Q8: =H46/'Income Statement'!D13*365 -> 19.218635 | R8: =I46/'Income Statement'!E13*365 -> 17.332494 | S8: =J46/'Income Statement'!F13*365 -> 14.603666 | T8: =K46/'Income Statement'!G13*365 -> 16.02046 | U8: =L46/'Income Statement'!H13*365 -> 15.4
A9: + Accounts & Notes Receiv | B9: BS_ACCT_NOTE_RCV | C9: 964.7 | D9: 1001 | E9: 1180.3 | F9: 1189.7 | G9: 1212.2 | H9: 1235.2 | I9: 1424.5 | J9: 1374.4 | K9: 1414.9 | L9: 1466.2
A10: + Accounts Receivable, Net | B10: BS_ACCTS_REC_EXCL_NOTES_REC | C10: 964.7 | D10: 1001 | E10: 1180.3 | F10: 1189.7 | G10: 1212.2 | H10: 1235.2 | I10: 1424.5 | J10: 1374.4 | K10: 1414.9 | L10: 1466.2
A11: + Notes Receivable, Net | B11: NOTES_RECEIVABLE | C11: 0 | D11: 0 | E11: 0 | F11: 0 | G11: 0 | H11: 0 | I11: 0 | J11: 0 | K11: 0 | L11: 0 | N11: Debt and Leverage Analysis | O11: FY 2018 | P11: FY 2019 | Q11: FY 2020 | R11: FY 2021 | S11: FY 2022 | T11: FY 2023 | U11: FY 2024
A12: + Inventories | B12: BS_INVENTORIES | C12: 478.7 | D12: 519.1 | E12: 609.6 | F12: 651.4 | G12: 663 | H12: 717.2 | I12: 907.2 | J12: 1009.9 | K12: 920.7 | L12: 978.1 | N12: Debt to Equity Ratio | O12: 2.0586326 | P12: 1.7274086 | Q12: 1.5335039 | R12: 1.7082207 | S12: 1.6032379 | T12: 1.6175572 | U12: 1.4608399
A13: + Raw Materials | B13: INVTRY_RAW_MATERIALS | C13: 180.5 | D13: 185 | E13: 214.6 | F13: 236.2 | G13: 231.6 | H13: 268.6 | I13: 393.6 | J13: 457.6 | K13: 415.4 | L13: 435 | N13: Debt to Asset Ratio | O13: 0.37975857 | P13: 0.37891707 | Q13: 0.37428294 | R13: 0.41237644 | S13: 0.40979813 | T13: 0.41925504 | U13: 0.40192999
A14: + Work In Process | B14: INVTRY_IN_PROGRESS | C14: 143 | D14: 156.8 | E14: 179.8 | F14: 196.7 | G14: 201 | H14: 210.3 | I14: 233.1 | J14: 255.1 | K14: 238.2 | L14: 224.9 | N14: Interest Coverage Ratio | O14: 13.470085 | P14: 10.866755 | Q14: 12.41 | R14: 15.517094 | S14: 12.9239 | T14: 7.8352941 | U14: 9.4264957
A15: + Finished Goods | B15: INVTRY_FINISHED_GOODS | C15: 155.2 | D15: 177.3 | E15: 215.2 | F15: 218.5 | G15: 230.4 | H15: 238.3 | I15: 280.5 | J15: 297.2 | K15: 267.1 | L15: 318.2
A16: + Other Inventory | B16: BS_OTHER_INV | C16: 0 | D16: 0 | E16: 0 | F16: 0 | G16: 0 | H16: 0 | I16: 0 | J16: 0 | K16: 0 | L16: 0
A17: + Other ST Assets | B17: OTHER_CURRENT_ASSETS_DETAILED | C17: 173.2 | D17: 189.6 | E17: 223.6 | F17: 228.5 | G17: 211.7 | H17: 211.5 | I17: 240.2 | J17: 230.5 | K17: 245.4 | L17: 305.3
A18: + Derivative & Hedging Assets | B18: BS_DERIV_HEDGING_ASST_ST | C18: 5.6 | D18: 5.1 | E18: 0.4 | F18: 0.6 | G18: 5.2 | H18: 5.2 | I18: 6.3 | J18: 4.3 | K18: 6.3 | L18: 11.9
A19: + Assets Held-for-Sale | B19: BS_ASSETS_HELD_FOR_SALE_ST | C19: 2.5 | D19: 6.8 | E19: 6.3 | F19: 3.6 | G19: — | H19: — | I19: — | J19: — | K19: — | L19: —
A20: + Deferred Tax Assets | B20: BS_DEFERRED_TAX_ASSETS_ST | C20: 30.9 | D20: 30.3 | E20: 28.9 | F20: — | G20: — | H20: — | I20: — | J20: — | K20: — | L20: —
A21: + Misc ST Assets | B21: BS_OTHER_CUR_ASSET_LESS_PREPAY | C21: 134.2 | D21: 147.4 | E21: 188 | F21: 224.3 | G21: 206.5 | H21: 206.3 | I21: 233.9 | J21: 226.2 | K21: 239.1 | L21: 293.4
A22: Total Current Assets | B22: BS_CUR_ASSET_REPORT | C22: 1775.4 | D22: 1904.8 | E22: 2237.9 | F22: 2298 | G22: 2340.6 | H22: 2416.2 | I22: 2734.6 | J22: 2782 | K22: 2796 | L22: 3078.7
A23: + Property, Plant & Equip, Net | B23: BS_NET_FIX_ASSET | C23: 847.9 | D23: 915.2 | E23: 1097.9 | F23: 1137.4 | G23: 1348.8 | H23: 1505 | I23: 1660.7 | J23: 1701.9 | K23: 1826 | L23: 1814.2
A24: + Property, Plant & Equip | B24: BS_GROSS_FIX_ASSET | C24: 2599.9 | D24: 2661.4 | E24: 3000.9 | F24: 3053.7 | G24: 3309.7 | H24: 3637.6 | I24: 3809.2 | J24: 3909.4 | K24: 4170.6 | L24: 4221
A25: - Accumulated Depreciation | B25: BS_ACCUM_DEPR | C25: 1752 | D25: 1746.2 | E25: 1903 | F25: 1916.3 | G25: 1960.9 | H25: 2132.6 | I25: 2148.5 | J25: 2207.5 | K25: 2344.6 | L25: 2406.8
A26: + LT Investments & Receivables | B26: BS_LT_INVEST | C26: 0 | D26: 0 | E26: 0 | F26: 0 | G26: 0 | H26: 0 | I26: 0 | J26: 0 | K26: 0 | L26: 0
A27: + Other LT Assets | B27: BS_OTHER_ASSETS_DEF_CHRG_OTHER | C27: 1510.4 | D27: 1576.4 | E27: 1801.1 | F27: 1742.1 | G27: 1799.4 | H27: 2162.7 | I27: 3576.3 | J27: 3466.6 | K27: 3587.8 | L27: 3511.3
A28: + Total Intangible Assets | B28: BS_DISCLOSED_INTANGIBLES | C28: 732 | D28: 860.3 | E28: 1151.4 | F28: 1085.8 | G28: 1057.3 | H28: 1361.3 | I28: 2792.9 | J28: 2702.7 | K28: 2862.7 | L28: 2731.5
A29: + Goodwill | B29: BS_GOODWILL | C29: 686.2 | D29: 793.6 | E29: 985.1 | F29: 941.8 | G29: 930.8 | H29: 1136.4 | I29: 1881.5 | J29: 1862.4 | K29: 2013.6 | L29: 1976.2 | N29: Change in Net Working Capital (% of Revenue)
A30: + Other Intangible Assets | B30: OTHER_INTANGIBLE_ASSETS_DETAILED | C30: 45.8 | D30: 66.7 | E30: 166.3 | F30: 144 | G30: 126.5 | H30: 224.9 | I30: 911.4 | J30: 840.3 | K30: 849.1 | L30: 755.3 | N30: Change in Net Working Capital (% of Revenue) | O30: FY 2018 | P30: FY 2019 | Q30: FY 2020 | R30: FY 2021 | S30: FY 2022 | T30: FY 2023 | U30: FY 2024 | V30: Average
A31: + Deferred Tax Assets | B31: BS_DEFERRED_TAX_ASSETS_LT | C31: 372.2 | D31: 313.2 | E31: 196.3 | F31: 205.3 | G31: 225.4 | H31: 197.7 | I31: 130.2 | J31: 115.1 | K31: 115.7 | L31: 110 | N31: Operating Current Assets | O31: 2065.4 | P31: 2081.7 | Q31: 2158.7 | R31: 2565.6 | S31: 2610.5 | T31: 2574.7 | U31: 2737.7
A32: + Derivative & Hedging Assets | B32: BS_DERIV_HEDGING_ASST_LT | C32: 0 | D32: 0.1 | E32: 0 | F32: 0 | G32: 0 | H32: 0 | I32: 0 | J32: 0 | K32: 0 | L32: 0 | N32: Operating Current Liabilities | O32: 1798.6 | P32: 1767.1 | Q32: 1808.5 | R32: 2178.9 | S32: 2149 | T32: 2025.9 | U32: 2216.5
A33: + Prepaid Pension Costs | B33: BS_PREPAID_PENSION_COSTS_LT | C33: — | D33: — | E33: — | F33: 12.6 | G33: 50.8 | H33: 92.4 | I33: 113.6 | J33: 70 | K33: 67.8 | L33: 84.7 | N33: NWC [(OpCA) - (OpCL)] | O33: 266.8 | P33: 314.6 | Q33: 350.2 | R33: 386.7 | S33: 461.5 | T33: 548.8 | U33: 521.2
A34: + Investments in Affiliates | B34: BS_INVEST_IN_ASSOC_CO | C34: — | D34: — | E34: 9.1 | F34: 6.7 | G34: 8.8 | H34: 5.3 | I34: — | J34: — | K34: — | L34: — | N34: ΔNWC = NWCₜ – NWCₜ₋₁ | P34: 47.8 | Q34: 35.6 | R34: 36.5 | S34: 74.8 | T34: 87.3 | U34: -27.6
A35: + Misc LT Assets | B35: OTHER_NONCURRENT_ASSETS_DETAILED | C35: 406.2 | D35: 402.8 | E35: 444.3 | F35: 431.7 | G35: 457.1 | H35: 506 | I35: 539.6 | J35: 578.8 | K35: 541.6 | L35: 585.1 | N35: ΔNWC (% of Revenue) | P35: 0.0066769102 | Q35: 0.0050352895 | R35: 0.0052356021 | S35: 0.0088959718 | T35: 0.0096578275 | U35: -0.0032997382 | V35: 0.0050846871
A36: Total Noncurrent Assets | B36: BS_TOT_NON_CUR_ASSET | C36: 2358.3 | D36: 2491.6 | E36: 2899 | F36: 2879.5 | G36: 3148.2 | H36: 3667.7 | I36: 5237 | J36: 5168.5 | K36: 5413.8 | L36: 5325.5
A37: Total Assets | B37: BS_TOT_ASSET | C37: 4133.7 | D37: 4396.4 | E37: 5136.9 | F37: 5177.5 | G37: 5488.8 | H37: 6083.9 | I37: 7971.6 | J37: 7950.5 | K37: 8209.8 | L37: 8404.2
N38: Effective Tax Rate (%)
A39: Liabilities & Shareholders' Equity | N39: Year | O39: FY 2018 | P39: FY 2019 | Q39: FY 2020 | R39: FY 2021 | S39: FY 2022 | T39: FY 2023 | U39: FY 2024 | V39: Average
A40: + Payables & Accruals | B40: ACCT_PAYABLE_ACCRUALS_DETAILED | C40: 1134.5 | D40: 1184.6 | E40: 1416.6 | F40: 1435.5 | G40: 1485.2 | H40: 1507.9 | I40: 1846.1 | J40: 1808 | K40: 1684.5 | L40: 1858 | N40: Income Tax Expense | O40: 85.4 | P40: -56.7 | Q40: 177.7 | R40: 248.6 | S40: 242.2 | T40: 191.7 | U40: 248.6
A41: + Accounts Payable | B41: BS_ACCT_PAYABLE | C41: 814.6 | D41: 841.9 | E41: 1007.2 | F41: 1030.5 | G41: 1066.1 | H41: 1050.9 | I41: 1298.8 | J41: 1339.3 | K41: 1277.1 | L41: 1340.7 | N41: Pretax Income | O41: 554.8 | P41: 249.5 | Q41: 737.3 | R41: 992.6 | S41: 999.3 | T41: 694.7 | U41: 953.5
A42: + Accrued Taxes | B42: BS_TAXES_PAYABLE | C42: 45.1 | D42: 37.9 | E42: 49.2 | F42: 58.1 | G42: 71.4 | H42: 86.3 | I42: 74.9 | J42: 76.2 | K42: 57.6 | L42: 74.7 | N42: Effective Tax Rate (%) | O42: 0.15392934 | P42: -0.22725451 | Q42: 0.24101451 | R42: 0.25045335 | S42: 0.24236966 | T42: 0.27594645 | U42: 0.26072365 | V42: 0.25967992
A43: + Other Payables & Accruals | B43: BS_ACCRUAL | C43: 274.8 | D43: 304.8 | E43: 360.2 | F43: 346.9 | G43: 347.7 | H43: 370.7 | I43: 472.4 | J43: 392.5 | K43: 349.8 | L43: 442.6 | N43: EBIT | O43: 788 | P43: 823.7 | Q43: 868.7 | R43: 1089.3 | S43: 1086.9 | T43: 932.4 | U43: 1102.9
A44: + ST Debt | B44: BS_ST_BORROW | C44: 95.3 | D44: 579.1 | E44: 265.4 | F44: 194.6 | G44: 481.6 | H44: 109 | I44: 366.1 | J44: 641 | K44: 667.6 | L44: 641.9 | N44: NOPAT | O44: 666.70368 | P44: 1010.8895 | Q44: 659.33069 | R44: 816.48116 | S44: 823.46842 | T44: 675.10753 | U44: 815.34789
A45: + ST Borrowings | B45: SHORT_TERM_DEBT_DETAILED | C45: 92.8 | D45: 326.4 | E45: 253.7 | F45: 170.5 | G45: 170.7 | H45: 59.1 | I45: 313.3 | J45: 343.5 | K45: 316.3 | L45: 36.9
A46: + ST Lease Liabilities | B46: ST_CAPITALIZED_LEASE_LIABILITIES | C46: — | D46: — | E46: 6.2 | F46: 5.9 | G46: 45.9 | H46: 49.9 | I46: 52.8 | J46: 47.8 | K46: 51.7 | L46: 53.9
A47: + ST Finance Leases | B47: ST_CAPITAL_LEASE_OBLIGATIONS | C47: — | D47: — | E47: 6.2 | F47: 5.9 | G47: 4.5 | H47: 5.6 | I47: 5.5 | J47: 5.4 | K47: 6.3 | L47: 4.3
A48: + ST Operating Leases | B48: BS_ST_OPERATING_LEASE_LIABS | C48: — | D48: — | E48: — | F48: — | G48: 41.4 | H48: 44.3 | I48: 47.3 | J48: 42.4 | K48: 45.4 | L48: 49.6
A49: + Current Portion of LT Debt | B49: BS_CURR_PORTION_LT_DEBT | C49: 2.5 | D49: 252.7 | E49: 5.5 | F49: 18.2 | G49: 265 | H49: 0 | I49: 0 | J49: 249.7 | K49: 299.6 | L49: 551.1
A50: + Other ST Liabilities | B50: OTHER_CURRENT_LIABS_SUB_DETAILED | C50: 229.3 | D50: 240.6 | E50: 289.8 | F50: 363.9 | G50: 287 | H50: 309.1 | I50: 335.7 | J50: 350.8 | K50: 347.4 | L50: 362.7
A51: + Deferred Revenue | B51: ST_DEFERRED_REVENUE | C51: 0 | D51: 0 | E51: 0 | F51: 0 | G51: 0 | H51: 0 | I51: 0 | J51: 0 | K51: 0 | L51: 0
A52: + Derivatives & Hedging | B52: BS_DERIV_HEDGING_LIAB_ST | C52: 5.2 | D52: 7.8 | E52: 0.6 | F52: 0.8 | G52: 5.1 | H52: 8.5 | I52: 2.9 | J52: 9.8 | K52: 6 | L52: 4.2
A53: + Misc ST Liabilities | B53: OTHER_CURRENT_LIABS_DETAILED | C53: 224.1 | D53: 232.8 | E53: 289.2 | F53: 363.1 | G53: 281.9 | H53: 300.6 | I53: 332.8 | J53: 341 | K53: 341.4 | L53: 358.5
A54: Total Current Liabilities | B54: BS_CUR_LIAB | C54: 1459.1 | D54: 2004.3 | E54: 1971.8 | F54: 1994 | G54: 2253.8 | H54: 1926 | I54: 2547.9 | J54: 2799.8 | K54: 2699.5 | L54: 2862.6
A55: + LT Debt | B55: BS_LT_BORROW | C55: 963.6 | D55: 713.4 | E55: 1316.3 | F55: 1771.6 | G55: 1598.2 | H55: 2168.1 | I55: 2921.2 | J55: 2617.1 | K55: 2774.4 | L55: 2736
A56: TOTAL DEBT | C56: =C55+C44 -> 1058.9 | D56: =D55+D44 -> 1292.5 | E56: =E55+E44 -> 1581.7 | F56: =F55+F44 -> 1966.2 | G56: =G55+G44 -> 2079.8 | H56: =H55+H44 -> 2277.1 | I56: =I55+I44 -> 3287.3 | J56: =J55+J44 -> 3258.1 | ... L56: =L55+L44 -> 3377.9
A57: + LT Borrowings | B57: LONG_TERM_BORROWINGS_DETAILED | C57: 937.6 | D57: 688.2 | E57: 1297.5 | F57: 1756.8 | G57: 1475.3 | H57: 2029.2 | I57: 2774.2 | J57: 2495.3 | K57: 2615.1 | L57: 2550.8
A58: + LT Lease Liabilities | B58: LT_CAPITALIZED_LEASE_LIABILITIES | C58: 26 | D58: 25.2 | E58: 18.8 | F58: 14.8 | G58: 122.9 | H58: 138.9 | I58: 147 | J58: 121.8 | K58: 159.3 | L58: 185.2
A59: + LT Finance Leases | B59: LT_CAPITAL_LEASE_OBLIGATIONS | C59: 26 | D59: 25.2 | E59: 18.8 | F59: 14.8 | G59: 24 | H59: 22.9 | I59: 11.7 | J59: 8.2 | K59: 7 | L59: 9.1
A60: + LT Operating Leases | B60: BS_LT_OPERATING_LEASE_LIABS | C60: — | D60: — | E60: — | F60: — | G60: 98.9 | H60: 116 | I60: 135.3 | J60: 113.6 | K60: 152.3 | L60: 176.1
A61: + Other LT Liabilities | B61: OTHER_NONCUR_LIABS_SUB_DETAILED | C61: 745.3 | D61: 753.2 | E61: 802.6 | F61: 456.8 | G61: 432.8 | H61: 504.9 | I61: 578.1 | J61: 501.4 | K61: 608 | L61: 493.3
A62: + Accrued Liabilities | B62: BS_ACCRUED_LIABILITIES | C62: 0 | D62: 0 | E62: 0 | F62: 0 | G62: 0 | H62: 0 | I62: 0 | J62: 0 | K62: 0 | L62: 0
A63: + Pension Liabilities | B63: PENSION_LIABILITIES | C63: 637.4 | D63: 660.9 | E63: 629.3 | F63: 334.7 | G63: 193.9 | H63: 215.8 | I63: 180.2 | J63: 116.8 | K63: 127.5 | L63: 124.9
A64: + Deferred Revenue | B64: LT_DEFERRED_REVENUE | C64: 0 | D64: 0 | E64: 0 | F64: 0 | G64: 0 | H64: 0 | I64: 0 | J64: 0 | K64: 0 | L64: 0
A65: + Deferred Tax Liabilities | B65: BS_DEFERRED_TAX_LIABILITIES_LT | C65: 107.9 | D65: 92.3 | E65: 173.3 | F65: 122.1 | G65: 110.3 | H65: 117.3 | I65: 238.5 | J65: 247.9 | K65: 260 | L65: 234.8
A66: + Derivatives & Hedging | B66: BS_DERIV_HEDGING_LIAB_LT | C66: 0 | D66: 0 | E66: 0 | F66: 0 | G66: 0 | H66: 0 | I66: 0 | J66: 0 | K66: 0 | L66: 0
A67: + Misc LT Liabilities | B67: OTHER_NONCURRENT_LIABS_DETAILED | C67: 0 | D67: 0 | E67: 0 | F67: 0 | G67: 128.6 | H67: 171.8 | I67: 159.4 | J67: 136.7 | K67: 220.5 | L67: 133.6
A68: Total Noncurrent Liabilities | B68: NON_CUR_LIAB | C68: 1708.9 | D68: 1466.6 | E68: 2118.9 | F68: 2228.4 | G68: 2031 | H68: 2673 | I68: 3499.3 | J68: 3118.5 | K68: 3382.4 | L68: 3229.3
A69: Total Liabilities | B69: BS_TOT_LIAB2 | C69: 3168 | D69: 3470.9 | E69: 4090.7 | F69: 4222.4 | G69: 4284.8 | H69: 4599 | I69: 6047.2 | J69: 5918.3 | K69: 6081.9 | L69: 6091.9
A70: + Preferred Equity and Hybrid Capital | B70: PFD_EQTY_HYBRID_CAPITAL | C70: 0 | D70: 0 | E70: 0 | F70: 0 | G70: 0 | H70: 0 | I70: 0 | J70: 0 | K70: 0 | L70: 0
A71: + Share Capital & APIC | B71: BS_SH_CAP_AND_APIC | C71: 958.1 | D71: 976.1 | E71: 986.7 | F71: 996.1 | G71: 998.1 | H71: 986.2 | I71: 986.4 | J71: 1003.4 | K71: 978.6 | L71: 964.7
A72: + Common Stock | B72: BS_COMMON_STOCK | C72: 124.1 | D72: 124.1 | E72: 124.1 | F72: 124.1 | G72: 124.1 | H72: 124.1 | I72: 124.1 | J72: 124.1 | K72: 124.1 | L72: 124.1
... A80: Total Liabilities & Equity | B80: TOT_LIAB_AND_EQY | C80: 4133.7 | D80: 4396.4 | E80: 5136.9 | F80: 5177.5 | G80: 5488.8 | H80: 6083.9 | I80: 7971.6 | J80: 7950.5 | K80: 8209.8 | L80: 8404.2
A82: Reference Items
A83: Accounting Standard | B83: ACCOUNTING_STANDARD | C83: US GAAP | D83: US GAAP | E83: US GAAP | F83: US GAAP | G83: US GAAP | H83: US GAAP | I83: US GAAP | J83: US GAAP | K83: US GAAP | L83: US GAAP
A84: Shares Outstanding | B84: BS_SH_OUT | C84: 89.9677 | D84: 88.3089 | E84: 88.0115 | F84: 84.7237 | G84: 83.1512 | H84: 83.1512 | I84: 82.606 | J84: 80.81 | K84: 80.4956 | L84: 79.8004
A85: Number of Treasury Shares | B85: BS_NUM_OF_TSY_SH | C85: 34.1589 | D85: 35.8178 | E85: 36.1151 | F85: 39.403 | G85: 40.9755 | H85: 40.9755 | I85: 41.5207 | J85: 43.3166 | K85: 43.631 | L85: 44.3262
A86: Pension Obligations | B86: BS_PENSION_RSRV | C86: 637.4 | D86: 660.9 | E86: 629.3 | F86: 334.7 | G86: 193.9 | H86: 215.8 | I86: 180.2 | J86: 116.8 | K86: 127.5 | L86: 124.9
A87: Future Minimum Operating Lease Obligations | B87: BS_FUTURE_MIN_OPER_LEASE_OBLIG | C87: 143 | D87: 137.8 | E87: 189.7 | F87: 184.8 | G87: 159.7 | H87: 183.6 | I87: 204.4 | J87: 174.1 | K87: 231.3 | L87: 261
A88: Capital Leases - Total | B88: BS_TOTAL_CAPITAL_LEASES | C88: 26 | D88: 25.2 | E88: 25 | F88: 20.7 | G88: 28.5 | H88: 28.5 | I88: 17.2 | J88: 13.6 | K88: 13.3 | L88: 13.4
A89: Options Granted During Period | B89: BS_OPTIONS_GRANTED | C89: — | D89: 0.1411 | E89: — | F89: — | G89: — | H89: — | I89: — | J89: — | K89: 0.063 | L89: 0
A90: Options Outstanding at Period End | B90: BS_OPTIONS_OUTSTANDING | C90: 2.3699 | D90: 1.1152 | E90: 0.5436 | F90: 0.5116 | G90: 0.2062 | H90: 0.1621 | I90: 0.142 | J90: 0.1411 | K90: 0.2041 | L90: 0.063
A91: Net Debt | B91: NET_DEBT | C91: 900.1 | D91: 1097.4 | E91: 1357.3 | F91: 1734.2 | G91: 1826.1 | H91: 2024.8 | I91: 3124.6 | J91: 3090.9 | K91: 3227 | L91: 3048.8
A92: Net Debt to Equity | B92: NET_DEBT_TO_SHRHLDR_EQTY | C92: 93.207 | D92: 118.5737 | E92: 129.7362 | F92: 181.5726 | G92: 151.6694 | H92: 136.3594 | I92: 162.3675 | J92: 152.0963 | K92: 151.6519 | L92: 131.8514
A93: Tangible Common Equity Ratio | B93: TCE_RATIO | C93: 6.8701 | D93: 1.8438 | E93: -2.6396 | F93: -3.1943 | G93: 3.3104 | H93: 2.6172 | I93: -16.7706 | J93: -12.7768 | K93: -13.742 | L93: -7.3898
A94: Current Ratio | B94: CUR_RATIO | C94: 1.2168 | D94: 0.9504 | E94: 1.135 | F94: 1.1525 | G94: 1.0385 | H94: 1.2545 | I94: 1.0733 | J94: 0.9936 | K94: 1.0357 | L94: 1.0755
A95: Cash Conversion Cycle | B95: CASH_CONVERSION_CYCLE | C95: 31.4058 | D95: 32.0778 | E95: 34.016 | F95: 33.8518 | G95: 34.4385 | H95: 38.6637 | I95: 38.1391 | J95: 37.7835 | K95: 39.0233 | L95: 39.5658
A96: Number of Employees | B96: NUM_OF_EMPLOYEES | C96: 25000 | D96: 25000 | E96: 30000 | F96: 32000 | G96: 32000 | H96: 32000 | I96: 36000 | J96: 36000 | K96: 35000 | L96: 35000

Sheet Cash Flow Statement
A1: Avery Dennison Corp (AVY US) - Standardized | B1: FY 2018 | C1: FY 2019 | D1: FY 2020 | E1: FY 2021 | F1: FY 2022 | G1: FY 2023 | H1: FY 2024
A2: In Millions of USD except Per Share
A3: 12 Months Ending | B3: 12/29/2018 | C3: 12/28/2019 | D3: 12/31/2020 | E3: 12/31/2021 | F3: 12/31/2022 | G3: 12/30/2023 | H3: 12/28/2024
A4: Cash from Operating Activities
A5: + Net Income | B5: 467.4 | C5: 303.6 | D5: 555.9 | E5: 740.1 | F5: 757.1 | G5: 503 | H5: 704.9
A6: + Depreciation & Amortization | B6: 181 | C6: 179 | D6: 205.3 | E6: 244.1 | F6: 290.7 | G6: 298.4 | H6: 312.2
A7: + Non-Cash Items | B7: -65.6 | C7: 272.4 | D7: 84.8 | E7: 110.6 | F7: -11.1 | G7: 35.9 | H7: -27.2
A8: + Stock-Based Compensation | B8: 34.3 | C8: 34.5 | D8: 24 | E8: 37.2 | F8: 47.4 | G8: 22.3 | H8: 28.7
A9: + Deferred Income Taxes | B9: -32.7 | C9: -216.9 | D9: 9.3 | E9: 2.6 | F9: 18.4 | G9: -24.4 | H9: -18.5
A10: + Other Non-Cash Adj | B10: -67.2 | C10: 454.8 | D10: 51.5 | E10: 70.8 | F10: -76.9 | G10: 38 | H10: -37.4
A11: + Chg in Non-Cash Work Cap | B11: -124.9 | C11: -8.5 | D11: -94.7 | E11: -48 | F11: -75.7 | G11: -11.3 | H11: -51.1
A12: + (Inc) Dec in Accts Receiv | B12: -62.5 | C12: -42.2 | D12: 14.7 | E12: -113.2 | F12: -22.1 | G12: -16.7 | H12: -107.3
A13: + (Inc) Dec in Inventories | B13: -70.5 | C13: -18.1 | D13: -6 | E13: -182.7 | F13: -140.7 | G13: 111.7 | H13: -90.7
A14: + Inc (Dec) in Accts Payable | B14: 43.6 | C14: 46.4 | D14: -68.2 | E14: 255.2 | F14: 68.2 | G14: -87.6 | H14: 106.7
A15: + Inc (Dec) in Other | B15: -35.5 | C15: 5.4 | D15: -35.2 | E15: -7.3 | F15: 18.9 | G15: -18.7 | H15: 40.2
A16: + Net Cash From Disc Ops | B16: 0 | C16: 0 | D16: 0 | E16: 0 | F16: 0 | G16: 0 | H16: 0
A17: Cash from Operating Activities | B17: 457.9 | C17: 746.5 | D17: 751.3 | E17: 1046.8 | F17: 961 | G17: 826 | H17: 938.8
A19: Cash from Investing Activities
A20: + Change in Fixed & Intang | B20: -247.2 | C20: -249.4 | D20: -209.4 | E20: -271 | F20: -296.2 | G20: -284.1 | H20: -239.2
A21: + Disp in Fixed & Intang | B21: 9.4 | C21: 7.8 | D21: 9.2 | E21: 1.1 | F21: 2.3 | G21: 1 | H21: 0.6
A22: + Disp of Fixed Prod Assets | B22: 9.4 | C22: 7.8 | D22: 9.2 | E22: 1.1 | F22: 2.3 | G22: 1 | H22: 0.6
A23: + Disp of Intangible Assets | B23: 0 | C23: 0 | D23: 0 | E23: 0 | F23: 0 | G23: 0 | H23: 0 | J23: CapEx as % of Revenue
A24: + Acq of Fixed & Intang | B24: -256.6 | C24: -257.2 | D24: -218.6 | E24: -272.1 | F24: -298.5 | G24: -285.1 | H24: -239.8 | J24: Year | K24: FY 2018 | L24: FY 2019 | M24: FY 2020 | N24: FY 2021 | O24: FY 2022 | P24: FY 2023 | Q24: FY 2024 | R24: Average
A25: + Acq of Fixed Prod Assets | B25: -226.7 | C25: -219.4 | D25: -201.4 | E25: -255 | F25: -278.1 | G25: -265.3 | H25: -208.8 | J25: CapEx | K25: =B25 -> -226.7 | L25: =C25 -> -219.4 | M25: =D25 -> -201.4 | N25: =E25 -> -255 | O25: =F25 -> -278.1 | P25: =G25 -> -265.3 | Q25: =H25 -> -208.8
A26: + Acq of Intangible Assets | B26: -29.9 | C26: -37.8 | D26: -17.2 | E26: -17.1 | F26: -20.4 | G26: -19.8 | H26: -31 | J26: CapEx (% of Revenue) | K26: =K25/'Income Statement'!B4 -> -0.031666434 | L26: =L25/'Income Statement'!C4 -> -0.031032093 | M26: =M25/'Income Statement'!D4 -> -0.028889048 | N26: =N25/'Income Statement'!E4 -> -0.030327177 | O26: =O25/'Income Statement'!F4 -> -0.030765657 | P26: =P25/'Income Statement'!G4 -> -0.031718135 | Q26: =Q25/'Income Statement'!H4 -> -0.023847322 | R26: =-AVERAGE(Table14[[#This Row],[Column6]:[Column8]]) -> 0.028777038
A27: + Net Change in LT Investment | B27: — | C27: 0 | D27: 0 | E27: 0 | F27: 0 | G27: 0 | H27: 0
A28: + Dec in LT Investment | B28: — | C28: 0 | D28: 0 | E28: 0 | F28: 0 | G28: 0 | H28: 0
A29: + Inc in LT Investment | B29: — | C29: 0 | D29: 0 | E29: 0 | F29: 0 | G29: 0 | H29: 0
A30: + Net Cash From Acq & Div | B30: -3.8 | C30: -6.5 | D30: -350.4 | E30: -1477.6 | F30: -39.5 | G30: -224.9 | H30: -3.8
A31: + Cash from Divestitures | B31: 0 | C31: 0 | D31: 0 | E31: 0 | F31: 0 | G31: 0 | H31: 0
A32: + Cash for Acq of Subs | B32: -3.8 | C32: -6.5 | D32: -350.4 | E32: -1477.6 | F32: -39.5 | G32: -224.9 | H32: -3.8
A33: + Cash for JVs | B33: 0 | C33: 0 | D33: 0 | E33: 0 | F33: 0 | G33: 0 | H33: 0
A34: + Other Investing Activities | B34: 18.5 | C34: 4.9 | D34: 5.6 | E34: 10.7 | F34: 3 | G34: 50 | H34: -0.1
A35: + Net Cash From Disc Ops | B35: 0 | C35: 0 | D35: 0 | E35: 0 | F35: 0 | G35: 0 | H35: 0
A36: Cash from Investing Activities | B36: -232.5 | C36: -251 | D36: -554.2 | E36: -1737.9 | F36: -332.7 | G36: -459 | H36: -243.1
A38: Cash from Financing Activities
A39: + Dividends Paid | B39: -175 | C39: -189.7 | D39: -196.8 | E39: -220.6 | F39: -238.9 | G39: -256.7 | H39: -277.5
A40: + Cash From (Repayment) Debt | B40: 409.3 | C40: -23.9 | D40: 113.1 | E40: 1037.5 | F40: 28.3 | G40: 102.4 | H40: -37.9
A41: + Cash From (Repay) ST Debt | B41: -77.6 | C41: -5.3 | D41: -110.4 | E41: 259.2 | F41: 34.6 | G41: -36.6 | H41: -269
A42: + Cash From LT Debt | B42: 493.3 | C42: 0 | D42: 993.7 | E42: 791.7 | F42: 0 | G42: 394.9 | H42: 539.2
A43: + Repayments of LT Debt | B43: -6.4 | C43: -18.6 | D43: -770.2 | E43: -13.4 | F43: -6.3 | G43: -255.9 | H43: -308.1
A44: + Cash (Repurchase) of Equity | B44: -392.9 | C44: -237.7 | D44: -104.3 | E44: -180.9 | F44: -379.5 | G44: -137.5 | H44: -247.5
A45: + Increase in Capital Stock | B45: 0 | C45: 0 | D45: 0 | E45: 0 | F45: 0 | G45: 0 | H45: 0
A46: + Decrease in Capital Stock | B46: -392.9 | C46: -237.7 | D46: -104.3 | E46: -180.9 | F46: -379.5 | G46: -137.5 | H46: -247.5
A47: + Other Financing Activities | B47: -49.5 | C47: -19 | D47: -19.7 | E47: -31.7 | F47: -25.1 | G47: -25.4 | H47: -13.2
A48: + Net Cash From Disc Ops | B48: 0 | C48: 0 | D48: 0 | E48: 0 | F48: 0 | G48: 0 | H48: 0
A49: Cash from Financing Activities | B49: -208.1 | C49: -470.3 | D49: -207.7 | E49: 604.3 | F49: -615.2 | G49: -317.2 | H49: -576.1
A51: Effect of Foreign Exchange Rates | B51: -9.7 | C51: -3.5 | D51: 9.2 | E51: -2.8 | F51: -8.6 | G51: -2 | H51: -5.5
... A56: Cash Paid for Interest | B56: 54.9 | C56: 74.3 | D56: 69.6 | E56: 62.8 | F56: 80.9 | G56: 109.9 | H56: 111.8
A58: Reference Items
A59: EBITDA | B59: 899.1 | C59: 1014.9 | D59: 1077.6 | E59: 1371.6 | F59: 1435.5 | G59: 1154.9 | H59: 1431.1
A60: Trailing 12M EBITDA Margin | B60: 12.559 | C60: 14.3548 | D60: 15.4572 | E60: 16.3125 | F60: 15.8807 | G60: 13.8075 | H60: 16.3448
A61: Net Cash Paid for Acquisitions | B61: 3.8 | C61: 6.5 | D61: 350.4 | E61: 1477.6 | F61: 39.5 | G61: 224.9 | H61: 3.8
A62: Free Cash Flow | B62: 231.2 | C62: 527.1 | D62: 549.9 | E62: 791.8 | F62: 682.9 | G62: 560.7 | H62: 730
A63: Free Cash Flow to Firm | B63: 280.6951 | C63: — | D63: 603.029 | E63: 844.4182 | F63: 746.6167 | G63: 646.8624 | H63: 816.4953
A64: Free Cash Flow to Equity | B64: 649.9 | C64: 511 | D64: 672.2 | E64: 1830.4 | F64: 713.5 | G64: 664.1 | H64: 692.7
A65: Free Cash Flow per Basic Share | B65: 2.6483 | C65: 6.275 | D65: 6.5935 | E65: 9.5513 | F65: 8.3689 | G65: 6.948 | H65: 9.0796
A66: Price to Free Cash Flow | B66: 33.5418 | C66: 20.9737 | D66: 23.5246 | E66: 22.6745 | F66: 21.6278 | G66: 29.0963 | H66: 20.7619
A67: Cash Flow to Net Income | B67: 0.9797 | C67: 2.4588 | D67: 1.3515 | E67: 1.4144 | F67: 1.2693 | G67: 1.6421 | H67: 1.3318

Sheet Assumptions
A1: Assumptions | B1: 2025 Est | C1: 2026 Est | D1: 2027 Est | E1: 2028 Est | F1: 2029 Est
A2: Revenue Growth Rate (%) | B2: =J12 -> 0.04 | C2: =B2*(1+$J$12) -> 0.0416 | D2: =C2*(1+$J$12) -> 0.043264 | E2: =D2*(1+$J$12) -> 0.04499456 | F2: =E2*(1+$J$12) -> 0.046794342 | H2: Given the historical average of 3.78% and the 2024 recovery, we assume a slightly conservative Revenue Growth of 4.0% for 2025–2029, reflecting cautious optimism for continued recovery and growth in high-value categories like Intelligent Labels.
A3: EBIT Margin (%) | B3: =$J$13 -> 0.11977327 | C3: =$J$13 -> 0.11977327 | D3: =$J$13 -> 0.11977327 | E3: =$J$13 -> 0.11977327 | F3: =$J$13 -> 0.11977327 | H3: Historical average (2018–2019) is 11.33%. Given productivity gains and high-value category growth, we assume an EBIT Margin of 11.98% for 2025–2029, slightly above historical but reflecting operational improvements noted in 10-Ks.
A4: Depreciation (% of Revenue) | B4: =J14 -> 0.021513736 | C4: =B4*(1+$J$13) -> 0.024090506 | D4: =C4*(1+$J$13) -> 0.026975905 | E4: =D4*(1+$J$13) -> 0.030206897 | F4: =E4*(1+$J$13) -> 0.033824876 | H4: Given historical consistency, we assume D&A at 2.0% of Revenue for 2025–2029.
A5: Capital Expenditure (% of Revenue) | B5: =J15 -> 0.028777038 | C5: =B5*(1+$J$15) -> 0.029605156 | D5: =C5*(1+$J$15) -> 0.030457105 | E5: =D5*(1+$J$15) -> 0.03133357 | F5: =E5*(1+$J$15) -> 0.032235257 | H5: We assume CapEx at historical average of Revenue for 2025–2029, balancing historical trends with recent data (2022–2024) at 2.88%.
A6: Change in Net Working Capital (% of Revenue) | B6: =J16 -> 0.0050846871 | C6: =B6*(1+$J$16) -> 0.0051105411 | D6: =C6*(1+$J$16) -> 0.0051365266 | E6: =D6*(1+$J$16) -> 0.0051626442 | F6: =E6*(1+$J$16) -> 0.0051888947 | H6: Based on the historical average and 10-K efficiency trends, we assume Change in NWC at 0.51% of Revenue for 2025–2029, due to improved NWC management.
A7: Effective Tax Rate (%) | B7: =$J$17 -> 0.25967992 | C7: =$J$17 -> 0.25967992 | D7: =$J$17 -> 0.25967992 | E7: =$J$17 -> 0.25967992 | F7: =$J$17 -> 0.25967992 | H7: Based on 2022–2024 10-K data, we assume an ETR of 26.0% for 2025–2029, aligning with the adjusted ETR trend.
H8: A 2.5% perpetual growth rate is appropriate, as it’s conservative and aligns with long-term global GDP growth, while accounting for AVY’s stable market position and innovation focus.
I11: Assumptions | J11: Calculations
I12: Revenue Growth Rate (%) | J12: 0.04
I13: EBIT Margin (%) | J13: 0.11977327
I14: Depreciation (% of Revenue) | J14: 0.021513736
I15: Capital Expenditure (% of Revenue) | J15: 0.028777038
I16: Change in Net Working Capital (% of Revenue) | J16: 0.0050846871
I17: Effective Tax Rate (%) | J17: 0.25967992
I18: Growth Rate | J18: 0.025

Sheet FCFF Forecast
A1: Metric | B1: 2025E | C1: 2026E | D1: 2027E | E1: 2028E | F1: 2029E
A2: In Millions of USD except Per Share
A3: Revenue | B3: ='Income Statement'!H4*(1+Assumptions!B2) -> 9105.928 | C3: =B3*(1+Assumptions!C2) -> 9484.7346 | D3: =C3*(1+Assumptions!D2) -> 9895.0822 | E3: =D3*(1+Assumptions!E2) -> 10340.307 | F3: =E3*(1+Assumptions!F2) -> 10824.175
A4: EBIT | B4: =B3*Assumptions!B3 -> 1090.6468 | C4: =C3*Assumptions!C3 -> 1136.0177 | D4: =D3*Assumptions!D3 -> 1185.1663 | E4: =E3*Assumptions!E3 -> 1238.4924 | F4: =F3*Assumptions!F3 -> 1296.4468
A5: Less: Taxes (EBIT*Tax Rate) | B5: =B4*Assumptions!B7 -> 283.21906 | C5: =C4*Assumptions!C7 -> 295.00098 | D5: =D4*Assumptions!D7 -> 307.7639 | E5: =E4*Assumptions!E7 -> 321.6116 | F5: =F4*Assumptions!F7 -> 336.6612
A6: NOPAT (EBIT after Tax) | B6: =B4-B5 -> 807.4277 | C6: =C4-C5 -> 841.01669 | D6: =D4-D5 -> 877.40244 | E6: =E4-E5 -> 916.88077 | F6: =F4-F5 -> 959.78561
A7: Add: Depreciation | B7: =B3*Assumptions!B4 -> 195.90253 | C7: =C3*Assumptions!C4 -> 228.49206 | D7: =D3*Assumptions!D4 -> 266.9288 | E7: =E3*Assumptions!E4 -> 312.34859 | F7: =F3*Assumptions!F4 -> 366.12637
A8: Less: Capex | B8: =B3*Assumptions!B5 -> 262.04164 | C8: =C3*Assumptions!C5 -> 280.79705 | D8: =D3*Assumptions!D5 -> 301.37555 | E8: =E3*Assumptions!E5 -> 323.99873 | F8: =F3*Assumptions!F5 -> 348.92006
A9: Less: Change in Net Working Capital | B9: =B3*Assumptions!B6 -> 46.300794 | C9: =C3*Assumptions!C6 -> 48.472126 | D9: =D3*Assumptions!D6 -> 50.826353 | E9: =E3*Assumptions!E6 -> 53.383326 | F9: =F3*Assumptions!F6 -> 56.165503
A10: FCFF (Free Cash Flow to Firm) | B10: =B6+B7-B8-B9 -> 694.9878 | C10: =C6+C7-C8-C9 -> 740.23958 | D10: =D6+D7-D8-D9 -> 792.12933 | E10: =E6+E7-E8-E9 -> 851.8473 | F10: =F6+F7-F8-F9 -> 920.82641

Sheet DCF Valuation
A1: Years | B1: 2025E | C1: 2026E | D1: 2027E | E1: 2028E | F1: 2029E | G1: Terminal Value
A2: FCFF | B2: ='FCFF Forecast'!B10 -> 694.9878 | C2: ='FCFF Forecast'!C10 -> 740.23958 | D2: ='FCFF Forecast'!D10 -> 792.12933 | E2: ='FCFF Forecast'!E10 -> 851.8473 | F2: ='FCFF Forecast'!F10 -> 920.82641 | G2: =F2*(1+B10)/B9-B10 -> 11865.889 | I2: Cost of Equity=Rf​+β×(Rm​−Rf​) | J2: =J4+J6*J8 -> 0.0917
A3: Dicsount Factror | B3: =1/(1+$B$9) -> 0.92631813 | C3: =1/(1+$B$9)^2 -> 0.85806529 | D3: =1/(1+$B$9)^3 -> 0.79484143 | E3: =1/(1+$B$9)^4 -> 0.73627603 | F3: =1/(1+$B$9)^5 -> 0.68202584 | G3: =G2*F3 -> 8092.8427
A4: PV of FCFF | B4: =B2*B3 -> 643.7798 | C4: =C2*C3 -> 635.17388 | D4: =D2*D3 -> 629.61721 | E4: =E2*E3 -> 627.19475 | F4: =F2*F3 -> 628.02741 | I4: Rf = 4.01% (from Treasury) | J4: 0.0401
A5: Sum of PV of FCFF | B5: =B4+C4+D4+E4+F4 -> 3163.7931
I6: Beta (β) = 0.86 (from Bloomberg) | J6: 0.86
A8: WACC and g | B8: Value | I8: Market Risk Premium (Rm – Rf) = 6% ✅ (from Bloomberg) | J8: 0.06
A9: WACC | B9: =(C32*J2)+(C33*C25*(1-Assumptions!J17)) -> 0.079542722
A10: g | B10: =Assumptions!J18 -> 0.025
A12: Metrics | B12: Value
A13: Enterprise Value | B13: =B5+G3 -> 11256.636
A14: Net Debt 2024 | B14: ='Balance Sheet'!L56-'Balance Sheet'!L7 -> 3048.8
A15: Equity Value | B15: =B13-B14 -> 8207.8357
A16: Implied Share Price | B16: =B15/'Balance Sheet'!L84 -> 102.85457 | C16: Sell (Overvalued)
A19: Metrics | B19: 2023 | C19: 2024
A20: Interest Expense | C20: ='Income Statement'!H19 -> 117
A21: Total Debt | B21: ='Balance Sheet'!K56 -> 3442 | C21: ='Balance Sheet'!L56 -> 3377.9
A22: Average Debt | C22: =(B21+C21)/2 -> 3409.95
A25: Cost of Debt | C25: =C20/C22 -> 0.034311354
A27: Total Equity | C27: =C28+C29 -> 18421.073
A28: Equity (Market Cap) | C28: 15043.173
A29: Debt | C29: ='Balance Sheet'!L56 -> 3377.9
A31: Proportions
A32: E/V | C32: =C28/C27 -> 0.81662848
A33: D/V | C33: =C29/C27 -> 0.18337152

Sheet Valuation Summary
A1: Valuation Component | B1: In Millions of USD
A2: PV of FCFF (2025-2029) | B2: ='DCF Valuation'!B5 -> 3163.7931
A3: PV of Terminal Value | B3: ='DCF Valuation'!G3 -> 8092.8427
A4: Enterprise Value (EV) | B4: ='DCF Valuation'!B13 -> 11256.636
A5: Less: Net Debt | B5: ='DCF Valuation'!B14 -> 3048.8
A6: Equity Value | B6: ='DCF Valuation'!B15 -> 8207.8357
A7: Shares Outstanding (millions) | B7: ='Balance Sheet'!L84 -> 79.8004
A8: Implied Share Price | B8: ='DCF Valuation'!B16 -> 102.85457

Sheet Sensitivity Analysis
A1: Terminal Growth Rate | B1: =Assumptions!J18 -> 0.025
A2: WACC | D2: FCFF (2029) | E2: ='FCFF Forecast'!F10 -> 920.82641
A3: 0.072 | B3: =IF( ISNUMBER(A3)*ISNUMBER(B$1)*(A3>B$1), ( $E$3+ (($E$2*(1+B$1))/(A3-B$1))*(1/((1+A3)^5)) -$E$4)/$E$5, NA()) -> 179.19722 | D3: PV of FCFF (2025-2029) | E3: ='DCF Valuation'!B5 -> 3163.7931
A4: 0.0775 | B4: =IF( ISNUMBER(A4)*ISNUMBER(B$1)*(A4>B$1), ( $E$3+ (($E$2*(1+B$1))/(A4-B$1))*(1/((1+A4)^5)) -$E$4)/$E$5, NA()) -> 156.55496 | D4: Net Debt | E4: ='DCF Valuation'!B14 -> 3048.8
A5: 0.0795 | B5: =IF( ISNUMBER(A5)*ISNUMBER(B$1)*(A5>B$1), ( $E$3+ (($E$2*(1+B$1))/(A5-B$1))*(1/((1+A5)^5)) -$E$4)/$E$5, NA()) -> 149.48365 | D5: Shares Outstanding | E5: ='Balance Sheet'!L84 -> 79.8004
A6: 0.0815 | B6: =IF( ISNUMBER(A6)*ISNUMBER(B$1)*(A6>B$1), ( $E$3+ (($E$2*(1+B$1))/(A6-B$1))*(1/((1+A6)^5)) -$E$4)/$E$5, NA()) -> 142.92767
A7: 0.0835 | B7: =IF( ISNUMBER(A7)*ISNUMBER(B$1)*(A7>B$1), ( $E$3+ (($E$2*(1+B$1))/(A7-B$1))*(1/((1+A7)^5)) -$E$4)/$E$5, NA()) -> 136.83398
