Workbook
Name TRNR_1e611cf493644709873896a434924896_133_1: '9.1. Predicted Returns Raw Data'!$E$1
Name TRNR_50167c8fbd3f4ef299eb1de21f0f593a_67_1: '9.1. Predicted Returns Raw Data'!$I$1
Name TRNR_b0020b4b00644088861eb40ea839b0a9_133_1: '9.1. Predicted Returns Raw Data'!$E$1
Name TRNR_c0f1caf514a04f2d8f993a8f9efeb008_133_1: '9.1. Predicted Returns Raw Data'!$E$1
Name TRNR_dfe0763fcdc840ce96aa4fde28ae5799_67_1: '9.1. Predicted Returns Raw Data'!$I$1

Sheet 1. Stock Price Series
A1: Date | B1: BA Closing Price | C1: CAT Closing Price
A2: 06/28/2024 | B2: $182.01 | C2: $333.10
A3: 06/27/2024 | B3: $182.51 | C3: $327.46
A4: 06/26/2024 | B4: $178.50 | C4: $326.73
A5: 06/25/2024 | B5: $175.10 | C5: $327.40
A6: 06/24/2024 | B6: $179.10 | C6: $330.00
A7: 06/21/2024 | B7: $176.56 | C7: $327.84
A8: 06/20/2024 | B8: $176.30 | C8: $329.13
A9: 06/18/2024 | B9: $174.99 | C9: $325.14
A10: 06/17/2024 | B10: $178.39 | C10: $322.40
A11: 06/14/2024 | B11: $177.27 | C11: $321.47
A12: 06/13/2024 | B12: $180.70 | C12: $326.36
A13: 45632 | B13: $182.67 | C13: $328.73
A14: 45602 | B14: $185.50 | C14: $327.31
A15: 45571 | B15: $190.12 | C15: $329.61
A16: 45479 | B16: $190.24 | C16: $328.94
A17: 45449 | B17: $191.42 | C17: $328.29
A18: 45418 | B18: $189.85 | C18: $329.45
A19: 45388 | B19: $188.62 | C19: $327.57
A20: 45357 | B20: $184.57 | C20: $331.36
A21: 05/31/2024 | B21: $177.61 | C21: $338.52
A22: 05/30/2024 | B22: $172.75 | C22: $339.25
A23: 05/29/2024 | B23: $171.65 | C23: $338.11
A24: 05/28/2024 | B24: $175.08 | C24: $346.47
A25: 05/24/2024 | B25: $174.52 | C25: $348.90
A26: 05/23/2024 | B26: $172.21 | C26: $350.70
A27: 05/22/2024 | B27: $186.28 | C27: $355.94
A28: 05/21/2024 | B28: $184.78 | C28: $359.07
A29: 05/20/2024 | B29: $186.61 | C29: $362.75
A30: 05/17/2024 | B30: $184.95 | C30: $356.27
A31: 05/16/2024 | B31: $182.96 | C31: $350.72
A32: 05/15/2024 | B32: $176.99 | C32: $360.04
... A34: 05/13/2024 | B34: $178.44 | C34: $356.68
A35: 45570 | B35: $178.51 | C35: $354.79
A36: 45540 | B36: $181.25 | C36: $351.78
A37: 45509 | B37: $180.35 | C37: $344.50
A38: 45478 | B38: $176.71 | C38: $345.00
A39: 45448 | B39: $178.35 | C39: $342.10
A40: 45356 | B40: $179.79 | C40: $336.75
A41: 45327 | B41: $178.85 | C41: $335.44
A42: 45296 | B42: $171.46 | C42: $331.07
A43: 04/30/2024 | B43: $167.84 | C43: $334.57
A44: 04/29/2024 | B44: $173.49 | C44: $349.80
A45: 04/26/2024 | B45: $167.22 | C45: $343.38
A46: 04/25/2024 | B46: $166.81 | C46: $338.00
A47: 04/24/2024 | B47: $164.33 | C47: $363.52
A48: 04/23/2024 | B48: $169.18 | C48: $363.25
A49: 04/22/2024 | B49: $170.48 | C49: $357.61
A50: 04/19/2024 | B50: $169.82 | C50: $354.66
A51: 04/18/2024 | B51: $170.23 | C51: $357.93
A52: 04/17/2024 | B52: $170.21 | C52: $358.32
A53: 04/16/2024 | B53: $170.55 | C53: $359.88
A54: 04/15/2024 | B54: $167.82 | C54: $363.91
A55: 45630 | B55: $169.55 | C55: $365.63
A56: 45600 | B56: $173.36 | C56: $371.98
A57: 45569 | B57: $174.63 | C57: $372.07
A58: 45539 | B58: $178.12 | C58: $371.90
A59: 45508 | B59: $181.56 | C59: $373.47
A60: 45416 | B60: $183.14 | C60: $379.30
A61: 45386 | B61: $183.29 | C61: $369.79
A62: 45355 | B62: $184.92 | C62: $375.79
A63: 45326 | B63: $188.04 | C63: $364.83
A64: 45295 | B64: $189.50 | C64: $363.74
A65: 03/28/2024 | B65: $192.99 | C65: $366.43
A66: 03/27/2024 | B66: $191.95 | C66: $364.65
A67: 03/26/2024 | B67: $187.50 | C67: $356.39
A68: 03/25/2024 | B68: $191.41 | C68: $355.95
A69: 03/22/2024 | B69: $188.85 | C69: $358.11
A70: 03/21/2024 | B70: $187.70 | C70: $364.56
A71: 03/20/2024 | B71: $187.78 | C71: $356.45
A72: 03/19/2024 | B72: $181.14 | C72: $353.90
A73: 03/18/2024 | B73: $179.84 | C73: $351.90
A74: 03/15/2024 | B74: $182.53 | C74: $346.97
A75: 03/14/2024 | B75: $181.15 | C75: $341.92
A76: 03/13/2024 | B76: $182.35 | C76: $341.52
A77: 45629 | B77: $184.24 | C77: $337.24
A78: 45599 | B78: $192.49 | C78: $334.97
A79: 45507 | B79: $198.49 | C79: $339.19
A80: 45476 | B80: $203.03 | C80: $340.22
A81: 45446 | B81: $201.00 | C81: $335.63
A82: 45415 | B82: $201.14 | C82: $333.53
A83: 45385 | B83: $200.54 | C83: $338.65
A84: 45294 | B84: $200.00 | C84: $336.70
A85: 02/29/2024 | B85: $203.72 | C85: $333.96
A86: 02/28/2024 | B86: $207.00 | C86: $329.56
A87: 02/27/2024 | B87: $201.40 | C87: $327.63
A88: 02/26/2024 | B88: $200.54 | C88: $325.38
A89: 02/23/2024 | B89: $200.83 | C89: $323.88
A90: 02/22/2024 | B90: $201.50 | C90: $322.09
A91: 02/21/2024 | B91: $201.57 | C91: $317.14
A92: 02/20/2024 | B92: $203.37 | C92: $313.74
A93: 02/16/2024 | B93: $203.89 | C93: $321.91
A94: 02/15/2024 | B94: $205.33 | C94: $323.07
A95: 02/14/2024 | B95: $203.38 | C95: $316.71
A96: 02/13/2024 | B96: $204.46 | C96: $312.84
A97: 45628 | B97: $209.33 | C97: $321.63
A98: 45537 | B98: $209.20 | C98: $317.16
A99: 45506 | B99: $209.22 | C99: $322.00
A100: 45475 | B100: $211.92 | C100: $323.59
A101: 45445 | B101: $208.58 | C101: $322.72
...

Sheet 2. Daily Log Returns
A1: Date | B1: BA Log Returns | C1: CAT Log Returns
A2: 06/28/2024 | B2: -0.0027433354 | C2: 0.017076835
A3: 06/27/2024 | B3: 0.022216365 | C3: 0.0022317685
A4: 06/26/2024 | B4: 0.019231362 | C4: -0.0020485232
A5: 06/25/2024 | B5: -0.02258707 | C5: -0.0079099895
A6: 06/24/2024 | B6: 0.014283547 | C6: 0.00656697
A7: 06/21/2024 | B7: 0.0014736725 | C7: -0.003927125
A8: 06/20/2024 | B8: 0.00745826 | C8: 0.012196951
A9: 06/18/2024 | B9: -0.019243335 | C9: 0.0084628482
A10: 06/17/2024 | B10: 0.0062981707 | C10: 0.0028887839
A11: 06/14/2024 | B11: -0.019164204 | C11: -0.01509684
A12: 06/13/2024 | B12: -0.010843049 | C12: -0.0072356786
A13: 45632 | B13: -0.015373636 | C13: 0.0043290111
A14: 45602 | B14: -0.02460057 | C14: -0.0070024033
A15: 45571 | B15: -0.0006309812 | C15: 0.0020347741
A16: 45479 | B16: -0.0061835338 | C16: 0.0019779992
A17: 45449 | B17: 0.0082356801 | C17: -0.0035272333
A18: 45418 | B18: 0.0064998776 | C18: 0.0057228247
A19: 45388 | B19: 0.021705614 | C19: -0.011503625
A20: 45357 | B20: 0.03843866 | C20: -0.021377777
A21: 05/31/2024 | B21: 0.027744673 | C21: -0.0021541239
A22: 05/30/2024 | B22: 0.0063879427 | C22: 0.0033660124
A23: 05/29/2024 | B23: -0.019785492 | C23: -0.024424948
A24: 05/28/2024 | B24: 0.0032036641 | C24: -0.0069891134
A25: 05/24/2024 | B25: 0.013324686 | C25: -0.005145809
A26: 05/23/2024 | B26: -0.078536256 | C26: -0.01483102
A27: 05/22/2024 | B27: 0.0080849899 | C27: -0.0087551782
A28: 05/21/2024 | B28: -0.0098549493 | C28: -0.010196536
A29: 05/20/2024 | B29: 0.0089353593 | C29: 0.018025021
A30: 05/17/2024 | B30: 0.010817969 | C30: 0.015700686
A31: 05/16/2024 | B31: 0.033174316 | C31: -0.026226952
A32: 05/15/2024 | B32: -0.021076951 | C32: 0.0051794831
... A34: 05/13/2024 | B34: -0.0003922118 | C34: 0.0053129561
A35: 45570 | B35: -0.015232672 | C35: 0.0085200849
A36: 45540 | B36: 0.0049778864 | C36: 0.02091189
A37: 45509 | B37: 0.020389437 | C37: -0.0014503266
A38: 45478 | B38: -0.009237941 | C38: 0.008441325
A39: 45448 | B39: -0.0080415913 | C39: 0.015762277
A40: 45356 | B40: 0.0052420374 | C40: 0.0038977124
A41: 45327 | B41: 0.042197462 | C41: 0.013113269
A42: 45296 | B42: 0.021338859 | C42: -0.010516292
A43: 04/30/2024 | B43: -0.033108816 | C43: -0.044515437
A44: 04/29/2024 | B44: 0.03680965 | C44: 0.018523857
A45: 04/26/2024 | B45: 0.0024548706 | C45: 0.01579181
A46: 04/25/2024 | B46: 0.014978839 | C46: -0.072788421
A47: 04/24/2024 | B47: -0.029086636 | C47: 0.00074301364
A48: 04/23/2024 | B48: -0.0076547509 | C48: 0.015648295
A49: 04/22/2024 | B49: 0.0038789352 | C49: 0.0082834231
A50: 04/19/2024 | B50: -0.0024114113 | C50: -0.0091778525
A51: 04/18/2024 | B51: 0.00011749501 | C51: -0.0010890053
A52: 04/17/2024 | B52: -0.00199554 | C52: -0.0043442007
A53: 04/16/2024 | B53: 0.016136532 | C53: -0.011135942
A54: 04/15/2024 | B54: -0.010255892 | C54: -0.0047153088
A55: 45630 | B55: -0.022222489 | C55: -0.017218196
A56: 45600 | B56: -0.0072990927 | C56: -0.00024191923
A57: 45569 | B57: -0.019788031 | C57: 0.00045700768
A58: 45539 | B58: -0.019128697 | C58: -0.0042126791
A59: 45508 | B59: -0.0086647101 | C59: -0.015489769
A60: 45416 | B60: -0.0008187103 | C60: 0.025392172
A61: 45386 | B61: -0.0088537011 | C61: -0.0160952
A62: 45355 | B62: -0.016731407 | C62: 0.029598985
A63: 45326 | B63: -0.0077343184 | C63: 0.002992165
A64: 45295 | B64: -0.01824935 | C64: -0.0073681805
A65: 03/28/2024 | B65: 0.0054034526 | C65: 0.0048695177
A66: 03/27/2024 | B66: 0.023456076 | C66: 0.022912353
A67: 03/26/2024 | B67: -0.020638879 | C67: 0.0012353653
A68: 03/25/2024 | B68: 0.013464675 | C68: -0.0060499302
A69: 03/22/2024 | B69: 0.0061081056 | C69: -0.017850945
A70: 03/21/2024 | B70: -0.00042612124 | C70: 0.022497169
A71: 03/20/2024 | B71: 0.036000852 | C71: 0.0071795902
A72: 03/19/2024 | B72: 0.0072026462 | C72: 0.005667343
A73: 03/18/2024 | B73: -0.014846976 | C73: 0.014108723
A74: 03/15/2024 | B74: 0.0075891257 | C74: 0.014661529
A75: 03/14/2024 | B75: -0.0066024999 | C75: 0.0011705491
A76: 03/13/2024 | B76: -0.010311338 | C76: 0.012611399
A77: 45629 | B77: -0.043804949 | C77: 0.0067538675
A78: 45599 | B78: -0.030694517 | C78: -0.012519447
A79: 45507 | B79: -0.02261503 | C79: -0.0030320448
A80: 45476 | B80: 0.010048843 | C80: 0.013583104
A81: 45446 | B81: -0.00069627496 | C81: 0.0062765464
A82: 45415 | B82: 0.0029874549 | C82: -0.015234309
A83: 45385 | B83: 0.0026963615 | C83: 0.0057747995
A84: 45294 | B84: -0.018429135 | C84: 0.0081711008
A85: 02/29/2024 | B85: -0.015972291 | C85: 0.013262794
A86: 02/28/2024 | B86: 0.027425813 | C86: 0.0058735086
A87: 02/27/2024 | B87: 0.0042792522 | C87: 0.0068911928
A88: 02/26/2024 | B88: -0.001445051 | C88: 0.0046206533
A89: 02/23/2024 | B89: -0.0033306023 | C89: 0.0055420672
A90: 02/22/2024 | B90: -0.00034733421 | C90: 0.015487693
A91: 02/21/2024 | B91: -0.0088902645 | C91: 0.010778699
A92: 02/20/2024 | B92: -0.0025536526 | C92: -0.025707386
A93: 02/16/2024 | B93: -0.0070378082 | C93: -0.0035970146
A94: 02/15/2024 | B94: 0.0095422906 | C94: 0.019882489
A95: 02/14/2024 | B95: -0.005296207 | C95: 0.012294651
A96: 02/13/2024 | B96: -0.023539597 | C96: -0.027709939
A97: 45628 | B97: 0.00062122192 | C97: 0.013995438
A98: 45537 | B98: -9.5597725e-05 | C98: -0.015145167
A99: 45506 | B99: -0.012822515 | C99: -0.0049257368
A100: 45475 | B100: 0.015886184 | C100: 0.0026922082
A101: 45445 | B101: 0.0093929064 | C101: 0.0040986209
...

Sheet 3. Efficient Frontier
G1: =(B9^2*$D$3^2+C9^2*$D$4^2+2*B9*C9*$D$3*$D$4*$C$6)^(1/2) -> 0.0324
C2: Exp Return (μ) | D2: Std Dev (σ) | G2: =(B10^2*$D$3^2+C10^2*$D$4^2+2*B10*C10*$D$3*$D$4*$C$6)^(1/2) -> 0.028123523
B3: Boeing | C3: -0.0005 | D3: 0.0324 | G3: =(B11^2*$D$3^2+C11^2*$D$4^2+2*B11*C11*$D$3*$D$4*$C$6)^(1/2) -> 0.024465647
B4: Caterpillar μ | C4: 0.0007 | D4: 0.0205 | G4: =(B12^2*$D$3^2+C12^2*$D$4^2+2*B12*C12*$D$3*$D$4*$C$6)^(1/2) -> 0.02174088 | U4: Portfolio | V4: w1 | W4: w2 | X4: Mean Return | Y4: Standard Deviation
U5: 1 | V5: 1.6 | W5: -0.6 | X5: 0.0012 | Y5: 0.0463
B6: Corr Coeff (ρ) | C6: 0.4812 | U6: 2 | V6: 1.4 | W6: -0.4 | X6: 0.001 | Y6: 0.0413
U7: 3 | V7: 1.2 | W7: -0.2 | X7: 0.0007 | Y7: 0.0365
B8: w (Boeing) | C8: w (Caterpillar) | D8: Exp Return (μ) | E8: Std Dev (σ) | U8: 4 | V8: 1 | W8: 0 | X8: 0.0005 | Y8: 0.032
B9: 1 | C9: 0 | D9: =(B9*C3)+(C9*C4) -> -0.0005 | E9: =(B9^2*$D$3^2+C9^2*$D$4^2+2*B9*C9*$D$3*$D$4*$C$6)^(1/2) -> 0.0324 | U9: 5 | V9: 0.8 | W9: 0.2 | X9: 0.0003 | Y9: 0.0279
B10: 0.8 | C10: 0.2 | D10: =(B10*C3)+(C10*C4) -> -0.00026 | E10: =(B10^2*$D$3^2+C10^2*$D$4^2+2*B10*C10*$D$3*$D$4*$C$6)^(1/2) -> 0.028123523 | U10: 6 | V10: 0.6 | W10: 0.4 | X10: 0 | Y10: 0.0243
B11: 0.6 | C11: 0.4 | D11: =(B11*C3)+(C11*C4) -> -2e-05 | E11: =(B11^2*$D$3^2+C11^2*$D$4^2+2*B11*C11*$D$3*$D$4*$C$6)^(1/2) -> 0.024465647 | U11: 7 | V11: 0.4 | W11: 0.6 | X11: -0.0002 | Y11: 0.0217
B12: 0.4 | C12: 0.6 | D12: =(B12*C3)+(C12*C4) -> 0.00022 | E12: =(B12^2*$D$3^2+C12^2*$D$4^2+2*B12*C12*$D$3*$D$4*$C$6)^(1/2) -> 0.02174088 | U12: 8 | V12: 0.2 | W12: 0.8 | X12: -0.0005 | Y12: 0.0203
B13: 0.2 | C13: 0.8 | D13: =(B13*C3)+(C13*C4) -> 0.00046 | E13: =(B13^2*$D$3^2+C13^2*$D$4^2+2*B13*C13*$D$3*$D$4*$C$6)^(1/2) -> 0.020327975 | U13: 9 | V13: 0 | W13: 1 | X13: -0.0007 | Y13: 0.0204
B14: 0 | C14: 1 | D14: =(B14*C3)+(C14*C4) -> 0.0007 | E14: =(B14^2*$D$3^2+C14^2*$D$4^2+2*B14*C14*$D$3*$D$4*$C$6)^(1/2) -> 0.0205 | U14: 10 | V14: -0.2 | W14: 1.2 | X14: -0.0009 | Y14: 0.022
U15: 11 | V15: -0.4 | W15: 1.4 | X15: -0.0012 | Y15: 0.0248
U16: 12 | V16: -0.6 | W16: 1.6 | X16: -0.0014 | Y16: 0.0284
B18: Variance | D18: Exp Return | E18: Std Deivation
B19: =(B9^2*D3^2)+(C9^2*D4^2)+2*B9*C9*D3*D4*C6 -> 0.00104976 | D19: 0.0005 | E19: =SQRT(B19) -> 0.0324
B20: =(B10^2*D3^2)+(C10^2*D4^2)+2*B10*C10*D3*D4*C6 -> 0.00079093257 | D20: 0.00026 | E20: =SQRT(B20) -> 0.028123523
B21: =(B11^2*D3^2)+(C11^2*D4^2)+2*B11*C11*D3*D4*C6 -> 0.00059856786 | D21: 2e-05 | E21: =SQRT(B21) -> 0.024465647
B22: =(B12^2*D3^2)+(C12^2*D4^2)+2*B12*C12*D3*D4*C6 -> 0.00047266586 | D22: -0.00022 | E22: =SQRT(B22) -> 0.02174088 | H22: Part 5: | J22: MVP | K22: Min σ
B23: =(B13^2*D3^2)+(C13^2*D4^2)+2*B13*C13*D3*D4*C6 -> 0.00041322657 | D23: -0.00046 | E23: =SQRT(B23) -> 0.020327975 | H23: W(Caterpillar) | I23: =(D3^2-D3*D4*C6)/D3^2+D4^2-2*D3*D4*C6 -> 0.69531806 | J23: =(D3^2*I24^2)+(D4^2*I23^2)+2*I23*I24*D3*D4*C6 -> 0.00043604804 | K23: =SQRT(J23) -> 0.020881763
B24: =(B14^2*D3^2)+(C14^2*D4^2)+2*B14*C14*D3*D4*C6 -> 0.00042025 | D24: -0.0007 | E24: =SQRT(B24) -> 0.0205 | H24: W(Boeng) | I24: =1-I23 -> 0.30468194

Sheet 4. Portfolio with Weights
A1: Portfolio | B1: Mean Return | C1: Standard Deviation
A2: --------- | B2: ------------ | C2: -------------------
A3: (160%, -60%) | B3: -0.00128 | C3: 0.0472
A4: (140%, -40%) | B4: -0.00103 | C4: 0.0421
A5: (120%, -20%) | B5: -0.00078 | C5: 0.0371
A6: (100%, 0%) | B6: -0.00053 | C6: 0.0324
A7: (80%, 20%) | B7: -0.00029 | C7: 0.0281
A8: (60%, 40%) | B8: -4e-05 | C8: 0.0245
A9: (40%, 60%) | B9: 0.00021 | C9: 0.0217
A10: (20%, 80%) | B10: 0.00046 | C10: 0.0203
A11: (0%, 100%) | B11: 0.00071 | C11: 0.0205
A12: (-20%, 120%) | B12: 0.00096 | C12: 0.0222
A13: (-40%, 140%) | B13: 0.00121 | C13: 0.0251
A14: (-60%, 160%) | B14: 0.00146 | C14: 0.0289

Sheet 5. Minimum Variance Portfolio
C6: Exp Return (μ) | D6: Std Dev (σ)
B7: Boeing | C7: -0.0005 | D7: 0.0324
B8: Caterpillar μ | C8: 0.0007 | D8: 0.0205
B10: Corr Coeff (ρ) | C10: 0.4812
G13: MVP | H13: Min Std Dev
E14: w(Caterpillar) | F14: =(D7^2-D7*D8*C10)/D7^2+D8^2+2*D7*D8*C10 -> 0.69659651 | G14: =(D7^2*F15^2)+(D8^2*F14^2)+2*F14*F15*D7*D8*C10 -> 0.0004356595 | H14: 0.0209
E15: w(Boeing) | F15: =1-F14 -> 0.30340349

Sheet Stock Details
B2: Boeing Price | G2: Caterpillar Price
B3: Date | C3: Closing | D3: Log Returns | E3: Daily Returns | G3: Date | H3: Closing | I3: Log Returns | J3: Daily Returns
B4: 45471 | C4: 182.01 | D4: =LN(C4/C5) -> -0.0027433354 | E4: N/A | G4: 45471 | H4: 333.1 | I4: =LN(H4/H5) -> 0.017076835 | J4: N/A
B5: 45470 | C5: 182.51 | D5: =LN(C5/C6) -> 0.022216365 | E5: 0.0027471018 | G5: 45470 | H5: 327.46 | I5: =LN(H5/H6) -> 0.0022317685 | J5: -0.016931852
B6: 45469 | C6: 178.5 | D6: =LN(C6/C7) -> 0.019231362 | E6: -0.021971399 | G6: 45469 | H6: 326.73 | I6: =LN(H6/H7) -> -0.0020485232 | J6: -0.0022292799
B7: 45468 | C7: 175.1 | D7: =LN(C7/C8) -> -0.02258707 | E7: -0.019047619 | G7: 45468 | H7: 327.4 | I7: =LN(H7/H8) -> -0.0079099895 | J7: 0.0020506228
B8: 45467 | C8: 179.1 | D8: =LN(C8/C9) -> 0.014283547 | E8: 0.022844089 | G8: 45467 | H8: 330 | I8: =LN(H8/H9) -> 0.00656697 | J8: 0.0079413561
B9: 45464 | C9: 176.56 | D9: =LN(C9/C10) -> 0.0014736725 | E9: -0.014182021 | G9: 45464 | H9: 327.84 | I9: =LN(H9/H10) -> -0.003927125 | J9: -0.0065454545
B10: 45463 | C10: 176.3 | D10: =LN(C10/C11) -> 0.00745826 | E10: -0.0014725872 | G10: 45463 | H10: 329.13 | I10: =LN(H10/H11) -> 0.012196951 | J10: 0.0039348463
B11: 45461 | C11: 174.99 | D11: =LN(C11/C12) -> -0.019243335 | E11: -0.0074305162 | G11: 45461 | H11: 325.14 | I11: =LN(H11/H12) -> 0.0084628482 | J11: -0.012122869
B12: 45460 | C12: 178.39 | D12: =LN(C12/C13) -> 0.0062981707 | E12: 0.019429682 | G12: 45460 | H12: 322.4 | I12: =LN(H12/H13) -> 0.0028887839 | J12: -0.0084271391
B13: 45457 | C13: 177.27 | D13: =LN(C13/C14) -> -0.019164204 | E13: -0.0062783788 | G13: 45457 | H13: 321.47 | I13: =LN(H13/H14) -> -0.01509684 | J13: -0.0028846154
B14: 45456 | C14: 180.7 | D14: =LN(C14/C15) -> -0.010843049 | E14: 0.019349016 | G14: 45456 | H14: 326.36 | I14: =LN(H14/H15) -> -0.0072356786 | J14: 0.015211373
B15: 45455 | C15: 182.67 | D15: =LN(C15/C16) -> -0.015373636 | E15: 0.010902048 | G15: 45455 | H15: 328.73 | I15: =LN(H15/H16) -> 0.0043290111 | J15: 0.0072619194
B16: 45454 | C16: 185.5 | D16: =LN(C16/C17) -> -0.02460057 | E16: 0.015492418 | G16: 45454 | H16: 327.31 | I16: =LN(H16/H17) -> -0.0070024033 | J16: -0.0043196544
... B1260: 43648 | C1260: 354.16 | D1260: =LN(C1260/C1261) -> -0.0064732432 | E1260: -0.0008745451 | G1260: 43648 | H1260: 135.85 | I1260: =LN(H1260/H1261) -> -0.0055056113 | J1260: 0.0019175455
B1261: 43647 | C1261: 356.46 | E1261: 0.0064942399 | G1261: 43647 | H1261: 136.6 | J1261: 0.005520795

Sheet Bond Historical Price
B1: Date US10YTB | C1: Rf-LT COMPOSITE (>10 Yrs) (%) | D1: Rf | E1: Rf Daily
B2: 06/28/2024 | C2: 4.58 | D2: =C2/100 -> 0.0458 | E2: {=(1+D2:D1259)^(1/252)-1} -> 0.00017772271
B3: 06/27/2024 | C3: 4.5 | D3: =C3/100 -> 0.045 | E3: 0.00017468544
B4: 06/26/2024 | C4: 4.52 | D4: =C4/100 -> 0.0452 | E4: 0.00017544497
B5: 06/25/2024 | C5: 4.43 | D5: =C5/100 -> 0.0443 | E5: 0.00017202592
B6: 06/24/2024 | C6: 4.45 | D6: =C6/100 -> 0.0445 | E6: 0.00017278597
B7: 06/21/2024 | C7: 4.46 | D7: =C7/100 -> 0.0446 | E7: 0.00017316593
B8: 06/20/2024 | C8: 4.46 | D8: =C8/100 -> 0.0446 | E8: 0.00017316593
B9: 06/18/2024 | C9: 4.43 | D9: =C9/100 -> 0.0443 | E9: 0.00017202592
B10: 06/17/2024 | C10: 4.48 | D10: =C10/100 -> 0.0448 | E10: 0.00017392576
B11: 06/14/2024 | C11: 4.42 | D11: =C11/100 -> 0.0442 | E11: 0.00017164585
B12: 06/13/2024 | C12: 4.46 | D12: =C12/100 -> 0.0446 | E12: 0.00017316593
B13: 45632 | C13: 4.53 | D13: =C13/100 -> 0.0453 | E13: 0.00017582468
B14: 45602 | C14: 4.59 | D14: =C14/100 -> 0.0459 | E14: 0.0001781022
B15: 45571 | C15: 4.66 | D15: =C15/100 -> 0.0466 | E15: 0.00018075766
B16: 45479 | C16: 4.61 | D16: =C16/100 -> 0.0461 | E16: 0.00017886109
B17: 45449 | C17: 4.48 | D17: =C17/100 -> 0.0448 | E17: 0.00017392576
B18: 45418 | C18: 4.5 | D18: =C18/100 -> 0.045 | E18: 0.00017468544
B19: 45388 | C19: 4.54 | D19: =C19/100 -> 0.0454 | E19: 0.00017620436
B20: 45357 | C20: 4.61 | D20: =C20/100 -> 0.0461 | E20: 0.00017886109
B21: 05/31/2024 | C21: 4.71 | D21: =C21/100 -> 0.0471 | E21: 0.00018265334
B22: 05/30/2024 | C22: 4.75 | D22: =C22/100 -> 0.0475 | E22: 0.00018416923
B23: 05/29/2024 | C23: 4.8 | D23: =C23/100 -> 0.048 | E23: 0.00018606328
B24: 05/28/2024 | C24: 4.73 | D24: =C24/100 -> 0.0473 | E24: 0.00018341136
B25: 05/24/2024 | C25: 4.64 | D25: =C25/100 -> 0.0464 | E25: 0.00017999914
B26: 05/23/2024 | C26: 4.65 | D26: =C26/100 -> 0.0465 | E26: 0.00018037842
B27: 05/22/2024 | C27: 4.61 | D27: =C27/100 -> 0.0461 | E27: 0.00017886109
B28: 05/21/2024 | C28: 4.62 | D28: =C28/100 -> 0.0462 | E28: 0.00017924047
B29: 05/20/2024 | C29: 4.64 | D29: =C29/100 -> 0.0464 | E29: 0.00017999914
B30: 05/17/2024 | C30: 4.62 | D30: =C30/100 -> 0.0462 | E30: 0.00017924047
B31: 05/16/2024 | C31: 4.58 | D31: =C31/100 -> 0.0458 | E31: 0.00017772271
B32: 05/15/2024 | C32: 4.57 | D32: =C32/100 -> 0.0457 | E32: 0.00017734317
... B34: 05/13/2024 | C34: 4.69 | D34: =C34/100 -> 0.0469 | E34: 0.00018189518
B35: 45570 | C35: 4.71 | D35: =C35/100 -> 0.0471 | E35: 0.00018265334
B36: 45540 | C36: 4.67 | D36: =C36/100 -> 0.0467 | E36: 0.00018113687
B37: 45509 | C37: 4.7 | D37: =C37/100 -> 0.047 | E37: 0.00018227428
B38: 45478 | C38: 4.67 | D38: =C38/100 -> 0.0467 | E38: 0.00018113687
B39: 45448 | C39: 4.7 | D39: =C39/100 -> 0.047 | E39: 0.00018227428
B40: 45356 | C40: 4.72 | D40: =C40/100 -> 0.0472 | E40: 0.00018303237
B41: 45327 | C41: 4.79 | D41: =C41/100 -> 0.0479 | E41: 0.00018568454
B42: 45296 | C42: 4.81 | D42: =C42/100 -> 0.0481 | E42: 0.00018644199
B43: 04/30/2024 | C43: 4.87 | D43: =C43/100 -> 0.0487 | E43: 0.00018871345
B44: 04/29/2024 | C44: 4.82 | D44: =C44/100 -> 0.0482 | E44: 0.00018682065
B45: 04/26/2024 | C45: 4.86 | D45: =C45/100 -> 0.0486 | E45: 0.00018833496
B46: 04/25/2024 | C46: 4.9 | D46: =C46/100 -> 0.049 | E46: 0.00018984869
B47: 04/24/2024 | C47: 4.86 | D47: =C47/100 -> 0.0486 | E47: 0.00018833496
B48: 04/23/2024 | C48: 4.81 | D48: =C48/100 -> 0.0481 | E48: 0.00018644199
B49: 04/22/2024 | C49: 4.81 | D49: =C49/100 -> 0.0481 | E49: 0.00018644199
B50: 04/19/2024 | C50: 4.8 | D50: =C50/100 -> 0.048 | E50: 0.00018606328
B51: 04/18/2024 | C51: 4.83 | D51: =C51/100 -> 0.0483 | E51: 0.00018719928
B52: 04/17/2024 | C52: 4.79 | D52: =C52/100 -> 0.0479 | E52: 0.00018568454
B53: 04/16/2024 | C53: 4.85 | D53: =C53/100 -> 0.0485 | E53: 0.00018795644
B54: 04/15/2024 | C54: 4.82 | D54: =C54/100 -> 0.0482 | E54: 0.00018682065
B55: 45630 | C55: 4.7 | D55: =C55/100 -> 0.047 | E55: 0.00018227428
B56: 45600 | C56: 4.74 | D56: =C56/100 -> 0.0474 | E56: 0.00018379031
B57: 45569 | C57: 4.72 | D57: =C57/100 -> 0.0472 | E57: 0.00018303237
B58: 45539 | C58: 4.56 | D58: =C58/100 -> 0.0456 | E58: 0.00017696361
B59: 45508 | C59: 4.62 | D59: =C59/100 -> 0.0462 | E59: 0.00017924047
B60: 45416 | C60: 4.61 | D60: =C60/100 -> 0.0461 | E60: 0.00017886109
B61: 45386 | C61: 4.54 | D61: =C61/100 -> 0.0454 | E61: 0.00017620436
B62: 45355 | C62: 4.58 | D62: =C62/100 -> 0.0458 | E62: 0.00017772271
B63: 45326 | C63: 4.58 | D63: =C63/100 -> 0.0458 | E63: 0.00017772271
B64: 45295 | C64: 4.54 | D64: =C64/100 -> 0.0454 | E64: 0.00017620436
B65: 03/28/2024 | C65: 4.42 | D65: =C65/100 -> 0.0442 | E65: 0.00017164585
B66: 03/27/2024 | C66: 4.43 | D66: =C66/100 -> 0.0443 | E66: 0.00017202592
B67: 03/26/2024 | C67: 4.47 | D67: =C67/100 -> 0.0447 | E67: 0.00017354586
B68: 03/25/2024 | C68: 4.49 | D68: =C68/100 -> 0.0449 | E68: 0.00017430561
B69: 03/22/2024 | C69: 4.46 | D69: =C69/100 -> 0.0446 | E69: 0.00017316593
B70: 03/21/2024 | C70: 4.52 | D70: =C70/100 -> 0.0452 | E70: 0.00017544497
B71: 03/20/2024 | C71: 4.52 | D71: =C71/100 -> 0.0452 | E71: 0.00017544497
B72: 03/19/2024 | C72: 4.52 | D72: =C72/100 -> 0.0452 | E72: 0.00017544497
B73: 03/18/2024 | C73: 4.55 | D73: =C73/100 -> 0.0455 | E73: 0.000176584
B74: 03/15/2024 | C74: 4.53 | D74: =C74/100 -> 0.0453 | E74: 0.00017582468
B75: 03/14/2024 | C75: 4.52 | D75: =C75/100 -> 0.0452 | E75: 0.00017544497
B76: 03/13/2024 | C76: 4.43 | D76: =C76/100 -> 0.0443 | E76: 0.00017202592
B77: 45629 | C77: 4.4 | D77: =C77/100 -> 0.044 | E77: 0.00017088559
B78: 45599 | C78: 4.34 | D78: =C78/100 -> 0.0434 | E78: 0.00016860394
B79: 45507 | C79: 4.34 | D79: =C79/100 -> 0.0434 | E79: 0.00016860394
B80: 45476 | C80: 4.33 | D80: =C80/100 -> 0.0433 | E80: 0.00016822354
B81: 45446 | C81: 4.33 | D81: =C81/100 -> 0.0433 | E81: 0.00016822354
B82: 45415 | C82: 4.37 | D82: =C82/100 -> 0.0437 | E82: 0.00016974493
B83: 45385 | C83: 4.46 | D83: =C83/100 -> 0.0446 | E83: 0.00017316593
B84: 45294 | C84: 4.43 | D84: =C84/100 -> 0.0443 | E84: 0.00017202592
B85: 02/29/2024 | C85: 4.48 | D85: =C85/100 -> 0.0448 | E85: 0.00017392576
B86: 02/28/2024 | C86: 4.51 | D86: =C86/100 -> 0.0451 | E86: 0.00017506522
B87: 02/27/2024 | C87: 4.55 | D87: =C87/100 -> 0.0455 | E87: 0.000176584
B88: 02/26/2024 | C88: 4.51 | D88: =C88/100 -> 0.0451 | E88: 0.00017506522
B89: 02/23/2024 | C89: 4.49 | D89: =C89/100 -> 0.0449 | E89: 0.00017430561
B90: 02/22/2024 | C90: 4.57 | D90: =C90/100 -> 0.0457 | E90: 0.00017734317
B91: 02/21/2024 | C91: 4.59 | D91: =C91/100 -> 0.0459 | E91: 0.0001781022
B92: 02/20/2024 | C92: 4.54 | D92: =C92/100 -> 0.0454 | E92: 0.00017620436
B93: 02/16/2024 | C93: 4.55 | D93: =C93/100 -> 0.0455 | E93: 0.000176584
B94: 02/15/2024 | C94: 4.51 | D94: =C94/100 -> 0.0451 | E94: 0.00017506522
B95: 02/14/2024 | C95: 4.54 | D95: =C95/100 -> 0.0454 | E95: 0.00017620436
B96: 02/13/2024 | C96: 4.57 | D96: =C96/100 -> 0.0457 | E96: 0.00017734317
B97: 45628 | C97: 4.46 | D97: =C97/100 -> 0.0446 | E97: 0.00017316593
B98: 45537 | C98: 4.46 | D98: =C98/100 -> 0.0446 | E98: 0.00017316593
B99: 45506 | C99: 4.45 | D99: =C99/100 -> 0.0445 | E99: 0.00017278597
B100: 45475 | C100: 4.39 | D100: =C100/100 -> 0.0439 | E100: 0.00017050541
B101: 45445 | C101: 4.37 | D101: =C101/100 -> 0.0437 | E101: 0.00016974493
...

Sheet 6. Efficient Frontier and CAL
B4: Summary Statistics | G4: Portfolio Weights | J4: Portfolio Stats | N4: Capital Allocation Line
C5: Boeing | D5: Caterpillar | G5: Boeing | H5: Caterpillar | J5: Returns | K5: Std Dev | L5: Sharpe Ratio | N5: Weight | O5: Return | P5: St Dev
B6: Mean | C6: =AVERAGE('Stock Details'!D4:D1260) -> -0.00053473381 | D6: =AVERAGE('Stock Details'!I4:I1260) -> 0.00070913747 | G6: =1-H6 -> 1.6 | H6: -0.6 | J6: =(G6*$C$6)+(H6*$D$6) -> -0.0012810566 | K6: =((G6^2*$C$7^2)+(H6^2*$D$7^2)+(2*G6*H6*$C$9*$C$7*$D$7))^(1/2) -> 0.046615381 | L6: =(J6-$C$10)/K6 -> -0.029835917 | N6: 0 | O6: =(N6*$J$17)+((1-N6)*C10) -> 0.00010975608 | P6: =(N6*$K$17) -> 0
B7: Standard Deviation | C7: =_xlfn.STDEV.P('Stock Details'!D4:D1260) -> 0.032019725 | D7: =_xlfn.STDEV.P('Stock Details'!I4:I1260) -> 0.020371718 | G7: =1-H7 -> 1.4 | H7: =H6+20% -> -0.4 | J7: =(G7*$C$6)+(H7*$D$6) -> -0.0010322823 | K7: =((G7^2*$C$7^2)+(H7^2*$D$7^2)+(2*G7*H7*$C$9*$C$7*$D$7))^(1/2) -> 0.041536554 | L7: =(J7-$C$10)/K7 -> -0.027494779 | N7: 1 | O7: =(N7*$J$17)+((1-N7)*C11) -> 0.0014554602 | P7: =(N7*$K$17) -> 0.028817196
B8: Variance | C8: =C7^2 -> 0.0010252628 | D8: =D7^2 -> 0.00041500691 | G8: =1-H8 -> 1.2 | H8: =H7+20% -> -0.2 | J8: =(G8*$C$6)+(H8*$D$6) -> -0.00078350807 | K8: =((G8^2*$C$7^2)+(H8^2*$D$7^2)+(2*G8*H8*$C$9*$C$7*$D$7))^(1/2) -> 0.036642985 | L8: =(J8-$C$10)/K8 -> -0.024377494 | N8: 2 | O8: =(N8*$J$17)+((1-N8)*C12) -> 0.0029109205 | P8: =(N8*$K$17) -> 0.057634393
B9: Correlation | C9: =CORREL('Stock Details'!D4:D1260,'Stock Details'!I4:I1260) -> 0.47993991 | G9: =1-H9 -> 1 | H9: =H8+20% -> 0 | J9: =(G9*$C$6)+(H9*$D$6) -> -0.00053473381 | K9: =((G9^2*$C$7^2)+(H9^2*$D$7^2)+(2*G9*H9*$C$9*$C$7*$D$7))^(1/2) -> 0.032019725 | L9: =(J9-$C$10)/K9 -> -0.020127902
B10: Risk Free Rate | C10: =AVERAGE(_xlfn.ANCHORARRAY('Bond Historical Price'!E2)) -> 0.00010975608 | G10: =1-H10 -> 0.8 | H10: =H9+20% -> 0.2 | J10: =(G10*$C$6)+(H10*$D$6) -> -0.00028595956 | K10: =((G10^2*$C$7^2)+(H10^2*$D$7^2)+(2*G10*H10*$C$9*$C$7*$D$7))^(1/2) -> 0.027801955 | L10: =(J10-$C$10)/K10 -> -0.014233374
G11: =1-H11 -> 0.6 | H11: =H10+20% -> 0.4 | J11: =(G11*$C$6)+(H11*$D$6) -> -3.7185299e-05 | K11: =((G11^2*$C$7^2)+(H11^2*$D$7^2)+(2*G11*H11*$C$9*$C$7*$D$7))^(1/2) -> 0.024202605 | L11: =(J11-$C$10)/K11 -> -0.0060713041
G12: =1-H12 -> 0.4 | H12: =H11+20% -> 0.6 | J12: =(G12*$C$6)+(H12*$D$6) -> 0.00021158896 | K12: =((G12^2*$C$7^2)+(H12^2*$D$7^2)+(2*G12*H12*$C$9*$C$7*$D$7))^(1/2) -> 0.021534041 | L12: =(J12-$C$10)/K12 -> 0.0047289257
G13: =1-H13 -> 0.2 | H13: =H12+20% -> 0.8 | J13: =(G13*$C$6)+(H13*$D$6) -> 0.00046036321 | K13: =((G13^2*$C$7^2)+(H13^2*$D$7^2)+(2*G13*H13*$C$9*$C$7*$D$7))^(1/2) -> 0.020169164 | L13: =(J13-$C$10)/K13 -> 0.017383325
G14: =1-H14 -> 0 | H14: =H13+20% -> 1 | J14: =(G14*$C$6)+(H14*$D$6) -> 0.00070913747 | K14: =((G14^2*$C$7^2)+(H14^2*$D$7^2)+(2*G14*H14*$C$9*$C$7*$D$7))^(1/2) -> 0.020371718 | L14: =(J14-$C$10)/K14 -> 0.02942223
G15: =1-H15 -> -0.2 | H15: =H14+20% -> 1.2 | J15: =(G15*$C$6)+(H15*$D$6) -> 0.00095791172 | K15: =((G15^2*$C$7^2)+(H15^2*$D$7^2)+(2*G15*H15*$C$9*$C$7*$D$7))^(1/2) -> 0.022098645 | L15: =(J15-$C$10)/K15 -> 0.038380438
G16: =1-H16 -> -0.4 | H16: =H15+20% -> 1.4 | J16: =(G16*$C$6)+(H16*$D$6) -> 0.001206686 | K16: =((G16^2*$C$7^2)+(H16^2*$D$7^2)+(2*G16*H16*$C$9*$C$7*$D$7))^(1/2) -> 0.025036468 | L16: =(J16-$C$10)/K16 -> 0.043813285
F17: Optimal Portfolio | G17: =1-H17 -> -0.6 | H17: =H16+20% -> 1.6 | J17: =(G17*$C$6)+(H17*$D$6) -> 0.0014554602 | K17: =((G17^2*$C$7^2)+(H17^2*$D$7^2)+(2*G17*H17*$C$9*$C$7*$D$7))^(1/2) -> 0.028817196 | L17: =(J17-$C$10)/K17 -> 0.046697956

Sheet 7. Risk Aversion with Utility
B3: k | C3: Weights
C4: Risk free asset(x) | D4: Asset A + Asset B(1-x) | E4: Portfolio return rp | F4: Portfolio Variance σp2 | G4: Utility (Portfolio return) - (k*portfolio variance)
B5: 1 | C5: =1-D5 -> 0.19143713 | D5: =$D$16/($E$16*B5) -> 0.80856287 | E5: =(C5*'6. Efficient Frontier and CAL'!$C$10)+('7. Risk Aversion with Utility'!D5*'6. Efficient Frontier and CAL'!$J$17) -> 0.0011978425 | F5: =(D5^2)*('6. Efficient Frontier and CAL'!$K$17^2) -> 0.000542914 | G5: =E5-(F5*B5) -> 0.0006549285
B6: 2 | C6: =1-D6 -> 0.59571856 | D6: =$D$16/($E$16*B6) -> 0.40428144 | E6: =(C6*'6. Efficient Frontier and CAL'!$C$10)+('7. Risk Aversion with Utility'!D6*'6. Efficient Frontier and CAL'!$J$17) -> 0.00065379929 | F6: =(D6^2)*('6. Efficient Frontier and CAL'!$K$17^2) -> 0.0001357285 | G6: =E6-(F6*B6) -> 0.00038234229
B7: 3 | C7: =1-D7 -> 0.73047904 | D7: =$D$16/($E$16*B7) -> 0.26952096 | E7: =(C7*'6. Efficient Frontier and CAL'!$C$10)+('7. Risk Aversion with Utility'!D7*'6. Efficient Frontier and CAL'!$J$17) -> 0.00047245155 | F7: =(D7^2)*('6. Efficient Frontier and CAL'!$K$17^2) -> 6.0323778e-05 | G7: =E7-(F7*B7) -> 0.00029148022
B8: 4 | C8: =1-D8 -> 0.79785928 | D8: =$D$16/($E$16*B8) -> 0.20214072 | E8: =(C8*'6. Efficient Frontier and CAL'!$C$10)+('7. Risk Aversion with Utility'!D8*'6. Efficient Frontier and CAL'!$J$17) -> 0.00038177768 | F8: =(D8^2)*('6. Efficient Frontier and CAL'!$K$17^2) -> 3.3932125e-05 | G8: =E8-(F8*B8) -> 0.00024604918
B9: 5 | C9: =1-D9 -> 0.83828743 | D9: =$D$16/($E$16*B9) -> 0.16171257 | E9: =(C9*'6. Efficient Frontier and CAL'!$C$10)+('7. Risk Aversion with Utility'!D9*'6. Efficient Frontier and CAL'!$J$17) -> 0.00032737336 | F9: =(D9^2)*('6. Efficient Frontier and CAL'!$K$17^2) -> 2.171656e-05 | G9: =E9-(F9*B9) -> 0.00021879056
B10: 6 | C10: =1-D10 -> 0.86523952 | D10: =$D$16/($E$16*B10) -> 0.13476048 | E10: =(C10*'6. Efficient Frontier and CAL'!$C$10)+('7. Risk Aversion with Utility'!D10*'6. Efficient Frontier and CAL'!$J$17) -> 0.00029110381 | F10: =(D10^2)*('6. Efficient Frontier and CAL'!$K$17^2) -> 1.5080945e-05 | G10: =E10-(F10*B10) -> 0.00020061815
B11: 7 | C11: =1-D11 -> 0.88449102 | D11: =$D$16/($E$16*B11) -> 0.11550898 | E11: =(C11*'6. Efficient Frontier and CAL'!$C$10)+('7. Risk Aversion with Utility'!D11*'6. Efficient Frontier and CAL'!$J$17) -> 0.00026519699 | F11: =(D11^2)*('6. Efficient Frontier and CAL'!$K$17^2) -> 1.1079878e-05 | G11: =E11-(F11*B11) -> 0.00018763785
B12: 8 | C12: =1-D12 -> 0.89892964 | D12: =$D$16/($E$16*B12) -> 0.10107036 | E12: =(C12*'6. Efficient Frontier and CAL'!$C$10)+('7. Risk Aversion with Utility'!D12*'6. Efficient Frontier and CAL'!$J$17) -> 0.00024576688 | F12: =(D12^2)*('6. Efficient Frontier and CAL'!$K$17^2) -> 8.4830313e-06 | G12: =E12-(F12*B12) -> 0.00017790263
D16: 0.0013503 | E16: 0.00167
B18: We know that :
B20: U = (Portfolio return)-(k*Portfolio variance) | E20: k is the risk aversion
B21: Let weight of risk free asset be 'x'
B22: Let weight of risky asset be 'y'
B24: U= (wf*rf+(1-wf)*rm)-k*((1-wf)*σm2
B26: rf is the return of the risk free asset
B27: rm is the expected return of the risky portfolio(consisting Stock A & Stock B)
B28: wf is the weight of the risk free asset
B30: k is the coefficient of risk aversion,
B31: As k increases, wf increases, meaning more weight is given to the risk free asset
B32: The weight of the Stock A and Stock B in the portfolio decrease as k increases, reflecting the investor's preference for lower risk
B33: That is the higher the k (risk aversion) the leaset are the portfolio returns and vice versa)
B34: Portfolio Returns, Portfolio Variance and the Utility Function are directly proportional where as K(risk aversion) is inversly proportional
B35: U= 0.0001097x + 0.00146y - k(y^2*(0.0289)^2)
... B46: And x here gives us the rate of risk free asset

Sheet 8.0 Market Raw Data
A1: Dates | B1: Rm-S&P PX_LAST | C1: Rm | E1: Date US10YTB | F1: Rf-LT COMPOSITE (>10 Yrs) (%) | G1: Rf (annual) | H1: Rf (daily) | J1: MARKET RISK PREMIUM (Rm-Rf)
A2: 45471 | B2: 5460.48 | C2: =LN(B2/B3) -> -0.0040919885 | E2: 06/28/2024 | F2: 4.58 | G2: =F2/100 -> 0.0458 | H2: =(1+G2)^(1/252)-1 -> 0.00017772271 | J2: =C2-H2 -> -0.0042697112
A3: 45470 | B3: 5482.87 | C3: =LN(B3/B4) -> 0.00090687066 | E3: 06/27/2024 | F3: 4.5 | G3: =F3/100 -> 0.045 | H3: =(1+G3)^(1/252)-1 -> 0.00017468544 | J3: =C3-H3 -> 0.00073218522
A4: 45469 | B4: 5477.9 | C4: =LN(B4/B5) -> 0.0015711783 | E4: 06/26/2024 | F4: 4.52 | G4: =F4/100 -> 0.0452 | H4: =(1+G4)^(1/252)-1 -> 0.00017544497 | J4: =C4-H4 -> 0.0013957334
A5: 45468 | B5: 5469.3 | C5: =LN(B5/B6) -> 0.0039259309 | E5: 06/25/2024 | F5: 4.43 | G5: =F5/100 -> 0.0443 | H5: =(1+G5)^(1/252)-1 -> 0.00017202592 | J5: =C5-H5 -> 0.003753905
A6: 45467 | B6: 5447.87 | C6: =LN(B6/B7) -> -0.0030698792 | E6: 06/24/2024 | F6: 4.45 | G6: =F6/100 -> 0.0445 | H6: =(1+G6)^(1/252)-1 -> 0.00017278597 | J6: =C6-H6 -> -0.0032426652
A7: 45464 | B7: 5464.62 | C7: =LN(B7/B8) -> -0.0015633874 | E7: 06/21/2024 | F7: 4.46 | G7: =F7/100 -> 0.0446 | H7: =(1+G7)^(1/252)-1 -> 0.00017316593 | J7: =C7-H7 -> -0.0017365534
A8: 45463 | B8: 5473.17 | C8: =LN(B8/B9) -> -0.0025291523 | E8: 06/20/2024 | F8: 4.46 | G8: =F8/100 -> 0.0446 | H8: =(1+G8)^(1/252)-1 -> 0.00017316593 | J8: =C8-H8 -> -0.0027023182
A9: 45461 | B9: 5487.03 | C9: =LN(B9/B10) -> 0.0025181898 | E9: 06/18/2024 | F9: 4.43 | G9: =F9/100 -> 0.0443 | H9: =(1+G9)^(1/252)-1 -> 0.00017202592 | J9: =C9-H9 -> 0.0023461638
A10: 45460 | B10: 5473.23 | C10: =LN(B10/B11) -> 0.0076351859 | E10: 06/17/2024 | F10: 4.48 | G10: =F10/100 -> 0.0448 | H10: =(1+G10)^(1/252)-1 -> 0.00017392576 | J10: =C10-H10 -> 0.0074612602
A11: 45457 | B11: 5431.6 | C11: =LN(B11/B12) -> -0.00039391313 | E11: 06/14/2024 | F11: 4.42 | G11: =F11/100 -> 0.0442 | H11: =(1+G11)^(1/252)-1 -> 0.00017164585 | J11: =C11-H11 -> -0.00056555898
A12: 45456 | B12: 5433.74 | C12: =LN(B12/B13) -> 0.0023418287 | E12: 06/13/2024 | F12: 4.46 | G12: =F12/100 -> 0.0446 | H12: =(1+G12)^(1/252)-1 -> 0.00017316593 | J12: =C12-H12 -> 0.0021686627
A13: 45455 | B13: 5421.03 | C13: =LN(B13/B14) -> 0.0084677272 | E13: 45632 | F13: 4.53 | G13: =F13/100 -> 0.0453 | H13: =(1+G13)^(1/252)-1 -> 0.00017582468 | J13: =C13-H13 -> 0.0082919025
A14: 45454 | B14: 5375.32 | C14: =LN(B14/B15) -> 0.0027067548 | E14: 45602 | F14: 4.59 | G14: =F14/100 -> 0.0459 | H14: =(1+G14)^(1/252)-1 -> 0.0001781022 | J14: =C14-H14 -> 0.0025286526
A15: 45453 | B15: 5360.79 | C15: =LN(B15/B16) -> 0.0025775665 | E15: 45571 | F15: 4.66 | G15: =F15/100 -> 0.0466 | H15: =(1+G15)^(1/252)-1 -> 0.00018075766 | J15: =C15-H15 -> 0.0023968089
A16: 45450 | B16: 5346.99 | C16: =LN(B16/B17) -> -0.0011158932 | E16: 45479 | F16: 4.61 | G16: =F16/100 -> 0.0461 | H16: =(1+G16)^(1/252)-1 -> 0.00017886109 | J16: =C16-H16 -> -0.0012947543
A17: 45449 | B17: 5352.96 | C17: =LN(B17/B18) -> -0.00019986943 | E17: 45449 | F17: 4.48 | G17: =F17/100 -> 0.0448 | H17: =(1+G17)^(1/252)-1 -> 0.00017392576 | J17: =C17-H17 -> -0.00037379519
A18: 45448 | B18: 5354.03 | C18: =LN(B18/B19) -> 0.011778026 | E18: 45418 | F18: 4.5 | G18: =F18/100 -> 0.045 | H18: =(1+G18)^(1/252)-1 -> 0.00017468544 | J18: =C18-H18 -> 0.011603341
A19: 45447 | B19: 5291.34 | C19: =LN(B19/B20) -> 0.001501692 | E19: 45388 | F19: 4.54 | G19: =F19/100 -> 0.0454 | H19: =(1+G19)^(1/252)-1 -> 0.00017620436 | J19: =C19-H19 -> 0.0013254877
A20: 45446 | B20: 5283.4 | C20: =LN(B20/B21) -> 0.0011154343 | E20: 45357 | F20: 4.61 | G20: =F20/100 -> 0.0461 | H20: =(1+G20)^(1/252)-1 -> 0.00017886109 | J20: =C20-H20 -> 0.00093657321
A21: 45443 | B21: 5277.51 | C21: =LN(B21/B22) -> 0.0079958649 | E21: 05/31/2024 | F21: 4.71 | G21: =F21/100 -> 0.0471 | H21: =(1+G21)^(1/252)-1 -> 0.00018265334 | J21: =C21-H21 -> 0.0078132116
A22: 45442 | B22: 5235.48 | C22: =LN(B22/B23) -> -0.0059929167 | E22: 05/30/2024 | F22: 4.75 | G22: =F22/100 -> 0.0475 | H22: =(1+G22)^(1/252)-1 -> 0.00018416923 | J22: =C22-H22 -> -0.006177086
A23: 45441 | B23: 5266.95 | C23: =LN(B23/B24) -> -0.0073943469 | E23: 05/29/2024 | F23: 4.8 | G23: =F23/100 -> 0.048 | H23: =(1+G23)^(1/252)-1 -> 0.00018606328 | J23: =C23-H23 -> -0.0075804102
A24: 45440 | B24: 5306.04 | C24: =LN(B24/B25) -> 0.00024880405 | E24: 05/28/2024 | F24: 4.73 | G24: =F24/100 -> 0.0473 | H24: =(1+G24)^(1/252)-1 -> 0.00018341136 | J24: =C24-H24 -> 6.5392689e-05
A25: 45436 | B25: 5304.72 | C25: =LN(B25/B26) -> 0.0069765789 | E25: 05/24/2024 | F25: 4.64 | G25: =F25/100 -> 0.0464 | H25: =(1+G25)^(1/252)-1 -> 0.00017999914 | J25: =C25-H25 -> 0.0067965798
A26: 45435 | B26: 5267.84 | C26: =LN(B26/B27) -> -0.0074081768 | E26: 05/23/2024 | F26: 4.65 | G26: =F26/100 -> 0.0465 | H26: =(1+G26)^(1/252)-1 -> 0.00018037842 | J26: =C26-H26 -> -0.0075885552
A27: 45434 | B27: 5307.01 | C27: =LN(B27/B28) -> -0.0027097177 | E27: 05/22/2024 | F27: 4.61 | G27: =F27/100 -> 0.0461 | H27: =(1+G27)^(1/252)-1 -> 0.00017886109 | J27: =C27-H27 -> -0.0028885788
A28: 45433 | B28: 5321.41 | C28: =LN(B28/B29) -> 0.0024986983 | E28: 05/21/2024 | F28: 4.62 | G28: =F28/100 -> 0.0462 | H28: =(1+G28)^(1/252)-1 -> 0.00017924047 | J28: =C28-H28 -> 0.0023194579
A29: 45432 | B29: 5308.13 | C29: =LN(B29/B30) -> 0.00091599607 | E29: 05/20/2024 | F29: 4.64 | G29: =F29/100 -> 0.0464 | H29: =(1+G29)^(1/252)-1 -> 0.00017999914 | J29: =C29-H29 -> 0.00073599693
A30: 45429 | B30: 5303.27 | C30: =LN(B30/B31) -> 0.0011641104 | E30: 05/17/2024 | F30: 4.62 | G30: =F30/100 -> 0.0462 | H30: =(1+G30)^(1/252)-1 -> 0.00017924047 | J30: =C30-H30 -> 0.00098486997
A31: 45428 | B31: 5297.1 | C31: =LN(B31/B32) -> -0.0020838743 | E31: 05/16/2024 | F31: 4.58 | G31: =F31/100 -> 0.0458 | H31: =(1+G31)^(1/252)-1 -> 0.00017772271 | J31: =C31-H31 -> -0.002261597
A32: 45427 | B32: 5308.15 | C32: =LN(B32/B33) -> 0.01164788 | E32: 05/15/2024 | F32: 4.57 | G32: =F32/100 -> 0.0457 | H32: =(1+G32)^(1/252)-1 -> 0.00017734317 | J32: =C32-H32 -> 0.011470537
... A34: 45425 | B34: 5221.42 | C34: =LN(B34/B35) -> -0.00024128455 | E34: 05/13/2024 | F34: 4.69 | G34: =F34/100 -> 0.0469 | H34: =(1+G34)^(1/252)-1 -> 0.00018189518 | J34: =C34-H34 -> -0.00042317973
A35: 45422 | B35: 5222.68 | C35: =LN(B35/B36) -> 0.0016480214 | E35: 45570 | F35: 4.71 | G35: =F35/100 -> 0.0471 | H35: =(1+G35)^(1/252)-1 -> 0.00018265334 | J35: =C35-H35 -> 0.0014653681
A36: 45421 | B36: 5214.08 | C36: =LN(B36/B37) -> 0.0050780026 | E36: 45540 | F36: 4.67 | G36: =F36/100 -> 0.0467 | H36: =(1+G36)^(1/252)-1 -> 0.00018113687 | J36: =C36-H36 -> 0.0048968657
A37: 45420 | B37: 5187.67 | C37: =LN(B37/B38) -> -5.7829263e-06 | E37: 45509 | F37: 4.7 | G37: =F37/100 -> 0.047 | H37: =(1+G37)^(1/252)-1 -> 0.00018227428 | J37: =C37-H37 -> -0.0001880572
A38: 45419 | B38: 5187.7 | C38: =LN(B38/B39) -> 0.0013425358 | E38: 45478 | F38: 4.67 | G38: =F38/100 -> 0.0467 | H38: =(1+G38)^(1/252)-1 -> 0.00018113687 | J38: =C38-H38 -> 0.0011613989
A39: 45418 | B39: 5180.74 | C39: =LN(B39/B40) -> 0.010273136 | E39: 45448 | F39: 4.7 | G39: =F39/100 -> 0.047 | H39: =(1+G39)^(1/252)-1 -> 0.00018227428 | J39: =C39-H39 -> 0.010090862
A40: 45415 | B40: 5127.79 | C40: =LN(B40/B41) -> 0.012478589 | E40: 45356 | F40: 4.72 | G40: =F40/100 -> 0.0472 | H40: =(1+G40)^(1/252)-1 -> 0.00018303237 | J40: =C40-H40 -> 0.012295556
A41: 45414 | B41: 5064.2 | C41: =LN(B41/B42) -> 0.0090870134 | E41: 45327 | F41: 4.79 | G41: =F41/100 -> 0.0479 | H41: =(1+G41)^(1/252)-1 -> 0.00018568454 | J41: =C41-H41 -> 0.0089013289
A42: 45413 | B42: 5018.39 | C42: =LN(B42/B43) -> -0.0034413924 | E42: 45296 | F42: 4.81 | G42: =F42/100 -> 0.0481 | H42: =(1+G42)^(1/252)-1 -> 0.00018644199 | J42: =C42-H42 -> -0.0036278344
A43: 45412 | B43: 5035.69 | C43: =LN(B43/B44) -> -0.015855555 | E43: 04/30/2024 | F43: 4.87 | G43: =F43/100 -> 0.0487 | H43: =(1+G43)^(1/252)-1 -> 0.00018871345 | J43: =C43-H43 -> -0.016044268
A44: 45411 | B44: 5116.17 | C44: =LN(B44/B45) -> 0.0031734157 | E44: 04/29/2024 | F44: 4.82 | G44: =F44/100 -> 0.0482 | H44: =(1+G44)^(1/252)-1 -> 0.00018682065 | J44: =C44-H44 -> 0.002986595
A45: 45408 | B45: 5099.96 | C45: =LN(B45/B46) -> 0.010157374 | E45: 04/26/2024 | F45: 4.86 | G45: =F45/100 -> 0.0486 | H45: =(1+G45)^(1/252)-1 -> 0.00018833496 | J45: =C45-H45 -> 0.0099690386
A46: 45407 | B46: 5048.42 | C46: =LN(B46/B47) -> -0.0045869419 | E46: 04/25/2024 | F46: 4.9 | G46: =F46/100 -> 0.049 | H46: =(1+G46)^(1/252)-1 -> 0.00018984869 | J46: =C46-H46 -> -0.0047767906
A47: 45406 | B47: 5071.63 | C47: =LN(B47/B48) -> 0.00021297197 | E47: 04/24/2024 | F47: 4.86 | G47: =F47/100 -> 0.0486 | H47: =(1+G47)^(1/252)-1 -> 0.00018833496 | J47: =C47-H47 -> 2.4637006e-05
A48: 45405 | B48: 5070.55 | C48: =LN(B48/B49) -> 0.011893625 | E48: 04/23/2024 | F48: 4.81 | G48: =F48/100 -> 0.0481 | H48: =(1+G48)^(1/252)-1 -> 0.00018644199 | J48: =C48-H48 -> 0.011707183
A49: 45404 | B49: 5010.6 | C49: =LN(B49/B50) -> 0.0086933277 | E49: 04/22/2024 | F49: 4.81 | G49: =F49/100 -> 0.0481 | H49: =(1+G49)^(1/252)-1 -> 0.00018644199 | J49: =C49-H49 -> 0.0085068857
A50: 45401 | B50: 4967.23 | C50: =LN(B50/B51) -> -0.0087971023 | E50: 04/19/2024 | F50: 4.8 | G50: =F50/100 -> 0.048 | H50: =(1+G50)^(1/252)-1 -> 0.00018606328 | J50: =C50-H50 -> -0.0089831656
A51: 45400 | B51: 5011.12 | C51: =LN(B51/B52) -> -0.0022106329 | E51: 04/18/2024 | F51: 4.83 | G51: =F51/100 -> 0.0483 | H51: =(1+G51)^(1/252)-1 -> 0.00018719928 | J51: =C51-H51 -> -0.0023978321
A52: 45399 | B52: 5022.21 | C52: =LN(B52/B53) -> -0.0057973364 | E52: 04/17/2024 | F52: 4.79 | G52: =F52/100 -> 0.0479 | H52: =(1+G52)^(1/252)-1 -> 0.00018568454 | J52: =C52-H52 -> -0.0059830209
A53: 45398 | B53: 5051.41 | C53: =LN(B53/B54) -> -0.0020586902 | E53: 04/16/2024 | F53: 4.85 | G53: =F53/100 -> 0.0485 | H53: =(1+G53)^(1/252)-1 -> 0.00018795644 | J53: =C53-H53 -> -0.0022466466
A54: 45397 | B54: 5061.82 | C54: =LN(B54/B55) -> -0.012094131 | E54: 04/15/2024 | F54: 4.82 | G54: =F54/100 -> 0.0482 | H54: =(1+G54)^(1/252)-1 -> 0.00018682065 | J54: =C54-H54 -> -0.012280951
A55: 45394 | B55: 5123.41 | C55: =LN(B55/B56) -> -0.014657607 | E55: 45630 | F55: 4.7 | G55: =F55/100 -> 0.047 | H55: =(1+G55)^(1/252)-1 -> 0.00018227428 | J55: =C55-H55 -> -0.014839881
A56: 45393 | B56: 5199.06 | C56: =LN(B56/B57) -> 0.0074172372 | E56: 45600 | F56: 4.74 | G56: =F56/100 -> 0.0474 | H56: =(1+G56)^(1/252)-1 -> 0.00018379031 | J56: =C56-H56 -> 0.0072334469
A57: 45392 | B57: 5160.64 | C57: =LN(B57/B58) -> -0.0095019783 | E57: 45569 | F57: 4.72 | G57: =F57/100 -> 0.0472 | H57: =(1+G57)^(1/252)-1 -> 0.00018303237 | J57: =C57-H57 -> -0.0096850107
A58: 45391 | B58: 5209.91 | C58: =LN(B58/B59) -> 0.0014444458 | E58: 45539 | F58: 4.56 | G58: =F58/100 -> 0.0456 | H58: =(1+G58)^(1/252)-1 -> 0.00017696361 | J58: =C58-H58 -> 0.0012674822
A59: 45390 | B59: 5202.39 | C59: =LN(B59/B60) -> -0.00037475749 | E59: 45508 | F59: 4.62 | G59: =F59/100 -> 0.0462 | H59: =(1+G59)^(1/252)-1 -> 0.00017924047 | J59: =C59-H59 -> -0.00055399797
A60: 45387 | B60: 5204.34 | C60: =LN(B60/B61) -> 0.011038073 | E60: 45416 | F60: 4.61 | G60: =F60/100 -> 0.0461 | H60: =(1+G60)^(1/252)-1 -> 0.00017886109 | J60: =C60-H60 -> 0.010859211
A61: 45386 | B61: 5147.21 | C61: =LN(B61/B62) -> -0.012410983 | E61: 45386 | F61: 4.54 | G61: =F61/100 -> 0.0454 | H61: =(1+G61)^(1/252)-1 -> 0.00017620436 | J61: =C61-H61 -> -0.012587187
A62: 45385 | B62: 5211.49 | C62: =LN(B62/B63) -> 0.0010904938 | E62: 45355 | F62: 4.58 | G62: =F62/100 -> 0.0458 | H62: =(1+G62)^(1/252)-1 -> 0.00017772271 | J62: =C62-H62 -> 0.0009127711
A63: 45384 | B63: 5205.81 | C63: =LN(B63/B64) -> -0.0072653957 | E63: 45326 | F63: 4.58 | G63: =F63/100 -> 0.0458 | H63: =(1+G63)^(1/252)-1 -> 0.00017772271 | J63: =C63-H63 -> -0.0074431184
A64: 45383 | B64: 5243.77 | C64: =LN(B64/B65) -> -0.0020155997 | E64: 45295 | F64: 4.54 | G64: =F64/100 -> 0.0454 | H64: =(1+G64)^(1/252)-1 -> 0.00017620436 | J64: =C64-H64 -> -0.002191804
A65: 45379 | B65: 5254.35 | C65: =LN(B65/B66) -> 0.0011158888 | E65: 03/28/2024 | F65: 4.42 | G65: =F65/100 -> 0.0442 | H65: =(1+G65)^(1/252)-1 -> 0.00017164585 | J65: =C65-H65 -> 0.00094424292
A66: 45378 | B66: 5248.49 | C66: =LN(B66/B67) -> 0.0085935659 | E66: 03/27/2024 | F66: 4.43 | G66: =F66/100 -> 0.0443 | H66: =(1+G66)^(1/252)-1 -> 0.00017202592 | J66: =C66-H66 -> 0.00842154
A67: 45377 | B67: 5203.58 | C67: =LN(B67/B68) -> -0.0028037482 | E67: 03/26/2024 | F67: 4.47 | G67: =F67/100 -> 0.0447 | H67: =(1+G67)^(1/252)-1 -> 0.00017354586 | J67: =C67-H67 -> -0.0029772941
A68: 45376 | B68: 5218.19 | C68: =LN(B68/B69) -> -0.0030595956 | E68: 03/25/2024 | F68: 4.49 | G68: =F68/100 -> 0.0449 | H68: =(1+G68)^(1/252)-1 -> 0.00017430561 | J68: =C68-H68 -> -0.0032339012
A69: 45373 | B69: 5234.18 | C69: =LN(B69/B70) -> -0.0014032464 | E69: 03/22/2024 | F69: 4.46 | G69: =F69/100 -> 0.0446 | H69: =(1+G69)^(1/252)-1 -> 0.00017316593 | J69: =C69-H69 -> -0.0015764123
A70: 45372 | B70: 5241.53 | C70: =LN(B70/B71) -> 0.0032313725 | E70: 03/21/2024 | F70: 4.52 | G70: =F70/100 -> 0.0452 | H70: =(1+G70)^(1/252)-1 -> 0.00017544497 | J70: =C70-H70 -> 0.0030559275
A71: 45371 | B71: 5224.62 | C71: =LN(B71/B72) -> 0.0088646978 | E71: 03/20/2024 | F71: 4.52 | G71: =F71/100 -> 0.0452 | H71: =(1+G71)^(1/252)-1 -> 0.00017544497 | J71: =C71-H71 -> 0.0086892529
A72: 45370 | B72: 5178.51 | C72: =LN(B72/B73) -> 0.0056332831 | E72: 03/19/2024 | F72: 4.52 | G72: =F72/100 -> 0.0452 | H72: =(1+G72)^(1/252)-1 -> 0.00017544497 | J72: =C72-H72 -> 0.0054578382
A73: 45369 | B73: 5149.42 | C73: =LN(B73/B74) -> 0.0062981689 | E73: 03/18/2024 | F73: 4.55 | G73: =F73/100 -> 0.0455 | H73: =(1+G73)^(1/252)-1 -> 0.000176584 | J73: =C73-H73 -> 0.0061215849
A74: 45366 | B74: 5117.09 | C74: =LN(B74/B75) -> -0.0065039961 | E74: 03/15/2024 | F74: 4.53 | G74: =F74/100 -> 0.0453 | H74: =(1+G74)^(1/252)-1 -> 0.00017582468 | J74: =C74-H74 -> -0.0066798208
A75: 45365 | B75: 5150.48 | C75: =LN(B75/B76) -> -0.0028752059 | E75: 03/14/2024 | F75: 4.52 | G75: =F75/100 -> 0.0452 | H75: =(1+G75)^(1/252)-1 -> 0.00017544497 | J75: =C75-H75 -> -0.0030506509
A76: 45364 | B76: 5165.31 | C76: =LN(B76/B77) -> -0.0019263916 | E76: 03/13/2024 | F76: 4.43 | G76: =F76/100 -> 0.0443 | H76: =(1+G76)^(1/252)-1 -> 0.00017202592 | J76: =C76-H76 -> -0.0020984175
A77: 45363 | B77: 5175.27 | C77: =LN(B77/B78) -> 0.011139497 | E77: 45629 | F77: 4.4 | G77: =F77/100 -> 0.044 | H77: =(1+G77)^(1/252)-1 -> 0.00017088559 | J77: =C77-H77 -> 0.010968612
A78: 45362 | B78: 5117.94 | C78: =LN(B78/B79) -> -0.0011228683 | E78: 45599 | F78: 4.34 | G78: =F78/100 -> 0.0434 | H78: =(1+G78)^(1/252)-1 -> 0.00016860394 | J78: =C78-H78 -> -0.0012914722
A79: 45359 | B79: 5123.69 | C79: =LN(B79/B80) -> -0.0065499381 | E79: 45507 | F79: 4.34 | G79: =F79/100 -> 0.0434 | H79: =(1+G79)^(1/252)-1 -> 0.00016860394 | J79: =C79-H79 -> -0.006718542
A80: 45358 | B80: 5157.36 | C80: =LN(B80/B81) -> 0.010251383 | E80: 45476 | F80: 4.33 | G80: =F80/100 -> 0.0433 | H80: =(1+G80)^(1/252)-1 -> 0.00016822354 | J80: =C80-H80 -> 0.010083159
A81: 45357 | B81: 5104.76 | C81: =LN(B81/B82) -> 0.0051279595 | E81: 45446 | F81: 4.33 | G81: =F81/100 -> 0.0433 | H81: =(1+G81)^(1/252)-1 -> 0.00016822354 | J81: =C81-H81 -> 0.004959736
A82: 45356 | B82: 5078.65 | C82: =LN(B82/B83) -> -0.010245349 | E82: 45415 | F82: 4.37 | G82: =F82/100 -> 0.0437 | H82: =(1+G82)^(1/252)-1 -> 0.00016974493 | J82: =C82-H82 -> -0.010415094
A83: 45355 | B83: 5130.95 | C83: =LN(B83/B84) -> -0.0011939974 | E83: 45385 | F83: 4.46 | G83: =F83/100 -> 0.0446 | H83: =(1+G83)^(1/252)-1 -> 0.00017316593 | J83: =C83-H83 -> -0.0013671634
A84: 45352 | B84: 5137.08 | C84: =LN(B84/B85) -> 0.0079759251 | E84: 45294 | F84: 4.43 | G84: =F84/100 -> 0.0443 | H84: =(1+G84)^(1/252)-1 -> 0.00017202592 | J84: =C84-H84 -> 0.0078038991
A85: 45351 | B85: 5096.27 | C85: =LN(B85/B86) -> 0.0052154204 | E85: 02/29/2024 | F85: 4.48 | G85: =F85/100 -> 0.0448 | H85: =(1+G85)^(1/252)-1 -> 0.00017392576 | J85: =C85-H85 -> 0.0050414946
A86: 45350 | B86: 5069.76 | C86: =LN(B86/B87) -> -0.0016594505 | E86: 02/28/2024 | F86: 4.51 | G86: =F86/100 -> 0.0451 | H86: =(1+G86)^(1/252)-1 -> 0.00017506522 | J86: =C86-H86 -> -0.0018345157
A87: 45349 | B87: 5078.18 | C87: =LN(B87/B88) -> 0.0017048185 | E87: 02/27/2024 | F87: 4.55 | G87: =F87/100 -> 0.0455 | H87: =(1+G87)^(1/252)-1 -> 0.000176584 | J87: =C87-H87 -> 0.0015282345
A88: 45348 | B88: 5069.53 | C88: =LN(B88/B89) -> -0.0037939352 | E88: 02/26/2024 | F88: 4.51 | G88: =F88/100 -> 0.0451 | H88: =(1+G88)^(1/252)-1 -> 0.00017506522 | J88: =C88-H88 -> -0.0039690005
A89: 45345 | B89: 5088.8 | C89: =LN(B89/B90) -> 0.00034788317 | E89: 02/23/2024 | F89: 4.49 | G89: =F89/100 -> 0.0449 | H89: =(1+G89)^(1/252)-1 -> 0.00017430561 | J89: =C89-H89 -> 0.00017357756
A90: 45344 | B90: 5087.03 | C90: =LN(B90/B91) -> 0.020902892 | E90: 02/22/2024 | F90: 4.57 | G90: =F90/100 -> 0.0457 | H90: =(1+G90)^(1/252)-1 -> 0.00017734317 | J90: =C90-H90 -> 0.020725549
A91: 45343 | B91: 4981.8 | C91: =LN(B91/B92) -> 0.0012633936 | E91: 02/21/2024 | F91: 4.59 | G91: =F91/100 -> 0.0459 | H91: =(1+G91)^(1/252)-1 -> 0.0001781022 | J91: =C91-H91 -> 0.0010852914
A92: 45342 | B92: 4975.51 | C92: =LN(B92/B93) -> -0.0060234145 | E92: 02/20/2024 | F92: 4.54 | G92: =F92/100 -> 0.0454 | H92: =(1+G92)^(1/252)-1 -> 0.00017620436 | J92: =C92-H92 -> -0.0061996188
A93: 45338 | B93: 5005.57 | C93: =LN(B93/B94) -> -0.0048150123 | E93: 02/16/2024 | F93: 4.55 | G93: =F93/100 -> 0.0455 | H93: =(1+G93)^(1/252)-1 -> 0.000176584 | J93: =C93-H93 -> -0.0049915963
A94: 45337 | B94: 5029.73 | C94: =LN(B94/B95) -> 0.0058044 | E94: 02/15/2024 | F94: 4.51 | G94: =F94/100 -> 0.0451 | H94: =(1+G94)^(1/252)-1 -> 0.00017506522 | J94: =C94-H94 -> 0.0056293348
A95: 45336 | B95: 5000.62 | C95: =LN(B95/B96) -> 0.0095341291 | E95: 02/14/2024 | F95: 4.54 | G95: =F95/100 -> 0.0454 | H95: =(1+G95)^(1/252)-1 -> 0.00017620436 | J95: =C95-H95 -> 0.0093579247
A96: 45335 | B96: 4953.17 | C96: =LN(B96/B97) -> -0.013768625 | E96: 02/13/2024 | F96: 4.57 | G96: =F96/100 -> 0.0457 | H96: =(1+G96)^(1/252)-1 -> 0.00017734317 | J96: =C96-H96 -> -0.013945968
A97: 45334 | B97: 5021.84 | C97: =LN(B97/B98) -> -0.00094940023 | E97: 45628 | F97: 4.46 | G97: =F97/100 -> 0.0446 | H97: =(1+G97)^(1/252)-1 -> 0.00017316593 | J97: =C97-H97 -> -0.0011225662
A98: 45331 | B98: 5026.61 | C98: =LN(B98/B99) -> 0.0057259756 | E98: 45537 | F98: 4.46 | G98: =F98/100 -> 0.0446 | H98: =(1+G98)^(1/252)-1 -> 0.00017316593 | J98: =C98-H98 -> 0.0055528097
A99: 45330 | B99: 4997.91 | C99: =LN(B99/B100) -> 0.00057040101 | E99: 45506 | F99: 4.45 | G99: =F99/100 -> 0.0445 | H99: =(1+G99)^(1/252)-1 -> 0.00017278597 | J99: =C99-H99 -> 0.00039761504
A100: 45329 | B100: 4995.06 | C100: =LN(B100/B101) -> 0.0082076669 | E100: 45475 | F100: 4.39 | G100: =F100/100 -> 0.0439 | H100: =(1+G100)^(1/252)-1 -> 0.00017050541 | J100: =C100-H100 -> 0.0080371615
A101: 45328 | B101: 4954.23 | C101: =LN(B101/B102) -> 0.0023077617 | E101: 45445 | F101: 4.37 | G101: =F101/100 -> 0.0437 | H101: =(1+G101)^(1/252)-1 -> 0.00016974493 | J101: =C101-H101 -> 0.0021380168
...

Sheet 8.1.Market Data
A1: Dates | B1: S&P PX_LAST= Rm | C1: Rm | D1: LT COMPOSITE (>10 Yrs)(%) | E1: Rf (annual) | F1: Rf (daily) | G1: MARKET RISK PREMIUM (Rm-Rf) | H1: R(BA) | I1: R(CAT) | J1: R(BA)-Rf | K1: R(CAT)-Rf
A2: 45471 | B2: 5460.48 | C2: =LN(B2/B3) -> -0.0040919885 | D2: 4.58 | E2: =D2/100 -> 0.0458 | F2: =(1+E2)^(1/252)-1 -> 0.00017772271 | G2: =C2-F2 -> -0.0042697112 | J2: =H2-F2 -> -0.00017772271 | K2: =I2-F2 -> -0.00017772271
A3: 45470 | B3: 5482.87 | C3: =LN(B3/B4) -> 0.00090687066 | D3: 4.5 | E3: =D3/100 -> 0.045 | F3: =(1+E3)^(1/252)-1 -> 0.00017468544 | G3: =C3-F3 -> 0.00073218522 | H3: 0.0027433354 | I3: -0.017076835 | J3: =H3-F3 -> 0.00256865 | K3: =I3-F3 -> -0.01725152
A4: 45469 | B4: 5477.9 | C4: =LN(B4/B5) -> 0.0015711783 | D4: 4.52 | E4: =D4/100 -> 0.0452 | F4: =(1+E4)^(1/252)-1 -> 0.00017544497 | G4: =C4-F4 -> 0.0013957334 | H4: -0.022216365 | I4: -0.0022317685 | J4: =H4-F4 -> -0.02239181 | K4: =I4-F4 -> -0.0024072134
A5: 45468 | B5: 5469.3 | C5: =LN(B5/B6) -> 0.0039259309 | D5: 4.43 | E5: =D5/100 -> 0.0443 | F5: =(1+E5)^(1/252)-1 -> 0.00017202592 | G5: =C5-F5 -> 0.003753905 | H5: -0.019231362 | I5: 0.0020485232 | J5: =H5-F5 -> -0.019403388 | K5: =I5-F5 -> 0.0018764973
A6: 45467 | B6: 5447.87 | C6: =LN(B6/B7) -> -0.0030698792 | D6: 4.45 | E6: =D6/100 -> 0.0445 | F6: =(1+E6)^(1/252)-1 -> 0.00017278597 | G6: =C6-F6 -> -0.0032426652 | H6: 0.02258707 | I6: 0.0079099895 | J6: =H6-F6 -> 0.022414284 | K6: =I6-F6 -> 0.0077372036
A7: 45464 | B7: 5464.62 | C7: =LN(B7/B8) -> -0.0015633874 | D7: 4.46 | E7: =D7/100 -> 0.0446 | F7: =(1+E7)^(1/252)-1 -> 0.00017316593 | G7: =C7-F7 -> -0.0017365534 | H7: -0.014283547 | I7: -0.00656697 | J7: =H7-F7 -> -0.014456713 | K7: =I7-F7 -> -0.0067401359
A8: 45463 | B8: 5473.17 | C8: =LN(B8/B9) -> -0.0025291523 | D8: 4.46 | E8: =D8/100 -> 0.0446 | F8: =(1+E8)^(1/252)-1 -> 0.00017316593 | G8: =C8-F8 -> -0.0027023182 | H8: -0.0014736725 | I8: 0.003927125 | J8: =H8-F8 -> -0.0016468385 | K8: =I8-F8 -> 0.0037539591
A9: 45461 | B9: 5487.03 | C9: =LN(B9/B10) -> 0.0025181898 | D9: 4.43 | E9: =D9/100 -> 0.0443 | F9: =(1+E9)^(1/252)-1 -> 0.00017202592 | G9: =C9-F9 -> 0.0023461638 | H9: -0.00745826 | I9: -0.012196951 | J9: =H9-F9 -> -0.0076302859 | K9: =I9-F9 -> -0.012368977
A10: 45460 | B10: 5473.23 | C10: =LN(B10/B11) -> 0.0076351859 | D10: 4.48 | E10: =D10/100 -> 0.0448 | F10: =(1+E10)^(1/252)-1 -> 0.00017392576 | G10: =C10-F10 -> 0.0074612602 | H10: 0.019243335 | I10: -0.0084628482 | J10: =H10-F10 -> 0.01906941 | K10: =I10-F10 -> -0.0086367739
A11: 45457 | B11: 5431.6 | C11: =LN(B11/B12) -> -0.00039391313 | D11: 4.42 | E11: =D11/100 -> 0.0442 | F11: =(1+E11)^(1/252)-1 -> 0.00017164585 | G11: =C11-F11 -> -0.00056555898 | H11: -0.0062981707 | I11: -0.0028887839 | J11: =H11-F11 -> -0.0064698166 | K11: =I11-F11 -> -0.0030604298
A12: 45456 | B12: 5433.74 | C12: =LN(B12/B13) -> 0.0023418287 | D12: 4.46 | E12: =D12/100 -> 0.0446 | F12: =(1+E12)^(1/252)-1 -> 0.00017316593 | G12: =C12-F12 -> 0.0021686627 | H12: 0.019164204 | I12: 0.01509684 | J12: =H12-F12 -> 0.018991038 | K12: =I12-F12 -> 0.014923674
A13: 45455 | B13: 5421.03 | C13: =LN(B13/B14) -> 0.0084677272 | D13: 4.53 | E13: =D13/100 -> 0.0453 | F13: =(1+E13)^(1/252)-1 -> 0.00017582468 | G13: =C13-F13 -> 0.0082919025 | H13: 0.010843049 | I13: 0.0072356786 | J13: =H13-F13 -> 0.010667224 | K13: =I13-F13 -> 0.0070598539
A14: 45454 | B14: 5375.32 | C14: =LN(B14/B15) -> 0.0027067548 | D14: 4.59 | E14: =D14/100 -> 0.0459 | F14: =(1+E14)^(1/252)-1 -> 0.0001781022 | G14: =C14-F14 -> 0.0025286526 | H14: 0.015373636 | I14: -0.0043290111 | J14: =H14-F14 -> 0.015195534 | K14: =I14-F14 -> -0.0045071133
... A1249: 43648 | B1249: 2973.01 | C1249: =LN(B1249/B1250) -> 0.0029238703 | D1249: 2.39 | E1249: =D1249/100 -> 0.0239 | F1249: =(1+E1249)^(1/252)-1 -> 9.373005e-05 | G1249: =C1249-F1249 -> 0.0028301403 | H1249: -0.00087492773 | I1249: 0.0019157094 | J1249: =H1249-F1249 -> -0.00096865778 | K1249: =I1249-F1249 -> 0.0018219793
A1250: 43647 | B1250: 2964.33 | D1250: 2.44 | E1250: =D1250/100 -> 0.0244 | F1250: =(1+E1250)^(1/252)-1 -> 9.5667573e-05 | G1250: =C1250-F1250 -> -9.5667573e-05 | H1250: 0.0064732432 | I1250: 0.0055056113 | J1250: =H1250-F1250 -> 0.0063775756 | K1250: =I1250-F1250 -> 0.0054099437

Sheet 8.2 Estimating Beta
A1: SUMMARY OUTPUT OF BOEING
A3: Regression Statistics
A4: Multiple R | B4: 0.063905725
A5: R Square | B5: 0.0040839417
A6: Adjusted R Square | B6: 0.0032852921
A7: Standard Error | B7: 0.032046391
A8: Observations | B8: 1249
A10: ANOVA
B11: df | C11: SS | D11: MS | E11: F | F11: Significance F
A12: Regression | B12: 1 | C12: 0.0052514776 | D12: 0.0052514776 | E12: 5.1135588 | F12: 0.023911257
A13: Residual | B13: 1247 | C13: 1.2806331 | D13: 0.0010269712
A14: Total | B14: 1248 | C14: 1.2858845
B16: Coefficients | C16: Standard Error | D16: t Stat | E16: P-value | F16: Lower 95% | G16: Upper 95% | H16: Lower 95.0% | I16: Upper 95.0%
A17: Intercept | B17: 0.00032098543 | C17: 0.00090712877 | D17: 0.3538477 | E17: 0.72351284 | F17: -0.0014586816 | G17: 0.0021006525 | H17: -0.0014586816 | I17: 0.0021006525
A18: MARKET RISK PREMIUM (Rm-Rf) | B18: 0.15204797 | C18: 0.06723865 | D18: 2.2613179 | E18: 0.023911257 | F18: 0.020134597 | G18: 0.28396133 | H18: 0.020134597 | I18: 0.28396133
A21: SUMMARY OUTPUT OF CATERPILLAR
A23: Regression Statistics
A24: Multiple R | B24: 0.073853051
A25: R Square | B25: 0.0054542731
A26: Adjusted R Square | B26: 0.0046567224
A27: Standard Error | B27: 0.020374229
A28: Observations | B28: 1249
A30: ANOVA
B31: df | C31: SS | D31: MS | E31: F | F31: Significance F
A32: Regression | B32: 1 | C32: 0.0028388402 | D32: 0.0028388402 | E32: 6.8387792 | F32: 0.0090275817
A33: Residual | B33: 1247 | C33: 0.51764117 | D33: 0.0004151092
A34: Total | B34: 1248 | C34: 0.52048001
B36: Coefficients | C36: Standard Error | D36: t Stat | E36: P-value | F36: Lower 95% | G36: Upper 95% | H36: Lower 95.0% | I36: Upper 95.0%
A37: Intercept | B37: -0.00084854501 | C37: 0.00057672794 | D37: -1.471309 | E37: 0.14145987 | F37: -0.0019800092 | G37: 0.00028291918 | H37: -0.0019800092 | I37: 0.00028291918
A38: MARKET RISK PREMIUM (Rm-Rf) | B38: 0.1117919 | C38: 0.042748515 | D38: 2.615106 | E38: 0.0090275817 | F38: 0.027924945 | G38: 0.19565885 | H38: 0.027924945 | I38: 0.19565885
A40: Interpretation
A41: The beta is a measure of how volatile an asset is as compared to the market. It signifies the sensitivty of the asset to movement in the market.
A42: The beta of both stocks are positive, which means that they move in line with the market. That is, an increase in the market would result in an increase in the stock prices as well.
A43: They are less than 1 however, which indicates that they are less volatile than the market. They are defensive and have smaller fluctuations in price as compared to to the market.
A44: The beta on the Boeing stock is higher than that of Caterpillar, which indicates greater sensitivity to the market.
A45: An increase in the market will provide higher returns on the Boeing stock than Caterpilar, but a fall in the market would lead to higher losses.
A46: Both stocks are defensive and can be added to a portfolio as a hedging tool. For a risk averse investor, Caterpillar is the more viable investment as it is more stable as compared to Boeing stock.

Sheet 9.1. Predicted Returns Raw Data
A1: Date | B1: Rm-S&P PX_LAST | C1: Rm | E1: =_xll.Thomson.Reuters.AFOSpreadsheetFormulas.DSGRID("U:BA","P","-6M","","D","RowHeader=true;ColHeader=true;DispSeriesDescription=false;YearlyTSFormat=false;QuarterlyTSFormat=false;MonthlyTSFormat=False","") -> #NAME? | F1: BOEING | G1: R(BA) | I1: =_xll.Thomson.Reuters.AFOSpreadsheetFormulas.DSGRID("U:CAT","P","-3M","","D","RowHeader=true;ColHeader=true;DispSeriesDescription=false;YearlyTSFormat=false;QuarterlyTSFormat=false;MonthlyTSFormat=False","") -> #NAME? | J1: CATERPILLAR | K1: R(CAT) | M1: Date | N1: Rf% | O1: Rf (Annual) | P1: Rf (daily)
A2: 45474 | B2: 5475.09 | E2: 45474 | F2: 186.7 | I2: 45474 | J2: 329.0801 | M2: 9th July 2024 | N2: 4.56 | O2: =N2/100 -> 0.0456 | P2: =(1+O2)^(1/252)-1 -> 0.00017696361
A3: 45475 | B3: 5509.01 | C3: =LN(B3/B2) -> 0.0061762198 | E3: 45475 | F3: 185.42 | G3: =LN(F3/F2) -> -0.0068795284 | I3: 45475 | J3: 327.76 | K3: =LN(J3/J2) -> -0.0040195529 | M3: 24th July 2024 | N3: 4.59 | O3: =N3/100 -> 0.0459 | P3: =(1+O3)^(1/252)-1 -> 0.0001781022
A4: 45476 | B4: 5537.02 | C4: =LN(B4/B3) -> 0.0050715162 | E4: 45476 | F4: 184.31 | G4: =LN(F4/F3) -> -0.0060043996 | I4: 45476 | J4: 330.6101 | K4: =LN(J4/J3) -> 0.0086581022 | M4: 31st July 2024 | N4: 4.39 | O4: =N4/100 -> 0.0439 | P4: =(1+O4)^(1/252)-1 -> 0.00017050541
A5: 45478 | B5: 5567.19 | C5: =LN(B5/B4) -> 0.0054339884 | E5: 45477 | F5: 184.31 | G5: =LN(F5/F4) -> 0 | I5: 45477 | J5: 330.6101 | K5: =LN(J5/J4) -> 0 | N5: *Source
A6: 45481 | B6: 5572.85 | C6: =LN(B6/B5) -> 0.0010161544 | E6: 45478 | F6: 184.83 | G6: =LN(F6/F5) -> 0.0028173611 | I6: 45478 | J6: 328.3501 | K6: =LN(J6/J5) -> -0.0068593182
A7: 45482 | B7: 5576.98 | C7: =LN(B7/B6) -> 0.0007408185 | E7: 45481 | F7: 185.84 | G7: =LN(F7/F6) -> 0.0054496048 | I7: 45481 | J7: 329.0601 | K7: =LN(J7/J6) -> 0.0021599917
A8: 45483 | B8: 5633.91 | C8: =LN(B8/B7) -> 0.010156284 | E8: 45482 | F8: 183.24 | G8: =LN(F8/F7) -> -0.014089319 | I8: 45482 | J8: 326.0601 | K8: =LN(J8/J7) -> -0.0091586887
A9: 45484 | B9: 5584.54 | C9: =LN(B9/B8) -> -0.0088016292 | E9: 45483 | F9: 183.73 | G9: =LN(F9/F8) -> 0.0026705196 | I9: 45483 | J9: 328.48 | K9: =LN(J9/J8) -> 0.0073942331
A10: 45485 | B10: 5615.35 | C10: =LN(B10/B9) -> 0.0055018536 | E10: 45484 | F10: 183.91 | G10: =LN(F10/F9) -> 0.00097921888 | I10: 45484 | J10: 331.1299 | K10: =LN(J10/J9) -> 0.0080347922
A11: 45488 | B11: 5631.22 | C11: =LN(B11/B10) -> 0.0028221957 | E11: 45485 | F11: 182.31 | G11: =LN(F11/F10) -> -0.0087379727 | I11: 45485 | J11: 335.5901 | K11: =LN(J11/J10) -> 0.013379729
A12: 45489 | B12: 5667.2 | C12: =LN(B12/B11) -> 0.0063690537 | E12: 45488 | F12: 179.11 | G12: =LN(F12/F11) -> -0.017708393 | I12: 45488 | J12: 345.77 | K12: =LN(J12/J11) -> 0.029883339
A13: 45490 | B13: 5588.27 | C13: =LN(B13/B12) -> -0.014025411 | E13: 45489 | F13: 186.05 | G13: =LN(F13/F12) -> 0.038015313 | I13: 45489 | J13: 360.5801 | K13: =LN(J13/J12) -> 0.041940309
A14: 45491 | B14: 5544.59 | C14: =LN(B14/B13) -> -0.0078470805 | E14: 45490 | F14: 184.84 | G14: =LN(F14/F13) -> -0.0065248688 | I14: 45490 | J14: 357.8 | K14: =LN(J14/J13) -> -0.0077399524
A15: 45492 | B15: 5505 | C15: =LN(B15/B14) -> -0.0071659074 | E15: 45491 | F15: 180.23 | G15: =LN(F15/F14) -> -0.025256773 | I15: 45491 | J15: 356.03 | K15: =LN(J15/J14) -> -0.0049591741
A16: 45495 | B16: 5564.41 | C16: =LN(B16/B15) -> 0.010734189 | E16: 45492 | F16: 179.67 | G16: =LN(F16/F15) -> -0.0031119781 | I16: 45492 | J16: 347.6299 | K16: =LN(J16/J15) -> -0.023876589
A17: 45496 | B17: 5555.74 | C17: =LN(B17/B16) -> -0.0015593318 | E17: 45495 | F17: 178.9 | G17: =LN(F17/F16) -> -0.0042948444 | I17: 45495 | J17: 347.8701 | K17: =LN(J17/J16) -> 0.00069072612
... A23: 45504 | B23: 5522.3 | C23: =LN(B23/B22) -> 0.015670005 | E23: 45503 | F23: 186.86 | G23: =LN(F23/F22) -> 0.007682221 | I23: 45503 | J23: 341.72 | K23: =LN(J23/J22) -> -0.0081894811
E24: 45504 | F24: 190.6 | G24: =LN(F24/F23) -> 0.019817318 | I24: 45504 | J24: 346.2 | K24: =LN(J24/J23) -> 0.013024954
E93: 45505 | F93: 178.31
E94: 45506 | F94: 169.95
E95: 45509 | F95: 167.03
E96: 45510 | F96: 165.04
E97: 45511 | F97: 163.24
E98: 45512 | F98: 168.87
E99: 45513 | F99: 167.91
E100: 45516 | F100: 164.13
E101: 45517 | F101: 168.76
E102: 45518 | F102: 168.5
E103: 45519 | F103: 176.41
E104: 45520 | F104: 179.99
... E134: 45562 | F134: 156.32

Sheet 9.2 Predicted Returns
A1: CAPM= Rf + Beta(Rm-Rf)
A3: Date | B3: Realised Market Risk Premium
B4: Rm | C4: Rf (daily) | D4: Rm-Rf
A5: 9th July 2024 | B5: ='9.1. Predicted Returns Raw Data'!$C$7 -> 0.0007408185 | C5: ='9.1. Predicted Returns Raw Data'!P2 -> 0.00017696361 | D5: =B5-C5 -> 0.0005638549
A6: 24th July 2024 | B6: ='9.1. Predicted Returns Raw Data'!C18 -> -0.023421178 | C6: ='9.1. Predicted Returns Raw Data'!P3 -> 0.0001781022 | D6: =B6-C6 -> -0.023599281
A7: 31st July 2024 | B7: ='9.1. Predicted Returns Raw Data'!C23 -> 0.015670005 | C7: ='9.1. Predicted Returns Raw Data'!P4 -> 0.00017050541 | D7: =B7-C7 -> 0.0154995
A10: Date | B10: Stock | C10: Beta | D10: Expected R(i)= CAPM | E10: Realised R(i) | F10: Jensons Alpha
A11: 9th July 2024 | B11: Rf | C11: 0 | D11: =$C$5+(C11*$D$5) -> 0.00017696361
B12: Boeing | C12: ='8.2 Estimating Beta'!$B$18 -> 0.15204797 | D12: =$C$5+(C12*$D$5) -> 0.0002626966 | E12: ='9.1. Predicted Returns Raw Data'!$G$8 -> -0.014089319 | F12: =E12-D12 -> -0.014352016
B13: Caterpillar | C13: ='8.2 Estimating Beta'!$B$38 -> 0.1117919 | D13: =$C$5+(C13*$D$5) -> 0.00023999801 | E13: ='9.1. Predicted Returns Raw Data'!$K$8 -> -0.0091586887 | F13: =E13-D13 -> -0.0093986867
A14: 24th July 2024 | B14: Rf | C14: 0 | D14: =$C$6+(C14*$D$6) -> 0.0001781022
B15: Boeing | C15: ='8.2 Estimating Beta'!$B$18 -> 0.15204797 | D15: =$C$6+(C15*$D$6) -> -0.0034101204 | E15: ='9.1. Predicted Returns Raw Data'!$G$19 -> -0.034978331 | F15: =E15-D15 -> -0.03156821
B16: Caterpillar | C16: ='8.2 Estimating Beta'!$B$38 -> 0.1117919 | D16: =$C$6+(C16*$D$6) -> -0.0024601062 | E16: ='9.1. Predicted Returns Raw Data'!$K$19 -> -0.02390523 | F16: =E16-D16 -> -0.021445124
A17: 31st July 2024 | B17: Rf | C17: 0 | D17: =$C$7+(C17*$D$7) -> 0.00017050541
B18: Boeing | C18: ='8.2 Estimating Beta'!$B$18 -> 0.15204797 | D18: =$C$7+(C18*$D$7) -> 0.0025271728 | E18: ='9.1. Predicted Returns Raw Data'!$G$24 -> 0.019817318 | F18: =E18-D18 -> 0.017290145
B19: Caterpillar | C19: ='8.2 Estimating Beta'!$B$38 -> 0.1117919 | D19: =$C$7+(C19*$D$7) -> 0.0019032239 | E19: ='9.1. Predicted Returns Raw Data'!$K$24 -> 0.013024954 | F19: =E19-D19 -> 0.011121731
H25: Interpretation
H26: The realised/actual returns plots below the SML for both 9th and 24th July. This signifies that the stocks underpeformed against the expected return on these two days.
H27: This is further proved by the negative Jenson's alpha calculated on both days.
H28: A negative alpha signifies that the stock in the market is yielding less than what is expected, which implies that both stocks are overvalued.
H29: The realised return on 31st July plots above the SML which indicates that the stocks are undervalued.
H30: A positive Jensons alpha signifies that the asset has outperformed the expected returns, which implies that the stocks are undervalued.
H32: Comparing the alphas across the two stocks, we can infer that the stock with a larger positiveJenson alpha has outperformed it's expectation more than the other stock, and a stock with a smaller negative alpha has underperformed at a smaller percentage than the other stock.
H33: That is, Caterpillar has provided better risk-adjusted returns on 9th and 24th July, given the stock has lower negative Jensons alpha on both days.
H34: On 31st July, Boeing has a higher positive alpha which implies that it has provided better risk-adjusted return.
H35: This is inline with the interpretation on q8) beta, that Caterpillar would be an attractive investment for a risk averse investor where the losses on unexpected risks are lower compared to Boeing, but also the gains are also smaller in comparision.
