Workbook

Sheet Q2. Implied Volatality
B4: CALLS (Implied Volatallity)
B7: Contract Name | C7: Volume | D7: STOCK Price | E7: STRIKE Price | F7: Last Price | G7: Bid | H7: Ask | I7: Risk Free Rate | J7: Dividend Yield | K7: Term (10 Days) | L7: Mid Price | M7: d1 | N7: d2 | O7: Volume | P7: Implied Volatility (Yahoo Finance) | Q7: Implied Volatality (σ) (Calculated) | R7: Call Price (Black-Scholes) | S7: Implied Volatility (Yahoo Finance)
B8: MRK 11/15/24 C95 | C8: 7 | D8: 101.65 | E8: 95 | F8: 6.95 | G8: 6.65 | H8: 6.95 | I8: ='Q1-(Without Zero Volume)'!$J$4 -> 0.046975 | J8: 0.0311 | K8: ='Q1-(Without Zero Volume)'!K4 -> 0.035714286 | L8: =(G8+H8)/2 -> 6.8 | M8: =(LN(D8/E8) + (I8 + (Q8^2) / 2*K8) / (Q8*SQRT(K8))) -> 1.235774 | N8: =M8 - Q8*SQRT(K8) -> -1.0595252 | O8: 7 | P8: 26.781515 | Q8: 12.145582 | R8: =E8*_xlfn.NORM.S.DIST(N8,TRUE) - F8*EXP(-J8*L8)*_xlfn.NORM.S.DIST(O8,TRUE) -> 8.1194025 | S8: =P8-Q8 -> 14.635934
B9: MRK 11/15/24 C98 | C9: 3 | D9: 101.65 | E9: 98 | F9: 4.2 | G9: 4.15 | H9: 4.3 | I9: ='Q1-(Without Zero Volume)'!$J$4 -> 0.046975 | J9: 0.0311 | K9: =K8 -> 0.035714286 | L9: =(G9+H9)/2 -> 4.225 | M9: =(LN(D9/E9) + (I9 + (Q9^2) / 2*K9) / (Q9*SQRT(K9))) -> 1.4325073 | N9: =M9 - Q9*SQRT(K9) -> -1.3253044 | O9: 3 | P9: 26.573425 | Q9: 14.592968 | R9: =E9*_xlfn.NORM.S.DIST(N9,TRUE) - F9*EXP(-J9*L9)*_xlfn.NORM.S.DIST(O9,TRUE) -> 5.390562 | S9: =P9-Q9 -> 11.980457
B10: MRK 11/15/24 C99 | C10: 7 | D10: 101.65 | E10: 99 | F10: 3.25 | G10: 3.4 | H10: 3.55 | I10: ='Q1-(Without Zero Volume)'!$J$4 -> 0.046975 | J10: 0.0311 | K10: =K9 -> 0.035714286 | L10: =(G10+H10)/2 -> 3.475 | M10: =(LN(D10/E10) + (I10 + (Q10^2) / 2*K10) / (Q10*SQRT(K10))) -> 1.5213034 | N10: =M10 - Q10*SQRT(K10) -> -1.4367109 | O10: 7 | P10: 26.641626 | Q10: 15.65234 | R10: =E10*_xlfn.NORM.S.DIST(N10,TRUE) - F10*EXP(-J10*L10)*_xlfn.NORM.S.DIST(O10,TRUE) -> 4.5475299 | S10: =P10-Q10 -> 10.989286
B11: MRK 11/15/24 C100 | C11: 8 | D11: 101.65 | E11: 100 | F11: 2.35 | G11: 2.73 | H11: 2.84 | I11: ='Q1-(Without Zero Volume)'!$J$4 -> 0.046975 | J11: 0.0311 | K11: =K10 -> 0.035714286 | L11: =(G11+H11)/2 -> 2.785 | M11: =(LN(D11/E11) + (I11 + (Q11^2) / 2*K11) / (Q11*SQRT(K11))) -> 1.6258619 | N11: =M11 - Q11*SQRT(K11) -> -1.5636755 | O11: 8 | P11: 25.299459 | Q11: 16.877446 | R11: =E11*_xlfn.NORM.S.DIST(N11,TRUE) - F11*EXP(-J11*L11)*_xlfn.NORM.S.DIST(O11,TRUE) -> 3.7396653 | S11: =P11-Q11 -> 8.4220136
B12: MRK 11/15/24 C101 | C12: 16 | D12: 101.65 | E12: 101 | F12: 1.87 | G12: 2.11 | H12: 2.21 | I12: ='Q1-(Without Zero Volume)'!$J$4 -> 0.046975 | J12: 0.0311 | K12: =K11 -> 0.035714286 | L12: =(G12+H12)/2 -> 2.16 | M12: =(LN(D12/E12) + (I12 + (Q12^2) / 2*K12) / (Q12*SQRT(K12))) -> 1.7141561 | N12: =M12 - Q12*SQRT(K12) -> -1.6735937 | O12: 16 | P12: 25.354883 | Q12: 17.926287 | R12: =E12*_xlfn.NORM.S.DIST(N12,TRUE) - F12*EXP(-J12*L12)*_xlfn.NORM.S.DIST(O12,TRUE) -> 3.0091214 | S12: =P12-Q12 -> 7.4285962
B13: MRK 11/15/24 C102 | C13: 41 | D13: 101.65 | E13: 102 | F13: 1.69 | G13: 1.6 | H13: 1.66 | I13: ='Q1-(Without Zero Volume)'!$J$4 -> 0.046975 | J13: 0.0311 | K13: =K12 -> 0.035714286 | L13: =(G13+H13)/2 -> 1.63 | M13: =(LN(D13/E13) + (I13 + (Q13^2) / 2*K13) / (Q13*SQRT(K13))) -> 1.7791679 | N13: =M13 - Q13*SQRT(K13) -> -1.7594928 | O13: 41 | P13: 24.818048 | Q13: 18.724832 | R13: =E13*_xlfn.NORM.S.DIST(N13,TRUE) - F13*EXP(-J13*L13)*_xlfn.NORM.S.DIST(O13,TRUE) -> 2.3967217 | S13: =P13-Q13 -> 6.0932162
B14: MRK 11/15/24 C103 | C14: 19 | D14: 101.65 | E14: 103 | F14: 1.27 | G14: 1.17 | H14: 1.22 | I14: ='Q1-(Without Zero Volume)'!$J$4 -> 0.046975 | J14: 0.0311 | K14: =K13 -> 0.035714286 | L14: =(G14+H14)/2 -> 1.195 | M14: =(LN(D14/E14) + (I14 + (Q14^2) / 2*K14) / (Q14*SQRT(K14))) -> 1.8825727 | N14: =M14 - Q14*SQRT(K14) -> -1.8840166 | O14: 19 | P14: 24.502392 | Q14: 19.930917 | R14: =E14*_xlfn.NORM.S.DIST(N14,TRUE) - F14*EXP(-J14*L14)*_xlfn.NORM.S.DIST(O14,TRUE) -> 1.8438132 | S14: =P14-Q14 -> 4.5714747
B15: MRK 11/15/24 C104 | C15: 2 | D15: 101.65 | E15: 104 | F15: 0.87 | G15: 0.82 | H15: 0.87 | I15: ='Q1-(Without Zero Volume)'!$J$4 -> 0.046975 | J15: 0.0311 | K15: =K14 -> 0.035714286 | L15: =(G15+H15)/2 -> 0.845 | M15: =(LN(D15/E15) + (I15 + (Q15^2) / 2*K15) / (Q15*SQRT(K15))) -> 2.0098107 | N15: =M15 - Q15*SQRT(K15) -> -2.0322785 | O15: 2 | P15: 24.700979 | Q15: 21.388726 | R15: =E15*_xlfn.NORM.S.DIST(N15,TRUE) - F15*EXP(-J15*L15)*_xlfn.NORM.S.DIST(O15,TRUE) -> 1.3623689 | S15: =P15-Q15 -> 3.3122532
B16: MRK 11/15/24 C105 | C16: 475 | D16: 101.65 | E16: 105 | F16: 0.52 | G16: 0.57 | H16: 0.61 | I16: ='Q1-(Without Zero Volume)'!$J$4 -> 0.046975 | J16: 0.0311 | K16: =K15 -> 0.035714286 | L16: =(G16+H16)/2 -> 0.59 | M16: =(LN(D16/E16) + (I16 + (Q16^2) / 2*K16) / (Q16*SQRT(K16))) -> 2.1475661 | N16: =M16 - Q16*SQRT(K16) -> -2.1907599 | O16: 475 | P16: 24.196188 | Q16: 22.956263 | R16: =E16*_xlfn.NORM.S.DIST(N16,TRUE) - F16*EXP(-J16*L16)*_xlfn.NORM.S.DIST(O16,TRUE) -> 0.98408598 | S16: =P16-Q16 -> 1.2399245
B17: MRK 11/15/24 C106 | C17: 29 | D17: 101.65 | E17: 106 | F17: 0.35 | G17: 0.39 | H17: 0.42 | I17: ='Q1-(Without Zero Volume)'!$J$4 -> 0.046975 | J17: 0.0311 | K17: =K16 -> 0.035714286 | L17: =(G17+H17)/2 -> 0.405 | M17: =(LN(D17/E17) + (I17 + (Q17^2) / 2*K17) / (Q17*SQRT(K17))) -> 2.264931 | N17: =M17 - Q17*SQRT(K17) -> -2.3282841 | O17: 29 | P17: 24.819933 | Q17: 24.30501 | R17: =E17*_xlfn.NORM.S.DIST(N17,TRUE) - F17*EXP(-J17*L17)*_xlfn.NORM.S.DIST(O17,TRUE) -> 0.70892308 | S17: =P17-Q17 -> 0.51492309
B18: MRK 11/15/24 C107 | C18: 2 | D18: 101.65 | E18: 107 | F18: 0.37 | G18: 0.24 | H18: 0.29 | I18: ='Q1-(Without Zero Volume)'!$J$4 -> 0.046975 | J18: 0.0311 | K18: =K17 -> 0.035714286 | L18: =(G18+H18)/2 -> 0.265 | M18: =(LN(D18/E18) + (I18 + (Q18^2) / 2*K18) / (Q18*SQRT(K18))) -> 2.3117288 | N18: =M18 - Q18*SQRT(K18) -> -2.3943519 | O18: 2 | P18: 24.942793 | Q18: 24.902238 | R18: =E18*_xlfn.NORM.S.DIST(N18,TRUE) - F18*EXP(-J18*L18)*_xlfn.NORM.S.DIST(O18,TRUE) -> 0.53214787 | S18: =P18-Q18 -> 0.040554768
B19: MRK 11/15/24 C110 | C19: 22 | D19: 101.65 | E19: 110 | F19: 0.08 | G19: 0.09 | H19: 0.12 | I19: ='Q1-(Without Zero Volume)'!$J$4 -> 0.046975 | J19: 0.0311 | K19: =K18 -> 0.035714286 | L19: =(G19+H19)/2 -> 0.105 | M19: =(LN(D19/E19) + (I19 + (Q19^2) / 2*K19) / (Q19*SQRT(K19))) -> 2.6448595 | N19: =M19 - Q19*SQRT(K19) -> -2.7854481 | O19: 22 | P19: 28.406557 | Q19: 28.734487 | R19: =E19*_xlfn.NORM.S.DIST(N19,TRUE) - F19*EXP(-J19*L19)*_xlfn.NORM.S.DIST(O19,TRUE) -> 0.21425672 | S19: =P19-Q19 -> -0.32792946
B20: MRK 11/15/24 C114 | C20: 68 | D20: 101.65 | E20: 114 | F20: 0.03 | G20: 0.02 | H20: 0.12 | I20: ='Q1-(Without Zero Volume)'!$J$4 -> 0.046975 | J20: 0.0311 | K20: =K19 -> 0.035714286 | L20: =(G20+H20)/2 -> 0.07 | M20: =(LN(D20/E20) + (I20 + (Q20^2) / 2*K20) / (Q20*SQRT(K20))) -> 2.7597516 | N20: =M20 - Q20*SQRT(K20) -> -2.9726883 | O20: 68 | P20: 32.74509 | Q20: 30.333221 | R20: =E20*_xlfn.NORM.S.DIST(N20,TRUE) - F20*EXP(-J20*L20)*_xlfn.NORM.S.DIST(O20,TRUE) -> 0.13833158 | S20: =P20-Q20 -> 2.4118697
B21: MRK 11/15/24 C130 | C21: 7 | D21: 101.65 | E21: 130 | F21: 0.01 | G21: 0 | H21: 0.04 | I21: ='Q1-(Without Zero Volume)'!$J$4 -> 0.046975 | J21: 0.0311 | K21: =K20 -> 0.035714286 | L21: =(G21+H21)/2 -> 0.02 | M21: =(LN(D21/E21) + (I21 + (Q21^2) / 2*K21) / (Q21*SQRT(K21))) -> 2.8538442 | N21: =M21 - Q21*SQRT(K21) -> -3.3306508 | O21: 7 | P21: 88.830597 | Q21: 32.725271 | R21: =E21*_xlfn.NORM.S.DIST(N21,TRUE) - F21*EXP(-J21*L21)*_xlfn.NORM.S.DIST(O21,TRUE) -> 0.046324312 | S21: =P21-Q21 -> 56.105326
B25: PUT (Implied Volatallity)
B28: Contract Name | D28: Last Trade Date (EDT) | E28: SPOT Price | F28: STRIKE Price | G28: Last Price | H28: Bid | I28: Ask | J28: Risk Free Rate | K28: Dividend Yield | L28: Term (10 Days) | M28: Mid Price | N28: d1 | O28: d2 | Q28: Implied Volatality (σ) (Calculated) | R28: Call Price (Black-Scholes) | S28: Implied Volatility
B29: ='[1]Tracked Data - MRK'!S9 -> MRK241115P00060000 | D29: ='[1]Tracked Data - MRK'!T9 -> 45589.762 | E29: 101.65 | F29: ='[1]Tracked Data - MRK'!U9 -> 60 | G29: ='[1]Tracked Data - MRK'!V9 -> 0.02 | H29: ='[1]Tracked Data - MRK'!W9 -> 0 | I29: ='[1]Tracked Data - MRK'!X9 -> 0.28 | J29: =J10 -> 0.0311 | K29: =K10 -> 0.035714286 | L29: =10/365 -> 0.02739726 | M29: =(H29+I29)/2 -> 0.14 | N29: =(LN(E29/F29) + (J29+ (Q29^2) / 2*L29) / (Q29*SQRT(L29))) -> 0.82436989 | O29: =N29-Q29*SQRT(L29) -> 0.36558868 | Q29: 2.7717372 | R29: =F29*EXP(-J29*L29)*_xlfn.NORM.S.DIST(-O29,TRUE)-E29*_xlfn.NORM.S.DIST(-N29,TRUE) -> 0.59740256 | S29: 1.4609402
B30: ='[1]Tracked Data - MRK'!S10 -> MRK241115P00070000 | D30: ='[1]Tracked Data - MRK'!T10 -> 45595.751 | E30: 101.65 | F30: ='[1]Tracked Data - MRK'!U10 -> 70 | G30: ='[1]Tracked Data - MRK'!V10 -> 0.03 | H30: ='[1]Tracked Data - MRK'!W10 -> 0 | I30: ='[1]Tracked Data - MRK'!X10 -> 0.29 | J30: =J11 -> 0.0311 | K30: =K29 -> 0.035714286 | L30: =L29 -> 0.02739726 | M30: =(H30+I30)/2 -> 0.145 | N30: =(LN(E30/F30) + (J30+ (Q30^2) / 2*L30) / (Q30*SQRT(L30))) -> 0.63941239 | O30: =N30-Q30*SQRT(L30) -> 0.27947698 | Q30: 2.1745581 | R30: =F30*EXP(-J30*L30)*_xlfn.NORM.S.DIST(-O30,TRUE)-E30*_xlfn.NORM.S.DIST(-N30,TRUE) -> 0.71366836 | S30: 1.0820358
B31: ='[1]Tracked Data - MRK'!S11 -> MRK241115P00080000 | D31: ='[1]Tracked Data - MRK'!T11 -> 45593.663 | E31: 101.65 | F31: ='[1]Tracked Data - MRK'!U11 -> 80 | G31: ='[1]Tracked Data - MRK'!V11 -> 0.09 | H31: ='[1]Tracked Data - MRK'!W11 -> 0 | I31: ='[1]Tracked Data - MRK'!X11 -> 0.13 | J31: =J12 -> 0.0311 | K31: =K30 -> 0.035714286 | L31: =L30 -> 0.02739726 | M31: =(H31+I31)/2 -> 0.065 | N31: =(LN(E31/F31) + (J31+ (Q31^2) / 2*L31) / (Q31*SQRT(L31))) -> 0.48892477 | O31: =N31-Q31*SQRT(L31) -> 0.23663289 | Q31: 1.5242272 | R31: =F31*EXP(-J31*L31)*_xlfn.NORM.S.DIST(-O31,TRUE)-E31*_xlfn.NORM.S.DIST(-N31,TRUE) -> 0.72968263 | S31: 0.64844102
B32: ='[1]Tracked Data - MRK'!S12 -> MRK241115P00085000 | D32: ='[1]Tracked Data - MRK'!T12 -> 45596.712 | E32: 101.65 | F32: ='[1]Tracked Data - MRK'!U12 -> 85 | G32: ='[1]Tracked Data - MRK'!V12 -> 0.06 | H32: ='[1]Tracked Data - MRK'!W12 -> 0 | I32: ='[1]Tracked Data - MRK'!X12 -> 0.1 | J32: =J13 -> 0.0311 | K32: =K31 -> 0.035714286 | L32: =L31 -> 0.02739726 | M32: =(H32+I32)/2 -> 0.05 | N32: =(LN(E32/F32) + (J32+ (Q32^2) / 2*L32) / (Q32*SQRT(L32))) -> 0.43532008 | O32: =N32-Q32*SQRT(L32) -> 0.23854429 | Q32: 1.1888255 | R32: =F32*EXP(-J32*L32)*_xlfn.NORM.S.DIST(-O32,TRUE)-E32*_xlfn.NORM.S.DIST(-N32,TRUE) -> 0.74388086 | S32: 0.537114
B33: ='[1]Tracked Data - MRK'!S13 -> MRK241115P00090000 | D33: ='[1]Tracked Data - MRK'!T13 -> 45601.605 | E33: 101.65 | F33: ='[1]Tracked Data - MRK'!U13 -> 90 | G33: ='[1]Tracked Data - MRK'!V13 -> 0.39 | H33: ='[1]Tracked Data - MRK'!W13 -> 0.01 | I33: ='[1]Tracked Data - MRK'!X13 -> 0.09 | J33: =J14 -> 0.0311 | K33: =K32 -> 0.035714286 | L33: =L32 -> 0.02739726 | M33: =(H33+I33)/2 -> 0.05 | N33: =(LN(E33/F33) + (J33+ (Q33^2) / 2*L33) / (Q33*SQRT(L33))) -> 0.41378718 | O33: =N33-Q33*SQRT(L33) -> 0.27371208 | Q33: 0.84626692 | R33: =F33*EXP(-J33*L33)*_xlfn.NORM.S.DIST(-O33,TRUE)-E33*_xlfn.NORM.S.DIST(-N33,TRUE) -> 0.7520073 | S33: 0.43945873
B34: ='[1]Tracked Data - MRK'!S14 -> MRK241115P00095000 | D34: ='[1]Tracked Data - MRK'!T14 -> 45601.646 | E34: 101.65 | F34: ='[1]Tracked Data - MRK'!U14 -> 95 | G34: ='[1]Tracked Data - MRK'!V14 -> 0.32 | H34: ='[1]Tracked Data - MRK'!W14 -> 0 | I34: ='[1]Tracked Data - MRK'!X14 -> 0.33 | J34: =J15 -> 0.0311 | K34: =K33 -> 0.035714286 | L34: =L33 -> 0.02739726 | M34: =(H34+I34)/2 -> 0.165 | N34: =(LN(E34/F34) + (J34+ (Q34^2) / 2*L34) / (Q34*SQRT(L34))) -> 0.47702658 | O34: =N34-Q34*SQRT(L34) -> 0.39228474 | Q34: 0.51196974 | R34: =F34*EXP(-J34*L34)*_xlfn.NORM.S.DIST(-O34,TRUE)-E34*_xlfn.NORM.S.DIST(-N34,TRUE) -> 0.78749392 | S34: 0.31934274
B35: ='[1]Tracked Data - MRK'!S15 -> MRK241115P00098000 | D35: ='[1]Tracked Data - MRK'!T15 -> 45601.634 | E35: 101.65 | F35: ='[1]Tracked Data - MRK'!U15 -> 98 | G35: ='[1]Tracked Data - MRK'!V15 -> 0.81 | H35: ='[1]Tracked Data - MRK'!W15 -> 0.08 | I35: ='[1]Tracked Data - MRK'!X15 -> 0.26 | J35: =J16 -> 0.0311 | K35: =K34 -> 0.035714286 | L35: =L34 -> 0.02739726 | M35: =(H35+I35)/2 -> 0.17 | N35: =(LN(E35/F35) + (J35+ (Q35^2) / 2*L35) / (Q35*SQRT(L35))) -> 0.69833411 | O35: =N35-Q35*SQRT(L35) -> 0.64953976 | Q35: 0.29479219 | R35: =F35*EXP(-J35*L35)*_xlfn.NORM.S.DIST(-O35,TRUE)-E35*_xlfn.NORM.S.DIST(-N35,TRUE) -> 0.61344206 | S35: 0.29785858
B36: ='[1]Tracked Data - MRK'!S16 -> MRK241115P00099000 | D36: ='[1]Tracked Data - MRK'!T16 -> 45600.78 | E36: 101.65 | F36: ='[1]Tracked Data - MRK'!U16 -> 99 | G36: ='[1]Tracked Data - MRK'!V16 -> 1.08 | H36: ='[1]Tracked Data - MRK'!W16 -> 0.98 | I36: ='[1]Tracked Data - MRK'!X16 -> 1.08 | J36: =J17 -> 0.0311 | K36: =K35 -> 0.035714286 | L36: =L35 -> 0.02739726 | M36: =(H36+I36)/2 -> 1.03 | N36: =(LN(E36/F36) + (J36+ (Q36^2) / 2*L36) / (Q36*SQRT(L36))) -> 0.59013834 | O36: =N36-Q36*SQRT(L36) -> 0.53196809 | Q36: 0.35143692 | R36: =F36*EXP(-J36*L36)*_xlfn.NORM.S.DIST(-O36,TRUE)-E36*_xlfn.NORM.S.DIST(-N36,TRUE) -> 1.2021059 | S36: 0.29248754
B37: ='[1]Tracked Data - MRK'!S17 -> MRK241115P00100000 | D37: ='[1]Tracked Data - MRK'!T17 -> 45601.64 | E37: 101.65 | F37: ='[1]Tracked Data - MRK'!U17 -> 100 | G37: ='[1]Tracked Data - MRK'!V17 -> 1.46 | H37: ='[1]Tracked Data - MRK'!W17 -> 1.38 | I37: ='[1]Tracked Data - MRK'!X17 -> 1.44 | J37: =J18 -> 0.0311 | K37: =K36 -> 0.035714286 | L37: =L36 -> 0.02739726 | M37: =(H37+I37)/2 -> 1.41 | N37: =(LN(E37/F37) + (J37+ (Q37^2) / 2*L37) / (Q37*SQRT(L37))) -> 0.60629816 | O37: =N37-Q37*SQRT(L37) -> 0.55098739 | Q37: 0.33416132 | R37: =F37*EXP(-J37*L37)*_xlfn.NORM.S.DIST(-O37,TRUE)-E37*_xlfn.NORM.S.DIST(-N37,TRUE) -> 1.3924468 | S37: 0.29102271
B38: ='[1]Tracked Data - MRK'!S18 -> MRK241115P00101000 | D38: ='[1]Tracked Data - MRK'!T18 -> 45601.644 | E38: 101.65 | F38: ='[1]Tracked Data - MRK'!U18 -> 101 | G38: ='[1]Tracked Data - MRK'!V18 -> 1.82 | H38: ='[1]Tracked Data - MRK'!W18 -> 1.74 | I38: ='[1]Tracked Data - MRK'!X18 -> 1.88 | J38: =J19 -> 0.0311 | K38: =K37 -> 0.035714286 | L38: =L37 -> 0.02739726 | M38: =(H38+I38)/2 -> 1.81 | N38: =(LN(E38/F38) + (J38+ (Q38^2) / 2*L38) / (Q38*SQRT(L38))) -> 0.62202071 | O38: =N38-Q38*SQRT(L38) -> 0.56923858 | Q38: 0.31888442 | R38: =F38*EXP(-J38*L38)*_xlfn.NORM.S.DIST(-O38,TRUE)-E38*_xlfn.NORM.S.DIST(-N38,TRUE) -> 1.5829245 | S38: 0.29004616
B39: ='[1]Tracked Data - MRK'!S19 -> MRK241115P00102000 | D39: ='[1]Tracked Data - MRK'!T19 -> 45601.643 | E39: 101.65 | F39: ='[1]Tracked Data - MRK'!U19 -> 102 | G39: ='[1]Tracked Data - MRK'!V19 -> 2.39 | H39: ='[1]Tracked Data - MRK'!W19 -> 2.3 | I39: ='[1]Tracked Data - MRK'!X19 -> 2.41 | J39: =J20 -> 0.0311 | K39: =K38 -> 0.035714286 | L39: =L38 -> 0.02739726 | M39: =(H39+I39)/2 -> 2.355 | N39: =(LN(E39/F39) + (J39+ (Q39^2) / 2*L39) / (Q39*SQRT(L39))) -> 0.60170566 | O39: =N39-Q39*SQRT(L39) -> 0.54792284 | Q39: 0.32493017 | R39: =F39*EXP(-J39*L39)*_xlfn.NORM.S.DIST(-O39,TRUE)-E39*_xlfn.NORM.S.DIST(-N39,TRUE) -> 1.9255492 | S39: 0.29077858
B40: ='[1]Tracked Data - MRK'!S20 -> MRK241115P00103000 | D40: ='[1]Tracked Data - MRK'!T20 -> 45600.866 | E40: 101.65 | F40: ='[1]Tracked Data - MRK'!U20 -> 103 | G40: ='[1]Tracked Data - MRK'!V20 -> 3.3 | H40: ='[1]Tracked Data - MRK'!W20 -> 2.79 | I40: ='[1]Tracked Data - MRK'!X20 -> 3.1 | J40: =J21 -> 0.0311 | K40: =K39 -> 0.035714286 | L40: =L39 -> 0.02739726 | M40: =(H40+I40)/2 -> 2.945 | N40: =(LN(E40/F40) + (J40+ (Q40^2) / 2*L40) / (Q40*SQRT(L40))) -> 0.57426495 | O40: =N40-Q40*SQRT(L40) -> 0.51869693 | Q40: 0.3357155 | R40: =F40*EXP(-J40*L40)*_xlfn.NORM.S.DIST(-O40,TRUE)-E40*_xlfn.NORM.S.DIST(-N40,TRUE) -> 2.3218702 | S40: 0.30396204
B41: ='[1]Tracked Data - MRK'!S21 -> MRK241115P00104000 | D41: ='[1]Tracked Data - MRK'!T21 -> 45601.646 | E41: 101.65 | F41: ='[1]Tracked Data - MRK'!U21 -> 104 | G41: ='[1]Tracked Data - MRK'!V21 -> 3.7 | H41: ='[1]Tracked Data - MRK'!W21 -> 3.65 | I41: ='[1]Tracked Data - MRK'!X21 -> 3.75 | J41: =#REF! -> #REF! | K41: =K40 -> 0.035714286 | L41: =L40 -> 0.02739726 | M41: =(H41+I41)/2 -> 3.7 | N41: =(LN(E41/F41) + (J41+ (Q41^2) / 2*L41) / (Q41*SQRT(L41))) -> #REF! | O41: =N41-Q41*SQRT(L41) -> #REF! | Q41: 0.36887944 | R41: =F41*EXP(-J41*L41)*_xlfn.NORM.S.DIST(-O41,TRUE)-E41*_xlfn.NORM.S.DIST(-N41,TRUE) -> #REF! | S41: 0.30127652
B42: ='[1]Tracked Data - MRK'!S22 -> MRK241115P00105000 | D42: ='[1]Tracked Data - MRK'!T22 -> 45601.622 | E42: 101.65 | F42: ='[1]Tracked Data - MRK'!U22 -> 105 | G42: ='[1]Tracked Data - MRK'!V22 -> 4.57 | H42: ='[1]Tracked Data - MRK'!W22 -> 4.45 | I42: ='[1]Tracked Data - MRK'!X22 -> 4.6 | J42: =#REF! -> #REF! | K42: =K41 -> 0.035714286 | L42: =L41 -> 0.02739726 | M42: =(H42+I42)/2 -> 4.525 | N42: =(LN(E42/F42) + (J42+ (Q42^2) / 2*L42) / (Q42*SQRT(L42))) -> #REF! | O42: =N42-Q42*SQRT(L42) -> #REF! | Q42: 0.41238558 | R42: =F42*EXP(-J42*L42)*_xlfn.NORM.S.DIST(-O42,TRUE)-E42*_xlfn.NORM.S.DIST(-N42,TRUE) -> #REF! | S42: 0.32178413
B43: ='[1]Tracked Data - MRK'!S23 -> MRK241115P00106000 | D43: ='[1]Tracked Data - MRK'!T23 -> 45600.763 | E43: 101.65 | F43: ='[1]Tracked Data - MRK'!U23 -> 106 | G43: ='[1]Tracked Data - MRK'!V23 -> 5.1 | H43: ='[1]Tracked Data - MRK'!W23 -> 5 | I43: ='[1]Tracked Data - MRK'!X23 -> 5.4 | J43: =#REF! -> #REF! | K43: =K42 -> 0.035714286 | L43: =L42 -> 0.02739726 | M43: =(H43+I43)/2 -> 5.2 | N43: =(LN(E43/F43) + (J43+ (Q43^2) / 2*L43) / (Q43*SQRT(L43))) -> #REF! | O43: =N43-Q43*SQRT(L43) -> #REF! | Q43: 0.43108975 | R43: =F43*EXP(-J43*L43)*_xlfn.NORM.S.DIST(-O43,TRUE)-E43*_xlfn.NORM.S.DIST(-N43,TRUE) -> #REF! | S43: 0.32691103
B44: ='[1]Tracked Data - MRK'!S24 -> MRK241115P00107000 | D44: ='[1]Tracked Data - MRK'!T24 -> 45600.724 | E44: 101.65 | F44: ='[1]Tracked Data - MRK'!U24 -> 107 | G44: ='[1]Tracked Data - MRK'!V24 -> 6 | H44: ='[1]Tracked Data - MRK'!W24 -> 5.75 | I44: ='[1]Tracked Data - MRK'!X24 -> 6.4 | J44: =#REF! -> #REF! | K44: =K43 -> 0.035714286 | L44: =L43 -> 0.02739726 | M44: =(H44+I44)/2 -> 6.075 | N44: =(LN(E44/F44) + (J44+ (Q44^2) / 2*L44) / (Q44*SQRT(L44))) -> #REF! | O44: =N44-Q44*SQRT(L44) -> #REF! | Q44: 0.47914753 | R44: =F44*EXP(-J44*L44)*_xlfn.NORM.S.DIST(-O44,TRUE)-E44*_xlfn.NORM.S.DIST(-N44,TRUE) -> #REF! | S44: 0.36524072
B45: ='[1]Tracked Data - MRK'!S25 -> MRK241115P00108000 | D45: ='[1]Tracked Data - MRK'!T25 -> 45597.687 | E45: 101.65 | F45: ='[1]Tracked Data - MRK'!U25 -> 108 | G45: ='[1]Tracked Data - MRK'!V25 -> 5.85 | H45: ='[1]Tracked Data - MRK'!W25 -> 7.05 | I45: ='[1]Tracked Data - MRK'!X25 -> 7.35 | J45: =#REF! -> #REF! | K45: =K44 -> 0.035714286 | L45: =L44 -> 0.02739726 | M45: =(H45+I45)/2 -> 7.2 | N45: =(LN(E45/F45) + (J45+ (Q45^2) / 2*L45) / (Q45*SQRT(L45))) -> #REF! | O45: =N45-Q45*SQRT(L45) -> #REF! | Q45: 0.56056945 | R45: =F45*EXP(-J45*L45)*_xlfn.NORM.S.DIST(-O45,TRUE)-E45*_xlfn.NORM.S.DIST(-N45,TRUE) -> #REF! | S45: 0.39111937
B46: ='[1]Tracked Data - MRK'!S26 -> MRK241115P00109000 | D46: ='[1]Tracked Data - MRK'!T26 -> 45600.612 | E46: 101.65 | F46: ='[1]Tracked Data - MRK'!U26 -> 109 | G46: ='[1]Tracked Data - MRK'!V26 -> 7.25 | H46: ='[1]Tracked Data - MRK'!W26 -> 7.95 | I46: ='[1]Tracked Data - MRK'!X26 -> 8.35 | J46: =#REF! -> #REF! | K46: =K45 -> 0.035714286 | L46: =L45 -> 0.02739726 | M46: =(H46+I46)/2 -> 8.15 | N46: =(LN(E46/F46) + (J46+ (Q46^2) / 2*L46) / (Q46*SQRT(L46))) -> #REF! | O46: =N46-Q46*SQRT(L46) -> #REF! | Q46: 0.61581756 | R46: =F46*EXP(-J46*L46)*_xlfn.NORM.S.DIST(-O46,TRUE)-E46*_xlfn.NORM.S.DIST(-N46,TRUE) -> #REF! | S46: 0.42578699
B47: ='[1]Tracked Data - MRK'!S27 -> MRK241115P00110000 | D47: ='[1]Tracked Data - MRK'!T27 -> 45601.622 | E47: 101.65 | F47: ='[1]Tracked Data - MRK'!U27 -> 110 | G47: ='[1]Tracked Data - MRK'!V27 -> 9.2 | H47: ='[1]Tracked Data - MRK'!W27 -> 9.05 | I47: ='[1]Tracked Data - MRK'!X27 -> 9.3 | J47: =#REF! -> #REF! | K47: =K46 -> 0.035714286 | L47: =L46 -> 0.02739726 | M47: =(H47+I47)/2 -> 9.175 | N47: =(LN(E47/F47) + (J47+ (Q47^2) / 2*L47) / (Q47*SQRT(L47))) -> #REF! | O47: =N47-Q47*SQRT(L47) -> #REF! | Q47: 0.68117607 | R47: =F47*EXP(-J47*L47)*_xlfn.NORM.S.DIST(-O47,TRUE)-E47*_xlfn.NORM.S.DIST(-N47,TRUE) -> #REF! | S47: 0.44775943
B48: ='[1]Tracked Data - MRK'!S28 -> MRK241115P00111000 | D48: ='[1]Tracked Data - MRK'!T28 -> 45597.736 | E48: 101.65 | F48: ='[1]Tracked Data - MRK'!U28 -> 111 | G48: ='[1]Tracked Data - MRK'!V28 -> 9 | H48: ='[1]Tracked Data - MRK'!W28 -> 10.05 | I48: ='[1]Tracked Data - MRK'!X28 -> 10.3 | J48: =#REF! -> #REF! | K48: =K47 -> 0.035714286 | L48: =L47 -> 0.02739726 | M48: =(H48+I48)/2 -> 10.175 | N48: =(LN(E48/F48) + (J48+ (Q48^2) / 2*L48) / (Q48*SQRT(L48))) -> #REF! | O48: =N48-Q48*SQRT(L48) -> #REF! | Q48: 0.74076021 | R48: =F48*EXP(-J48*L48)*_xlfn.NORM.S.DIST(-O48,TRUE)-E48*_xlfn.NORM.S.DIST(-N48,TRUE) -> #REF! | S48: 0.47998567
B49: ='[1]Tracked Data - MRK'!S29 -> MRK241115P00112000 | D49: ='[1]Tracked Data - MRK'!T29 -> 45587.784 | E49: 101.65 | F49: ='[1]Tracked Data - MRK'!U29 -> 112 | G49: ='[1]Tracked Data - MRK'!V29 -> 6.54 | H49: ='[1]Tracked Data - MRK'!W29 -> 11.05 | I49: ='[1]Tracked Data - MRK'!X29 -> 12.75 | J49: =#REF! -> #REF! | K49: =K48 -> 0.035714286 | L49: =L48 -> 0.02739726 | M49: =(H49+I49)/2 -> 11.9 | N49: =(LN(E49/F49) + (J49+ (Q49^2) / 2*L49) / (Q49*SQRT(L49))) -> #REF! | O49: =N49-Q49*SQRT(L49) -> #REF! | Q49: 0.90186219 | R49: =F49*EXP(-J49*L49)*_xlfn.NORM.S.DIST(-O49,TRUE)-E49*_xlfn.NORM.S.DIST(-N49,TRUE) -> #REF! | S49: 0.64599963
B50: ='[1]Tracked Data - MRK'!S30 -> MRK241115P00113000 | D50: ='[1]Tracked Data - MRK'!T30 -> 45596.567 | E50: 101.65 | F50: ='[1]Tracked Data - MRK'!U30 -> 113 | G50: ='[1]Tracked Data - MRK'!V30 -> 14.05 | H50: ='[1]Tracked Data - MRK'!W30 -> 12 | I50: ='[1]Tracked Data - MRK'!X30 -> 12.8 | J50: =#REF! -> #REF! | K50: =K49 -> 0.035714286 | L50: =L49 -> 0.02739726 | M50: =(H50+I50)/2 -> 12.4 | N50: =(LN(E50/F50) + (J50+ (Q50^2) / 2*L50) / (Q50*SQRT(L50))) -> #REF! | O50: =N50-Q50*SQRT(L50) -> #REF! | Q50: 0.88729413 | R50: =F50*EXP(-J50*L50)*_xlfn.NORM.S.DIST(-O50,TRUE)-E50*_xlfn.NORM.S.DIST(-N50,TRUE) -> #REF! | S50: 0.56738714
B51: ='[1]Tracked Data - MRK'!S31 -> MRK241115P00114000 | D51: ='[1]Tracked Data - MRK'!T31 -> 45587.606 | E51: 101.65 | F51: ='[1]Tracked Data - MRK'!U31 -> 114 | G51: ='[1]Tracked Data - MRK'!V31 -> 8.27 | H51: ='[1]Tracked Data - MRK'!W31 -> 12.95 | I51: ='[1]Tracked Data - MRK'!X31 -> 13.25 | J51: =#REF! -> #REF! | K51: =K50 -> 0.035714286 | L51: =L50 -> 0.02739726 | M51: =(H51+I51)/2 -> 13.1 | N51: =(LN(E51/F51) + (J51+ (Q51^2) / 2*L51) / (Q51*SQRT(L51))) -> #REF! | O51: =N51-Q51*SQRT(L51) -> #REF! | Q51: 0.90032798 | R51: =F51*EXP(-J51*L51)*_xlfn.NORM.S.DIST(-O51,TRUE)-E51*_xlfn.NORM.S.DIST(-N51,TRUE) -> #REF! | S51: 0.51221191
B52: ='[1]Tracked Data - MRK'!S32 -> MRK241115P00115000 | D52: ='[1]Tracked Data - MRK'!T32 -> 45600.851 | E52: 101.65 | F52: ='[1]Tracked Data - MRK'!U32 -> 115 | G52: ='[1]Tracked Data - MRK'!V32 -> 13.33 | H52: ='[1]Tracked Data - MRK'!W32 -> 13.95 | I52: ='[1]Tracked Data - MRK'!X32 -> 14.2 | J52: =#REF! -> #REF! | K52: =K51 -> 0.035714286 | L52: =L51 -> 0.02739726 | M52: =(H52+I52)/2 -> 14.075 | N52: =(LN(E52/F52) + (J52+ (Q52^2) / 2*L52) / (Q52*SQRT(L52))) -> #REF! | O52: =N52-Q52*SQRT(L52) -> #REF! | Q52: 0.95199995 | R52: =F52*EXP(-J52*L52)*_xlfn.NORM.S.DIST(-O52,TRUE)-E52*_xlfn.NORM.S.DIST(-N52,TRUE) -> #REF! | S52: 0.53125469
... B66: ='[1]Tracked Data - MRK'!S46 -> MRK241115P00155000 | D66: ='[1]Tracked Data - MRK'!T46 -> 0 | E66: 101.65 | F66: ='[1]Tracked Data - MRK'!U46 -> 155 | G66: ='[1]Tracked Data - MRK'!V46 -> 0 | H66: ='[1]Tracked Data - MRK'!W46 -> 51.699997 | I66: ='[1]Tracked Data - MRK'!X46 -> 55.449997 | J66: =#REF! -> #REF! | K66: =K65 -> 0.035714286 | L66: =L65 -> 0.02739726 | M66: =(H66+I66)/2 -> 53.574997 | N66: =(LN(E66/F66) + (J66+ (Q66^2) / 2*L66) / (Q66*SQRT(L66))) -> #REF! | O66: =N66-Q66*SQRT(L66) -> #REF! | Q66: 2.3773719 | R66: =F66*EXP(-J66*L66)*_xlfn.NORM.S.DIST(-O66,TRUE)-E66*_xlfn.NORM.S.DIST(-N66,TRUE) -> #REF! | S66: 1.0654344
B67: ='[1]Tracked Data - MRK'!S47 -> MRK241115P00160000 | D67: ='[1]Tracked Data - MRK'!T47 -> 0 | E67: 101.65 | F67: ='[1]Tracked Data - MRK'!U47 -> 160 | G67: ='[1]Tracked Data - MRK'!V47 -> 0 | H67: ='[1]Tracked Data - MRK'!W47 -> 56.75 | I67: ='[1]Tracked Data - MRK'!X47 -> 60.399994 | J67: =J22 -> 0 | K67: =K65 -> 0.035714286 | L67: =L65 -> 0.02739726 | M67: =(H67+I67)/2 -> 58.574997 | N67: =(LN(E67/F67) + (J67+ (Q67^2) / 2*L67) / (Q67*SQRT(L67))) -> -0.24658982 | O67: =N67-Q67*SQRT(L67) -> -0.66068673 | Q67: 2.501776 | R67: =F67*EXP(-J67*L67)*_xlfn.NORM.S.DIST(-O67,TRUE)-E67*_xlfn.NORM.S.DIST(-N67,TRUE) -> 58.570537 | S67: 1.0654344
B68: ='[1]Tracked Data - MRK'!S48 -> MRK241115P00170000 | D68: ='[1]Tracked Data - MRK'!T48 -> 0 | E68: 101.65 | F68: ='[1]Tracked Data - MRK'!U48 -> 170 | G68: ='[1]Tracked Data - MRK'!V48 -> 0 | H68: ='[1]Tracked Data - MRK'!W48 -> 66.449997 | I68: ='[1]Tracked Data - MRK'!X48 -> 70.449997 | J68: =J23 -> 0 | K68: =K67 -> 0.035714286 | L68: =L67 -> 0.02739726 | M68: =(H68+I68)/2 -> 68.449997 | N68: =(LN(E68/F68) + (J68+ (Q68^2) / 2*L68) / (Q68*SQRT(L68))) -> -0.29012278 | O68: =N68-Q68*SQRT(L68) -> -0.73840301 | Q68: 2.7082953 | R68: =F68*EXP(-J68*L68)*_xlfn.NORM.S.DIST(-O68,TRUE)-E68*_xlfn.NORM.S.DIST(-N68,TRUE) -> 68.449872 | S68: 1.0654344

Sheet Q1-(Without Zero Volume)
A1: A. PUT-CALL Parity for all Options as on November 5, 2024
V2: Arbitrage Strategy
A3: Option Symbol | B3: Option Date | C3: Trading Volume | D3: Call Price( Bid and ask Average) ( C ) | E3: Option Symbol | F3: Trading Volume | G3: Put Price (P) ( Bid and ask Average)\ | H3: Stock Price/ Spot Price (S) | I3: Strike Price (K) | J3: Risk-Free Rate ( R ) | K3: (t)=Time to Maturity (15-6=9/252) | L3: S+P | M3: e^(-r*t) | N3: K*e^(-rt) | O3: C+K*e^-rt | P3: Violation of Put-Call parity | Q3: Difference | R3: C-P | S3: ='Q1. Put- Call Parity(With zero '!K4 -> S - K*e^-r(T-t) | T3: Difference | U3: Theoretical Value of Put Option P=C+K*e^-rt-S | V3: S+P>C+K⋅e ^−r(T−t) (OVERVALUED) | W3: S+P<C+K⋅e ^−r(T−t) (UNDERVALUED)
A4: MRK 11/15/24 C95 | B4: 45423 | C4: 12 | D4: =('Bloomberg Raw Data-5th(No zero)'!C6+'Bloomberg Raw Data-5th(No zero)'!D6)/2 -> 6.8000002 | E4: MRK 11/15/24 P95 | F4: 24 | G4: =('Bloomberg Raw Data-5th(No zero)'!J6+'Bloomberg Raw Data-5th(No zero)'!K6)/2 -> 0.16999999 | H4: 101.65 | I4: 95 | J4: =4.6975/100 -> 0.046975 | K4: =9/252 -> 0.035714286 | L4: =H4+G4 -> 101.82 | M4: =$D$31^((-J4)*(K4)) -> 0.99832373 | N4: =I4*M4 -> 94.840754 | O4: =D4+N4 -> 101.64075 | P4: =IF(L4=O4,"Not Violated","Violated") -> Violated | Q4: =ABS(L4-O4) -> 0.17924559 | R4: =D4-G4 -> 6.6300002 | S4: =H4-N4 -> 6.8092458 | T4: =R4-S4 -> -0.17924559 | U4: =O4-H4 -> -0.009245606 | V4: =IF(ABS(G4-U4)<=0.01,"NO VIOLATION",IF(G4>U4,"YES", "NO")) -> YES | W4: =IF(ABS(G4-U4)<=0.01,"NO VIOLATION",IF(G4>U4,"NO", "YES")) -> NO
A5: MRK 11/15/24 C98 | B5: 45423 | C5: 2 | D5: =('Bloomberg Raw Data-5th(No zero)'!C7+'Bloomberg Raw Data-5th(No zero)'!D7)/2 -> 4.2250004 | E5: MRK 11/15/24 P98 | F5: 124 | G5: =('Bloomberg Raw Data-5th(No zero)'!J7+'Bloomberg Raw Data-5th(No zero)'!K7)/2 -> 0.61000001 | H5: 101.65 | I5: 98 | J5: =4.6975/100 -> 0.046975 | K5: =9/252 -> 0.035714286 | L5: =H5+G5 -> 102.26 | M5: =$D$31^((-J5)*(K5)) -> 0.99832373 | N5: =I5*M5 -> 97.835725 | O5: =D5+N5 -> 102.06073 | P5: =IF(L5=O5,"Not Violated","Violated") -> Violated | Q5: =ABS(L5-O5) -> 0.19927424 | R5: =D5-G5 -> 3.6150004 | S5: =H5-N5 -> 3.8142746 | T5: =R5-S5 -> -0.19927424 | U5: =O5-H5 -> 0.41072577 | V5: =IF(ABS(G5-U5)<=0.01,"NO VIOLATION",IF(G5>U5,"YES", "NO")) -> YES | W5: =IF(ABS(G5-U5)<=0.01,"NO VIOLATION",IF(G5>U5,"NO", "YES")) -> NO
A6: MRK 11/15/24 C99 | B6: 45423 | C6: 10 | D6: =('Bloomberg Raw Data-5th(No zero)'!C8+'Bloomberg Raw Data-5th(No zero)'!D8)/2 -> 3.4750004 | E6: MRK 11/15/24 P99 | F6: 56 | G6: =('Bloomberg Raw Data-5th(No zero)'!J8+'Bloomberg Raw Data-5th(No zero)'!K8)/2 -> 0.88 | H6: 101.65 | I6: 99 | J6: =4.6975/100 -> 0.046975 | K6: =9/252 -> 0.035714286 | L6: =H6+G6 -> 102.53 | M6: =$D$31^((-J6)*(K6)) -> 0.99832373 | N6: =I6*M6 -> 98.834049 | O6: =D6+N6 -> 102.30905 | P6: =IF(L6=O6,"Not Violated","Violated") -> Violated | Q6: =ABS(L6-O6) -> 0.2209505 | R6: =D6-G6 -> 2.5950004 | S6: =H6-N6 -> 2.8159509 | T6: =R6-S6 -> -0.2209505 | U6: =O6-H6 -> 0.6590495 | V6: =IF(ABS(G6-U6)<=0.01,"NO VIOLATION",IF(G6>U6,"YES", "NO")) -> YES | W6: =IF(ABS(G6-U6)<=0.01,"NO VIOLATION",IF(G6>U6,"NO", "YES")) -> NO
A7: MRK 11/15/24 C100 | B7: 45423 | C7: 55 | D7: =('Bloomberg Raw Data-5th(No zero)'!C9+'Bloomberg Raw Data-5th(No zero)'!D9)/2 -> 2.7850003 | E7: MRK 11/15/24 P100 | F7: 84 | G7: =('Bloomberg Raw Data-5th(No zero)'!J9+'Bloomberg Raw Data-5th(No zero)'!K9)/2 -> 1.1300001 | H7: 101.65 | I7: 100 | J7: =4.6975/100 -> 0.046975 | K7: =9/252 -> 0.035714286 | L7: =H7+G7 -> 102.78 | M7: =$D$31^((-J7)*(K7)) -> 0.99832373 | N7: =I7*M7 -> 99.832373 | O7: =D7+N7 -> 102.61737 | P7: =IF(L7=O7,"Not Violated","Violated") -> Violated | Q7: =ABS(L7-O7) -> 0.16262694 | R7: =D7-G7 -> 1.6550002 | S7: =H7-N7 -> 1.8176272 | T7: =R7-S7 -> -0.16262694 | U7: =O7-H7 -> 0.96737317 | V7: =IF(ABS(G7-U7)<=0.01,"NO VIOLATION",IF(G7>U7,"YES", "NO")) -> YES | W7: =IF(ABS(G7-U7)<=0.01,"NO VIOLATION",IF(G7>U7,"NO", "YES")) -> NO
A8: MRK 11/15/24 C101 | B8: 45423 | C8: 28 | D8: =('Bloomberg Raw Data-5th(No zero)'!C10+'Bloomberg Raw Data-5th(No zero)'!D10)/2 -> 2.1599998 | E8: MRK 11/15/24 P101 | F8: 100 | G8: =('Bloomberg Raw Data-5th(No zero)'!J10+'Bloomberg Raw Data-5th(No zero)'!K10)/2 -> 1.5499997 | H8: 101.65 | I8: 101 | J8: =4.6975/100 -> 0.046975 | K8: =9/252 -> 0.035714286 | L8: =H8+G8 -> 103.2 | M8: =$D$31^((-J8)*(K8)) -> 0.99832373 | N8: =I8*M8 -> 100.8307 | O8: =D8+N8 -> 102.9907 | P8: =IF(L8=O8,"Not Violated","Violated") -> Violated | Q8: =ABS(L8-O8) -> 0.20930329 | R8: =D8-G8 -> 0.61000013 | S8: =H8-N8 -> 0.81930343 | T8: =R8-S8 -> -0.20930329 | U8: =O8-H8 -> 1.3406964 | V8: =IF(ABS(G8-U8)<=0.01,"NO VIOLATION",IF(G8>U8,"YES", "NO")) -> YES | W8: =IF(ABS(G8-U8)<=0.01,"NO VIOLATION",IF(G8>U8,"NO", "YES")) -> NO
A9: MRK 11/15/24 C102 | B9: 45423 | C9: 41 | D9: =('Bloomberg Raw Data-5th(No zero)'!C11+'Bloomberg Raw Data-5th(No zero)'!D11)/2 -> 1.6299996 | E9: MRK 11/15/24 P102 | F9: 65 | G9: =('Bloomberg Raw Data-5th(No zero)'!J11+'Bloomberg Raw Data-5th(No zero)'!K11)/2 -> 2.0149999 | H9: 101.65 | I9: 102 | J9: =4.6975/100 -> 0.046975 | K9: =9/252 -> 0.035714286 | L9: =H9+G9 -> 103.665 | M9: =$D$31^((-J9)*(K9)) -> 0.99832373 | N9: =I9*M9 -> 101.82902 | O9: =D9+N9 -> 103.45902 | P9: =IF(L9=O9,"Not Violated","Violated") -> Violated | Q9: =ABS(L9-O9) -> 0.20597993 | R9: =D9-G9 -> -0.38500023 | S9: =H9-N9 -> -0.1790203 | T9: =R9-S9 -> -0.20597993 | U9: =O9-H9 -> 1.8090199 | V9: =IF(ABS(G9-U9)<=0.01,"NO VIOLATION",IF(G9>U9,"YES", "NO")) -> YES | W9: =IF(ABS(G9-U9)<=0.01,"NO VIOLATION",IF(G9>U9,"NO", "YES")) -> NO
A10: MRK 11/15/24 C103 | B10: 45423 | C10: 89 | D10: =('Bloomberg Raw Data-5th(No zero)'!C12+'Bloomberg Raw Data-5th(No zero)'!D12)/2 -> 1.1950002 | E10: MRK 11/15/24 P103 | F10: 28 | G10: =('Bloomberg Raw Data-5th(No zero)'!J12+'Bloomberg Raw Data-5th(No zero)'!K12)/2 -> 2.585 | H10: 101.65 | I10: 103 | J10: =4.6975/100 -> 0.046975 | K10: =9/252 -> 0.035714286 | L10: =H10+G10 -> 104.235 | M10: =$D$31^((-J10)*(K10)) -> 0.99832373 | N10: =I10*M10 -> 102.82734 | O10: =D10+N10 -> 104.02234 | P10: =IF(L10=O10,"Not Violated","Violated") -> Violated | Q10: =ABS(L10-O10) -> 0.21265584 | R10: =D10-G10 -> -1.3899999 | S10: =H10-N10 -> -1.177344 | T10: =R10-S10 -> -0.21265584 | U10: =O10-H10 -> 2.3723442 | V10: =IF(ABS(G10-U10)<=0.01,"NO VIOLATION",IF(G10>U10,"YES", "NO")) -> YES | W10: =IF(ABS(G10-U10)<=0.01,"NO VIOLATION",IF(G10>U10,"NO", "YES")) -> NO
A11: MRK 11/15/24 C104 | B11: 45423 | C11: 56 | D11: =('Bloomberg Raw Data-5th(No zero)'!C13+'Bloomberg Raw Data-5th(No zero)'!D13)/2 -> 0.845 | E11: MRK 11/15/24 P104 | F11: 29 | G11: =('Bloomberg Raw Data-5th(No zero)'!J13+'Bloomberg Raw Data-5th(No zero)'!K13)/2 -> 3.2750001 | H11: 101.65 | I11: 104 | J11: =4.6975/100 -> 0.046975 | K11: =9/252 -> 0.035714286 | L11: =H11+G11 -> 104.925 | M11: =$D$31^((-J11)*(K11)) -> 0.99832373 | N11: =I11*M11 -> 103.82567 | O11: =D11+N11 -> 104.67067 | P11: =IF(L11=O11,"Not Violated","Violated") -> Violated | Q11: =ABS(L11-O11) -> 0.25433234 | R11: =D11-G11 -> -2.4300001 | S11: =H11-N11 -> -2.1756678 | T11: =R11-S11 -> -0.25433234 | U11: =O11-H11 -> 3.0206678 | V11: =IF(ABS(G11-U11)<=0.01,"NO VIOLATION",IF(G11>U11,"YES", "NO")) -> YES | W11: =IF(ABS(G11-U11)<=0.01,"NO VIOLATION",IF(G11>U11,"NO", "YES")) -> NO
A12: MRK 11/15/24 C105 | B12: 45423 | C12: 660 | D12: =('Bloomberg Raw Data-5th(No zero)'!C14+'Bloomberg Raw Data-5th(No zero)'!D14)/2 -> 0.59 | E12: MRK 11/15/24 P105 | F12: 69 | G12: =('Bloomberg Raw Data-5th(No zero)'!J14+'Bloomberg Raw Data-5th(No zero)'!K14)/2 -> 4 | H12: 101.65 | I12: 105 | J12: =4.6975/100 -> 0.046975 | K12: =9/252 -> 0.035714286 | L12: =H12+G12 -> 105.65 | M12: =$D$31^((-J12)*(K12)) -> 0.99832373 | N12: =I12*M12 -> 104.82399 | O12: =D12+N12 -> 105.41399 | P12: =IF(L12=O12,"Not Violated","Violated") -> Violated | Q12: =ABS(L12-O12) -> 0.23600851 | R12: =D12-G12 -> -3.41 | S12: =H12-N12 -> -3.1739915 | T12: =R12-S12 -> -0.23600851 | U12: =O12-H12 -> 3.7639915 | V12: =IF(ABS(G12-U12)<=0.01,"NO VIOLATION",IF(G12>U12,"YES", "NO")) -> YES | W12: =IF(ABS(G12-U12)<=0.01,"NO VIOLATION",IF(G12>U12,"NO", "YES")) -> NO
A13: MRK 11/15/24 C106 | B13: 45423 | C13: 107 | D13: =('Bloomberg Raw Data-5th(No zero)'!C15+'Bloomberg Raw Data-5th(No zero)'!D15)/2 -> 0.405 | E13: MRK 11/15/24 P106 | F13: 11 | G13: =('Bloomberg Raw Data-5th(No zero)'!J15+'Bloomberg Raw Data-5th(No zero)'!K15)/2 -> 4.8500004 | H13: 101.65 | I13: 106 | J13: =4.6975/100 -> 0.046975 | K13: =9/252 -> 0.035714286 | L13: =H13+G13 -> 106.5 | M13: =$D$31^((-J13)*(K13)) -> 0.99832373 | N13: =I13*M13 -> 105.82232 | O13: =D13+N13 -> 106.22732 | P13: =IF(L13=O13,"Not Violated","Violated") -> Violated | Q13: =ABS(L13-O13) -> 0.27268516 | R13: =D13-G13 -> -4.4450004 | S13: =H13-N13 -> -4.1723152 | T13: =R13-S13 -> -0.27268516 | U13: =O13-H13 -> 4.5773152 | V13: =IF(ABS(G13-U13)<=0.01,"NO VIOLATION",IF(G13>U13,"YES", "NO")) -> YES | W13: =IF(ABS(G13-U13)<=0.01,"NO VIOLATION",IF(G13>U13,"NO", "YES")) -> NO
A14: MRK 11/15/24 C107 | B14: 45423 | C14: 36 | D14: =('Bloomberg Raw Data-5th(No zero)'!C16+'Bloomberg Raw Data-5th(No zero)'!D16)/2 -> 0.26500002 | E14: MRK 11/15/24 P107 | F14: 6 | G14: =('Bloomberg Raw Data-5th(No zero)'!J16+'Bloomberg Raw Data-5th(No zero)'!K16)/2 -> 5.7250004 | H14: 101.65 | I14: 107 | J14: =4.6975/100 -> 0.046975 | K14: =9/252 -> 0.035714286 | L14: =H14+G14 -> 107.375 | M14: =$D$31^((-J14)*(K14)) -> 0.99832373 | N14: =I14*M14 -> 106.82064 | O14: =D14+N14 -> 107.08564 | P14: =IF(L14=O14,"Not Violated","Violated") -> Violated | Q14: =ABS(L14-O14) -> 0.28936142 | R14: =D14-G14 -> -5.4600004 | S14: =H14-N14 -> -5.1706389 | T14: =R14-S14 -> -0.28936142 | U14: =O14-H14 -> 5.435639 | V14: =IF(ABS(G14-U14)<=0.01,"NO VIOLATION",IF(G14>U14,"YES", "NO")) -> YES | W14: =IF(ABS(G14-U14)<=0.01,"NO VIOLATION",IF(G14>U14,"NO", "YES")) -> NO
A15: MRK 11/15/24 C110 | B15: 45423 | C15: 114 | D15: =('Bloomberg Raw Data-5th(No zero)'!C17+'Bloomberg Raw Data-5th(No zero)'!D17)/2 -> 0.10500002 | E15: MRK 11/15/24 P110 | F15: 143 | G15: =('Bloomberg Raw Data-5th(No zero)'!J17+'Bloomberg Raw Data-5th(No zero)'!K17)/2 -> 8.5999999 | H15: 101.65 | I15: 110 | J15: =4.6975/100 -> 0.046975 | K15: =9/252 -> 0.035714286 | L15: =H15+G15 -> 110.25 | M15: =$D$31^((-J15)*(K15)) -> 0.99832373 | N15: =I15*M15 -> 109.81561 | O15: =D15+N15 -> 109.92061 | P15: =IF(L15=O15,"Not Violated","Violated") -> Violated | Q15: =ABS(L15-O15) -> 0.32938976 | R15: =D15-G15 -> -8.4949999 | S15: =H15-N15 -> -8.1656101 | T15: =R15-S15 -> -0.32938976 | U15: =O15-H15 -> 8.2706101 | V15: =IF(ABS(G15-U15)<=0.01,"NO VIOLATION",IF(G15>U15,"YES", "NO")) -> YES | W15: =IF(ABS(G15-U15)<=0.01,"NO VIOLATION",IF(G15>U15,"NO", "YES")) -> NO
... A17: MRK 11/15/24 C130 | B17: 45423 | C17: 10 | D17: =('Bloomberg Raw Data-5th(No zero)'!C19+'Bloomberg Raw Data-5th(No zero)'!D19)/2 -> 0.02 | E17: MRK 11/15/24 P130 | F17: 4 | G17: =('Bloomberg Raw Data-5th(No zero)'!J19+'Bloomberg Raw Data-5th(No zero)'!K19)/2 -> 28.899994 | H17: 101.65 | I17: 130 | J17: =4.6975/100 -> 0.046975 | K17: =9/252 -> 0.035714286 | L17: =H17+G17 -> 130.54999 | M17: =$D$31^((-J17)*(K17)) -> 0.99832373 | N17: =I17*M17 -> 129.78208 | O17: =D17+N17 -> 129.80208 | P17: =IF(L17=O17,"Not Violated","Violated") -> Violated | Q17: =ABS(L17-O17) -> 0.7479092 | R17: =D17-G17 -> -28.879994 | S17: =H17-N17 -> -28.132085 | T17: =R17-S17 -> -0.7479092 | U17: =O17-H17 -> 28.152085 | V17: =IF(ABS(G17-U17)<=0.01,"NO VIOLATION",IF(G17>U17,"YES", "NO")) -> YES | W17: =IF(ABS(G17-U17)<=0.01,"NO VIOLATION",IF(G17>U17,"NO", "YES")) -> NO
A20: #Arbitrage Strategy Analysis for MRK 11/15/24 C102: Validating Overpriced Option via Put-Call Parity
A22: Category | B22: Parameter | D22: Value | F22: Category | G22: Parameter | I22: Value | L22: Factors Impacting Arbitrage Feasibility:
A23: Put-Call Parity Relationship | B23: C − P = S− K*e^−r(T−t) | D23: Alternatively formula can be written as S+P = C+ K*e^−r(T−t) | F23: Situation | L23: Risks to Arbitrage | M23: 1. Execution Risks - Arbitrage depends on the simultaneous execution of several trades. Any delay might lead to price fluctuations, negating potential gains sanction Cost - Brokerage fees and bid-ask spreads can quickly erode small profits.
F24: C−P (Observed) < S−K*e^−r(T−t) (Theoretical) → Overpriced Scenario | G24: Results | I24: Overpriced Scenario | M24: 2. Transaction Costs - Fees from brokers and the difference between bid and ask prices can quickly diminish small profit margins.
A25: Market Data on November 5, 2024 | B25: Price of the CALL Option (C) | D25: =D9 -> 1.6299996 | F25: C−P (Observed) > S−K*e^−r(T−t) (Theoretical) → Underpriced Scenario | M25: 3. European Options - This analysis is based on European-style options. In contrast, American-style options, which can be exercised anytime, may interfere with the strategy.
B26: Price of the PUT Option (P) | D26: =G9 -> 2.0149999 | F26: Arbitrage Strategy | G26: A. Initial Cash Flow: | M26: 4. Liquidity - Low open interest and trading volume for some options can increase the risk of slippage or incomplete transactions.
B27: Current Stock Price (S) | D27: =H9 -> 101.65 | G27: Buy Call | I27: =-D9 -> -1.6299996
B28: Strike Price of the Option (K) | D28: =I9 -> 102 | G28: Sell Put | I28: =G9 -> 2.0149999
B29: Risk-Free Interest Rate (r) | D29: =J4 -> 0.046975 | G29: Short Stock | I29: 101.65
B30: Time to Expiration (T-t) | D30: =9/252 -> 0.035714286 | G30: Invest in Bonds (PV of Strike Price) | I30: =-N9 -> -101.82902
B31: Constant e | D31: 2.718281 | G31: Net Initial Cash Flow | I31: =SUM(I27:I30) -> 0.20597993
A32: Discounted Strike Price | B32: {PV(K) = K*e^−r(T−t)} | D32: =D28*D31^(-D29*D30) -> 101.82902
D33: (102)*e^(-4.6975%*0.035714) | F33: Underlying Price as of November 15, 2024 | G33: ='Bloomberg Raw Data-5th(No zero)'!I54 -> 96.31
A34: Empirical Value | B34: [ C - P ] | D34: =D25-D26 -> -0.38500023 | G34: Net Payoff | I34: =I31 -> 0.20597993
A35: Model Value | B35: [ S - K*e^−r(T−t) ] | D35: =S9 -> -0.1790203 | F35: Arbitrage Strategy (At Expiration) When my Stock price (S) < Strike Price (K), we can exercise the put and sell the at K (102). This strategy allows us to cover the short position(96.31). The bonds will mature to K(102), ensuring sufficient funds are maintained to cover all liabilities. Thus, The call expires worthless, avoiding additional costs
A36: PUT-CALL Parity Violation | B36: [ Deviation ] | D36: =D34-D35 -> -0.20597993
D37: Potential Arbitrage Opportunity
G41: Net Payoff | I41: =I31 -> 0.20597993
A42: Option Arbitrage Strategies: Steps for Overpriced and Underpriced Scenarios
A44: Scenario | B44: Step and Description
A45: Overpriced Stock (S + P > C + K⋅e^−r(T−t)) | B45: 1.Identify Mispricing: Compare market and theoretical values to confirm mispricing
B46: 2.Short the stock: Benefit from the expected price drop
B47: 3.Sell overpriced put: Lock in inflated premiums
B48: 4.Buy a call option: Hedge against unexpected price increases
B49: 5.Invest discounted strike price: Secure future obligations
B50: Expiration Outcomes: If Stock Price > K: Call exercised, short position covered; If Stock Price < K: Put exercised, stock acquired, short repurchased
A51: Underpriced Stock (S + P < C + K⋅e^−r(T−t)) | B51: 1.Spot Opportunity: Observe put price undervaluation relative to theoretical pricing
B52: 2.Buy a put: Secure the right to sell at strike price K
B53: 3.Sell the call option: Capitalize on the overpricing
B54: 4.Purchase the stock: Benefit from undervaluation
B55: 5.Borrow PV(K) to fund purchase: Fund the purchase with borrowed amount equal to PV(K)
B56: Expiration Outcomes: If Stock Price > K: Call exercised, stock sold for K, borrowed amount repaid; If Stock Price < K: Put exercised, stock sold at K, borrowed amount repaid

Sheet Q1. Put- Call Parity(With zero 
B2: A. PUT-CALL Partity for all Options as on November 5, 2024
R3: Arbirtage Startegy | U3: Category | V3: Parameter | X3: Value | Z3: Category | AA3: Parameter | AC3: Value | AF3: Factors Impacting Arbitrage Feasibility:
B4: Option Symbol | C4: Option Expiry Date (EDT) | D4: Call Price( Bid and ask Average) ( C ) | E4: ='Q1-(Without Zero Volume)'!G3 -> Put Price (P) ( Bid and ask Average)\ | F4: C - P | G4: ='Q1-(Without Zero Volume)'!H3 -> Stock Price/ Spot Price (S) | H4: ='Q1-(Without Zero Volume)'!I3 -> Strike Price (K) | I4: e^-r(T-t) | J4: K*e^-r(T-t) | K4: S - K*e^-r(T-t) | L4: Difference | M4: CALL+Strike*e^(-rt) | N4: Put+Spot | O4: Difference | P4: Violation of Put-Call parity | Q4: Theoretical Value of Put Option P=C+K*e^-rt-S | R4: S+P>C+K⋅e ^−r(T−t) (OVERVALUED) | S4: S+P<C+K⋅e ^−r(T−t) (UNDERVALUED) | U4: Put-Call Parity Relationship | V4: C − P = S− K*e^−r(T−t) | X4: Alternatively formula can be written as S+P = C+ K*e^−r(T−t) | Z4: Situation | AF4: Risks to Arbitrage | AG4: 1. Execution Risks - Arbitrage depends on the simultaneous execution of several trades. Any delay might lead to price fluctuations, negating potential gains.nsaction Cost - Brokerage fees and bid-ask spreads can quickly erode small profits.
B5: MRK241115C00060000 | C5: 45558.775 | D5: =('Bloomberg Raw Data-5th (2)'!C8+'Bloomberg Raw Data-5th (2)'!D8)/2 -> 41.675003 | E5: =('Bloomberg Raw Data-5th (2)'!J8+'Bloomberg Raw Data-5th (2)'!K8)/2 -> 0.14000002 | F5: =D5-E5 -> 41.535003 | G5: 101.65 | H5: ='Bloomberg Raw Data-5th (2)'!A8 -> 60 | I5: =2.718281^(-$X$10*$X$11) -> 0.99832373 | J5: =H5*I5 -> 59.899424 | K5: =G5-J5 -> 41.750576 | L5: =F5-K5 -> -0.21557326 | M5: =D5+J5 -> 101.57443 | N5: =E5+G5 -> 101.79 | O5: =M5-N5 -> -0.21557326 | P5: =IF(M5=N5,"Not Violated","Voilated") -> Voilated | Q5: =M5-G5 -> -0.075573241 | R5: =IF(ABS(E5-Q5)<=0.01,"NO VIOLATION",IF(E5>Q5,"YES", "NO")) -> YES | S5: =IF(ABS(E5-Q5)<=0.01,"NO VIOLATION",IF(E5>Q5,"NO", "YES")) -> NO | Z5: C−P (Observed) < S−K*e^−r(T−t) (Theoretical) → Underpricing Scenario | AA5: Results | AC5: Underpricing Scenario | AG5: 2. Transaction Costs - Fees from brokers and the difference between bid and ask prices can quickly diminish small profit margins.
B6: MRK241115C00070000 | C6: 45574.588 | D6: =('Bloomberg Raw Data-5th (2)'!C9+'Bloomberg Raw Data-5th (2)'!D9)/2 -> 31.649994 | E6: =('Bloomberg Raw Data-5th (2)'!J9+'Bloomberg Raw Data-5th (2)'!K9)/2 -> 0.14500001 | F6: =D6-E6 -> 31.504994 | G6: =G5 -> 101.65 | H6: ='Bloomberg Raw Data-5th (2)'!A9 -> 70 | I6: =2.718281^(-$X$10*$X$11) -> 0.99832373 | J6: =H6*I6 -> 69.882661 | K6: =G6-J6 -> 31.767339 | L6: =F6-K6 -> -0.26234512 | M6: =D6+J6 -> 101.53265 | N6: =E6+G6 -> 101.795 | O6: =M6-N6 -> -0.26234512 | P6: =IF(M6=N6,"Not Violated","Voilated") -> Voilated | Q6: =M6-G6 -> -0.11734511 | R6: =IF(ABS(E6-Q6)<=0.01,"NO VIOLATION",IF(E6>Q6,"YES", "NO")) -> YES | S6: =IF(ABS(E6-Q6)<=0.01,"NO VIOLATION",IF(E6>Q6,"NO", "YES")) -> NO | U6: Market Data on November 5, 2024 | V6: Price of the CALL Option (C) | X6: =D15 -> 1.6299996 | Z6: C−P (Observed) > S−K*e^−r(T−t) (Theoretical) → Overpricing Scenario | AG6: 3. European Options - This analysis is based on European-style options. In contrast, American-style options, which can be exercised anytime, may interfere with the strategy.
B7: MRK241115C00080000 | C7: 45596.817 | D7: =('Bloomberg Raw Data-5th (2)'!C10+'Bloomberg Raw Data-5th (2)'!D10)/2 -> 21.674995 | E7: =('Bloomberg Raw Data-5th (2)'!J10+'Bloomberg Raw Data-5th (2)'!K10)/2 -> 0.064999998 | F7: =D7-E7 -> 21.609995 | G7: =G6 -> 101.65 | H7: ='Bloomberg Raw Data-5th (2)'!A10 -> 80 | I7: =2.718281^(-$X$10*$X$11) -> 0.99832373 | J7: =H7*I7 -> 79.865898 | K7: =G7-J7 -> 21.784102 | L7: =F7-K7 -> -0.1741063 | M7: =D7+J7 -> 101.54089 | N7: =E7+G7 -> 101.715 | O7: =M7-N7 -> -0.1741063 | P7: =IF(M7=N7,"Not Violated","Voilated") -> Voilated | Q7: =M7-G7 -> -0.1091063 | R7: =IF(ABS(E7-Q7)<=0.01,"NO VIOLATION",IF(E7>Q7,"YES", "NO")) -> YES | S7: =IF(ABS(E7-Q7)<=0.01,"NO VIOLATION",IF(E7>Q7,"NO", "YES")) -> NO | V7: Price of the PUT Option (P) | X7: =E15 -> 2.0149999 | Z7: Arbitrage Strategy | AA7: A. Initial Cash Flow: | AG7: 4. Liquidity - Low open interest and trading volume for some options can increase the risk of slippage or incomplete transactions.
B8: MRK241115C00085000 | C8: 45600.701 | D8: =('Bloomberg Raw Data-5th (2)'!C11+'Bloomberg Raw Data-5th (2)'!D11)/2 -> 16.599998 | E8: =('Bloomberg Raw Data-5th (2)'!J11+'Bloomberg Raw Data-5th (2)'!K11)/2 -> 0.050000012 | F8: =D8-E8 -> 16.549998 | G8: =G7 -> 101.65 | H8: ='Bloomberg Raw Data-5th (2)'!A11 -> 85 | I8: =2.718281^(-$X$10*$X$11) -> 0.99832373 | J8: =H8*I8 -> 84.857517 | K8: =G8-J8 -> 16.792483 | L8: =F8-K8 -> -0.24248462 | M8: =D8+J8 -> 101.45752 | N8: =E8+G8 -> 101.7 | O8: =M8-N8 -> -0.24248462 | P8: =IF(M8=N8,"Not Violated","Voilated") -> Voilated | Q8: =M8-G8 -> -0.19248461 | R8: =IF(ABS(E8-Q8)<=0.01,"NO VIOLATION",IF(E8>Q8,"YES", "NO")) -> YES | S8: =IF(ABS(E8-Q8)<=0.01,"NO VIOLATION",IF(E8>Q8,"NO", "YES")) -> NO | V8: Current Stock Price (S) | X8: =G15 -> 101.65 | AA8: Buy Call | AC8: =-$D$15 -> -1.6299996
B9: MRK241115C00090000 | C9: 45589.61 | D9: =('Bloomberg Raw Data-5th (2)'!C12+'Bloomberg Raw Data-5th (2)'!D12)/2 -> 11.65 | E9: =('Bloomberg Raw Data-5th (2)'!J12+'Bloomberg Raw Data-5th (2)'!K12)/2 -> 0.050000017 | F9: =D9-E9 -> 11.6 | G9: =G8 -> 101.65 | H9: ='Bloomberg Raw Data-5th (2)'!A12 -> 90 | I9: =2.718281^(-$X$10*$X$11) -> 0.99832373 | J9: =H9*I9 -> 89.849136 | K9: =G9-J9 -> 11.800864 | L9: =F9-K9 -> -0.20086436 | M9: =D9+J9 -> 101.49914 | N9: =E9+G9 -> 101.7 | O9: =M9-N9 -> -0.20086436 | P9: =IF(M9=N9,"Not Violated","Voilated") -> Voilated | Q9: =M9-G9 -> -0.15086434 | R9: =IF(ABS(E9-Q9)<=0.01,"NO VIOLATION",IF(E9>Q9,"YES", "NO")) -> YES | S9: =IF(ABS(E9-Q9)<=0.01,"NO VIOLATION",IF(E9>Q9,"NO", "YES")) -> NO | V9: Strike Price of the Option (K) | X9: =H15 -> 102 | AA9: Sell Put | AC9: =$E$15 -> 2.0149999
B10: MRK241115C00095000 | C10: 45601.621 | D10: =('Bloomberg Raw Data-5th (2)'!C13+'Bloomberg Raw Data-5th (2)'!D13)/2 -> 6.8000002 | E10: =('Bloomberg Raw Data-5th (2)'!J13+'Bloomberg Raw Data-5th (2)'!K13)/2 -> 0.16999999 | F10: =D10-E10 -> 6.6300002 | G10: =G9 -> 101.65 | H10: ='Bloomberg Raw Data-5th (2)'!A13 -> 95 | I10: =2.718281^(-$X$10*$X$11) -> 0.99832373 | J10: =H10*I10 -> 94.840754 | K10: =G10-J10 -> 6.8092458 | L10: =F10-K10 -> -0.17924559 | M10: =D10+J10 -> 101.64075 | N10: =E10+G10 -> 101.82 | O10: =M10-N10 -> -0.17924559 | P10: =IF(M10=N10,"Not Violated","Voilated") -> Voilated | Q10: =M10-G10 -> -0.009245606 | R10: =IF(ABS(E10-Q10)<=0.01,"NO VIOLATION",IF(E10>Q10,"YES", "NO")) -> YES | S10: =IF(ABS(E10-Q10)<=0.01,"NO VIOLATION",IF(E10>Q10,"NO", "YES")) -> NO | V10: Risk-Free Interest Rate (r) | X10: ='Q2. Implied Volatality - Final'!I8 -> 0.046975 | AA10: Short Stock | AC10: 101.65 | AD10: ***Note: This is the arbitrage profit per contract, assuming no transaction costs.
B11: MRK241115C00098000 | C11: 45597.675 | D11: =('Bloomberg Raw Data-5th (2)'!C14+'Bloomberg Raw Data-5th (2)'!D14)/2 -> 4.2250004 | E11: =('Bloomberg Raw Data-5th (2)'!J14+'Bloomberg Raw Data-5th (2)'!K14)/2 -> 0.61000001 | F11: =D11-E11 -> 3.6150004 | G11: =G10 -> 101.65 | H11: ='Bloomberg Raw Data-5th (2)'!A14 -> 98 | I11: =2.718281^(-$X$10*$X$11) -> 0.99832373 | J11: =H11*I11 -> 97.835725 | K11: =G11-J11 -> 3.8142746 | L11: =F11-K11 -> -0.19927424 | M11: =D11+J11 -> 102.06073 | N11: =E11+G11 -> 102.26 | O11: =M11-N11 -> -0.19927424 | P11: =IF(M11=N11,"Not Violated","Voilated") -> Voilated | Q11: =M11-G11 -> 0.41072577 | R11: =IF(ABS(E11-Q11)<=0.01,"NO VIOLATION",IF(E11>Q11,"YES", "NO")) -> YES | S11: =IF(ABS(E11-Q11)<=0.01,"NO VIOLATION",IF(E11>Q11,"NO", "YES")) -> NO | V11: Time to Expiration (T-t) | X11: =9/252 -> 0.035714286 | AA11: Invest in Bonds (PV of Strike Price) | AC11: =-$J$15 -> -101.82902
B12: MRK241115C00099000 | C12: 45600.629 | D12: =('Bloomberg Raw Data-5th (2)'!C15+'Bloomberg Raw Data-5th (2)'!D15)/2 -> 3.4750004 | E12: =('Bloomberg Raw Data-5th (2)'!J15+'Bloomberg Raw Data-5th (2)'!K15)/2 -> 0.88 | F12: =D12-E12 -> 2.5950004 | G12: =G11 -> 101.65 | H12: ='Bloomberg Raw Data-5th (2)'!A15 -> 99 | I12: =2.718281^(-$X$10*$X$11) -> 0.99832373 | J12: =H12*I12 -> 98.834049 | K12: =G12-J12 -> 2.8159509 | L12: =F12-K12 -> -0.2209505 | M12: =D12+J12 -> 102.30905 | N12: =E12+G12 -> 102.53 | O12: =M12-N12 -> -0.2209505 | P12: =IF(M12=N12,"Not Violated","Voilated") -> Voilated | Q12: =M12-G12 -> 0.6590495 | R12: =IF(ABS(E12-Q12)<=0.01,"NO VIOLATION",IF(E12>Q12,"YES", "NO")) -> YES | S12: =IF(ABS(E12-Q12)<=0.01,"NO VIOLATION",IF(E12>Q12,"NO", "YES")) -> NO | V12: Constant e | X12: 2.718281 | AA12: Net Initial Cash Flow | AC12: =SUM(AC8:AC11) -> 0.20597993
B13: MRK241115C00100000 | C13: 45601.636 | D13: =('Bloomberg Raw Data-5th (2)'!C16+'Bloomberg Raw Data-5th (2)'!D16)/2 -> 2.7850003 | E13: =('Bloomberg Raw Data-5th (2)'!J16+'Bloomberg Raw Data-5th (2)'!K16)/2 -> 1.1300001 | F13: =D13-E13 -> 1.6550002 | G13: =G12 -> 101.65 | H13: ='Bloomberg Raw Data-5th (2)'!A16 -> 100 | I13: =2.718281^(-$X$10*$X$11) -> 0.99832373 | J13: =H13*I13 -> 99.832373 | K13: =G13-J13 -> 1.8176272 | L13: =F13-K13 -> -0.16262694 | M13: =D13+J13 -> 102.61737 | N13: =E13+G13 -> 102.78 | O13: =M13-N13 -> -0.16262694 | P13: =IF(M13=N13,"Not Violated","Voilated") -> Voilated | Q13: =M13-G13 -> 0.96737317 | R13: =IF(ABS(E13-Q13)<=0.01,"NO VIOLATION",IF(E13>Q13,"YES", "NO")) -> YES | S13: =IF(ABS(E13-Q13)<=0.01,"NO VIOLATION",IF(E13>Q13,"NO", "YES")) -> NO | U13: Discounted Strike Price | V13: {PV(K) = K*e^−r(T−t)} | X13: =X9*X12^(-X10*X11) -> 101.82902
B14: MRK241115C00101000 | C14: 45601.644 | D14: =('Bloomberg Raw Data-5th (2)'!C17+'Bloomberg Raw Data-5th (2)'!D17)/2 -> 2.1599998 | E14: =('Bloomberg Raw Data-5th (2)'!J17+'Bloomberg Raw Data-5th (2)'!K17)/2 -> 1.5499997 | F14: =D14-E14 -> 0.61000013 | G14: =G13 -> 101.65 | H14: ='Bloomberg Raw Data-5th (2)'!A17 -> 101 | I14: =2.718281^(-$X$10*$X$11) -> 0.99832373 | J14: =H14*I14 -> 100.8307 | K14: =G14-J14 -> 0.81930343 | L14: =F14-K14 -> -0.20930329 | M14: =D14+J14 -> 102.9907 | N14: =E14+G14 -> 103.2 | O14: =M14-N14 -> -0.20930329 | P14: =IF(M14=N14,"Not Violated","Voilated") -> Voilated | Q14: =M14-G14 -> 1.3406964 | R14: =IF(ABS(E14-Q14)<=0.01,"NO VIOLATION",IF(E14>Q14,"YES", "NO")) -> YES | S14: =IF(ABS(E14-Q14)<=0.01,"NO VIOLATION",IF(E14>Q14,"NO", "YES")) -> NO | X14: (102)*e^(-4.6975%*0.039683) | Z14: Underlying Price as of November 15, 2024 | AA14: ='Bloomberg Raw Data-5th(No zero)'!I54 -> 96.31
B15: MRK241115C00102000 | C15: 45601.618 | D15: =('Bloomberg Raw Data-5th (2)'!C18+'Bloomberg Raw Data-5th (2)'!D18)/2 -> 1.6299996 | E15: =('Bloomberg Raw Data-5th (2)'!J18+'Bloomberg Raw Data-5th (2)'!K18)/2 -> 2.0149999 | F15: =D15-E15 -> -0.38500023 | G15: =G14 -> 101.65 | H15: ='Bloomberg Raw Data-5th (2)'!A18 -> 102 | I15: =2.718281^(-$X$10*$X$11) -> 0.99832373 | J15: =H15*I15 -> 101.82902 | K15: =G15-J15 -> -0.1790203 | L15: =F15-K15 -> -0.20597993 | M15: =D15+J15 -> 103.45902 | N15: =E15+G15 -> 103.665 | O15: =M15-N15 -> -0.20597993 | P15: =IF(M15=N15,"Not Violated","Voilated") -> Voilated | Q15: =M15-G15 -> 1.8090199 | R15: =IF(ABS(E15-Q15)<=0.01,"NO VIOLATION",IF(E15>Q15,"YES", "NO")) -> YES | S15: =IF(ABS(E15-Q15)<=0.01,"NO VIOLATION",IF(E15>Q15,"NO", "YES")) -> NO | U15: Empirical Value | V15: [ C - P ] | X15: =X6-X7 -> -0.38500023
B16: MRK241115C00103000 | C16: 45601.642 | D16: =('Bloomberg Raw Data-5th (2)'!C19+'Bloomberg Raw Data-5th (2)'!D19)/2 -> 1.1950002 | E16: =('Bloomberg Raw Data-5th (2)'!J19+'Bloomberg Raw Data-5th (2)'!K19)/2 -> 2.585 | F16: =D16-E16 -> -1.3899999 | G16: =G15 -> 101.65 | H16: ='Bloomberg Raw Data-5th (2)'!A19 -> 103 | I16: =2.718281^(-$X$10*$X$11) -> 0.99832373 | J16: =H16*I16 -> 102.82734 | K16: =G16-J16 -> -1.177344 | L16: =F16-K16 -> -0.21265584 | M16: =D16+J16 -> 104.02234 | N16: =E16+G16 -> 104.235 | O16: =M16-N16 -> -0.21265584 | P16: =IF(M16=N16,"Not Violated","Voilated") -> Voilated | Q16: =M16-G16 -> 2.3723442 | R16: =IF(ABS(E16-Q16)<=0.01,"NO VIOLATION",IF(E16>Q16,"YES", "NO")) -> YES | S16: =IF(ABS(E16-Q16)<=0.01,"NO VIOLATION",IF(E16>Q16,"NO", "YES")) -> NO | U16: Model Value | V16: [ S - K*e^−r(T−t) ] | X16: =K15 -> -0.1790203 | Z16: Arbitrage Strategy | AA16: B. At Expiration
B17: MRK241115C00104000 | C17: 45601.618 | D17: =('Bloomberg Raw Data-5th (2)'!C20+'Bloomberg Raw Data-5th (2)'!D20)/2 -> 0.845 | E17: =('Bloomberg Raw Data-5th (2)'!J20+'Bloomberg Raw Data-5th (2)'!K20)/2 -> 3.2750001 | F17: =D17-E17 -> -2.4300001 | G17: =G16 -> 101.65 | H17: ='Bloomberg Raw Data-5th (2)'!A20 -> 104 | I17: =2.718281^(-$X$10*$X$11) -> 0.99832373 | J17: =H17*I17 -> 103.82567 | K17: =G17-J17 -> -2.1756678 | L17: =F17-K17 -> -0.25433234 | M17: =D17+J17 -> 104.67067 | N17: =E17+G17 -> 104.925 | O17: =M17-N17 -> -0.25433234 | P17: =IF(M17=N17,"Not Violated","Voilated") -> Voilated | Q17: =M17-G17 -> 3.0206678 | R17: =IF(ABS(E17-Q17)<=0.01,"NO VIOLATION",IF(E17>Q17,"YES", "NO")) -> YES | S17: =IF(ABS(E17-Q17)<=0.01,"NO VIOLATION",IF(E17>Q17,"NO", "YES")) -> NO | U17: PUT-CALL Parity Violation | V17: [ Deviation ] | X17: =L15 -> -0.20597993 | AA17: Stock Prics < Strike Price | AC17: The put option is excercised
B18: MRK241115C00105000 | C18: 45601.647 | D18: =('Bloomberg Raw Data-5th (2)'!C21+'Bloomberg Raw Data-5th (2)'!D21)/2 -> 0.59 | E18: =('Bloomberg Raw Data-5th (2)'!J21+'Bloomberg Raw Data-5th (2)'!K21)/2 -> 4 | F18: =D18-E18 -> -3.41 | G18: =G17 -> 101.65 | H18: ='Bloomberg Raw Data-5th (2)'!A21 -> 105 | I18: =2.718281^(-$X$10*$X$11) -> 0.99832373 | J18: =H18*I18 -> 104.82399 | K18: =G18-J18 -> -3.1739915 | L18: =F18-K18 -> -0.23600851 | M18: =D18+J18 -> 105.41399 | N18: =E18+G18 -> 105.65 | O18: =M18-N18 -> -0.23600851 | P18: =IF(M18=N18,"Not Violated","Voilated") -> Voilated | Q18: =M18-G18 -> 3.7639915 | R18: =IF(ABS(E18-Q18)<=0.01,"NO VIOLATION",IF(E18>Q18,"YES", "NO")) -> YES | S18: =IF(ABS(E18-Q18)<=0.01,"NO VIOLATION",IF(E18>Q18,"NO", "YES")) -> NO | X18: Potential Arbitrage Opportunity | AC18: Sell stock at K=102.
B19: MRK241115C00106000 | C19: 45601.646 | D19: =('Bloomberg Raw Data-5th (2)'!C22+'Bloomberg Raw Data-5th (2)'!D22)/2 -> 0.405 | E19: =('Bloomberg Raw Data-5th (2)'!J22+'Bloomberg Raw Data-5th (2)'!K22)/2 -> 4.8500004 | F19: =D19-E19 -> -4.4450004 | G19: =G18 -> 101.65 | H19: ='Bloomberg Raw Data-5th (2)'!A22 -> 106 | I19: =2.718281^(-$X$10*$X$11) -> 0.99832373 | J19: =H19*I19 -> 105.82232 | K19: =G19-J19 -> -4.1723152 | L19: =F19-K19 -> -0.27268516 | M19: =D19+J19 -> 106.22732 | N19: =E19+G19 -> 106.5 | O19: =M19-N19 -> -0.27268516 | P19: =IF(M19=N19,"Not Violated","Voilated") -> Voilated | Q19: =M19-G19 -> 4.5773152 | R19: =IF(ABS(E19-Q19)<=0.01,"NO VIOLATION",IF(E19>Q19,"YES", "NO")) -> YES | S19: =IF(ABS(E19-Q19)<=0.01,"NO VIOLATION",IF(E19>Q19,"NO", "YES")) -> NO | AC19: The call option expires worthless.
B20: MRK241115C00107000 | C20: 45600.875 | D20: =('Bloomberg Raw Data-5th (2)'!C23+'Bloomberg Raw Data-5th (2)'!D23)/2 -> 0.26500002 | E20: =('Bloomberg Raw Data-5th (2)'!J23+'Bloomberg Raw Data-5th (2)'!K23)/2 -> 5.7250004 | F20: =D20-E20 -> -5.4600004 | G20: =G19 -> 101.65 | H20: ='Bloomberg Raw Data-5th (2)'!A23 -> 107 | I20: =2.718281^(-$X$10*$X$11) -> 0.99832373 | J20: =H20*I20 -> 106.82064 | K20: =G20-J20 -> -5.1706389 | L20: =F20-K20 -> -0.28936142 | M20: =D20+J20 -> 107.08564 | N20: =E20+G20 -> 107.375 | O20: =M20-N20 -> -0.28936142 | P20: =IF(M20=N20,"Not Violated","Voilated") -> Voilated | Q20: =M20-G20 -> 5.435639 | R20: =IF(ABS(E20-Q20)<=0.01,"NO VIOLATION",IF(E20>Q20,"YES", "NO")) -> YES | S20: =IF(ABS(E20-Q20)<=0.01,"NO VIOLATION",IF(E20>Q20,"NO", "YES")) -> NO | AC20: Short stock is covered at K=96.31
B21: MRK241115C00108000 | C21: 45601.623 | D21: =('Bloomberg Raw Data-5th (2)'!C24+'Bloomberg Raw Data-5th (2)'!D24)/2 -> 0.19 | E21: =('Bloomberg Raw Data-5th (2)'!J24+'Bloomberg Raw Data-5th (2)'!K24)/2 -> 5.9750004 | F21: =D21-E21 -> -5.7850004 | G21: =G20 -> 101.65 | H21: ='Bloomberg Raw Data-5th (2)'!A24 -> 108 | I21: =2.718281^(-$X$10*$X$11) -> 0.99832373 | J21: =H21*I21 -> 107.81896 | K21: =G21-J21 -> -6.1689627 | L21: =F21-K21 -> 0.38396229 | M21: =D21+J21 -> 108.00896 | N21: =E21+G21 -> 107.625 | O21: =M21-N21 -> 0.38396229 | P21: =IF(M21=N21,"Not Violated","Voilated") -> Voilated | Q21: =M21-G21 -> 6.3589627 | R21: =IF(ABS(E21-Q21)<=0.01,"NO VIOLATION",IF(E21>Q21,"YES", "NO")) -> NO | S21: =IF(ABS(E21-Q21)<=0.01,"NO VIOLATION",IF(E21>Q21,"NO", "YES")) -> YES | AC21: Bonds mature to K=102
B22: MRK241115C00109000 | C22: 45601.642 | D22: =('Bloomberg Raw Data-5th (2)'!C25+'Bloomberg Raw Data-5th (2)'!D25)/2 -> 0.13000003 | E22: =('Bloomberg Raw Data-5th (2)'!J25+'Bloomberg Raw Data-5th (2)'!K25)/2 -> 7.625 | F22: =D22-E22 -> -7.495 | G22: =G21 -> 101.65 | H22: ='Bloomberg Raw Data-5th (2)'!A25 -> 109 | I22: =2.718281^(-$X$10*$X$11) -> 0.99832373 | J22: =H22*I22 -> 108.81729 | K22: =G22-J22 -> -7.1672864 | L22: =F22-K22 -> -0.32771357 | M22: =D22+J22 -> 108.94729 | N22: =E22+G22 -> 109.275 | O22: =M22-N22 -> -0.32771357 | P22: =IF(M22=N22,"Not Violated","Voilated") -> Voilated | Q22: =M22-G22 -> 7.2972864 | R22: =IF(ABS(E22-Q22)<=0.01,"NO VIOLATION",IF(E22>Q22,"YES", "NO")) -> YES | S22: =IF(ABS(E22-Q22)<=0.01,"NO VIOLATION",IF(E22>Q22,"NO", "YES")) -> NO | AA22: Net Payoff | AC22: =AC12 -> 0.20597993
B23: MRK241115C00110000 | C23: 45601.636 | D23: =('Bloomberg Raw Data-5th (2)'!C26+'Bloomberg Raw Data-5th (2)'!D26)/2 -> 0.10500002 | E23: =('Bloomberg Raw Data-5th (2)'!J26+'Bloomberg Raw Data-5th (2)'!K26)/2 -> 8.5999999 | F23: =D23-E23 -> -8.4949999 | G23: =G22 -> 101.65 | H23: ='Bloomberg Raw Data-5th (2)'!A26 -> 110 | I23: =2.718281^(-$X$10*$X$11) -> 0.99832373 | J23: =H23*I23 -> 109.81561 | K23: =G23-J23 -> -8.1656101 | L23: =F23-K23 -> -0.32938976 | M23: =D23+J23 -> 109.92061 | N23: =E23+G23 -> 110.25 | O23: =M23-N23 -> -0.32938976 | P23: =IF(M23=N23,"Not Violated","Voilated") -> Voilated | Q23: =M23-G23 -> 8.2706101 | R23: =IF(ABS(E23-Q23)<=0.01,"NO VIOLATION",IF(E23>Q23,"YES", "NO")) -> YES | S23: =IF(ABS(E23-Q23)<=0.01,"NO VIOLATION",IF(E23>Q23,"NO", "YES")) -> NO
B24: MRK241115C00111000 | C24: 45600.772 | D24: =('Bloomberg Raw Data-5th (2)'!C27+'Bloomberg Raw Data-5th (2)'!D27)/2 -> 0.075000016 | E24: =('Bloomberg Raw Data-5th (2)'!J27+'Bloomberg Raw Data-5th (2)'!K27)/2 -> 9.2750001 | F24: =D24-E24 -> -9.2000001 | G24: =G23 -> 101.65 | H24: ='Bloomberg Raw Data-5th (2)'!A27 -> 111 | I24: =2.718281^(-$X$10*$X$11) -> 0.99832373 | J24: =H24*I24 -> 110.81393 | K24: =G24-J24 -> -9.1639339 | L24: =F24-K24 -> -0.036066221 | M24: =D24+J24 -> 110.88893 | N24: =E24+G24 -> 110.925 | O24: =M24-N24 -> -0.036066221 | P24: =IF(M24=N24,"Not Violated","Voilated") -> Voilated | Q24: =M24-G24 -> 9.2389339 | R24: =IF(ABS(E24-Q24)<=0.01,"NO VIOLATION",IF(E24>Q24,"YES", "NO")) -> YES | S24: =IF(ABS(E24-Q24)<=0.01,"NO VIOLATION",IF(E24>Q24,"NO", "YES")) -> NO
B25: MRK241115C00112000 | C25: 45600.803 | D25: =('Bloomberg Raw Data-5th (2)'!C28+'Bloomberg Raw Data-5th (2)'!D28)/2 -> 0.13 | E25: =('Bloomberg Raw Data-5th (2)'!J28+'Bloomberg Raw Data-5th (2)'!K28)/2 -> 10.525 | F25: =D25-E25 -> -10.395 | G25: =G24 -> 101.65 | H25: ='Bloomberg Raw Data-5th (2)'!A28 -> 112 | I25: =2.718281^(-$X$10*$X$11) -> 0.99832373 | J25: =H25*I25 -> 111.81226 | K25: =G25-J25 -> -10.162258 | L25: =F25-K25 -> -0.23274251 | M25: =D25+J25 -> 111.94226 | N25: =E25+G25 -> 112.175 | O25: =M25-N25 -> -0.23274251 | P25: =IF(M25=N25,"Not Violated","Voilated") -> Voilated | Q25: =M25-G25 -> 10.292258 | R25: =IF(ABS(E25-Q25)<=0.01,"NO VIOLATION",IF(E25>Q25,"YES", "NO")) -> YES | S25: =IF(ABS(E25-Q25)<=0.01,"NO VIOLATION",IF(E25>Q25,"NO", "YES")) -> NO
B26: MRK241115C00113000 | C26: 45600.657 | D26: =('Bloomberg Raw Data-5th (2)'!C29+'Bloomberg Raw Data-5th (2)'!D29)/2 -> 0.20000002 | E26: =('Bloomberg Raw Data-5th (2)'!J29+'Bloomberg Raw Data-5th (2)'!K29)/2 -> 11.725 | F26: =D26-E26 -> -11.525 | G26: =G25 -> 101.65 | H26: ='Bloomberg Raw Data-5th (2)'!A29 -> 113 | I26: =2.718281^(-$X$10*$X$11) -> 0.99832373 | J26: =H26*I26 -> 112.81058 | K26: =G26-J26 -> -11.160581 | L26: =F26-K26 -> -0.36441857 | M26: =D26+J26 -> 113.01058 | N26: =E26+G26 -> 113.375 | O26: =M26-N26 -> -0.36441857 | P26: =IF(M26=N26,"Not Violated","Voilated") -> Voilated | Q26: =M26-G26 -> 11.360581 | R26: =IF(ABS(E26-Q26)<=0.01,"NO VIOLATION",IF(E26>Q26,"YES", "NO")) -> YES | S26: =IF(ABS(E26-Q26)<=0.01,"NO VIOLATION",IF(E26>Q26,"NO", "YES")) -> NO
B27: MRK241115C00114000 | C27: 45600.708 | D27: =('Bloomberg Raw Data-5th (2)'!C30+'Bloomberg Raw Data-5th (2)'!D30)/2 -> 0.070000002 | E27: =('Bloomberg Raw Data-5th (2)'!J30+'Bloomberg Raw Data-5th (2)'!K30)/2 -> 12.55 | F27: =D27-E27 -> -12.48 | G27: =G26 -> 101.65 | H27: ='Bloomberg Raw Data-5th (2)'!A30 -> 114 | I27: =2.718281^(-$X$10*$X$11) -> 0.99832373 | J27: =H27*I27 -> 113.80891 | K27: =G27-J27 -> -12.158905 | L27: =F27-K27 -> -0.32109467 | M27: =D27+J27 -> 113.87891 | N27: =E27+G27 -> 114.2 | O27: =M27-N27 -> -0.32109467 | P27: =IF(M27=N27,"Not Violated","Voilated") -> Voilated | Q27: =M27-G27 -> 12.228905 | R27: =IF(ABS(E27-Q27)<=0.01,"NO VIOLATION",IF(E27>Q27,"YES", "NO")) -> YES | S27: =IF(ABS(E27-Q27)<=0.01,"NO VIOLATION",IF(E27>Q27,"NO", "YES")) -> NO
B28: MRK241115C00115000 | C28: 45601.64 | D28: =('Bloomberg Raw Data-5th (2)'!C31+'Bloomberg Raw Data-5th (2)'!D31)/2 -> 0.025 | E28: =('Bloomberg Raw Data-5th (2)'!J31+'Bloomberg Raw Data-5th (2)'!K31)/2 -> 13.325 | F28: =D28-E28 -> -13.3 | G28: =G27 -> 101.65 | H28: ='Bloomberg Raw Data-5th (2)'!A31 -> 115 | I28: =2.718281^(-$X$10*$X$11) -> 0.99832373 | J28: =H28*I28 -> 114.80723 | K28: =G28-J28 -> -13.157229 | L28: =F28-K28 -> -0.14277104 | M28: =D28+J28 -> 114.83223 | N28: =E28+G28 -> 114.975 | O28: =M28-N28 -> -0.14277104 | P28: =IF(M28=N28,"Not Violated","Voilated") -> Voilated | Q28: =M28-G28 -> 13.182229 | R28: =IF(ABS(E28-Q28)<=0.01,"NO VIOLATION",IF(E28>Q28,"YES", "NO")) -> YES | S28: =IF(ABS(E28-Q28)<=0.01,"NO VIOLATION",IF(E28>Q28,"NO", "YES")) -> NO
B29: MRK241115C00116000 | C29: 45595.832 | D29: =('Bloomberg Raw Data-5th (2)'!C32+'Bloomberg Raw Data-5th (2)'!D32)/2 -> 0.065000003 | E29: =('Bloomberg Raw Data-5th (2)'!J32+'Bloomberg Raw Data-5th (2)'!K32)/2 -> 14.625 | F29: =D29-E29 -> -14.56 | G29: =G28 -> 101.65 | H29: ='Bloomberg Raw Data-5th (2)'!A32 -> 116 | I29: =2.718281^(-$X$10*$X$11) -> 0.99832373 | J29: =H29*I29 -> 115.80555 | K29: =G29-J29 -> -14.155553 | L29: =F29-K29 -> -0.4044475 | M29: =D29+J29 -> 115.87055 | N29: =E29+G29 -> 116.275 | O29: =M29-N29 -> -0.4044475 | P29: =IF(M29=N29,"Not Violated","Voilated") -> Voilated | Q29: =M29-G29 -> 14.220553 | R29: =IF(ABS(E29-Q29)<=0.01,"NO VIOLATION",IF(E29>Q29,"YES", "NO")) -> YES | S29: =IF(ABS(E29-Q29)<=0.01,"NO VIOLATION",IF(E29>Q29,"NO", "YES")) -> NO
B30: MRK241115C00117000 | C30: 45595.815 | D30: =('Bloomberg Raw Data-5th (2)'!C33+'Bloomberg Raw Data-5th (2)'!D33)/2 -> 0.16 | E30: =('Bloomberg Raw Data-5th (2)'!J33+'Bloomberg Raw Data-5th (2)'!K33)/2 -> 16.000003 | F30: =D30-E30 -> -15.840003 | G30: =G29 -> 101.65 | H30: ='Bloomberg Raw Data-5th (2)'!A33 -> 117 | I30: =2.718281^(-$X$10*$X$11) -> 0.99832373 | J30: =H30*I30 -> 116.80388 | K30: =G30-J30 -> -15.153876 | L30: =F30-K30 -> -0.68612664 | M30: =D30+J30 -> 116.96388 | N30: =E30+G30 -> 117.65 | O30: =M30-N30 -> -0.68612664 | P30: =IF(M30=N30,"Not Violated","Voilated") -> Voilated | Q30: =M30-G30 -> 15.313876 | R30: =IF(ABS(E30-Q30)<=0.01,"NO VIOLATION",IF(E30>Q30,"YES", "NO")) -> YES | S30: =IF(ABS(E30-Q30)<=0.01,"NO VIOLATION",IF(E30>Q30,"NO", "YES")) -> NO
B31: MRK241115C00118000 | C31: 45595.808 | D31: =('Bloomberg Raw Data-5th (2)'!C34+'Bloomberg Raw Data-5th (2)'!D34)/2 -> 0.050000012 | E31: =('Bloomberg Raw Data-5th (2)'!J34+'Bloomberg Raw Data-5th (2)'!K34)/2 -> 16.099997 | F31: =D31-E31 -> -16.049997 | G31: =G30 -> 101.65 | H31: ='Bloomberg Raw Data-5th (2)'!A34 -> 118 | I31: =2.718281^(-$X$10*$X$11) -> 0.99832373 | J31: =H31*I31 -> 117.8022 | K31: =G31-J31 -> -16.1522 | L31: =F31-K31 -> 0.10220293 | M31: =D31+J31 -> 117.8522 | N31: =E31+G31 -> 117.75 | O31: =M31-N31 -> 0.10220293 | P31: =IF(M31=N31,"Not Violated","Voilated") -> Voilated | Q31: =M31-G31 -> 16.2022 | R31: =IF(ABS(E31-Q31)<=0.01,"NO VIOLATION",IF(E31>Q31,"YES", "NO")) -> NO | S31: =IF(ABS(E31-Q31)<=0.01,"NO VIOLATION",IF(E31>Q31,"NO", "YES")) -> YES
B32: MRK241115C00119000 | C32: 45590.582 | D32: =('Bloomberg Raw Data-5th (2)'!C35+'Bloomberg Raw Data-5th (2)'!D35)/2 -> 0.15000001 | E32: =('Bloomberg Raw Data-5th (2)'!J35+'Bloomberg Raw Data-5th (2)'!K35)/2 -> 17.899994 | F32: =D32-E32 -> -17.749994 | G32: =G31 -> 101.65 | H32: ='Bloomberg Raw Data-5th (2)'!A35 -> 119 | I32: =2.718281^(-$X$10*$X$11) -> 0.99832373 | J32: =H32*I32 -> 118.80052 | K32: =G32-J32 -> -17.150524 | L32: =F32-K32 -> -0.5994702 | M32: =D32+J32 -> 118.95052 | N32: =E32+G32 -> 119.54999 | O32: =M32-N32 -> -0.5994702 | P32: =IF(M32=N32,"Not Violated","Voilated") -> Voilated | Q32: =M32-G32 -> 17.300524 | R32: =IF(ABS(E32-Q32)<=0.01,"NO VIOLATION",IF(E32>Q32,"YES", "NO")) -> YES | S32: =IF(ABS(E32-Q32)<=0.01,"NO VIOLATION",IF(E32>Q32,"NO", "YES")) -> NO
B33: MRK241115C00120000 | C33: 45600.843 | D33: =('Bloomberg Raw Data-5th (2)'!C36+'Bloomberg Raw Data-5th (2)'!D36)/2 -> 0.015000001 | E33: =('Bloomberg Raw Data-5th (2)'!J36+'Bloomberg Raw Data-5th (2)'!K36)/2 -> 18.5 | F33: =D33-E33 -> -18.485 | G33: =G32 -> 101.65 | H33: ='Bloomberg Raw Data-5th (2)'!A36 -> 120 | I33: =2.718281^(-$X$10*$X$11) -> 0.99832373 | J33: =H33*I33 -> 119.79885 | K33: =G33-J33 -> -18.148847 | L33: =F33-K33 -> -0.33615258 | M33: =D33+J33 -> 119.81385 | N33: =E33+G33 -> 120.15 | O33: =M33-N33 -> -0.33615258 | P33: =IF(M33=N33,"Not Violated","Voilated") -> Voilated | Q33: =M33-G33 -> 18.163847 | R33: =IF(ABS(E33-Q33)<=0.01,"NO VIOLATION",IF(E33>Q33,"YES", "NO")) -> YES | S33: =IF(ABS(E33-Q33)<=0.01,"NO VIOLATION",IF(E33>Q33,"NO", "YES")) -> NO
B34: MRK241115C00121000 | C34: 45601.605 | D34: =('Bloomberg Raw Data-5th (2)'!C37+'Bloomberg Raw Data-5th (2)'!D37)/2 -> 0.13500002 | E34: =('Bloomberg Raw Data-5th (2)'!J37+'Bloomberg Raw Data-5th (2)'!K37)/2 -> 20.024994 | F34: =D34-E34 -> -19.889994 | G34: =G33 -> 101.65 | H34: ='Bloomberg Raw Data-5th (2)'!A37 -> 121 | I34: =2.718281^(-$X$10*$X$11) -> 0.99832373 | J34: =H34*I34 -> 120.79717 | K34: =G34-J34 -> -19.147171 | L34: =F34-K34 -> -0.74282273 | M34: =D34+J34 -> 120.93217 | N34: =E34+G34 -> 121.67499 | O34: =M34-N34 -> -0.74282273 | P34: =IF(M34=N34,"Not Violated","Voilated") -> Voilated | Q34: =M34-G34 -> 19.282171 | R34: =IF(ABS(E34-Q34)<=0.01,"NO VIOLATION",IF(E34>Q34,"YES", "NO")) -> YES | S34: =IF(ABS(E34-Q34)<=0.01,"NO VIOLATION",IF(E34>Q34,"NO", "YES")) -> NO
... B44: MRK241115C00170000 | C44: 45545.747 | D44: =('Bloomberg Raw Data-5th (2)'!C47+'Bloomberg Raw Data-5th (2)'!D47)/2 -> 0.14000002 | E44: =('Bloomberg Raw Data-5th (2)'!J47+'Bloomberg Raw Data-5th (2)'!K47)/2 -> 68.449997 | F44: =D44-E44 -> -68.309997 | G44: =G43 -> 101.65 | H44: ='Bloomberg Raw Data-5th (2)'!A47 -> 170 | I44: =2.718281^(-$X$10*$X$11) -> 0.99832373 | J44: =H44*I44 -> 169.71503 | K44: =G44-J44 -> -68.065034 | L44: =F44-K44 -> -0.2449631 | M44: =D44+J44 -> 169.85503 | N44: =E44+G44 -> 170.1 | O44: =M44-N44 -> -0.2449631 | P44: =IF(M44=N44,"Not Violated","Voilated") -> Voilated | Q44: =M44-G44 -> 68.205034 | R44: =IF(ABS(E44-Q44)<=0.01,"NO VIOLATION",IF(E44>Q44,"YES", "NO")) -> YES | S44: =IF(ABS(E44-Q44)<=0.01,"NO VIOLATION",IF(E44>Q44,"NO", "YES")) -> NO
B46: B. PUT-CALL Partity for Opions with Strike Price of 96.00 from (Nov. 5 to Nov. 15)
C48: Dates | D48: CALL (C) | E48: PUT (P) | F48: Observed Value (C - P) | G48: Stock Price (S) | H48: Strike Price (K) | I48: e^-r(T-t) | J48: K*e^-r(T-t) | K48: Theoretical Value (S - K*e^-r(T-t)) | L48: Difference | M48: PV of Strike Price
C49: 45601 | D49: =([1]Calculations!G10+[1]Calculations!H10)/2 -> 1.63 | E49: =([1]Calculations!G30+[1]Calculations!H30)/2 -> 2.01495 | F49: =D49-E49 -> -0.38495 | G49: 101.65 | H49: 102 | J49: =H49*2.718281^(-$X$10*(9/365)) -> 101.88192 | K49: =G49-J49 -> -0.23192309 | L49: =F49-K49 -> -0.15302691 | M49: =H49*$X$12^(-$X$10*(9/365)) -> 101.88192
C50: 45602 | D50: =([1]Calculations!G11+[1]Calculations!H11)/2 -> 0.82 | E50: =([1]Calculations!G31+[1]Calculations!H31)/2 -> 1.8295 | F50: =D50-E50 -> -1.0095 | G50: 100.73 | H50: 102 | J50: =H50*2.718281^(-$X$10*(8/365)) -> 101.89504 | K50: =G50-J50 -> -1.165036 | L50: =F50-K50 -> 0.15553599 | M50: =H50*$X$12^(-$X$10*(8/365)) -> 101.89504
C51: 45603 | D51: =([1]Calculations!G12+[1]Calculations!H12)/2 -> 1.19 | E51: =([1]Calculations!G32+[1]Calculations!H32)/2 -> 1.6695 | F51: =D51-E51 -> -0.4795 | G51: 101.17 | H51: 102 | J51: =H51*2.718281^(-$X$10*(7/365)) -> 101.90815 | K51: =G51-J51 -> -0.73815059 | L51: =F51-K51 -> 0.25865059 | M51: =H51*$X$12^(-$X$10*(7/365)) -> 101.90815
C52: 45604 | D52: =([1]Calculations!G13+[1]Calculations!H13)/2 -> 1.86 | E52: =([1]Calculations!G33+[1]Calculations!H33)/2 -> 0.62995 | F52: =D52-E52 -> 1.23005 | G52: 102.92 | H52: 102 | J52: =H52*2.718281^(-$X$10*(6/365)) -> 101.92127 | K52: =G52-J52 -> 0.99873314 | L52: =F52-K52 -> 0.23131686 | M52: =H52*$X$12^(-$X$10*(6/365)) -> 101.92127
C53: 45605 | D53: =([1]Calculations!G14+[1]Calculations!H14)/2 -> 1.86 | E53: =([1]Calculations!G34+[1]Calculations!H34)/2 -> 0.62995 | F53: =D53-E53 -> 1.23005 | G53: 102.92 | H53: 102 | J53: =H53*2.718281^(-$X$10*(6/365)) -> 101.92127 | K53: =G53-J53 -> 0.99873314 | L53: =F53-K53 -> 0.23131686 | M53: =H53*$X$12^(-$X$10*(6/365)) -> 101.92127
C54: 45606 | D54: =([1]Calculations!G15+[1]Calculations!H15)/2 -> 1.86 | E54: =([1]Calculations!G35+[1]Calculations!H35)/2 -> 0.62995 | F54: =D54-E54 -> 1.23005 | G54: 102.92 | H54: 102 | J54: =H54*2.718281^(-$X$10*(6/365)) -> 101.92127 | K54: =G54-J54 -> 0.99873314 | L54: =F54-K54 -> 0.23131686 | M54: =H54*$X$12^(-$X$10*(6/365)) -> 101.92127
C55: 45607 | D55: =([1]Calculations!G16+[1]Calculations!H16)/2 -> 0.455 | E55: =([1]Calculations!G36+[1]Calculations!H36)/2 -> 1.75445 | F55: =D55-E55 -> -1.29945 | G55: 100.73 | H55: 102 | J55: =H55*2.718281^(-$X$10*(5/365)) -> 101.93438 | K55: =G55-J55 -> -1.2043848 | L55: =F55-K55 -> -0.095065168 | M55: =H55*$X$12^(-$X$10*(5/365)) -> 101.93438
C56: 45608 | D56: =([1]Calculations!G17+[1]Calculations!H17)/2 -> 0.095 | E56: =([1]Calculations!G37+[1]Calculations!H37)/2 -> 3.065 | F56: =D56-E56 -> -2.97 | G56: 98.58 | H56: 102 | J56: =H56*2.718281^(-$X$10*(4/365)) -> 101.9475 | K56: =G56-J56 -> -3.3675045 | L56: =F56-K56 -> 0.39750449 | M56: =H56*$X$12^(-$X$10*(4/365)) -> 101.9475
C57: 45609 | D57: =([1]Calculations!G18+[1]Calculations!H18)/2 -> 0.04 | E57: =([1]Calculations!G38+[1]Calculations!H38)/2 -> 3.5 | F57: =D57-E57 -> -3.46 | G57: 98.5 | H57: 102 | J57: =H57*2.718281^(-$X$10*(3/365)) -> 101.96063 | K57: =G57-J57 -> -3.4606258 | L57: =F57-K57 -> 0.00062583277 | M57: =H57*$X$12^(-$X$10*(3/365)) -> 101.96063
C58: 45610 | D58: =([1]Calculations!G19+[1]Calculations!H19)/2 -> 0.025 | E58: =([1]Calculations!G39+[1]Calculations!H39)/2 -> 3.505 | F58: =D58-E58 -> -3.48 | G58: 98.36 | H58: 102 | J58: =H58*2.718281^(-$X$10*(2/365)) -> 101.97375 | K58: =G58-J58 -> -3.6137489 | L58: =F58-K58 -> 0.13374887 | M58: =H58*$X$12^(-$X$10*(2/365)) -> 101.97375
C59: 45611 | D59: =([1]Calculations!G20+[1]Calculations!H20)/2 -> 0.005 | E59: =([1]Calculations!G40+[1]Calculations!H40)/2 -> 6.2245 | F59: =D59-E59 -> -6.2195 | G59: 96.31 | H59: 102 | J59: =H59*2.718281^(-$X$10*(1/365)) -> 101.98687 | K59: =G59-J59 -> -5.6768736 | L59: =F59-K59 -> -0.54262641 | M59: =H59*$X$12^(-$X$10*(1/365)) -> 101.98687

Sheet Q2. Implied Volatality - Final
B4: CALLS (Implied Volatility)
B7: Option Symbol | C7: Option Date | D7: SPOT Price | E7: STRIKE Price | F7: Last Price | G7: Bid | H7: Ask | I7: Risk Free Interest Rate | J7: Underlying Dividend Rate | K7: Time to Maturity (9 Days) | L7: Mid Price | M7: BSM d1 | N7: BSM d2 | O7: Trading Volume | P7: Model Implied Volatility (Calculated) | Q7: Theoretical Call Price (Black-Scholes) | R7: Market Implied Volatility | S7: Pricing Error
B8: ='Bloomberg Raw Data-5th(No zero)'!B6 -> MRK 11/15/24 C95 | C8: 45423 | D8: 101.65 | E8: ='Bloomberg Raw Data-5th(No zero)'!A6 -> 95 | F8: ='Bloomberg Raw Data-5th(No zero)'!E6 -> 6.9499998 | G8: ='Bloomberg Raw Data-5th(No zero)'!C6 -> 6.6500006 | H8: ='Bloomberg Raw Data-5th(No zero)'!D6 -> 6.9499998 | I8: ='Q1-(Without Zero Volume)'!J4 -> 0.046975 | J8: 0.0311 | K8: ='Q1-(Without Zero Volume)'!K4 -> 0.035714286 | L8: =(G8+H8)/2 -> 6.8000002 | M8: =(LN(D8/E8) + ((I8+ (P8^2) / 2)*K8) / (P8*SQRT(K8))) -> 0.12883564 | N8: =M8 - P8*SQRT(K8) -> 0.047979546 | O8: 12 | P8: 0.42785023 | Q8: =D8*_xlfn.NORM.S.DIST(M8,TRUE) - E8*EXP(-I8*K8)*_xlfn.NORM.S.DIST(N8,TRUE) -> 6.8001531 | R8: 0.2858 | S8: =L8-Q8 -> -0.00015293139
B9: ='Bloomberg Raw Data-5th(No zero)'!B7 -> MRK 11/15/24 C98 | C9: =C8 -> 45423 | D9: 101.65 | E9: ='Bloomberg Raw Data-5th(No zero)'!A7 -> 98 | F9: ='Bloomberg Raw Data-5th(No zero)'!E7 -> 4.1999998 | G9: ='Bloomberg Raw Data-5th(No zero)'!C7 -> 4.1500006 | H9: ='Bloomberg Raw Data-5th(No zero)'!D7 -> 4.3000002 | I9: ='Q1-(Without Zero Volume)'!J5 -> 0.046975 | J9: 0.0311 | K9: ='Q1-(Without Zero Volume)'!K5 -> 0.035714286 | L9: =(G9+H9)/2 -> 4.2250004 | M9: =(LN(D9/E9) + ((I9+ (P9^2) / 2)*K9) / (P9*SQRT(K9))) -> 0.094532453 | N9: =M9 - P9*SQRT(K9) -> 0.03869258 | O9: 2 | P9: 0.29547683 | Q9: =D9*_xlfn.NORM.S.DIST(M9,TRUE) - E9*EXP(-I9*K9)*_xlfn.NORM.S.DIST(N9,TRUE) -> 4.2251351 | R9: 0.2717 | S9: =L9-Q9 -> -0.00013472409
B10: ='Bloomberg Raw Data-5th(No zero)'!B8 -> MRK 11/15/24 C99 | C10: =C9 -> 45423 | D10: 101.65 | E10: ='Bloomberg Raw Data-5th(No zero)'!A8 -> 99 | F10: ='Bloomberg Raw Data-5th(No zero)'!E8 -> 3.6700001 | G10: ='Bloomberg Raw Data-5th(No zero)'!C8 -> 3.4000006 | H10: ='Bloomberg Raw Data-5th(No zero)'!D8 -> 3.5500002 | I10: ='Q1-(Without Zero Volume)'!J6 -> 0.046975 | J10: 0.0311 | K10: ='Q1-(Without Zero Volume)'!K6 -> 0.035714286 | L10: =(G10+H10)/2 -> 3.4750004 | M10: =(LN(D10/E10) + ((I10+ (P10^2) / 2)*K10) / (P10*SQRT(K10))) -> 0.084951581 | N10: =M10 - P10*SQRT(K10) -> 0.034847378 | O10: 10 | P10: 0.26512652 | Q10: =D10*_xlfn.NORM.S.DIST(M10,TRUE) - E10*EXP(-I10*K10)*_xlfn.NORM.S.DIST(N10,TRUE) -> 3.4751118 | R10: 0.2683 | S10: =L10-Q10 -> -0.00011141679
B11: ='Bloomberg Raw Data-5th(No zero)'!B9 -> MRK 11/15/24 C100 | C11: =C10 -> 45423 | D11: 101.65 | E11: ='Bloomberg Raw Data-5th(No zero)'!A9 -> 100 | F11: ='Bloomberg Raw Data-5th(No zero)'!E9 -> 2.8000002 | G11: ='Bloomberg Raw Data-5th(No zero)'!C9 -> 2.7300005 | H11: ='Bloomberg Raw Data-5th(No zero)'!D9 -> 2.8400002 | I11: ='Q1-(Without Zero Volume)'!J7 -> 0.046975 | J11: 0.0311 | K11: ='Q1-(Without Zero Volume)'!K7 -> 0.035714286 | L11: =(G11+H11)/2 -> 2.7850003 | M11: =(LN(D11/E11) + ((I11+ (P11^2) / 2)*K11) / (P11*SQRT(K11))) -> 0.075896596 | N11: =M11 - P11*SQRT(K11) -> 0.03009895 | O11: 55 | P11: 0.24233836 | Q11: =D11*_xlfn.NORM.S.DIST(M11,TRUE) - E11*EXP(-I11*K11)*_xlfn.NORM.S.DIST(N11,TRUE) -> 2.7850762 | R11: 0.2636 | S11: =L11-Q11 -> -7.5835412e-05
B12: ='Bloomberg Raw Data-5th(No zero)'!B10 -> MRK 11/15/24 C101 | C12: =C11 -> 45423 | D12: 101.65 | E12: ='Bloomberg Raw Data-5th(No zero)'!A10 -> 101 | F12: ='Bloomberg Raw Data-5th(No zero)'!E10 -> 2.3299999 | G12: ='Bloomberg Raw Data-5th(No zero)'!C10 -> 2.1099997 | H12: ='Bloomberg Raw Data-5th(No zero)'!D10 -> 2.21 | I12: ='Q1-(Without Zero Volume)'!J8 -> 0.046975 | J12: 0.0311 | K12: ='Q1-(Without Zero Volume)'!K8 -> 0.035714286 | L12: =(G12+H12)/2 -> 2.1599998 | M12: =(LN(D12/E12) + ((I12+ (P12^2) / 2)*K12) / (P12*SQRT(K12))) -> 0.066923336 | N12: =M12 - P12*SQRT(K12) -> 0.023904986 | O12: 28 | P12: 0.22763171 | Q12: =D12*_xlfn.NORM.S.DIST(M12,TRUE) - E12*EXP(-I12*K12)*_xlfn.NORM.S.DIST(N12,TRUE) -> 2.1600332 | R12: 0.2573 | S12: =L12-Q12 -> -3.3381827e-05
B13: ='Bloomberg Raw Data-5th(No zero)'!B11 -> MRK 11/15/24 C102 | C13: =C12 -> 45423 | D13: 101.65 | E13: ='Bloomberg Raw Data-5th(No zero)'!A11 -> 102 | F13: ='Bloomberg Raw Data-5th(No zero)'!E11 -> 1.6900005 | G13: ='Bloomberg Raw Data-5th(No zero)'!C11 -> 1.5999994 | H13: ='Bloomberg Raw Data-5th(No zero)'!D11 -> 1.6599998 | I13: ='Q1-(Without Zero Volume)'!J9 -> 0.046975 | J13: 0.0311 | K13: ='Q1-(Without Zero Volume)'!K9 -> 0.035714286 | L13: =(G13+H13)/2 -> 1.6299996 | M13: =(LN(D13/E13) + ((I13+ (P13^2) / 2)*K13) / (P13*SQRT(K13))) -> 0.057305261 | N13: =M13 - P13*SQRT(K13) -> 0.014846554 | O13: 41 | P13: 0.22467036 | Q13: =D13*_xlfn.NORM.S.DIST(M13,TRUE) - E13*EXP(-I13*K13)*_xlfn.NORM.S.DIST(N13,TRUE) -> 1.6299864 | R13: 0.2529 | S13: =L13-Q13 -> 1.3196902e-05
B14: ='Bloomberg Raw Data-5th(No zero)'!B12 -> MRK 11/15/24 C103 | C14: =C13 -> 45423 | D14: 101.65 | E14: ='Bloomberg Raw Data-5th(No zero)'!A12 -> 103 | F14: ='Bloomberg Raw Data-5th(No zero)'!E12 -> 1.2799997 | G14: ='Bloomberg Raw Data-5th(No zero)'!C12 -> 1.1700001 | H14: ='Bloomberg Raw Data-5th(No zero)'!D12 -> 1.2200003 | I14: ='Q1-(Without Zero Volume)'!J10 -> 0.046975 | J14: 0.0311 | K14: ='Q1-(Without Zero Volume)'!K10 -> 0.035714286 | L14: =(G14+H14)/2 -> 1.1950002 | M14: =(LN(D14/E14) + ((I14+ (P14^2) / 2)*K14) / (P14*SQRT(K14))) -> 0.04692331 | N14: =M14 - P14*SQRT(K14) -> 0.0028896956 | O14: 89 | P14: 0.23300399 | Q14: =D14*_xlfn.NORM.S.DIST(M14,TRUE) - E14*EXP(-I14*K14)*_xlfn.NORM.S.DIST(N14,TRUE) -> 1.1949453 | R14: 0.2496 | S14: =L14-Q14 -> 5.4911295e-05
B15: ='Bloomberg Raw Data-5th(No zero)'!B13 -> MRK 11/15/24 C104 | C15: =C14 -> 45423 | D15: 101.65 | E15: ='Bloomberg Raw Data-5th(No zero)'!A13 -> 104 | F15: ='Bloomberg Raw Data-5th(No zero)'!E13 -> 0.87 | G15: ='Bloomberg Raw Data-5th(No zero)'!C13 -> 0.81999999 | H15: ='Bloomberg Raw Data-5th(No zero)'!D13 -> 0.87 | I15: ='Q1-(Without Zero Volume)'!J11 -> 0.046975 | J15: 0.0311 | K15: ='Q1-(Without Zero Volume)'!K11 -> 0.035714286 | L15: =(G15+H15)/2 -> 0.845 | M15: =(LN(D15/E15) + ((I15+ (P15^2) / 2)*K15) / (P15*SQRT(K15))) -> 0.036231597 | N15: =M15 - P15*SQRT(K15) -> -0.011197264 | O15: 56 | P15: 0.25096994 | Q15: =D15*_xlfn.NORM.S.DIST(M15,TRUE) - E15*EXP(-I15*K15)*_xlfn.NORM.S.DIST(N15,TRUE) -> 0.84491194 | R15: 0.2464 | S15: =L15-Q15 -> 8.8060992e-05
B16: ='Bloomberg Raw Data-5th(No zero)'!B14 -> MRK 11/15/24 C105 | C16: =C15 -> 45423 | D16: 101.65 | E16: ='Bloomberg Raw Data-5th(No zero)'!A14 -> 105 | F16: ='Bloomberg Raw Data-5th(No zero)'!E14 -> 0.56999999 | G16: ='Bloomberg Raw Data-5th(No zero)'!C14 -> 0.56999999 | H16: ='Bloomberg Raw Data-5th(No zero)'!D14 -> 0.61000001 | I16: ='Q1-(Without Zero Volume)'!J12 -> 0.046975 | J16: 0.0311 | K16: ='Q1-(Without Zero Volume)'!K12 -> 0.035714286 | L16: =(G16+H16)/2 -> 0.59 | M16: =(LN(D16/E16) + ((I16+ (P16^2) / 2)*K16) / (P16*SQRT(K16))) -> 0.025745262 | N16: =M16 - P16*SQRT(K16) -> -0.027095636 | O16: 660 | P16: 0.27960775 | Q16: =D16*_xlfn.NORM.S.DIST(M16,TRUE) - E16*EXP(-I16*K16)*_xlfn.NORM.S.DIST(N16,TRUE) -> 0.58988947 | R16: 0.246 | S16: =L16-Q16 -> 0.00011052865
B17: ='Bloomberg Raw Data-5th(No zero)'!B15 -> MRK 11/15/24 C106 | C17: =C16 -> 45423 | D17: 101.65 | E17: ='Bloomberg Raw Data-5th(No zero)'!A15 -> 106 | F17: ='Bloomberg Raw Data-5th(No zero)'!E15 -> 0.40000004 | G17: ='Bloomberg Raw Data-5th(No zero)'!C15 -> 0.38999999 | H17: ='Bloomberg Raw Data-5th(No zero)'!D15 -> 0.42000002 | I17: ='Q1-(Without Zero Volume)'!J13 -> 0.046975 | J17: 0.0311 | K17: ='Q1-(Without Zero Volume)'!K13 -> 0.035714286 | L17: =(G17+H17)/2 -> 0.405 | M17: =(LN(D17/E17) + ((I17+ (P17^2) / 2)*K17) / (P17*SQRT(K17))) -> 0.016046894 | N17: =M17 - P17*SQRT(K17) -> -0.043605703 | O17: 107 | P17: 0.31565187 | Q17: =D17*_xlfn.NORM.S.DIST(M17,TRUE) - E17*EXP(-I17*K17)*_xlfn.NORM.S.DIST(N17,TRUE) -> 0.40487442 | R17: 0.2468 | S17: =L17-Q17 -> 0.00012558038
B18: ='Bloomberg Raw Data-5th(No zero)'!B16 -> MRK 11/15/24 C107 | C18: =C17 -> 45423 | D18: 101.65 | E18: ='Bloomberg Raw Data-5th(No zero)'!A16 -> 107 | F18: ='Bloomberg Raw Data-5th(No zero)'!E16 -> 0.30000001 | G18: ='Bloomberg Raw Data-5th(No zero)'!C16 -> 0.24000001 | H18: ='Bloomberg Raw Data-5th(No zero)'!D16 -> 0.29000002 | I18: ='Q1-(Without Zero Volume)'!J14 -> 0.046975 | J18: 0.0311 | K18: ='Q1-(Without Zero Volume)'!K14 -> 0.035714286 | L18: =(G18+H18)/2 -> 0.26500002 | M18: =(LN(D18/E18) + ((I18+ (P18^2) / 2)*K18) / (P18*SQRT(K18))) -> 0.007281209 | N18: =M18 - P18*SQRT(K18) -> -0.059989 | O18: 36 | P18: 0.35596049 | Q18: =D18*_xlfn.NORM.S.DIST(M18,TRUE) - E18*EXP(-I18*K18)*_xlfn.NORM.S.DIST(N18,TRUE) -> 0.26486396 | R18: 0.246 | S18: =L18-Q18 -> 0.00013605111
B19: ='Bloomberg Raw Data-5th(No zero)'!B17 -> MRK 11/15/24 C110 | C19: =C18 -> 45423 | D19: 101.65 | E19: ='Bloomberg Raw Data-5th(No zero)'!A17 -> 110 | F19: ='Bloomberg Raw Data-5th(No zero)'!E17 -> 0.090000033 | G19: ='Bloomberg Raw Data-5th(No zero)'!C17 -> 0.090000033 | H19: ='Bloomberg Raw Data-5th(No zero)'!D17 -> 0.12 | I19: ='Q1-(Without Zero Volume)'!J15 -> 0.046975 | J19: 0.0311 | K19: ='Q1-(Without Zero Volume)'!K15 -> 0.035714286 | L19: =(G19+H19)/2 -> 0.10500002 | M19: =(LN(D19/E19) + ((I19+ (P19^2) / 2)*K19) / (P19*SQRT(K19))) -> -0.013857543 | N19: =M19 - P19*SQRT(K19) -> -0.10862642 | O19: 114 | P19: 0.50146978 | Q19: =D19*_xlfn.NORM.S.DIST(M19,TRUE) - E19*EXP(-I19*K19)*_xlfn.NORM.S.DIST(N19,TRUE) -> 0.10484613 | R19: 0.2705 | S19: =L19-Q19 -> 0.00015389342
B20: ='Bloomberg Raw Data-5th(No zero)'!B18 -> MRK 11/15/24 C114 | C20: =C19 -> 45423 | D20: 101.65 | E20: ='Bloomberg Raw Data-5th(No zero)'!A18 -> 114 | F20: ='Bloomberg Raw Data-5th(No zero)'!E18 -> 0.059999999 | G20: ='Bloomberg Raw Data-5th(No zero)'!C18 -> 0.02 | H20: ='Bloomberg Raw Data-5th(No zero)'!D18 -> 0.12 | I20: ='Q1-(Without Zero Volume)'!J16 -> 0.046975 | J20: 0.0311 | K20: ='Q1-(Without Zero Volume)'!K16 -> 0.035714286 | L20: =(G20+H20)/2 -> 0.070000002 | M20: =(LN(D20/E20) + ((I20+ (P20^2) / 2)*K20) / (P20*SQRT(K20))) -> -0.035793305 | N20: =M20 - P20*SQRT(K20) -> -0.16818914 | O20: 30 | P20: 0.7005729 | Q20: =D20*_xlfn.NORM.S.DIST(M20,TRUE) - E20*EXP(-I20*K20)*_xlfn.NORM.S.DIST(N20,TRUE) -> 0.06982246 | R20: 0.3387 | S20: =L20-Q20 -> 0.000177542
B21: ='Bloomberg Raw Data-5th(No zero)'!B19 -> MRK 11/15/24 C130 | C21: =C20 -> 45423 | D21: 101.65 | E21: ='Bloomberg Raw Data-5th(No zero)'!A19 -> 130 | F21: ='Bloomberg Raw Data-5th(No zero)'!E19 -> 0.010000002 | G21: ='Bloomberg Raw Data-5th(No zero)'!C19 -> 0 | H21: ='Bloomberg Raw Data-5th(No zero)'!D19 -> 0.039999999 | I21: ='Q1-(Without Zero Volume)'!J17 -> 0.046975 | J21: 0.0311 | K21: ='Q1-(Without Zero Volume)'!K17 -> 0.035714286 | L21: =(G21+H21)/2 -> 0.02 | M21: =(LN(D21/E21) + ((I21+ (P21^2) / 2)*K21) / (P21*SQRT(K21))) -> -0.11154585 | N21: =M21 - P21*SQRT(K21) -> -0.36733427 | O21: 10 | P21: 1.3535051 | Q21: =D21*_xlfn.NORM.S.DIST(M21,TRUE) - E21*EXP(-I21*K21)*_xlfn.NORM.S.DIST(N21,TRUE) -> 0.019598933 | R21: 0.5925 | S21: =L21-Q21 -> 0.00040106661
B25: PUT (Implied Volatility)
B28: Option Symbol | C28: Option Date | D28: SPOT Price | E28: STRIKE Price | F28: Last Price | G28: Bid | H28: Ask | I28: Risk Free Interest Rate | J28: Underlying Dividend Rate | K28: Time to Maturity (10 Days) | L28: Mid Price | M28: BSM d1 | N28: BSM d2 | O28: Trading Volume | P28: Model Implied Volatility (Calculated) | Q28: Theoretical Put Price (Black-Scholes) | R28: Market Implied Volatility | S28: Pricing Error
B29: ='Bloomberg Raw Data-5th(No zero)'!I6 -> MRK 11/15/24 P95 | C29: =C8 -> 45423 | D29: 101.65 | E29: ='Bloomberg Raw Data-5th(No zero)'!H6 -> 95 | F29: ='Bloomberg Raw Data-5th(No zero)'!L6 -> 0.24000001 | G29: 0.079999983 | H29: 0.25999999 | I29: =I8 -> 0.046975 | J29: =J8 -> 0.0311 | K29: =K8 -> 0.035714286 | L29: =(G29+H29)/2 -> 0.16999999 | M29: =(LN(D29/E29) + ((I29+ (P29^2) / 2)*K29) / (P29*SQRT(K29))) -> 0.13003621 | N29: =M29-P29*SQRT(K29) -> 0.044515536 | O29: 24 | P29: 0.45253289 | Q29: =E29*EXP(-I29*K29)*_xlfn.NORM.S.DIST(-N29,TRUE)-D29*_xlfn.NORM.S.DIST(-M29,TRUE) -> 0.17011154 | R29: 0.31934274 | S29: =L29-Q29 -> -0.00011155397
B30: ='Bloomberg Raw Data-5th(No zero)'!I7 -> MRK 11/15/24 P98 | C30: =C9 -> 45423 | D30: 101.65 | E30: ='Bloomberg Raw Data-5th(No zero)'!H7 -> 98 | F30: ='Bloomberg Raw Data-5th(No zero)'!L7 -> 0.60000002 | G30: 0.56 | H30: 0.66000003 | I30: =I9 -> 0.046975 | J30: =J9 -> 0.0311 | K30: =K9 -> 0.035714286 | L30: =(G30+H30)/2 -> 0.61000001 | M30: =(LN(D30/E30) + ((I30+ (P30^2) / 2)*K30) / (P30*SQRT(K30))) -> 0.094568371 | N30: =M30-P30*SQRT(K30) -> 0.03362209 | O30: 124 | P30: 0.3224974 | Q30: =E30*EXP(-I30*K30)*_xlfn.NORM.S.DIST(-N30,TRUE)-D30*_xlfn.NORM.S.DIST(-M30,TRUE) -> 0.61008629 | R30: 0.29785858 | S30: =L30-Q30 -> -8.627941e-05
B31: ='Bloomberg Raw Data-5th(No zero)'!I8 -> MRK 11/15/24 P99 | C31: =C10 -> 45423 | D31: 101.65 | E31: ='Bloomberg Raw Data-5th(No zero)'!H8 -> 99 | F31: ='Bloomberg Raw Data-5th(No zero)'!L8 -> 0.88 | G31: 0.87 | H31: 0.88999999 | I31: =I10 -> 0.046975 | J31: =J10 -> 0.0311 | K31: =K10 -> 0.035714286 | L31: =(G31+H31)/2 -> 0.88 | M31: =(LN(D31/E31) + ((I31+ (P31^2) / 2)*K31) / (P31*SQRT(K31))) -> 0.08438462 | N31: =M31-P31*SQRT(K31) -> 0.028660617 | O31: 56 | P31: 0.29486371 | Q31: =E31*EXP(-I31*K31)*_xlfn.NORM.S.DIST(-N31,TRUE)-D31*_xlfn.NORM.S.DIST(-M31,TRUE) -> 0.88006641 | R31: 0.29248754 | S31: =L31-Q31 -> -6.6412016e-05
B32: ='Bloomberg Raw Data-5th(No zero)'!I9 -> MRK 11/15/24 P100 | C32: =C11 -> 45423 | D32: 101.65 | E32: ='Bloomberg Raw Data-5th(No zero)'!H9 -> 100 | F32: ='Bloomberg Raw Data-5th(No zero)'!L9 -> 1.1700001 | G32: 1.0600004 | H32: 1.1999998 | I32: =I11 -> 0.046975 | J32: =J11 -> 0.0311 | K32: =K11 -> 0.035714286 | L32: =(G32+H32)/2 -> 1.1300001 | M32: =(LN(D32/E32) + ((I32+ (P32^2) / 2)*K32) / (P32*SQRT(K32))) -> 0.074936724 | N32: =M32-P32*SQRT(K32) -> 0.025039926 | O32: 84 | P32: 0.26402904 | Q32: =E32*EXP(-I32*K32)*_xlfn.NORM.S.DIST(-N32,TRUE)-D32*_xlfn.NORM.S.DIST(-M32,TRUE) -> 1.1300451 | R32: 0.29102271 | S32: =L32-Q32 -> -4.494436e-05
B33: ='Bloomberg Raw Data-5th(No zero)'!I10 -> MRK 11/15/24 P101 | C33: =C12 -> 45423 | D33: 101.65 | E33: ='Bloomberg Raw Data-5th(No zero)'!H10 -> 101 | F33: ='Bloomberg Raw Data-5th(No zero)'!L10 -> 1.4800005 | G33: 1.5099993 | H33: 1.5900002 | I33: =I12 -> 0.046975 | J33: =J12 -> 0.0311 | K33: =K12 -> 0.035714286 | L33: =(G33+H33)/2 -> 1.5499997 | M33: =(LN(D33/E33) + ((I33+ (P33^2) / 2)*K33) / (P33*SQRT(K33))) -> 0.065314497 | N33: =M33-P33*SQRT(K33) -> 0.017082302 | O33: 100 | P33: 0.25522079 | Q33: =E33*EXP(-I33*K33)*_xlfn.NORM.S.DIST(-N33,TRUE)-D33*_xlfn.NORM.S.DIST(-M33,TRUE) -> 1.5500184 | R33: 0.29004616 | S33: =L33-Q33 -> -1.8669463e-05
B34: ='Bloomberg Raw Data-5th(No zero)'!I11 -> MRK 11/15/24 P102 | C34: =C13 -> 45423 | D34: 101.65 | E34: ='Bloomberg Raw Data-5th(No zero)'!H11 -> 102 | F34: ='Bloomberg Raw Data-5th(No zero)'!L11 -> 2.0200005 | G34: 1.9699993 | H34: 2.0600004 | I34: =I13 -> 0.046975 | J34: =J13 -> 0.0311 | K34: =K13 -> 0.035714286 | L34: =(G34+H34)/2 -> 2.0149999 | M34: =(LN(D34/E34) + ((I34+ (P34^2) / 2)*K34) / (P34*SQRT(K34))) -> 0.055626418 | N34: =M34-P34*SQRT(K34) -> 0.0081023313 | O34: 65 | P34: 0.25147383 | Q34: =E34*EXP(-I34*K34)*_xlfn.NORM.S.DIST(-N34,TRUE)-D34*_xlfn.NORM.S.DIST(-M34,TRUE) -> 2.014992 | R34: 0.29077858 | S34: =L34-Q34 -> 7.8973838e-06
B35: ='Bloomberg Raw Data-5th(No zero)'!I12 -> MRK 11/15/24 P103 | C35: =C14 -> 45423 | D35: 101.65 | E35: ='Bloomberg Raw Data-5th(No zero)'!H12 -> 103 | F35: ='Bloomberg Raw Data-5th(No zero)'!L12 -> 2.5900002 | G35: 2.5500002 | H35: 2.6199999 | I35: =I14 -> 0.046975 | J35: =J14 -> 0.0311 | K35: =K14 -> 0.035714286 | L35: =(G35+H35)/2 -> 2.585 | M35: =(LN(D35/E35) + ((I35+ (P35^2) / 2)*K35) / (P35*SQRT(K35))) -> 0.04550564 | N35: =M35-P35*SQRT(K35) -> -0.003694722 | O35: 28 | P35: 0.26034384 | Q35: =E35*EXP(-I35*K35)*_xlfn.NORM.S.DIST(-N35,TRUE)-D35*_xlfn.NORM.S.DIST(-M35,TRUE) -> 2.5849672 | R35: 0.30396204 | S35: =L35-Q35 -> 3.2869309e-05
B36: ='Bloomberg Raw Data-5th(No zero)'!I13 -> MRK 11/15/24 P104 | C36: =C15 -> 45423 | D36: 101.65 | E36: ='Bloomberg Raw Data-5th(No zero)'!H13 -> 104 | F36: ='Bloomberg Raw Data-5th(No zero)'!L13 -> 3.3000002 | G36: 3.1999998 | H36: 3.3500004 | I36: =I15 -> 0.046975 | J36: =J15 -> 0.0311 | K36: =K15 -> 0.035714286 | L36: =(G36+H36)/2 -> 3.2750001 | M36: =(LN(D36/E36) + ((I36+ (P36^2) / 2)*K36) / (P36*SQRT(K36))) -> 0.035248876 | N36: =M36-P36*SQRT(K36) -> -0.018300687 | O36: 29 | P36: 0.28335765 | Q36: =E36*EXP(-I36*K36)*_xlfn.NORM.S.DIST(-N36,TRUE)-D36*_xlfn.NORM.S.DIST(-M36,TRUE) -> 3.2749477 | R36: 0.30127652 | S36: =L36-Q36 -> 5.2389367e-05
B37: ='Bloomberg Raw Data-5th(No zero)'!I14 -> MRK 11/15/24 P105 | C37: =C16 -> 45423 | D37: 101.65 | E37: ='Bloomberg Raw Data-5th(No zero)'!H14 -> 105 | F37: ='Bloomberg Raw Data-5th(No zero)'!L14 -> 4.0500002 | G37: 3.9499998 | H37: 4.0500002 | I37: =I16 -> 0.046975 | J37: =J16 -> 0.0311 | K37: =K16 -> 0.035714286 | L37: =(G37+H37)/2 -> 4 | M37: =(LN(D37/E37) + ((I37+ (P37^2) / 2)*K37) / (P37*SQRT(K37))) -> 0.025503271 | N37: =M37-P37*SQRT(K37) -> -0.032977478 | O37: 69 | P37: 0.30945104 | Q37: =E37*EXP(-I37*K37)*_xlfn.NORM.S.DIST(-N37,TRUE)-D37*_xlfn.NORM.S.DIST(-M37,TRUE) -> 3.9999306 | R37: 0.32178413 | S37: =L37-Q37 -> 6.936774e-05
B38: ='Bloomberg Raw Data-5th(No zero)'!I15 -> MRK 11/15/24 P106 | C38: =C17 -> 45423 | D38: 101.65 | E38: ='Bloomberg Raw Data-5th(No zero)'!H15 -> 106 | F38: ='Bloomberg Raw Data-5th(No zero)'!L15 -> 4.8500004 | G38: 4.8000002 | H38: 4.9000006 | I38: =I17 -> 0.046975 | J38: =J17 -> 0.0311 | K38: =K17 -> 0.035714286 | L38: =(G38+H38)/2 -> 4.8500004 | M38: =(LN(D38/E38) + ((I38+ (P38^2) / 2)*K38) / (P38*SQRT(K38))) -> 0.016531833 | N38: =M38-P38*SQRT(K38) -> -0.049606628 | O38: 11 | P38: 0.34997184 | Q38: =E38*EXP(-I38*K38)*_xlfn.NORM.S.DIST(-N38,TRUE)-D38*_xlfn.NORM.S.DIST(-M38,TRUE) -> 4.8499181 | R38: 0.32691103 | S38: =L38-Q38 -> 8.225501e-05
B39: ='Bloomberg Raw Data-5th(No zero)'!I16 -> MRK 11/15/24 P107 | C39: =C18 -> 45423 | D39: 101.65 | E39: ='Bloomberg Raw Data-5th(No zero)'!H16 -> 107 | F39: ='Bloomberg Raw Data-5th(No zero)'!L16 -> 5.6999998 | G39: 5.6500006 | H39: 5.8000002 | I39: =I18 -> 0.046975 | J39: =J18 -> 0.0311 | K39: =K18 -> 0.035714286 | L39: =(G39+H39)/2 -> 5.7250004 | M39: =(LN(D39/E39) + ((I39+ (P39^2) / 2)*K39) / (P39*SQRT(K39))) -> 0.0084026856 | N39: =M39-P39*SQRT(K39) -> -0.065724264 | O39: 6 | P39: 0.39224295 | Q39: =E39*EXP(-I39*K39)*_xlfn.NORM.S.DIST(-N39,TRUE)-D39*_xlfn.NORM.S.DIST(-M39,TRUE) -> 5.7249072 | R39: 0.36524072 | S39: =L39-Q39 -> 9.3143397e-05
B40: ='Bloomberg Raw Data-5th(No zero)'!I17 -> MRK 11/15/24 P110 | C40: =C19 -> 45423 | D40: 101.65 | E40: ='Bloomberg Raw Data-5th(No zero)'!H17 -> 110 | F40: ='Bloomberg Raw Data-5th(No zero)'!L17 -> 8.4799995 | G40: 8.5 | H40: 8.6999998 | I40: =I19 -> 0.046975 | J40: =J19 -> 0.0311 | K40: =K19 -> 0.035714286 | L40: =(G40+H40)/2 -> 8.5999999 | M40: =(LN(D40/E40) + ((I40+ (P40^2) / 2)*K40) / (P40*SQRT(K40))) -> -0.011324177 | N40: =M40-P40*SQRT(K40) -> -0.11383315 | O40: 143 | P40: 0.54242648 | Q40: =E40*EXP(-I40*K40)*_xlfn.NORM.S.DIST(-N40,TRUE)-D40*_xlfn.NORM.S.DIST(-M40,TRUE) -> 8.5998823 | R40: 0.44775943 | S40: =L40-Q40 -> 0.00011759751
... B42: ='Bloomberg Raw Data-5th(No zero)'!I19 -> MRK 11/15/24 P130 | C42: =C21 -> 45423 | D42: 101.65 | E42: ='Bloomberg Raw Data-5th(No zero)'!H19 -> 130 | F42: ='Bloomberg Raw Data-5th(No zero)'!L19 -> 28.850006 | G42: 27.399994 | H42: 30.399994 | I42: =I21 -> 0.046975 | J42: =J21 -> 0.0311 | K42: =K21 -> 0.035714286 | L42: =(G42+H42)/2 -> 28.899994 | M42: =(LN(D42/E42) + ((I42+ (P42^2) / 2)*K42) / (P42*SQRT(K42))) -> -0.10354876 | N42: =M42-P42*SQRT(K42) -> -0.37613994 | O42: 4 | P42: 1.4424169 | Q42: =E42*EXP(-I42*K42)*_xlfn.NORM.S.DIST(-N42,TRUE)-D42*_xlfn.NORM.S.DIST(-M42,TRUE) -> 28.899594 | R42: 1.0625047 | S42: =L42-Q42 -> 0.00040018564

Sheet Q3. Delta Hedging 
B4: Delta Hedging(Using Implied Volatility)
B7: Date | C7: Option Symbol | D7: SPOT Price | E7: Daily Log Returns | F7: STRIKE Price | G7: Closing Price | H7: Bid | I7: Ask | J7: Risk Free Interest Rate | K7: Time to Maturity (Trading days) | L7: Mid Price | M7: BSM d1 | N7: Contracts Sold (Assumed) | O7: Short call Options | P7: Model Implied Volatility (Calculated) | Q7: Delta | R7: Stocks to Buy | S7: ∆ Stocks Bought/sold | T7: Cost of shares ( '000s) | U7: Cumulative cost including interest | V7: Interest cost | W7: Option Payoff | Z7: (in 000's)
B8: ='Bloomberg Raw Data- all volumes'!A87 -> 45601 | C8: ='Bloomberg Raw Data- all volumes'!C87 -> MRK 11/15/24 C102 | D8: ='Bloomberg Raw Data- all volumes'!I87 -> 101.65 | E8: =LN(D8/D61) -> -0.0021619505 | F8: ='Bloomberg Raw Data- all volumes'!B87 -> 102 | G8: ='Bloomberg Raw Data- all volumes'!F87 -> 1.6900005 | H8: ='Bloomberg Raw Data- all volumes'!D87 -> 1.5999994 | I8: ='Bloomberg Raw Data- all volumes'!E87 -> 1.6599998 | J8: ='Q1-(Without Zero Volume)'!J4 -> 0.046975 | K8: =8/252 -> 0.031746032 | L8: =(H8+I8)/2 -> 1.6299996 | M8: =(LN(D8/F8)+(J8+($P$8^2)/2)*K8)/($P$8*SQRT(K8)) -> -0.028597847 | N8: 10 | O8: =N8*100 -> 1000 | P8: ='Q2. Implied Volatality - Final'!P13 -> 0.22467036 | Q8: =_xlfn.NORM.DIST(M8,0,1,TRUE) -> 0.48859266 | R8: =Q8*O8 -> 488.59266 | S8: =R8 -> 488.59266 | T8: =(S8*D8)/1000 -> 49.665444 | U8: =T8 -> 49.665444 | V8: =U8*J8*(1/252) -> 0.0092580724 | Y8: Cumulative cost including interest | Z8: =U16 -> 1.7198322
B9: ='Bloomberg Raw Data- all volumes'!A88 -> 45602 | C9: ='Bloomberg Raw Data- all volumes'!C88 -> MRK 11/15/24 C102 | D9: ='Bloomberg Raw Data- all volumes'!I88 -> 100.73 | E9: =LN(D9/D62) -> -0.0090918701 | F9: ='Bloomberg Raw Data- all volumes'!B88 -> 102 | G9: ='Bloomberg Raw Data- all volumes'!F88 -> 0.87 | H9: ='Bloomberg Raw Data- all volumes'!D88 -> 0.73000002 | I9: ='Bloomberg Raw Data- all volumes'!E88 -> 0.91000003 | J9: ='Q1-(Without Zero Volume)'!J5 -> 0.046975 | K9: =7/252 -> 0.027777778 | L9: =(H9+I9)/2 -> 0.82000002 | M9: =(LN(D9/F9)+(J9+($P$8^2)/2)*K9)/($P$8*SQRT(K9)) -> -0.28103082 | N9: 10 | O9: =N9*100 -> 1000 | P9: =P8 -> 0.22467036 | Q9: =_xlfn.NORM.DIST(M9,0,1,TRUE) -> 0.38934338 | R9: =Q9*O9 -> 389.34338 | S9: =R9-R8 -> -99.249284 | T9: =(S9*D9)/1000 -> -9.9973804 | U9: =T9+V8+U8 -> 39.677322 | V9: =U9*J9*(1/252) -> 0.0073961992 | Y9: Option Payoff | Z9: =W16 -> 0
B10: ='Bloomberg Raw Data- all volumes'!A89 -> 45603 | C10: ='Bloomberg Raw Data- all volumes'!C89 -> MRK 11/15/24 C102 | D10: ='Bloomberg Raw Data- all volumes'!I89 -> 101.17 | E10: =LN(D10/D63) -> 0.0043586003 | F10: ='Bloomberg Raw Data- all volumes'!B89 -> 102 | G10: ='Bloomberg Raw Data- all volumes'!F89 -> 0.93000001 | H10: ='Bloomberg Raw Data- all volumes'!D89 -> 0.88 | I10: ='Bloomberg Raw Data- all volumes'!E89 -> 1.5 | J10: ='Q1-(Without Zero Volume)'!J6 -> 0.046975 | K10: =6/252 -> 0.023809524 | L10: =(H10+I10)/2 -> 1.19 | M10: =(LN(D10/F10)+(J10+($P$8^2)/2)*K10)/($P$8*SQRT(K10)) -> -0.18608776 | N10: 10 | O10: =N10*100 -> 1000 | P10: =P9 -> 0.22467036 | Q10: =_xlfn.NORM.DIST(M10,0,1,TRUE) -> 0.42618797 | R10: =Q10*O10 -> 426.18797 | S10: =R10-R9 -> 36.844591 | T10: =(S10*D10)/1000 -> 3.7275672 | U10: =T10+V9+U9 -> 43.412285 | V10: =U10*J10*(1/252) -> 0.008092429 | Y10: Total option payoff | Z10: =(Z9*J8)/100 -> 0
B11: ='Bloomberg Raw Data- all volumes'!A90 -> 45604 | C11: ='Bloomberg Raw Data- all volumes'!C90 -> MRK 11/15/24 C102 | D11: ='Bloomberg Raw Data- all volumes'!I90 -> 102.92 | E11: =LN(D11/D64) -> 0.017149717 | F11: ='Bloomberg Raw Data- all volumes'!B90 -> 102 | G11: ='Bloomberg Raw Data- all volumes'!F90 -> 1.6999998 | H11: ='Bloomberg Raw Data- all volumes'!D90 -> 1.5799999 | I11: ='Bloomberg Raw Data- all volumes'!E90 -> 2.1400003 | J11: ='Q1-(Without Zero Volume)'!J7 -> 0.046975 | K11: =5/252 -> 0.01984127 | L11: =(H11+I11)/2 -> 1.8600001 | M11: =(LN(D11/F11)+(J11+($P$8^2)/2)*K11)/($P$8*SQRT(K11)) -> 0.32900522 | N11: 10 | O11: =N11*100 -> 1000 | P11: =P10 -> 0.22467036 | Q11: =_xlfn.NORM.DIST(M11,0,1,TRUE) -> 0.62892413 | R11: =Q11*O11 -> 628.92413 | S11: =R11-R10 -> 202.73616 | T11: =(S11*D11)/1000 -> 20.865605 | U11: =T11+V10+U10 -> 64.285983 | V11: =U11*J11*(1/252) -> 0.011983468 | Y11: Final Hedge Portfolio Value | Z11: =(R16*D16)/1000 -> 0
B12: ='Bloomberg Raw Data- all volumes'!A93 -> 45607 | C12: ='Bloomberg Raw Data- all volumes'!C93 -> MRK 11/15/24 C102 | D12: ='Bloomberg Raw Data- all volumes'!I93 -> 100.73 | E12: =LN(D12/D67) -> 0.021575269 | F12: ='Bloomberg Raw Data- all volumes'!B93 -> 102 | G12: ='Bloomberg Raw Data- all volumes'!F93 -> 0.41000003 | H12: ='Bloomberg Raw Data- all volumes'!D93 -> 0.34000003 | I12: ='Bloomberg Raw Data- all volumes'!E93 -> 0.56999999 | J12: ='Q1-(Without Zero Volume)'!J10 -> 0.046975 | K12: =4/252 -> 0.015873016 | L12: =(H12+I12)/2 -> 0.45500001 | M12: =(LN(D12/F12)+(J12+($P$8^2)/2)*K12)/($P$8*SQRT(K12)) -> -0.4021401 | N12: 10 | O12: =N12*100 -> 1000 | P12: =P11 -> 0.22467036 | Q12: =_xlfn.NORM.DIST(M12,0,1,TRUE) -> 0.34379046 | R12: =Q12*O12 -> 343.79046 | S12: =R12-R11 -> -285.13367 | T12: =(S12*D12)/1000 -> -28.721514 | U12: =T12+V11+U11 -> 35.576452 | V12: =U12*J12*(1/252) -> 0.0066317613 | Y12: Premium received | Z12: ='Bloomberg Raw Data-5th(No zero)'!E11 -> 1.6900005
B13: ='Bloomberg Raw Data- all volumes'!A94 -> 45608 | C13: ='Bloomberg Raw Data- all volumes'!C94 -> MRK 11/15/24 C102 | D13: ='Bloomberg Raw Data- all volumes'!I94 -> 98.58 | E13: =LN(D13/D68) -> 0.0008118531 | F13: ='Bloomberg Raw Data- all volumes'!B94 -> 102 | G13: ='Bloomberg Raw Data- all volumes'!F94 -> 0.079999983 | H13: ='Bloomberg Raw Data- all volumes'!D94 -> 0.079999983 | I13: ='Bloomberg Raw Data- all volumes'!E94 -> 0.11000001 | J13: ='Q1-(Without Zero Volume)'!J11 -> 0.046975 | K13: =3/252 -> 0.011904762 | L13: =(H13+I13)/2 -> 0.094999999 | M13: =(LN(D13/F13)+(J13+($P$8^2)/2)*K13)/($P$8*SQRT(K13)) -> -1.3561779 | N13: 10 | O13: =N13*100 -> 1000 | P13: =P12 -> 0.22467036 | Q13: =_xlfn.NORM.DIST(M13,0,1,TRUE) -> 0.08752129 | R13: =Q13*O13 -> 87.52129 | S13: =R13-R12 -> -256.26917 | T13: =(S13*D13)/1000 -> -25.263015 | U13: =T13+V12+U12 -> 10.320069 | V13: =U13*J13*(1/252) -> 0.001923751 | Y13: Profit/(Loss) | Z13: =Z12-Z8 -> -0.029831616
B14: ='Bloomberg Raw Data- all volumes'!A95 -> 45609 | C14: ='Bloomberg Raw Data- all volumes'!C95 -> MRK 11/15/24 C102 | D14: ='Bloomberg Raw Data- all volumes'!I95 -> 98.5 | E14: =LN(D14/D69) -> 0.0014223308 | F14: ='Bloomberg Raw Data- all volumes'!B95 -> 102 | G14: ='Bloomberg Raw Data- all volumes'!F95 -> 0.050000001 | H14: ='Bloomberg Raw Data- all volumes'!D95 -> 0.030000001 | I14: ='Bloomberg Raw Data- all volumes'!E95 -> 0.050000001 | J14: ='Q1-(Without Zero Volume)'!J12 -> 0.046975 | K14: =2/252 -> 0.0079365079 | L14: =(H14+I14)/2 -> 0.040000001 | M14: =(LN(D14/F14)+(J14+($P$8^2)/2)*K14)/($P$8*SQRT(K14)) -> -1.7158508 | N14: 10 | O14: =N14*100 -> 1000 | P14: =P13 -> 0.22467036 | Q14: =_xlfn.NORM.DIST(M14,0,1,TRUE) -> 0.043094674 | R14: =Q14*O14 -> 43.094674 | S14: =R14-R13 -> -44.426615 | T14: =(S14*D14)/1000 -> -4.3760216 | U14: =T14+V13+U13 -> 5.9459714 | V14: =U14*J14*(1/252) -> 0.001108381
B15: ='Bloomberg Raw Data- all volumes'!A96 -> 45610 | C15: ='Bloomberg Raw Data- all volumes'!C96 -> MRK 11/15/24 C102 | D15: ='Bloomberg Raw Data- all volumes'!I96 -> 98.36 | E15: =LN(D15/D70) -> 0.021062062 | F15: ='Bloomberg Raw Data- all volumes'!B96 -> 102 | G15: ='Bloomberg Raw Data- all volumes'!F96 -> 0.02 | H15: ='Bloomberg Raw Data- all volumes'!D96 -> 0.0099999998 | I15: ='Bloomberg Raw Data- all volumes'!E96 -> 0.039999999 | J15: ='Q1-(Without Zero Volume)'!J13 -> 0.046975 | K15: =1/252 -> 0.003968254 | L15: =(H15+I15)/2 -> 0.024999999 | M15: =(LN(D15/F15)+(J15+($P$8^2)/2)*K15)/($P$8*SQRT(K15)) -> -2.5473245 | N15: 10 | O15: =N15*100 -> 1000 | P15: =P14 -> 0.22467036 | Q15: =_xlfn.NORM.DIST(M15,0,1,TRUE) -> 0.0054276222 | R15: =Q15*O15 -> 5.4276222 | S15: =R15-R14 -> -37.667052 | T15: =(S15*D15)/1000 -> -3.7049313 | U15: =T15+V14+U14 -> 2.2421485 | V15: =U15*J15*(1/252) -> 0.00041795605 | W15: =MAX(D15-F15,0) -> 0
B16: ='Bloomberg Raw Data- all volumes'!A97 -> 45611 | C16: ='Bloomberg Raw Data- all volumes'!C97 -> MRK 11/15/24 C102 | D16: ='Bloomberg Raw Data- all volumes'!I97 -> 96.31 | E16: 0 | F16: ='Bloomberg Raw Data- all volumes'!B97 -> 102 | G16: ='Bloomberg Raw Data- all volumes'!F97 -> 0.010000002 | H16: ='Bloomberg Raw Data- all volumes'!D97 -> 0 | I16: ='Bloomberg Raw Data- all volumes'!E97 -> 0.010000002 | J16: ='Q1-(Without Zero Volume)'!J14 -> 0.046975 | K16: =0/252 -> 0 | L16: =(H16+I16)/2 -> 0.0050000008 | M16: 0 | N16: 10 | O16: =N16*100 -> 1000 | P16: =P15 -> 0.22467036 | R16: =Q16*O16 -> 0 | S16: =R16-R15 -> -5.4276222 | T16: =(S16*D16)/1000 -> -0.52273429 | U16: =T16+V15+U15 -> 1.7198322 | V16: =U16*J16*(1/252) -> 0.00032059173 | W16: =MAX(D16-F16,0) -> 0
B20: Delta Hedging(Using Historical Volatility)
B23: Date | C23: Option Symbol | D23: SPOT Price | E23: Daily Log Returns | F23: STRIKE Price | G23: Closing Price | H23: Bid | I23: Ask | J23: Risk Free Interest Rate | K23: Time to Maturity (Trading days) | L23: Mid Price | M23: BSM d1 | N23: Contracts Sold (Assumed) | O23: Short call Options | P23: 22 Day Implied Volatility (Yahoo) | Q23: Delta | R23: Stocks to Buy | S23: ∆ Stocks Bought/sold | T23: Cost of shares ( '000s) | U23: Cumulative cost including interest | V23: Interest cost | W23: Option Payoff
B24: =B8 -> 45601 | C24: =C8 -> MRK 11/15/24 C102 | D24: =D8 -> 101.65 | E24: =E8 -> -0.0021619505 | F24: =F8 -> 102 | G24: =G8 -> 1.6900005 | H24: =H8 -> 1.5999994 | I24: =I8 -> 1.6599998 | ... K24: =K8 -> 0.031746032 | L24: =(H24+I24)/2 -> 1.6299996 | M24: =(LN(D24/F24)+(J24+(P24^2)/2)*K24)/(P24*SQRT(K24)) -> -0.051337467 | N24: =N8 -> 10 | O24: =O8 -> 1000 | P24: ='Historical Prices'!F24 -> 0.16531993 | Q24: =_xlfn.NORM.S.DIST(M24,TRUE) -> 0.47952831 | R24: =Q24*O24 -> 479.52831 | S24: =R24 -> 479.52831 | T24: =(S24*D24)/1000 -> 48.744052 | U24: =T24 -> 48.744052 | V24: =U24*J24*(1/252) -> 0.0090863169 | Z24: (in 000's)
B25: =B9 -> 45602 | C25: =C9 -> MRK 11/15/24 C102 | D25: =D9 -> 100.73 | E25: =E9 -> -0.0090918701 | F25: =F9 -> 102 | G25: =G9 -> 0.87 | H25: =H9 -> 0.73000002 | I25: =I9 -> 0.91000003 | ... K25: =K9 -> 0.027777778 | L25: =(H25+I25)/2 -> 0.82000002 | M25: =(LN(D25/F25)+(J25+(P25^2)/2)*K25)/(P25*SQRT(K25)) -> -0.40331698 | N25: =N9 -> 10 | O25: =O9 -> 1000 | P25: ='Historical Prices'!F25 -> 0.16158479 | Q25: =_xlfn.NORM.S.DIST(M25,TRUE) -> 0.34335753 | R25: =Q25*O25 -> 343.35753 | S25: =R25-R24 -> -136.17078 | T25: =(S25*D25)/1000 -> -13.716483 | U25: =T25+V24+U24 -> 35.036656 | V25: =U25*J25*(1/252) -> 0.0065311385 | Y25: Cumulative cost including interest | Z25: =U32 -> 1.7432722
B26: =B10 -> 45603 | C26: =C10 -> MRK 11/15/24 C102 | D26: =D10 -> 101.17 | E26: =E10 -> 0.0043586003 | F26: =F10 -> 102 | G26: =G10 -> 0.93000001 | H26: =H10 -> 0.88 | I26: =I10 -> 1.5 | ... K26: =K10 -> 0.023809524 | L26: =(H26+I26)/2 -> 1.19 | M26: =(LN(D26/F26)+(J26+(P26^2)/2)*K26)/(P26*SQRT(K26)) -> -0.27182878 | N26: =N10 -> 10 | O26: =O10 -> 1000 | P26: ='Historical Prices'!F26 -> 0.16079265 | Q26: =_xlfn.NORM.S.DIST(M26,TRUE) -> 0.39287684 | R26: =Q26*O26 -> 392.87684 | S26: =R26-R25 -> 49.51931 | T26: =(S26*D26)/1000 -> 5.0098686 | U26: =T26+V25+U25 -> 40.053056 | V26: =U26*J26*(1/252) -> 0.0074662392 | Y26: Option Payoff | Z26: =W32 -> 0
B27: =B11 -> 45604 | C27: =C11 -> MRK 11/15/24 C102 | D27: =D11 -> 102.92 | E27: =E11 -> 0.017149717 | F27: =F11 -> 102 | G27: =G11 -> 1.6999998 | H27: =H11 -> 1.5799999 | I27: =I11 -> 2.1400003 | ... K27: =K11 -> 0.01984127 | L27: =(H27+I27)/2 -> 1.8600001 | M27: =(LN(D27/F27)+(J27+(P27^2)/2)*K27)/(P27*SQRT(K27)) -> 0.44413243 | N27: =N11 -> 10 | O27: =O11 -> 1000 | P27: ='Historical Prices'!F27 -> 0.1626209 | Q27: =_xlfn.NORM.S.DIST(M27,TRUE) -> 0.67152658 | R27: =Q27*O27 -> 671.52658 | S27: =R27-R26 -> 278.64974 | T27: =(S27*D27)/1000 -> 28.678632 | U27: =T27+V26+U26 -> 68.739154 | V27: =U27*J27*(1/252) -> 0.012813578 | Y27: Total option payoff | Z27: =(Z26*J24)/100 -> 0
B28: =B12 -> 45607 | C28: =C12 -> MRK 11/15/24 C102 | D28: =D12 -> 100.73 | E28: =E12 -> 0.021575269 | F28: =F12 -> 102 | G28: =G12 -> 0.41000003 | H28: =H12 -> 0.34000003 | I28: =I12 -> 0.56999999 | ... K28: =K12 -> 0.015873016 | L28: =(H28+I28)/2 -> 0.45500001 | M28: =(LN(D28/F28)+(J28+(P28^2)/2)*K28)/(P28*SQRT(K28)) -> -0.5592061 | N28: =N12 -> 10 | O28: =O12 -> 1000 | P28: ='Historical Prices'!F28 -> 0.16421489 | Q28: =_xlfn.NORM.S.DIST(M28,TRUE) -> 0.28801054 | R28: =Q28*O28 -> 288.01054 | S28: =R28-R27 -> -383.51604 | T28: =(S28*D28)/1000 -> -38.631571 | U28: =T28+V27+U27 -> 30.120396 | V28: =U28*J28*(1/252) -> 0.0056147048 | Y28: Final Hedge Portfolio Value | Z28: =(R32*D32)/1000 -> 0
B29: =B13 -> 45608 | C29: =C13 -> MRK 11/15/24 C102 | D29: =D13 -> 98.58 | E29: =E13 -> 0.0008118531 | F29: =F13 -> 102 | G29: =G13 -> 0.079999983 | H29: =H13 -> 0.079999983 | I29: =I13 -> 0.11000001 | ... K29: =K13 -> 0.011904762 | L29: =(H29+I29)/2 -> 0.094999999 | M29: =(LN(D29/F29)+(J29+(P29^2)/2)*K29)/(P29*SQRT(K29)) -> -1.7516417 | N29: =N13 -> 10 | O29: =O13 -> 1000 | P29: ='Historical Prices'!F29 -> 0.17457005 | Q29: =_xlfn.NORM.S.DIST(M29,TRUE) -> 0.03991772 | R29: =Q29*O29 -> 39.91772 | S29: =R29-R28 -> -248.09282 | T29: =(S29*D29)/1000 -> -24.45699 | U29: =T29+V28+U28 -> 5.6690209 | V29: =U29*J29*(1/252) -> 0.001056755 | Y29: Premium received | Z29: ='Bloomberg Raw Data-5th(No zero)'!E11 -> 1.6900005
B30: =B14 -> 45609 | C30: =C14 -> MRK 11/15/24 C102 | D30: =D14 -> 98.5 | E30: =E14 -> 0.0014223308 | F30: =F14 -> 102 | G30: =G14 -> 0.050000001 | H30: =H14 -> 0.030000001 | I30: =I14 -> 0.050000001 | ... K30: =K14 -> 0.0079365079 | L30: =(H30+I30)/2 -> 0.040000001 | M30: =(LN(D30/F30)+(J30+(P30^2)/2)*K30)/(P30*SQRT(K30)) -> -2.1175558 | N30: =N14 -> 10 | O30: =O14 -> 1000 | P30: ='Historical Prices'!F30 -> 0.18241177 | Q30: =_xlfn.NORM.S.DIST(M30,TRUE) -> 0.017106354 | R30: =Q30*O30 -> 17.106354 | S30: =R30-R29 -> -22.811366 | T30: =(S30*D30)/1000 -> -2.2469195 | U30: =T30+V29+U29 -> 3.4231582 | V30: =U30*J30*(1/252) -> 0.00063810657 | Y30: Profit/(Loss) | Z30: =Z28+Z27-Z25 -> -1.7432722
B31: =B15 -> 45610 | C31: =C15 -> MRK 11/15/24 C102 | D31: =D15 -> 98.36 | E31: =E15 -> 0.021062062 | F31: =F15 -> 102 | G31: =G15 -> 0.02 | H31: =H15 -> 0.0099999998 | I31: =I15 -> 0.039999999 | ... K31: =K15 -> 0.003968254 | L31: =(H31+I31)/2 -> 0.024999999 | M31: =(LN(D31/F31)+(J31+(P31^2)/2)*K31)/(P31*SQRT(K31)) -> -3.1425084 | N31: =N15 -> 10 | O31: =O15 -> 1000 | P31: ='Historical Prices'!F31 -> 0.18229117 | Q31: =_xlfn.NORM.S.DIST(M31,TRUE) -> 0.00083753463 | R31: =Q31*O31 -> 0.83753463 | S31: =R31-R30 -> -16.26882 | T31: =(S31*D31)/1000 -> -1.6002011 | U31: =T31+V30+U30 -> 1.8235952 | V31: =U31*J31*(1/252) -> 0.00033993406 | W31: =MAX(D31-F31,0) -> 0
B32: =B16 -> 45611 | C32: =C16 -> MRK 11/15/24 C102 | D32: =D16 -> 96.31 | E32: =E16 -> 0 | F32: =F16 -> 102 | G32: =G16 -> 0.010000002 | H32: =H16 -> 0 | I32: =I16 -> 0.010000002 | ... K32: =K16 -> 0 | L32: =(H32+I32)/2 -> 0.0050000008 | M32: 0 | N32: =N16 -> 10 | O32: =O16 -> 1000 | P32: ='Historical Prices'!F32 -> 0.16700371 | R32: =Q32*O32 -> 0 | S32: =R32-R31 -> -0.83753463 | T32: =(S32*D32)/1000 -> -0.08066296 | U32: =T32+V31+U31 -> 1.7432722 | V32: =U32*J32*(1/252) -> 0.00032496115 | W32: =MAX(D32-F32,0) -> 0
B37: Historical Stock Price : October 15 - November 15 (2024)
C39: Date | D39: Stock Price | E39: Daily Return | F39: Log returns | G39: Standard Deviation | H39: Annualized Standard Deviation
C40: 45569 | D40: 109.77 | E40: =(C41-C40)/D41 -> 0.027626853
C41: 45572 | D41: 108.59 | E41: =(C42-C41)/D42 -> 0.0092148913 | F41: =LN(D41/D40) -> -0.010807945
C42: 45573 | D42: 108.52 | E42: =(C43-C42)/D43 -> 0.0090686497 | F42: =LN(D42/D41) -> -0.00064483444
C43: 45574 | D43: 110.27 | E43: =(C44-C43)/D44 -> 0.0091407678 | F43: =LN(D43/D42) -> 0.015997416
C44: 45575 | D44: 109.4 | E44: =(C45-C44)/D45 -> 0.009113278 | F44: =LN(D44/D43) -> -0.0079210138
C45: 45576 | D45: 109.73 | E45: =(C46-C45)/D46 -> 0.027349804 | F45: =LN(D45/D44) -> 0.003011913
C46: 45579 | D46: 109.69 | E46: =(C47-C46)/D47 -> 0.0089661974 | F46: =LN(D46/D45) -> -0.00036459758
C47: 45580 | D47: 111.53 | E47: =(C48-C47)/D48 -> 0.0090563304 | F47: =LN(D47/D46) -> 0.016635408
C48: 45581 | D48: 110.42 | E48: =(C49-C48)/D49 -> 0.0091116173 | F48: =LN(D48/D47) -> -0.010002336
C49: 45582 | D49: 109.75 | E49: =(C50-C49)/D50 -> 0.009199632 | F49: =LN(D49/D48) -> -0.0060862249
C50: 45583 | D50: 108.7 | E50: =(C51-C50)/D51 -> 0.028211397 | F50: =LN(D50/D49) -> -0.0096132578
C51: 45586 | D51: 106.34 | E51: =(C52-C51)/D52 -> 0.0093773443 | F51: =LN(D51/D50) -> -0.021950286
C52: 45587 | D52: 106.64 | E52: =(C53-C52)/D53 -> 0.0094002632 | F52: =LN(D52/D51) -> 0.0028171678
... C61: 45600 | D61: 101.87 | E61: =(C62-C61)/D62 -> 0.0098376783 | F61: =LN(D61/D60) -> -9.8159509e-05
C62: 45601 | D62: 101.65 | E62: =(C63-C62)/D63 -> 0.009927529 | F62: =LN(D62/D61) -> -0.0021619505 | G62: =_xlfn.STDEV.P(F40:F61) -> 0.010414177 | H62: =G62*SQRT(252) -> 0.16531993
C63: 45602 | D63: 100.73 | E63: =(C64-C63)/D64 -> 0.0098843531 | F63: =LN(D63/D62) -> -0.0090918701 | G63: =_xlfn.STDEV.P(F41:F62) -> 0.010178885 | H63: =G63*SQRT(252) -> 0.16158479
C64: 45603 | D64: 101.17 | E64: =(C65-C64)/D65 -> 0.0097162845 | F64: =LN(D64/D63) -> 0.0043586003 | G64: =_xlfn.STDEV.P(F42:F63) -> 0.010128985 | H64: =G64*SQRT(252) -> 0.16079265
C65: 45604 | D65: 102.92 | E65: =(C66-C65)/D66 -> 0.029782587 | F65: =LN(D65/D64) -> 0.017149717 | G65: =_xlfn.STDEV.P(F43:F64) -> 0.010244154 | H65: =G65*SQRT(252) -> 0.1626209
C66: 45607 | D66: 100.73 | E66: =(C67-C66)/D67 -> 0.010144045 | F66: =LN(D66/D65) -> -0.021508317 | G66: =_xlfn.STDEV.P(F44:F65) -> 0.010344566 | H66: =G66*SQRT(252) -> 0.16421489
C67: 45608 | D67: 98.58 | E67: =(C68-C67)/D68 -> 0.010152284 | F67: =LN(D67/D66) -> -0.021575269 | G67: =_xlfn.STDEV.P(F45:F66) -> 0.010996879 | H67: =G67*SQRT(252) -> 0.17457005
C68: 45609 | D68: 98.5 | E68: =(C69-C68)/D69 -> 0.010166734 | F68: =LN(D68/D67) -> -0.0008118531 | G68: =_xlfn.STDEV.P(F46:F67) -> 0.011490861 | H68: =G68*SQRT(252) -> 0.18241177
C69: 45610 | D69: 98.36 | E69: =(C70-C69)/D70 -> 0.010383138 | F69: =LN(D69/D68) -> -0.0014223308 | G69: =_xlfn.STDEV.P(F47:F68) -> 0.011483264 | H69: =G69*SQRT(252) -> 0.18229117
C70: 45611 | D70: 96.31 | E70: 0 | F70: =LN(D70/D69) -> -0.021062062 | G70: =_xlfn.STDEV.P(F48:F69) -> 0.010520245 | H70: =G70*SQRT(252) -> 0.16700371

Sheet Q3. Delta Hedging
F1: Volume- confirm
F2: Time
B4: Delta Hedging(Using Implied Volatility)
B7: Date | C7: Option Symbol | D7: SPOT Price | E7: Daily Log Returns | F7: STRIKE Price | G7: Closing Price | H7: Bid | I7: Ask | J7: Risk Free Interest Rate | K7: Underlying Dividend Rate | L7: Time to Maturity (10 Days) | M7: Mid Price | N7: BSM d1 | O7: BSM d2 | P7: Trading Volume | Q7: Model Implied Volatility (Calculated) | R7: Theoretical Call Price (Black-Scholes) | S7: Market Implied Volatility | T7: Pricing Error | U7: Delta | V7: Delta change | W7: ∆ Spot Price | X7: Stocks to Buy | Y7: P&L | Z7: Cumulative P&L | AA7: Option Payoff | AB7: Options Payoff (No Hedging) | AC7: Net Off (Hedging)
B8: ='Bloomberg Raw Data- all volumes'!A87 -> 45601 | C8: ='Bloomberg Raw Data- all volumes'!C87 -> MRK 11/15/24 C102 | D8: ='Bloomberg Raw Data- all volumes'!I87 -> 101.65 | E8: =LN(D8/D61) -> -0.0021619505 | F8: ='Bloomberg Raw Data- all volumes'!B87 -> 102 | G8: ='Bloomberg Raw Data- all volumes'!F87 -> 1.6900005 | H8: ='Bloomberg Raw Data- all volumes'!D87 -> 1.5999994 | I8: ='Bloomberg Raw Data- all volumes'!E87 -> 1.6599998 | J8: ='Q1-(Without Zero Volume)'!J4 -> 0.046975 | K8: 0.0311 | L8: =(15-5)/252 -> 0.03968254 | M8: =(H8+I8)/2 -> 1.6299996 | N8: =(LN(D8/F8) + ((J8+ (Q8^2) / 2)*L8) / (Q8*SQRT(L8))) -> 0.061822633 | O8: =N8 - Q8*SQRT(L8) -> 0.019599236 | P8: ='Bloomberg Raw Data- all volumes'!H87 -> 41 | Q8: 0.21195977 | R8: =D8*_xlfn.NORM.S.DIST(N8,TRUE) - F8*EXP(-J8*L8)*_xlfn.NORM.S.DIST(O8,TRUE) -> 1.629447 | S8: ='Bloomberg Raw Data- all volumes'!G87 -> 0.25288134 | T8: =M8-R8 -> 0.00055264158 | U8: =_xlfn.NORM.S.DIST(N8,TRUE) -> 0.52464796 | V8: 0 | W8: =D8-D61 -> -0.22 | X8: =U8*P8 -> 21.510566 | Y8: =X8*W8 -> -4.7323246 | Z8: =Y8 -> -4.7323246 | AB8: =F8-D8 -> 0.35 | AC8: =AB8+Y8 -> -4.3823246
B9: ='Bloomberg Raw Data- all volumes'!A88 -> 45602 | C9: ='Bloomberg Raw Data- all volumes'!C88 -> MRK 11/15/24 C102 | D9: ='Bloomberg Raw Data- all volumes'!I88 -> 100.73 | E9: =LN(D9/D62) -> -0.0090918701 | F9: ='Bloomberg Raw Data- all volumes'!B88 -> 102 | G9: ='Bloomberg Raw Data- all volumes'!F88 -> 0.87 | H9: ='Bloomberg Raw Data- all volumes'!D88 -> 0.73000002 | I9: ='Bloomberg Raw Data- all volumes'!E88 -> 0.91000003 | J9: ='Q1-(Without Zero Volume)'!J5 -> 0.046975 | K9: 0.0311 | L9: =(15-6)/252 -> 0.035714286 | M9: =(H9+I9)/2 -> 0.82000002 | N9: =(LN(D9/F9) + ((J9+ (Q9^2) / 2)*L9) / (Q9*SQRT(L9))) -> 0.053527954 | O9: =N9 - Q9*SQRT(L9) -> 0.019222755 | P9: ='Bloomberg Raw Data- all volumes'!H88 -> 667 | Q9: 0.18152606 | R9: =D9*_xlfn.NORM.S.DIST(N9,TRUE) - F9*EXP(-J9*L9)*_xlfn.NORM.S.DIST(O9,TRUE) -> 0.81965316 | S9: ='Bloomberg Raw Data- all volumes'!G88 -> 0.17977623 | T9: =M9-R9 -> 0.00034686422 | U9: =_xlfn.NORM.S.DIST(N9,TRUE) -> 0.52134437 | V9: =U9-U8 -> -0.0033035894 | W9: =D9-D8 -> -0.92 | X9: =U9*P9 -> 347.7367 | Y9: =X9*W9 -> -319.91776 | Z9: =Y9+Z8 -> -324.65008 | AB9: =F9-D9 -> 1.27 | AC9: =AB9+Y9 -> -318.64776
B10: ='Bloomberg Raw Data- all volumes'!A89 -> 45603 | C10: ='Bloomberg Raw Data- all volumes'!C89 -> MRK 11/15/24 C102 | D10: ='Bloomberg Raw Data- all volumes'!I89 -> 101.17 | E10: =LN(D10/D63) -> -0.086129634 | F10: ='Bloomberg Raw Data- all volumes'!B89 -> 102 | G10: ='Bloomberg Raw Data- all volumes'!F89 -> 0.93000001 | H10: ='Bloomberg Raw Data- all volumes'!D89 -> 0.88 | I10: ='Bloomberg Raw Data- all volumes'!E89 -> 1.5 | J10: ='Q1-(Without Zero Volume)'!J6 -> 0.046975 | K10: 0.0311 | L10: =(15-7)/252 -> 0.031746032 | M10: =(H10+I10)/2 -> 1.19 | N10: =(LN(D10/F10) + ((J10+ (Q10^2) / 2)*L10) / (Q10*SQRT(L10))) -> 0.050082377 | O10: =N10 - Q10*SQRT(L10) -> 0.012099212 | P10: ='Bloomberg Raw Data- all volumes'!H89 -> 697 | Q10: 0.21317998 | R10: =D10*_xlfn.NORM.S.DIST(N10,TRUE) - F10*EXP(-J10*L10)*_xlfn.NORM.S.DIST(O10,TRUE) -> 1.1899309 | S10: ='Bloomberg Raw Data- all volumes'!G89 -> 0.23807673 | T10: =M10-R10 -> 6.9135141e-05 | U10: =_xlfn.NORM.S.DIST(N10,TRUE) -> 0.51997163 | V10: =U10-U9 -> -0.0013727426 | W10: =D10-D9 -> 0.44 | X10: =U10*P10 -> 362.42022 | Y10: =X10*W10 -> 159.4649 | Z10: =Z9+Y10 -> -165.18519 | AB10: =F10-D10 -> 0.83 | AC10: =AB10+Y10 -> 160.2949
B11: ='Bloomberg Raw Data- all volumes'!A90 -> 45604 | C11: ='Bloomberg Raw Data- all volumes'!C90 -> MRK 11/15/24 C102 | D11: ='Bloomberg Raw Data- all volumes'!I90 -> 102.92 | E11: =LN(D11/D64) -> -0.061058903 | F11: ='Bloomberg Raw Data- all volumes'!B90 -> 102 | G11: ='Bloomberg Raw Data- all volumes'!F90 -> 1.6999998 | H11: ='Bloomberg Raw Data- all volumes'!D90 -> 1.5799999 | I11: ='Bloomberg Raw Data- all volumes'!E90 -> 2.1400003 | J11: ='Q1-(Without Zero Volume)'!J7 -> 0.046975 | K11: 0.0311 | L11: =(15-8)/252 -> 0.027777778 | M11: =(H11+I11)/2 -> 1.8600001 | N11: =(LN(D11/F11) + ((J11+ (Q11^2) / 2)*L11) / (Q11*SQRT(L11))) -> 0.065618743 | O11: =N11 - Q11*SQRT(L11) -> 0.033439724 | P11: ='Bloomberg Raw Data- all volumes'!H90 -> 796 | Q11: 0.19307411 | R11: =D11*_xlfn.NORM.S.DIST(N11,TRUE) - F11*EXP(-J11*L11)*_xlfn.NORM.S.DIST(O11,TRUE) -> 1.860116 | S11: ='Bloomberg Raw Data- all volumes'!G90 -> 0.22628731 | T11: =M11-R11 -> -0.00011587608 | U11: =_xlfn.NORM.S.DIST(N11,TRUE) -> 0.52615932 | V11: =U11-U10 -> 0.0061876883 | W11: =D11-D10 -> 1.75 | X11: =U11*P11 -> 418.82282 | Y11: =X11*W11 -> 732.93993 | Z11: =Z10+Y11 -> 567.75474 | AB11: =F11-D11 -> -0.92 | AC11: =AB11+Y11 -> 732.01993
B12: ='Bloomberg Raw Data- all volumes'!A93 -> 45607 | C12: ='Bloomberg Raw Data- all volumes'!C93 -> MRK 11/15/24 C102 | D12: ='Bloomberg Raw Data- all volumes'!I93 -> 100.73 | E12: =LN(D12/D67) -> -0.10184994 | F12: ='Bloomberg Raw Data- all volumes'!B93 -> 102 | G12: ='Bloomberg Raw Data- all volumes'!F93 -> 0.41000003 | H12: ='Bloomberg Raw Data- all volumes'!D93 -> 0.34000003 | I12: ='Bloomberg Raw Data- all volumes'!E93 -> 0.56999999 | J12: ='Q1-(Without Zero Volume)'!J10 -> 0.046975 | K12: 0.0311 | L12: =(15-11)/252 -> 0.015873016 | M12: =(H12+I12)/2 -> 0.45500001 | N12: =(LN(D12/F12) + ((J12+ (Q12^2) / 2)*L12) / (Q12*SQRT(L12))) -> 0.029021556 | O12: =N12 - Q12*SQRT(L12) -> 0.0028067876 | P12: ='Bloomberg Raw Data- all volumes'!H93 -> 715 | Q12: 0.20807327 | R12: =D12*_xlfn.NORM.S.DIST(N12,TRUE) - F12*EXP(-J12*L12)*_xlfn.NORM.S.DIST(O12,TRUE) -> 0.45496514 | S12: ='Bloomberg Raw Data- all volumes'!G91 -> 0.22628731 | T12: =M12-R12 -> 3.4874283e-05 | U12: =_xlfn.NORM.S.DIST(N12,TRUE) -> 0.5115763 | V12: =U12-U11 -> -0.014583016 | W12: =D12-D11 -> -2.19 | X12: =U12*P12 -> 365.77706 | Y12: =X12*W12 -> -801.05175 | Z12: =Z11+Y12 -> -233.29701 | AB12: =F12-D12 -> 1.27 | AC12: =AB12+Y12 -> -799.78175
B13: ='Bloomberg Raw Data- all volumes'!A94 -> 45608 | C13: ='Bloomberg Raw Data- all volumes'!C94 -> MRK 11/15/24 C102 | D13: ='Bloomberg Raw Data- all volumes'!I94 -> 98.58 | E13: =LN(D13/D68) -> -0.11342288 | F13: ='Bloomberg Raw Data- all volumes'!B94 -> 102 | G13: ='Bloomberg Raw Data- all volumes'!F94 -> 0.079999983 | H13: ='Bloomberg Raw Data- all volumes'!D94 -> 0.079999983 | I13: ='Bloomberg Raw Data- all volumes'!E94 -> 0.11000001 | J13: ='Q1-(Without Zero Volume)'!J11 -> 0.046975 | K13: 0.0311 | L13: =(15-12)/252 -> 0.011904762 | M13: =(H13+I13)/2 -> 0.094999999 | N13: =(LN(D13/F13) + ((J13+ (Q13^2) / 2)*L13) / (Q13*SQRT(L13))) -> 0.00054510034 | O13: =N13 - Q13*SQRT(L13) -> -0.043167321 | P13: ='Bloomberg Raw Data- all volumes'!H94 -> 997 | Q13: 0.40063096 | R13: =D13*_xlfn.NORM.S.DIST(N13,TRUE) - F13*EXP(-J13*L13)*_xlfn.NORM.S.DIST(O13,TRUE) -> 0.094992495 | S13: ='Bloomberg Raw Data- all volumes'!G92 -> 0.22628731 | T13: =M13-R13 -> 7.5040716e-06 | U13: =_xlfn.NORM.S.DIST(N13,TRUE) -> 0.50021746 | V13: =U13-U12 -> -0.011358837 | W13: =D13-D12 -> -2.15 | X13: =U13*P13 -> 498.71681 | Y13: =X13*W13 -> -1072.2411 | Z13: =Z12+Y13 -> -1305.5382 | AB13: =F13-D13 -> 3.42 | AC13: =AB13+Y13 -> -1068.8211
B14: ='Bloomberg Raw Data- all volumes'!A95 -> 45609 | C14: ='Bloomberg Raw Data- all volumes'!C95 -> MRK 11/15/24 C102 | D14: ='Bloomberg Raw Data- all volumes'!I95 -> 98.5 | E14: =LN(D14/D69) -> -0.1081485 | F14: ='Bloomberg Raw Data- all volumes'!B95 -> 102 | G14: ='Bloomberg Raw Data- all volumes'!F95 -> 0.050000001 | H14: ='Bloomberg Raw Data- all volumes'!D95 -> 0.030000001 | I14: ='Bloomberg Raw Data- all volumes'!E95 -> 0.050000001 | J14: ='Q1-(Without Zero Volume)'!J12 -> 0.046975 | K14: 0.0311 | L14: =(15-13)/252 -> 0.0079365079 | M14: =(H14+I14)/2 -> 0.040000001 | N14: =(LN(D14/F14) + ((J14+ (Q14^2) / 2)*L14) / (Q14*SQRT(L14))) -> -0.0046290502 | O14: =N14 - Q14*SQRT(L14) -> -0.048018954 | P14: ='Bloomberg Raw Data- all volumes'!H95 -> 174 | Q14: 0.48705047 | R14: =D14*_xlfn.NORM.S.DIST(N14,TRUE) - F14*EXP(-J14*L14)*_xlfn.NORM.S.DIST(O14,TRUE) -> 0.039622461 | S14: ='Bloomberg Raw Data- all volumes'!G93 -> 0.19944824 | T14: =M14-R14 -> 0.00037753975 | U14: =_xlfn.NORM.S.DIST(N14,TRUE) -> 0.49815328 | V14: =U14-U13 -> -0.0020641808 | W14: =D14-D13 -> -0.08 | X14: =U14*P14 -> 86.678671 | Y14: =X14*W14 -> -6.9342937 | Z14: =Z13+Y14 -> -1312.4724 | AB14: =F14-D14 -> 3.5 | AC14: =AB14+Y14 -> -3.4342937
B15: ='Bloomberg Raw Data- all volumes'!A96 -> 45610 | C15: ='Bloomberg Raw Data- all volumes'!C96 -> MRK 11/15/24 C102 | D15: ='Bloomberg Raw Data- all volumes'!I96 -> 98.36 | E15: =LN(D15/D70) -> -0.099957577 | F15: ='Bloomberg Raw Data- all volumes'!B96 -> 102 | G15: ='Bloomberg Raw Data- all volumes'!F96 -> 0.02 | H15: ='Bloomberg Raw Data- all volumes'!D96 -> 0.0099999998 | I15: ='Bloomberg Raw Data- all volumes'!E96 -> 0.039999999 | J15: ='Q1-(Without Zero Volume)'!J13 -> 0.046975 | K15: 0.0311 | L15: =(15-14)/252 -> 0.003968254 | M15: =(H15+I15)/2 -> 0.024999999 | N15: =(LN(D15/F15) + ((J15+ (Q15^2) / 2)*L15) / (Q15*SQRT(L15))) -> -0.0097797627 | O15: =N15 - Q15*SQRT(L15) -> -0.054574664 | P15: ='Bloomberg Raw Data- all volumes'!H96 -> 779 | Q15: 0.71109701 | R15: =D15*_xlfn.NORM.S.DIST(N15,TRUE) - F15*EXP(-J15*L15)*_xlfn.NORM.S.DIST(O15,TRUE) -> 0.024997296 | S15: ='Bloomberg Raw Data- all volumes'!G94 -> 0.2110037 | T15: =M15-R15 -> 2.7036729e-06 | U15: =_xlfn.NORM.S.DIST(N15,TRUE) -> 0.4960985 | V15: =U15-U14 -> -0.0020547814 | W15: =D15-D14 -> -0.14 | X15: =U15*P15 -> 386.46073 | Y15: =X15*W15 -> -54.104503 | Z15: =Z14+Y15 -> -1366.5769 | AA15: =MAX(D15-F15,0) -> 0 | AB15: =F15-D15 -> 3.64 | AC15: =AB15+Y15 -> -50.464503
B16: ='Bloomberg Raw Data- all volumes'!A97 -> 45611 | C16: ='Bloomberg Raw Data- all volumes'!C97 -> MRK 11/15/24 C102 | D16: ='Bloomberg Raw Data- all volumes'!I97 -> 96.31 | E16: 0 | F16: ='Bloomberg Raw Data- all volumes'!B97 -> 102 | G16: ='Bloomberg Raw Data- all volumes'!F97 -> 0.010000002 | H16: ='Bloomberg Raw Data- all volumes'!D97 -> 0 | I16: ='Bloomberg Raw Data- all volumes'!E97 -> 0.010000002 | J16: ='Q1-(Without Zero Volume)'!J14 -> 0.046975 | K16: 0.0311 | L16: =(15-15)/252 -> 0 | M16: =(H16+I16)/2 -> 0.0050000008 | N16: =(LN(D16/F16) + ((J16+ (Q16^2) / 2)*L16) / (Q16*SQRT(L16))) -> #DIV/0! | O16: =N16 - Q16*SQRT(L16) -> #DIV/0! | P16: ='Bloomberg Raw Data- all volumes'!H97 -> 19 | Q16: 0.33714516 | R16: =D16*_xlfn.NORM.S.DIST(N16,TRUE) - F16*EXP(-J16*L16)*_xlfn.NORM.S.DIST(O16,TRUE) -> #DIV/0! | S16: ='Bloomberg Raw Data- all volumes'!G95 -> 0.2314974 | T16: =M16-R16 -> #DIV/0! | U16: =_xlfn.NORM.S.DIST(N16,TRUE) -> #DIV/0! | V16: =U16-U15 -> #DIV/0! | W16: =D16-D15 -> -2.05 | X16: =U16*P16 -> #DIV/0! | Y16: =X16*W16 -> #DIV/0! | Z16: =Z15+Y16 -> #DIV/0! | AB16: =F16-D16 -> 5.69 | AC16: =AB16+Y16 -> #DIV/0!
B20: Delta Hedging(Using Historical Volatility)
B23: Date | C23: Option Symbol | D23: SPOT Price | E23: Daily Log Returns | F23: STRIKE Price | G23: Closing Price | H23: Bid | I23: Ask | J23: Risk Free Interest Rate | K23: Underlying Dividend Rate | L23: Time to Maturity (10 Days) | M23: Mid Price | N23: BSM d1 | O23: BSM d2 | P23: Trading Volume | Q23: Historical Volatility | R23: Theoretical Call Price (Black-Scholes) | S23: Market Implied Volatility | T23: Pricing Error | U23: Delta | V23: Delta change | W23: ∆ Spot Price | X23: Stocks to Buy | Y23: P&L | Z23: Cumulative P&L | AA23: Option Payoff | AB23: Options Payoff (No Hedging) | AC23: Net Off (Hedging)
B24: =B8 -> 45601 | C24: =C8 -> MRK 11/15/24 C102 | D24: =D8 -> 101.65 | E24: =E8 -> -0.0021619505 | F24: =F8 -> 102 | G24: =G8 -> 1.6900005 | H24: =H8 -> 1.5999994 | I24: =I8 -> 1.6599998 | ... L24: =L8 -> 0.03968254 | M24: =(H24+I24)/2 -> 1.6299996 | N24: =(LN(D24/F24) + ((J24+ (Q24^2) / 2)*L24) / (Q24*SQRT(L24))) -> 0.058754402 | O24: =N24-Q24*SQRT(L24) -> 0.0083792338 | P24: 24 | Q24: ='Bloomberg Raw Data- all volumes'!G87 -> 0.25288134 | R24: =D24*_xlfn.NORM.S.DIST(N24,TRUE) - F24*EXP(-J24*L24)*_xlfn.NORM.S.DIST(O24,TRUE) -> 1.9609169 | S24: 0.31934274 | T24: =M24-R24 -> -0.33091726 | U24: =_xlfn.NORM.S.DIST(N24,TRUE) -> 0.52342614 | V24: 0 | W24: =D24-D61 -> -0.22 | X24: =U24*P24 -> 12.562227 | Y24: =X24*W24 -> -2.76369 | Z24: =Y24 -> -2.76369 | AB24: =F24-D24 -> 0.35 | AC24: =AB24+Y24 -> -2.41369
B25: =B9 -> 45602 | C25: =C9 -> MRK 11/15/24 C102 | D25: =D9 -> 100.73 | E25: =E9 -> -0.0090918701 | F25: =F9 -> 102 | G25: =G9 -> 0.87 | H25: =H9 -> 0.73000002 | I25: =I9 -> 0.91000003 | ... L25: =L9 -> 0.035714286 | M25: =(H25+I25)/2 -> 0.82000002 | N25: =(LN(D25/F25) + ((J25+ (Q25^2) / 2)*L25) / (Q25*SQRT(L25))) -> 0.053838616 | O25: =N25-Q25*SQRT(L25) -> 0.019864102 | P25: 124 | Q25: ='Bloomberg Raw Data- all volumes'!G88 -> 0.17977623 | R25: =D25*_xlfn.NORM.S.DIST(N25,TRUE) - F25*EXP(-J25*L25)*_xlfn.NORM.S.DIST(O25,TRUE) -> 0.8060702 | S25: 0.29785858 | T25: =M25-R25 -> 0.013929823 | U25: =_xlfn.NORM.S.DIST(N25,TRUE) -> 0.52146813 | V25: =U25-U24 -> -0.0019580076 | W25: =D25-D62 -> -0.92 | X25: =U25*P25 -> 64.662048 | Y25: =X25*W25 -> -59.489084 | Z25: =Y25+Z24 -> -62.252774 | AB25: =F25-D25 -> 1.27 | AC25: =AB25+Y25 -> -58.219084
B26: =B10 -> 45603 | C26: =C10 -> MRK 11/15/24 C102 | D26: =D10 -> 101.17 | E26: =E10 -> -0.086129634 | F26: =F10 -> 102 | G26: =G10 -> 0.93000001 | H26: =H10 -> 0.88 | I26: =I10 -> 1.5 | ... L26: =L10 -> 0.031746032 | M26: =(H26+I26)/2 -> 1.19 | N26: =(LN(D26/F26) + ((J26+ (Q26^2) / 2)*L26) / (Q26*SQRT(L26))) -> 0.048194622 | O26: =N26-Q26*SQRT(L26) -> 0.0057755012 | P26: 56 | Q26: ='Bloomberg Raw Data- all volumes'!G89 -> 0.23807673 | R26: =D26*_xlfn.NORM.S.DIST(N26,TRUE) - F26*EXP(-J26*L26)*_xlfn.NORM.S.DIST(O26,TRUE) -> 1.3707622 | S26: 0.29248754 | T26: =M26-R26 -> -0.18076218 | U26: =_xlfn.NORM.S.DIST(N26,TRUE) -> 0.51921943 | V26: =U26-U25 -> -0.0022486967 | W26: =D26-D63 -> -9.1 | X26: =U26*P26 -> 29.076288 | Y26: =X26*W26 -> -264.59422 | Z26: =Y26+Z25 -> -326.847 | AB26: =F26-D26 -> 0.83 | AC26: =AB26+Y26 -> -263.76422
B27: =B11 -> 45604 | C27: =C11 -> MRK 11/15/24 C102 | D27: =D11 -> 102.92 | E27: =E11 -> -0.061058903 | F27: =F11 -> 102 | G27: =G11 -> 1.6999998 | H27: =H11 -> 1.5799999 | I27: =I11 -> 2.1400003 | ... L27: =L11 -> 0.027777778 | M27: =(H27+I27)/2 -> 1.8600001 | N27: =(LN(D27/F27) + ((J27+ (Q27^2) / 2)*L27) / (Q27*SQRT(L27))) -> 0.062434796 | O27: =N27-Q27*SQRT(L27) -> 0.024720245 | P27: 84 | Q27: ='Bloomberg Raw Data- all volumes'!G90 -> 0.22628731 | R27: =D27*_xlfn.NORM.S.DIST(N27,TRUE) - F27*EXP(-J27*L27)*_xlfn.NORM.S.DIST(O27,TRUE) -> 2.0838541 | S27: 0.29102271 | T27: =M27-R27 -> -0.22385393 | U27: =_xlfn.NORM.S.DIST(N27,TRUE) -> 0.52489171 | V27: =U27-U26 -> 0.0056722753 | W27: =D27-D64 -> -6.48 | X27: =U27*P27 -> 44.090903 | Y27: =X27*W27 -> -285.70905 | Z27: =Y27+Z26 -> -612.55605 | AB27: =F27-D27 -> -0.92 | AC27: =AB27+Y27 -> -286.62905
B28: =B12 -> 45607 | C28: =C12 -> MRK 11/15/24 C102 | D28: =D12 -> 100.73 | E28: =E12 -> -0.10184994 | F28: =F12 -> 102 | G28: =G12 -> 0.41000003 | H28: =H12 -> 0.34000003 | I28: =I12 -> 0.56999999 | ... L28: =L12 -> 0.015873016 | M28: =(H28+I28)/2 -> 0.45500001 | N28: =(LN(D28/F28) + ((J28+ (Q28^2) / 2)*L28) / (Q28*SQRT(L28))) -> 0.027879509 | O28: =N28-Q28*SQRT(L28) -> -0.00063001228 | P28: 100 | Q28: ='Bloomberg Raw Data- all volumes'!G91 -> 0.22628731 | R28: =D28*_xlfn.NORM.S.DIST(N28,TRUE) - F28*EXP(-J28*L28)*_xlfn.NORM.S.DIST(O28,TRUE) -> 0.54883628 | S28: 0.29004616 | T28: =M28-R28 -> -0.093836265 | U28: =_xlfn.NORM.S.DIST(N28,TRUE) -> 0.51112087 | V28: =U28-U27 -> -0.013770833 | W28: =D28-D65 -> -9 | X28: =U28*P28 -> 51.112087 | Y28: =X28*W28 -> -460.00879 | Z28: =Y28+Z27 -> -1072.5648 | AB28: =F28-D28 -> 1.27 | AC28: =AB28+Y28 -> -458.73879
B29: =B13 -> 45608 | C29: =C13 -> MRK 11/15/24 C102 | D29: =D13 -> 98.58 | E29: =E13 -> -0.11342288 | F29: =F13 -> 102 | G29: =G13 -> 0.079999983 | H29: =H13 -> 0.079999983 | I29: =I13 -> 0.11000001 | ... L29: =L13 -> 0.011904762 | M29: =(H29+I29)/2 -> 0.094999999 | N29: =(LN(D29/F29) + ((J29+ (Q29^2) / 2)*L29) / (Q29*SQRT(L29))) -> 0.00089050721 | O29: =N29-Q29*SQRT(L29) -> -0.023799462 | P29: 65 | Q29: ='Bloomberg Raw Data- all volumes'!G92 -> 0.22628731 | R29: =D29*_xlfn.NORM.S.DIST(N29,TRUE) - F29*EXP(-J29*L29)*_xlfn.NORM.S.DIST(O29,TRUE) -> -0.67864821 | S29: 0.29077858 | T29: =M29-R29 -> 0.77364821 | U29: =_xlfn.NORM.S.DIST(N29,TRUE) -> 0.50035526 | V29: =U29-U28 -> -0.010765613 | W29: =D29-D66 -> -11.11 | X29: =U29*P29 -> 32.523092 | Y29: =X29*W29 -> -361.33155 | Z29: =Y29+Z28 -> -1433.8964 | AB29: =F29-D29 -> 3.42 | AC29: =AB29+Y29 -> -357.91155
B30: =B14 -> 45609 | C30: =C14 -> MRK 11/15/24 C102 | D30: =D14 -> 98.5 | E30: =E14 -> -0.1081485 | F30: =F14 -> 102 | G30: =G14 -> 0.050000001 | H30: =H14 -> 0.030000001 | I30: =I14 -> 0.050000001 | ... L30: =L14 -> 0.0079365079 | M30: =(H30+I30)/2 -> 0.040000001 | N30: =(LN(D30/F30) + ((J30+ (Q30^2) / 2)*L30) / (Q30*SQRT(L30))) -> -0.0050499207 | O30: =N30-Q30*SQRT(L30) -> -0.022818182 | P30: 28 | Q30: ='Bloomberg Raw Data- all volumes'!G93 -> 0.19944824 | R30: =D30*_xlfn.NORM.S.DIST(N30,TRUE) - F30*EXP(-J30*L30)*_xlfn.NORM.S.DIST(O30,TRUE) -> -1.0013364 | S30: 0.30396204 | T30: =M30-R30 -> 1.0413364 | U30: =_xlfn.NORM.S.DIST(N30,TRUE) -> 0.49798538 | V30: =U30-U29 -> -0.0023698793 | W30: =D30-D67 -> -13.03 | X30: =U30*P30 -> 13.943591 | Y30: =X30*W30 -> -181.68499 | Z30: =Y30+Z29 -> -1615.5814 | AB30: =F30-D30 -> 3.5 | AC30: =AB30+Y30 -> -178.18499
B31: =B15 -> 45610 | C31: =C15 -> MRK 11/15/24 C102 | D31: =D15 -> 98.36 | E31: =E15 -> -0.099957577 | F31: =F15 -> 102 | G31: =G15 -> 0.02 | H31: =H15 -> 0.0099999998 | I31: =I15 -> 0.039999999 | ... L31: =L15 -> 0.003968254 | M31: =(H31+I31)/2 -> 0.024999999 | N31: =(LN(D31/F31) + ((J31+ (Q31^2) / 2)*L31) / (Q31*SQRT(L31))) -> -0.015668457 | O31: =N31-Q31*SQRT(L31) -> -0.028960441 | P31: 29 | Q31: ='Bloomberg Raw Data- all volumes'!G94 -> 0.2110037 | R31: =D31*_xlfn.NORM.S.DIST(N31,TRUE) - F31*EXP(-J31*L31)*_xlfn.NORM.S.DIST(O31,TRUE) -> -1.2472214 | S31: 0.30127652 | T31: =M31-R31 -> 1.2722214 | U31: =_xlfn.NORM.S.DIST(N31,TRUE) -> 0.49374945 | V31: =U31-U30 -> -0.0042359361 | W31: =D31-D68 -> -12.06 | X31: =U31*P31 -> 14.318734 | Y31: =X31*W31 -> -172.68393 | Z31: =Y31+Z30 -> -1788.2653 | AA31: =MAX(D31-F31,0) -> 0 | AB31: =F31-D31 -> 3.64 | AC31: =AB31+Y31 -> -169.04393
B32: =B16 -> 45611 | C32: =C16 -> MRK 11/15/24 C102 | D32: =D16 -> 96.31 | E32: =E16 -> 0 | F32: =F16 -> 102 | G32: =G16 -> 0.010000002 | H32: =H16 -> 0 | I32: =I16 -> 0.010000002 | ... L32: =L16 -> 0 | M32: =(H32+I32)/2 -> 0.0050000008 | N32: =(LN(D32/F32) + ((J32+ (Q32^2) / 2)*L32) / (Q32*SQRT(L32))) -> #DIV/0! | O32: =N32-Q32*SQRT(L32) -> #DIV/0! | P32: 69 | Q32: ='Bloomberg Raw Data- all volumes'!G95 -> 0.2314974 | R32: =D32*_xlfn.NORM.S.DIST(N32,TRUE) - F32*EXP(-J32*L32)*_xlfn.NORM.S.DIST(O32,TRUE) -> #DIV/0! | S32: 0.32178413 | T32: =M32-R32 -> #DIV/0! | U32: =_xlfn.NORM.S.DIST(N32,TRUE) -> #DIV/0! | V32: =U32-U31 -> #DIV/0! | W32: =D32-D69 -> -13.44 | X32: =U32*P32 -> #DIV/0! | Y32: =X32*W32 -> #DIV/0! | Z32: =Y32+Z31 -> #DIV/0! | AB32: =F32-D32 -> 5.69 | AC32: =AB32+Y32 -> #DIV/0!
B37: Historical Stock Price : October 15 - November 15 (2024)
C39: Date | D39: Stock Price | E39: Daily Return | F39: Log returns | G39: Standard Deviation | H39: Annualized Standard Deviation
C40: 45569 | D40: 109.77 | E40: =(C41-C40)/D41 -> 0.027626853 | I40: (TBD)
C41: 45572 | D41: 108.59 | E41: =(C42-C41)/D42 -> 0.0092148913 | F41: =LN(D41/D40) -> -0.010807945
C42: 45573 | D42: 108.52 | E42: =(C43-C42)/D43 -> 0.0090686497 | F42: =LN(D42/D41) -> -0.00064483444
C43: 45574 | D43: 110.27 | E43: =(C44-C43)/D44 -> 0.0091407678 | F43: =LN(D43/D42) -> 0.015997416
C44: 45575 | D44: 109.4 | E44: =(C45-C44)/D45 -> 0.009113278 | F44: =LN(D44/D43) -> -0.0079210138
C45: 45576 | D45: 109.73 | E45: =(C46-C45)/D46 -> 0.027349804 | F45: =LN(D45/D44) -> 0.003011913
C46: 45579 | D46: 109.69 | E46: =(C47-C46)/D47 -> 0.0089661974 | F46: =LN(D46/D45) -> -0.00036459758
C47: 45580 | D47: 111.53 | E47: =(C48-C47)/D48 -> 0.0090563304 | F47: =LN(D47/D46) -> 0.016635408
C48: 45581 | D48: 110.42 | E48: =(C49-C48)/D49 -> 0.0091116173 | F48: =LN(D48/D47) -> -0.010002336
C49: 45582 | D49: 109.75 | E49: =(C50-C49)/D50 -> 0.009199632 | F49: =LN(D49/D48) -> -0.0060862249
C50: 45583 | D50: 108.7 | E50: =(C51-C50)/D51 -> 0.028211397 | F50: =LN(D50/D49) -> -0.0096132578
C51: 45586 | D51: 106.34 | E51: =(C52-C51)/D52 -> 0.0093773443 | F51: =LN(D51/D50) -> -0.021950286
C52: 45587 | D52: 106.64 | E52: =(C53-C52)/D53 -> 0.0094002632 | F52: =LN(D52/D51) -> 0.0028171678
... C61: 45600 | D61: 101.87 | E61: =(C62-C61)/D62 -> 0.0098376783 | F61: =LN(D61/D60) -> -9.8159509e-05
C62: 45601 | D62: 101.65 | E62: =(C63-C62)/D63 -> 0.0090686497 | F62: =LN(D62/D61) -> -0.0021619505 | G62: =_xlfn.STDEV.P(F40:F61) -> 0.010414177 | H62: =G62*SQRT(252) -> 0.16531993
C63: 45602 | D63: =D43 -> 110.27 | E63: =(C64-C63)/D64 -> 0.0091407678 | F63: =LN(D63/D62) -> 0.081396364 | G63: =_xlfn.STDEV.P(F41:F62) -> 0.010178885 | H63: =G63*SQRT(252) -> 0.16158479
C64: 45603 | D64: =D44 -> 109.4 | E64: =(C65-C64)/D65 -> 0.009113278 | F64: =LN(D64/D63) -> -0.0079210138 | G64: =_xlfn.STDEV.P(F42:F63) -> 0.020277304 | H64: =G64*SQRT(252) -> 0.32189222
C65: 45604 | D65: =D45 -> 109.73 | E65: =(C66-C65)/D66 -> 0.027349804 | F65: =LN(D65/D64) -> 0.003011913 | G65: =_xlfn.STDEV.P(F43:F64) -> 0.020355694 | H65: =G65*SQRT(252) -> 0.32313663
C66: 45607 | D66: =D46 -> 109.69 | E66: =(C67-C66)/D67 -> 0.0089661974 | F66: =LN(D66/D65) -> -0.00036459758 | G66: =_xlfn.STDEV.P(F44:F65) -> 0.020080314 | H66: =G66*SQRT(252) -> 0.3187651
C67: 45608 | D67: =D47 -> 111.53 | E67: =(C68-C67)/D68 -> 0.0090563304 | F67: =LN(D67/D66) -> 0.016635408 | G67: =_xlfn.STDEV.P(F45:F66) -> 0.020010208 | H67: =G67*SQRT(252) -> 0.31765221
C68: 45609 | D68: =D48 -> 110.42 | E68: =(C69-C68)/D69 -> 0.0091116173 | F68: =LN(D68/D67) -> -0.010002336 | G68: =_xlfn.STDEV.P(F46:F67) -> 0.020298831 | H68: =G68*SQRT(252) -> 0.32223395
C69: 45610 | D69: =D49 -> 109.75 | E69: =(C70-C69)/D70 -> 0.009199632 | F69: =LN(D69/D68) -> -0.0060862249 | G69: =_xlfn.STDEV.P(F47:F68) -> 0.020421561 | H69: =G69*SQRT(252) -> 0.32418223
C70: 45611 | D70: =D50 -> 108.7 | E70: 0 | F70: =LN(D70/D69) -> -0.0096132578 | G70: =_xlfn.STDEV.P(F48:F69) -> 0.020142022 | H70: =G70*SQRT(252) -> 0.31974468

Sheet Q3. Delta Hedging (2)
B4: Delta Hedging(Using Implied Volatality)
B7: Date | C7: Option Symbol | D7: SPOT Price | E7: Daily Log Retruns | F7: STRIKE Price | G7: Closing Price | H7: Bid | I7: Ask | J7: Risk Free Interest Rate | K7: Underlying Dividend Rate | L7: Time to Maturity (10 Days) | M7: Mid Price | N7: BSM d1 | O7: BSM d2 | P7: Trading Volume | Q7: Model Implied Volatality (Calculated) | R7: Theortical Call Price (Black-Scholes) | S7: Market Implied Volatility | T7: Pricing Error | U7: Delta | V7: Delta change | W7: ∆ Spot Price | X7: Stocks to Buy | Y7: P&L | Z7: Cummultive P&L | AA7: Option Payoff | AB7: Options Payoff (No Hedging) | AC7: Net Off (Hedging)
B8: ='Bloomberg Raw Data- all volumes'!A87 -> 45601 | C8: ='Bloomberg Raw Data- all volumes'!C87 -> MRK 11/15/24 C102 | D8: ='Bloomberg Raw Data- all volumes'!I87 -> 101.65 | E8: =LN(D8/D61) -> -0.0021619505 | F8: ='Bloomberg Raw Data- all volumes'!B87 -> 102 | G8: ='Bloomberg Raw Data- all volumes'!F87 -> 1.6900005 | H8: ='Bloomberg Raw Data- all volumes'!D87 -> 1.5999994 | I8: ='Bloomberg Raw Data- all volumes'!E87 -> 1.6599998 | J8: ='Q1-(Without Zero Volume)'!J4 -> 0.046975 | K8: 0.0311 | L8: =8/252 -> 0.031746032 | M8: =(H8+I8)/2 -> 1.6299996 | N8: =(LN(D8/F8) + ((J8+ (Q8^2) / 2)*L8) / (Q8*SQRT(L8))) -> 0.052843403 | O8: =N8 - Q8*SQRT(L8) -> 0.010163273 | P8: 100 | Q8: 0.23954164 | R8: =D8*_xlfn.NORM.S.DIST(N8,TRUE) - F8*EXP(-J8*L8)*_xlfn.NORM.S.DIST(O8,TRUE) -> 1.6299907 | S8: ='Bloomberg Raw Data- all volumes'!G87 -> 0.25288134 | T8: =M8-R8 -> 8.9388352e-06 | U8: =_xlfn.NORM.S.DIST(N8,TRUE) -> 0.52107166 | V8: 0 | W8: =D8-D61 -> -0.22 | X8: =U8*P8 -> 52.107166 | Y8: =X8*W8 -> -11.463577 | Z8: =Y8 -> -11.463577 | AB8: =F8-D8 -> 0.35 | AC8: =AB8+Y8 -> -11.113577
B9: ='Bloomberg Raw Data- all volumes'!A88 -> 45602 | C9: ='Bloomberg Raw Data- all volumes'!C88 -> MRK 11/15/24 C102 | D9: ='Bloomberg Raw Data- all volumes'!I88 -> 100.73 | E9: =LN(D9/D62) -> -0.0090918701 | F9: ='Bloomberg Raw Data- all volumes'!B88 -> 102 | G9: ='Bloomberg Raw Data- all volumes'!F88 -> 0.87 | H9: ='Bloomberg Raw Data- all volumes'!D88 -> 0.73000002 | I9: ='Bloomberg Raw Data- all volumes'!E88 -> 0.91000003 | J9: ='Q1-(Without Zero Volume)'!J5 -> 0.046975 | K9: 0.0311 | L9: =7/252 -> 0.027777778 | M9: =(H9+I9)/2 -> 0.82000002 | N9: =(LN(D9/F9) + ((J9+ (Q9^2) / 2)*L9) / (Q9*SQRT(L9))) -> 0.042453601 | O9: =N9 - Q9*SQRT(L9) -> 0.0078026044 | P9: 100 | Q9: 0.20790598 | R9: =D9*_xlfn.NORM.S.DIST(N9,TRUE) - F9*EXP(-J9*L9)*_xlfn.NORM.S.DIST(O9,TRUE) -> 0.8199223 | S9: ='Bloomberg Raw Data- all volumes'!G88 -> 0.17977623 | T9: =M9-R9 -> 7.7721808e-05 | U9: =_xlfn.NORM.S.DIST(N9,TRUE) -> 0.51693145 | V9: =U9-U8 -> -0.0041402102 | W9: =D9-D8 -> -0.92 | X9: =U9*P9 -> 51.693145 | Y9: =X9*W9 -> -47.557693 | Z9: =Y9+Z8 -> -59.02127 | AB9: =F9-D9 -> 1.27 | AC9: =AB9+Y9 -> -46.287693
B10: ='Bloomberg Raw Data- all volumes'!A89 -> 45603 | C10: ='Bloomberg Raw Data- all volumes'!C89 -> MRK 11/15/24 C102 | D10: ='Bloomberg Raw Data- all volumes'!I89 -> 101.17 | E10: =LN(D10/D63) -> -0.086129634 | F10: ='Bloomberg Raw Data- all volumes'!B89 -> 102 | G10: ='Bloomberg Raw Data- all volumes'!F89 -> 0.93000001 | H10: ='Bloomberg Raw Data- all volumes'!D89 -> 0.88 | I10: ='Bloomberg Raw Data- all volumes'!E89 -> 1.5 | J10: ='Q1-(Without Zero Volume)'!J6 -> 0.046975 | K10: 0.0311 | L10: =6/252 -> 0.023809524 | M10: =(H10+I10)/2 -> 1.19 | N10: =(LN(D10/F10) + ((J10+ (Q10^2) / 2)*L10) / (Q10*SQRT(L10))) -> 0.042277965 | O10: =N10 - Q10*SQRT(L10) -> 0.0093835802 | P10: 100 | Q10: 0.21317998 | R10: =D10*_xlfn.NORM.S.DIST(N10,TRUE) - F10*EXP(-J10*L10)*_xlfn.NORM.S.DIST(O10,TRUE) -> 0.96647627 | S10: ='Bloomberg Raw Data- all volumes'!G89 -> 0.23807673 | T10: =M10-R10 -> 0.22352373 | U10: =_xlfn.NORM.S.DIST(N10,TRUE) -> 0.51686144 | V10: =U10-U9 -> -7.000567e-05 | W10: =D10-D9 -> 0.44 | X10: =U10*P10 -> 51.686144 | Y10: =X10*W10 -> 22.741904 | Z10: =Z9+Y10 -> -36.279366 | AB10: =F10-D10 -> 0.83 | AC10: =AB10+Y10 -> 23.571904
B11: ='Bloomberg Raw Data- all volumes'!A90 -> 45604 | C11: ='Bloomberg Raw Data- all volumes'!C90 -> MRK 11/15/24 C102 | D11: ='Bloomberg Raw Data- all volumes'!I90 -> 102.92 | E11: =LN(D11/D64) -> -0.061058903 | F11: ='Bloomberg Raw Data- all volumes'!B90 -> 102 | G11: ='Bloomberg Raw Data- all volumes'!F90 -> 1.6999998 | H11: ='Bloomberg Raw Data- all volumes'!D90 -> 1.5799999 | I11: ='Bloomberg Raw Data- all volumes'!E90 -> 2.1400003 | J11: ='Q1-(Without Zero Volume)'!J7 -> 0.046975 | K11: 0.0311 | L11: =5/252 -> 0.01984127 | M11: =(H11+I11)/2 -> 1.8600001 | N11: =(LN(D11/F11) + ((J11+ (Q11^2) / 2)*L11) / (Q11*SQRT(L11))) -> 0.056848346 | O11: =N11 - Q11*SQRT(L11) -> 0.029652112 | P11: 100 | Q11: 0.19307411 | R11: =D11*_xlfn.NORM.S.DIST(N11,TRUE) - F11*EXP(-J11*L11)*_xlfn.NORM.S.DIST(O11,TRUE) -> 1.6350933 | S11: ='Bloomberg Raw Data- all volumes'!G90 -> 0.22628731 | T11: =M11-R11 -> 0.22490683 | U11: =_xlfn.NORM.S.DIST(N11,TRUE) -> 0.522667 | V11: =U11-U10 -> 0.0058055546 | W11: =D11-D10 -> 1.75 | X11: =U11*P11 -> 52.2667 | Y11: =X11*W11 -> 91.466725 | Z11: =Z10+Y11 -> 55.187358 | AB11: =F11-D11 -> -0.92 | AC11: =AB11+Y11 -> 90.546725
B12: ='Bloomberg Raw Data- all volumes'!A93 -> 45607 | C12: ='Bloomberg Raw Data- all volumes'!C93 -> MRK 11/15/24 C102 | D12: ='Bloomberg Raw Data- all volumes'!I93 -> 100.73 | E12: =LN(D12/D67) -> -0.10184994 | F12: ='Bloomberg Raw Data- all volumes'!B93 -> 102 | G12: ='Bloomberg Raw Data- all volumes'!F93 -> 0.41000003 | H12: ='Bloomberg Raw Data- all volumes'!D93 -> 0.34000003 | I12: ='Bloomberg Raw Data- all volumes'!E93 -> 0.56999999 | J12: ='Q1-(Without Zero Volume)'!J10 -> 0.046975 | K12: 0.0311 | L12: =4/252 -> 0.015873016 | M12: =(H12+I12)/2 -> 0.45500001 | N12: =(LN(D12/F12) + ((J12+ (Q12^2) / 2)*L12) / (Q12*SQRT(L12))) -> 0.029021556 | O12: =N12 - Q12*SQRT(L12) -> 0.0028067876 | P12: 100 | Q12: 0.20807327 | R12: =D12*_xlfn.NORM.S.DIST(N12,TRUE) - F12*EXP(-J12*L12)*_xlfn.NORM.S.DIST(O12,TRUE) -> 0.45496514 | S12: ='Bloomberg Raw Data- all volumes'!G91 -> 0.22628731 | T12: =M12-R12 -> 3.4874283e-05 | U12: =_xlfn.NORM.S.DIST(N12,TRUE) -> 0.5115763 | V12: =U12-U11 -> -0.011090699 | W12: =D12-D11 -> -2.19 | X12: =U12*P12 -> 51.15763 | Y12: =X12*W12 -> -112.03521 | Z12: =Z11+Y12 -> -56.847851 | AB12: =F12-D12 -> 1.27 | AC12: =AB12+Y12 -> -110.76521
B13: ='Bloomberg Raw Data- all volumes'!A94 -> 45608 | C13: ='Bloomberg Raw Data- all volumes'!C94 -> MRK 11/15/24 C102 | D13: ='Bloomberg Raw Data- all volumes'!I94 -> 98.58 | E13: =LN(D13/D68) -> -0.11342288 | F13: ='Bloomberg Raw Data- all volumes'!B94 -> 102 | G13: ='Bloomberg Raw Data- all volumes'!F94 -> 0.079999983 | H13: ='Bloomberg Raw Data- all volumes'!D94 -> 0.079999983 | I13: ='Bloomberg Raw Data- all volumes'!E94 -> 0.11000001 | J13: ='Q1-(Without Zero Volume)'!J11 -> 0.046975 | K13: 0.0311 | L13: =3/252 -> 0.011904762 | M13: =(H13+I13)/2 -> 0.094999999 | N13: =(LN(D13/F13) + ((J13+ (Q13^2) / 2)*L13) / (Q13*SQRT(L13))) -> 0.00054510034 | O13: =N13 - Q13*SQRT(L13) -> -0.043167321 | P13: 100 | Q13: 0.40063096 | R13: =D13*_xlfn.NORM.S.DIST(N13,TRUE) - F13*EXP(-J13*L13)*_xlfn.NORM.S.DIST(O13,TRUE) -> 0.094992495 | S13: ='Bloomberg Raw Data- all volumes'!G92 -> 0.22628731 | T13: =M13-R13 -> 7.5040716e-06 | U13: =_xlfn.NORM.S.DIST(N13,TRUE) -> 0.50021746 | V13: =U13-U12 -> -0.011358837 | W13: =D13-D12 -> -2.15 | X13: =U13*P13 -> 50.021746 | Y13: =X13*W13 -> -107.54675 | Z13: =Z12+Y13 -> -164.39461 | AB13: =F13-D13 -> 3.42 | AC13: =AB13+Y13 -> -104.12675
B14: ='Bloomberg Raw Data- all volumes'!A95 -> 45609 | C14: ='Bloomberg Raw Data- all volumes'!C95 -> MRK 11/15/24 C102 | D14: ='Bloomberg Raw Data- all volumes'!I95 -> 98.5 | E14: =LN(D14/D69) -> -0.1081485 | F14: ='Bloomberg Raw Data- all volumes'!B95 -> 102 | G14: ='Bloomberg Raw Data- all volumes'!F95 -> 0.050000001 | H14: ='Bloomberg Raw Data- all volumes'!D95 -> 0.030000001 | I14: ='Bloomberg Raw Data- all volumes'!E95 -> 0.050000001 | J14: ='Q1-(Without Zero Volume)'!J12 -> 0.046975 | K14: 0.0311 | L14: =2/252 -> 0.0079365079 | M14: =(H14+I14)/2 -> 0.040000001 | N14: =(LN(D14/F14) + ((J14+ (Q14^2) / 2)*L14) / (Q14*SQRT(L14))) -> -0.0046290502 | O14: =N14 - Q14*SQRT(L14) -> -0.048018954 | P14: 100 | Q14: 0.48705047 | R14: =D14*_xlfn.NORM.S.DIST(N14,TRUE) - F14*EXP(-J14*L14)*_xlfn.NORM.S.DIST(O14,TRUE) -> 0.039622461 | S14: ='Bloomberg Raw Data- all volumes'!G93 -> 0.19944824 | T14: =M14-R14 -> 0.00037753975 | U14: =_xlfn.NORM.S.DIST(N14,TRUE) -> 0.49815328 | V14: =U14-U13 -> -0.0020641808 | W14: =D14-D13 -> -0.08 | X14: =U14*P14 -> 49.815328 | Y14: =X14*W14 -> -3.9852263 | Z14: =Z13+Y14 -> -168.37983 | AB14: =F14-D14 -> 3.5 | AC14: =AB14+Y14 -> -0.48522626
B15: ='Bloomberg Raw Data- all volumes'!A96 -> 45610 | C15: ='Bloomberg Raw Data- all volumes'!C96 -> MRK 11/15/24 C102 | D15: ='Bloomberg Raw Data- all volumes'!I96 -> 98.36 | E15: =LN(D15/D70) -> -0.099957577 | F15: ='Bloomberg Raw Data- all volumes'!B96 -> 102 | G15: ='Bloomberg Raw Data- all volumes'!F96 -> 0.02 | H15: ='Bloomberg Raw Data- all volumes'!D96 -> 0.0099999998 | I15: ='Bloomberg Raw Data- all volumes'!E96 -> 0.039999999 | J15: ='Q1-(Without Zero Volume)'!J13 -> 0.046975 | K15: 0.0311 | L15: =1/252 -> 0.003968254 | M15: =(H15+I15)/2 -> 0.024999999 | N15: =(LN(D15/F15) + ((J15+ (Q15^2) / 2)*L15) / (Q15*SQRT(L15))) -> -0.0097797627 | O15: =N15 - Q15*SQRT(L15) -> -0.054574664 | P15: 100 | Q15: 0.71109701 | R15: =D15*_xlfn.NORM.S.DIST(N15,TRUE) - F15*EXP(-J15*L15)*_xlfn.NORM.S.DIST(O15,TRUE) -> 0.024997296 | S15: ='Bloomberg Raw Data- all volumes'!G94 -> 0.2110037 | T15: =M15-R15 -> 2.7036729e-06 | U15: =_xlfn.NORM.S.DIST(N15,TRUE) -> 0.4960985 | V15: =U15-U14 -> -0.0020547814 | W15: =D15-D14 -> -0.14 | X15: =U15*P15 -> 49.60985 | Y15: =X15*W15 -> -6.945379 | Z15: =Z14+Y15 -> -175.32521 | AA15: =MAX(D15-F15,0) -> 0 | AB15: =F15-D15 -> 3.64 | AC15: =AB15+Y15 -> -3.305379
B16: ='Bloomberg Raw Data- all volumes'!A97 -> 45611 | C16: ='Bloomberg Raw Data- all volumes'!C97 -> MRK 11/15/24 C102 | D16: ='Bloomberg Raw Data- all volumes'!I97 -> 96.31 | E16: 0 | F16: ='Bloomberg Raw Data- all volumes'!B97 -> 102 | G16: ='Bloomberg Raw Data- all volumes'!F97 -> 0.010000002 | H16: ='Bloomberg Raw Data- all volumes'!D97 -> 0 | I16: ='Bloomberg Raw Data- all volumes'!E97 -> 0.010000002 | J16: ='Q1-(Without Zero Volume)'!J14 -> 0.046975 | K16: 0.0311 | L16: =0/252 -> 0 | M16: =(H16+I16)/2 -> 0.0050000008 | N16: =(LN(D16/F16) + ((J16+ (Q16^2) / 2)*L16) / (Q16*SQRT(L16))) -> #DIV/0! | O16: =N16 - Q16*SQRT(L16) -> #DIV/0! | P16: 100 | Q16: 0.33714516 | R16: =D16*_xlfn.NORM.S.DIST(N16,TRUE) - F16*EXP(-J16*L16)*_xlfn.NORM.S.DIST(O16,TRUE) -> #DIV/0! | S16: ='Bloomberg Raw Data- all volumes'!G95 -> 0.2314974 | T16: =M16-R16 -> #DIV/0! | U16: =_xlfn.NORM.S.DIST(N16,TRUE) -> #DIV/0! | V16: =U16-U15 -> #DIV/0! | W16: =D16-D15 -> -2.05 | X16: =U16*P16 -> #DIV/0! | Y16: =X16*W16 -> #DIV/0! | Z16: =Z15+Y16 -> #DIV/0! | AB16: =F16-D16 -> 5.69 | AC16: =AB16+Y16 -> #DIV/0!
B20: Delta Hedging(Using Historical Volatality)
B23: Date | C23: Option Symbol | D23: SPOT Price | E23: Daily Log Retruns | F23: STRIKE Price | G23: Closing Price | H23: Bid | I23: Ask | J23: Risk Free Interest Rate | K23: Underlying Dividend Rate | L23: Time to Maturity (10 Days) | M23: Mid Price | N23: BSM d1 | O23: BSM d2 | P23: Trading Volume | Q23: Historical Volatility | R23: Theortical Call Price (Black-Scholes) | S23: Market Implied Volatility | T23: Pricing Error | U23: Delta | V23: Delta change | W23: ∆ Spot Price | X23: Stocks to Buy | Y23: P&L | Z23: Cummultive P&L | AA23: Option Payoff | AB23: Options Payoff (No Hedging) | AC23: Net Off (Hedging)
B24: =B8 -> 45601 | C24: =C8 -> MRK 11/15/24 C102 | D24: =D8 -> 101.65 | E24: =E8 -> -0.0021619505 | F24: =F8 -> 102 | G24: =G8 -> 1.6900005 | H24: =H8 -> 1.5999994 | I24: =I8 -> 1.6599998 | ... L24: =L8 -> 0.031746032 | M24: =(H24+I24)/2 -> 1.6299996 | N24: =(LN(D24/F24) + ((J24+ (Q24^2) / 2)*L24) / (Q24*SQRT(L24))) -> 0.061918075 | O24: =N24-Q24*SQRT(L24) -> 0.032462336 | P24: 100 | Q24: ='Historical Prices'!F24 -> 0.16531993 | R24: =D24*_xlfn.NORM.S.DIST(N24,TRUE) - F24*EXP(-J24*L24)*_xlfn.NORM.S.DIST(O24,TRUE) -> 1.0915653 | S24: 0.31934274 | T24: =M24-R24 -> 0.53843432 | U24: =_xlfn.NORM.S.DIST(N24,TRUE) -> 0.52468596 | V24: 0 | W24: =D24-D61 -> -0.22 | X24: =U24*P24 -> 52.468596 | Y24: =X24*W24 -> -11.543091 | Z24: =Y24 -> -11.543091 | AB24: =F24-D24 -> 0.35 | AC24: =AB24+Y24 -> -11.193091
B25: =B9 -> 45602 | C25: =C9 -> MRK 11/15/24 C102 | D25: =D9 -> 100.73 | E25: =E9 -> -0.0090918701 | F25: =F9 -> 102 | G25: =G9 -> 0.87 | H25: =H9 -> 0.73000002 | I25: =I9 -> 0.91000003 | ... L25: =L9 -> 0.027777778 | M25: =(H25+I25)/2 -> 0.82000002 | N25: =(LN(D25/F25) + ((J25+ (Q25^2) / 2)*L25) / (Q25*SQRT(L25))) -> 0.04938863 | O25: =N25-Q25*SQRT(L25) -> 0.022457832 | P25: 100 | Q25: ='Historical Prices'!F25 -> 0.16158479 | R25: =D25*_xlfn.NORM.S.DIST(N25,TRUE) - F25*EXP(-J25*L25)*_xlfn.NORM.S.DIST(O25,TRUE) -> 0.50281434 | S25: 0.29785858 | T25: =M25-R25 -> 0.31718569 | U25: =_xlfn.NORM.S.DIST(N25,TRUE) -> 0.51969521 | V25: =U25-U24 -> -0.0049907581 | W25: =D25-D62 -> -0.92 | X25: =U25*P25 -> 51.969521 | Y25: =X25*W25 -> -47.811959 | Z25: =Y25+Z24 -> -59.35505 | AB25: =F25-D25 -> 1.27 | AC25: =AB25+Y25 -> -46.541959
B26: =B10 -> 45603 | C26: =C10 -> MRK 11/15/24 C102 | D26: =D10 -> 101.17 | E26: =E10 -> -0.086129634 | F26: =F10 -> 102 | G26: =G10 -> 0.93000001 | H26: =H10 -> 0.88 | I26: =I10 -> 1.5 | ... L26: =L10 -> 0.023809524 | M26: =(H26+I26)/2 -> 1.19 | N26: =(LN(D26/F26) + ((J26+ (Q26^2) / 2)*L26) / (Q26*SQRT(L26))) -> 0.049314053 | O26: =N26-Q26*SQRT(L26) -> 0.024503209 | P26: 100 | Q26: ='Historical Prices'!F26 -> 0.16079265 | R26: =D26*_xlfn.NORM.S.DIST(N26,TRUE) - F26*EXP(-J26*L26)*_xlfn.NORM.S.DIST(O26,TRUE) -> 0.63569369 | S26: 0.29248754 | T26: =M26-R26 -> 0.55430631 | U26: =_xlfn.NORM.S.DIST(N26,TRUE) -> 0.51966549 | V26: =U26-U25 -> -2.9715468e-05 | W26: =D26-D63 -> -9.1 | X26: =U26*P26 -> 51.966549 | Y26: =X26*W26 -> -472.8956 | Z26: =Y26+Z25 -> -532.25065 | AB26: =F26-D26 -> 0.83 | AC26: =AB26+Y26 -> -472.0656
B27: =B11 -> 45604 | C27: =C11 -> MRK 11/15/24 C102 | D27: =D11 -> 102.92 | E27: =E11 -> -0.061058903 | F27: =F11 -> 102 | G27: =G11 -> 1.6999998 | H27: =H11 -> 1.5799999 | I27: =I11 -> 2.1400003 | ... L27: =L11 -> 0.01984127 | M27: =(H27+I27)/2 -> 1.8600001 | N27: =(LN(D27/F27) + ((J27+ (Q27^2) / 2)*L27) / (Q27*SQRT(L27))) -> 0.061121313 | O27: =N27-Q27*SQRT(L27) -> 0.038214689 | P27: 100 | Q27: ='Historical Prices'!F27 -> 0.1626209 | R27: =D27*_xlfn.NORM.S.DIST(N27,TRUE) - F27*EXP(-J27*L27)*_xlfn.NORM.S.DIST(O27,TRUE) -> 1.4623292 | S27: 0.29102271 | T27: =M27-R27 -> 0.39767092 | U27: =_xlfn.NORM.S.DIST(N27,TRUE) -> 0.5243687 | V27: =U27-U26 -> 0.0047032122 | W27: =D27-D64 -> -6.48 | X27: =U27*P27 -> 52.43687 | Y27: =X27*W27 -> -339.79092 | Z27: =Y27+Z26 -> -872.04156 | AB27: =F27-D27 -> -0.92 | AC27: =AB27+Y27 -> -340.71092
B28: =B12 -> 45607 | C28: =C12 -> MRK 11/15/24 C102 | D28: =D12 -> 100.73 | E28: =E12 -> -0.10184994 | F28: =F12 -> 102 | G28: =G12 -> 0.41000003 | H28: =H12 -> 0.34000003 | I28: =I12 -> 0.56999999 | ... L28: =L12 -> 0.015873016 | M28: =(H28+I28)/2 -> 0.45500001 | N28: =(LN(D28/F28) + ((J28+ (Q28^2) / 2)*L28) / (Q28*SQRT(L28))) -> 0.033855356 | O28: =N28-Q28*SQRT(L28) -> 0.013166225 | P28: 100 | Q28: ='Historical Prices'!F28 -> 0.16421489 | R28: =D28*_xlfn.NORM.S.DIST(N28,TRUE) - F28*EXP(-J28*L28)*_xlfn.NORM.S.DIST(O28,TRUE) -> 0.22789957 | S28: 0.29004616 | T28: =M28-R28 -> 0.22710044 | U28: =_xlfn.NORM.S.DIST(N28,TRUE) -> 0.51350375 | V28: =U28-U27 -> -0.010864949 | W28: =D28-D65 -> -9 | X28: =U28*P28 -> 51.350375 | Y28: =X28*W28 -> -462.15338 | Z28: =Y28+Z27 -> -1334.1949 | AB28: =F28-D28 -> 1.27 | AC28: =AB28+Y28 -> -460.88338
B29: =B13 -> 45608 | C29: =C13 -> MRK 11/15/24 C102 | D29: =D13 -> 98.58 | E29: =E13 -> -0.11342288 | F29: =F13 -> 102 | G29: =G13 -> 0.079999983 | H29: =H13 -> 0.079999983 | I29: =I13 -> 0.11000001 | ... L29: =L13 -> 0.011904762 | M29: =(H29+I29)/2 -> 0.094999999 | N29: =(LN(D29/F29) + ((J29+ (Q29^2) / 2)*L29) / (Q29*SQRT(L29))) -> 0.0047792569 | O29: =N29-Q29*SQRT(L29) -> -0.014267897 | P29: 100 | Q29: ='Historical Prices'!F29 -> 0.17457005 | R29: =D29*_xlfn.NORM.S.DIST(N29,TRUE) - F29*EXP(-J29*L29)*_xlfn.NORM.S.DIST(O29,TRUE) -> -0.91328423 | S29: 0.29077858 | T29: =M29-R29 -> 1.0082842 | U29: =_xlfn.NORM.S.DIST(N29,TRUE) -> 0.50190664 | V29: =U29-U28 -> -0.011597113 | W29: =D29-D66 -> -11.11 | X29: =U29*P29 -> 50.190664 | Y29: =X29*W29 -> -557.61828 | Z29: =Y29+Z28 -> -1891.8132 | AB29: =F29-D29 -> 3.42 | AC29: =AB29+Y29 -> -554.19828
B30: =B14 -> 45609 | C30: =C14 -> MRK 11/15/24 C102 | D30: =D14 -> 98.5 | E30: =E14 -> -0.1081485 | F30: =F14 -> 102 | G30: =G14 -> 0.050000001 | H30: =H14 -> 0.030000001 | I30: =I14 -> 0.050000001 | ... L30: =L14 -> 0.0079365079 | M30: =(H30+I30)/2 -> 0.040000001 | N30: =(LN(D30/F30) + ((J30+ (Q30^2) / 2)*L30) / (Q30*SQRT(L30))) -> -0.0038491374 | O30: =N30-Q30*SQRT(L30) -> -0.020099669 | P30: 100 | Q30: ='Historical Prices'!F30 -> 0.18241177 | R30: =D30*_xlfn.NORM.S.DIST(N30,TRUE) - F30*EXP(-J30*L30)*_xlfn.NORM.S.DIST(O30,TRUE) -> -1.0647064 | S30: 0.30396204 | T30: =M30-R30 -> 1.1047064 | U30: =_xlfn.NORM.S.DIST(N30,TRUE) -> 0.49846442 | V30: =U30-U29 -> -0.0034422202 | W30: =D30-D67 -> -13.03 | X30: =U30*P30 -> 49.846442 | Y30: =X30*W30 -> -649.49914 | Z30: =Y30+Z29 -> -2541.3124 | AB30: =F30-D30 -> 3.5 | AC30: =AB30+Y30 -> -645.99914
B31: =B15 -> 45610 | C31: =C15 -> MRK 11/15/24 C102 | D31: =D15 -> 98.36 | E31: =E15 -> -0.099957577 | F31: =F15 -> 102 | G31: =G15 -> 0.02 | H31: =H15 -> 0.0099999998 | I31: =I15 -> 0.039999999 | ... L31: =L15 -> 0.003968254 | M31: =(H31+I31)/2 -> 0.024999999 | N31: =(LN(D31/F31) + ((J31+ (Q31^2) / 2)*L31) / (Q31*SQRT(L31))) -> -0.014363885 | O31: =N31-Q31*SQRT(L31) -> -0.02584715 | P31: 100 | Q31: ='Historical Prices'!F31 -> 0.18229117 | R31: =D31*_xlfn.NORM.S.DIST(N31,TRUE) - F31*EXP(-J31*L31)*_xlfn.NORM.S.DIST(O31,TRUE) -> -1.322651 | S31: 0.30127652 | T31: =M31-R31 -> 1.347651 | U31: =_xlfn.NORM.S.DIST(N31,TRUE) -> 0.49426984 | V31: =U31-U30 -> -0.0041945843 | W31: =D31-D68 -> -12.06 | X31: =U31*P31 -> 49.426984 | Y31: =X31*W31 -> -596.08942 | Z31: =Y31+Z30 -> -3137.4018 | AA31: =MAX(D31-F31,0) -> 0 | AB31: =F31-D31 -> 3.64 | AC31: =AB31+Y31 -> -592.44942
B32: =B16 -> 45611 | C32: =C16 -> MRK 11/15/24 C102 | D32: =D16 -> 96.31 | E32: =E16 -> 0 | F32: =F16 -> 102 | G32: =G16 -> 0.010000002 | H32: =H16 -> 0 | I32: =I16 -> 0.010000002 | ... L32: =L16 -> 0 | M32: =(H32+I32)/2 -> 0.0050000008 | N32: =(LN(D32/F32) + ((J32+ (Q32^2) / 2)*L32) / (Q32*SQRT(L32))) -> #DIV/0! | O32: =N32-Q32*SQRT(L32) -> #DIV/0! | P32: 100 | Q32: ='Historical Prices'!F32 -> 0.16700371 | R32: =D32*_xlfn.NORM.S.DIST(N32,TRUE) - F32*EXP(-J32*L32)*_xlfn.NORM.S.DIST(O32,TRUE) -> #DIV/0! | S32: 0.32178413 | T32: =M32-R32 -> #DIV/0! | U32: =_xlfn.NORM.S.DIST(N32,TRUE) -> #DIV/0! | V32: =U32-U31 -> #DIV/0! | W32: =D32-D69 -> -13.44 | X32: =U32*P32 -> #DIV/0! | Y32: =X32*W32 -> #DIV/0! | Z32: =Y32+Z31 -> #DIV/0! | AB32: =F32-D32 -> 5.69 | AC32: =AB32+Y32 -> #DIV/0!
B37: Historical Stock Price : October 15 - November 15 (2024)
C39: Date | D39: Stock Price | E39: Daily Return | F39: Log returns | G39: Standard Deviation | H39: Annualised Standard Deviation
C40: 45569 | D40: 109.77 | E40: =(C41-C40)/D41 -> 0.027626853 | I40: (TBD)
C41: 45572 | D41: 108.59 | E41: =(C42-C41)/D42 -> 0.0092148913 | F41: =LN(D41/D40) -> -0.010807945
C42: 45573 | D42: 108.52 | E42: =(C43-C42)/D43 -> 0.0090686497 | F42: =LN(D42/D41) -> -0.00064483444
C43: 45574 | D43: 110.27 | E43: =(C44-C43)/D44 -> 0.0091407678 | F43: =LN(D43/D42) -> 0.015997416
C44: 45575 | D44: 109.4 | E44: =(C45-C44)/D45 -> 0.009113278 | F44: =LN(D44/D43) -> -0.0079210138
C45: 45576 | D45: 109.73 | E45: =(C46-C45)/D46 -> 0.027349804 | F45: =LN(D45/D44) -> 0.003011913
C46: 45579 | D46: 109.69 | E46: =(C47-C46)/D47 -> 0.0089661974 | F46: =LN(D46/D45) -> -0.00036459758
C47: 45580 | D47: 111.53 | E47: =(C48-C47)/D48 -> 0.0090563304 | F47: =LN(D47/D46) -> 0.016635408
C48: 45581 | D48: 110.42 | E48: =(C49-C48)/D49 -> 0.0091116173 | F48: =LN(D48/D47) -> -0.010002336
C49: 45582 | D49: 109.75 | E49: =(C50-C49)/D50 -> 0.009199632 | F49: =LN(D49/D48) -> -0.0060862249
C50: 45583 | D50: 108.7 | E50: =(C51-C50)/D51 -> 0.028211397 | F50: =LN(D50/D49) -> -0.0096132578
C51: 45586 | D51: 106.34 | E51: =(C52-C51)/D52 -> 0.0093773443 | F51: =LN(D51/D50) -> -0.021950286
C52: 45587 | D52: 106.64 | E52: =(C53-C52)/D53 -> 0.0094002632 | F52: =LN(D52/D51) -> 0.0028171678
... C61: 45600 | D61: 101.87 | E61: =(C62-C61)/D62 -> 0.0098376783 | F61: =LN(D61/D60) -> -9.8159509e-05
C62: 45601 | D62: 101.65 | E62: =(C63-C62)/D63 -> 0.0090686497 | F62: =LN(D62/D61) -> -0.0021619505 | G62: =_xlfn.STDEV.P(F40:F61) -> 0.010414177 | H62: =G62*SQRT(252) -> 0.16531993
C63: 45602 | D63: =D43 -> 110.27 | E63: =(C64-C63)/D64 -> 0.0091407678 | F63: =LN(D63/D62) -> 0.081396364 | G63: =_xlfn.STDEV.P(F41:F62) -> 0.010178885 | H63: =G63*SQRT(252) -> 0.16158479
C64: 45603 | D64: =D44 -> 109.4 | E64: =(C65-C64)/D65 -> 0.009113278 | F64: =LN(D64/D63) -> -0.0079210138 | G64: =_xlfn.STDEV.P(F42:F63) -> 0.020277304 | H64: =G64*SQRT(252) -> 0.32189222
C65: 45604 | D65: =D45 -> 109.73 | E65: =(C66-C65)/D66 -> 0.027349804 | F65: =LN(D65/D64) -> 0.003011913 | G65: =_xlfn.STDEV.P(F43:F64) -> 0.020355694 | H65: =G65*SQRT(252) -> 0.32313663
C66: 45607 | D66: =D46 -> 109.69 | E66: =(C67-C66)/D67 -> 0.0089661974 | F66: =LN(D66/D65) -> -0.00036459758 | G66: =_xlfn.STDEV.P(F44:F65) -> 0.020080314 | H66: =G66*SQRT(252) -> 0.3187651
C67: 45608 | D67: =D47 -> 111.53 | E67: =(C68-C67)/D68 -> 0.0090563304 | F67: =LN(D67/D66) -> 0.016635408 | G67: =_xlfn.STDEV.P(F45:F66) -> 0.020010208 | H67: =G67*SQRT(252) -> 0.31765221
C68: 45609 | D68: =D48 -> 110.42 | E68: =(C69-C68)/D69 -> 0.0091116173 | F68: =LN(D68/D67) -> -0.010002336 | G68: =_xlfn.STDEV.P(F46:F67) -> 0.020298831 | H68: =G68*SQRT(252) -> 0.32223395
C69: 45610 | D69: =D49 -> 109.75 | E69: =(C70-C69)/D70 -> 0.009199632 | F69: =LN(D69/D68) -> -0.0060862249 | G69: =_xlfn.STDEV.P(F47:F68) -> 0.020421561 | H69: =G69*SQRT(252) -> 0.32418223
C70: 45611 | D70: =D50 -> 108.7 | E70: 0 | F70: =LN(D70/D69) -> -0.0096132578 | G70: =_xlfn.STDEV.P(F48:F69) -> 0.020142022 | H70: =G70*SQRT(252) -> 0.31974468

Sheet Q4. Volatility Trade
A2: Historical Stock Price : October 15 - November 15 (2024)
A4: Date | B4: Stock Price | C4: Daily Return | D4: Log returns | E4: Standard Deviation | F4: Annualised Standard Deviation | H4: Compare Volatilities
A5: 45569 | B5: 109.77 | C5: =(A6-A5)/B6 -> 0.027626853 | H5: Date | I5: Historical Volatility | J5: Call Implied Volatility | K5: Put Implied Volatility
A6: 45572 | B6: 108.59 | C6: =(A7-A6)/B7 -> 0.0092148913 | D6: =LN(B6/B5) -> -0.010807945 | H6: 45601 | I6: 0.31974488 | J6: 0.22467036 | K6: 0.25147383
A7: 45573 | B7: 108.52 | C7: =(A8-A7)/B8 -> 0.0090686497 | D7: =LN(B7/B6) -> -0.00064483444
A8: 45574 | B8: 110.27 | C8: =(A9-A8)/B9 -> 0.0091407678 | D8: =LN(B8/B7) -> 0.015997416
A9: 45575 | B9: 109.4 | C9: =(A10-A9)/B10 -> 0.009113278 | D9: =LN(B9/B8) -> -0.0079210138 | H9: Option Type | I9: Cost | J9: Break Even Point (Upper) | K9: Break Even Point (Lower) | L9: Maximum Loss
A10: 45576 | B10: 109.73 | C10: =(A11-A10)/B11 -> 0.027349804 | D10: =LN(B10/B9) -> 0.003011913 | H10: Call Option | I10: 1.63 | J10: =B45+I10 -> 103.63
A11: 45579 | B11: 109.69 | C11: =(A12-A11)/B12 -> 0.0089661974 | D11: =LN(B11/B10) -> -0.00036459758 | H11: Put Option | I11: 2.015 | K11: =B45-I11 -> 99.985
A12: 45580 | B12: 111.53 | C12: =(A13-A12)/B13 -> 0.0090563304 | D12: =LN(B12/B11) -> 0.016635408 | H12: Straddle Option | I12: =I10+I11 -> 3.645 | J12: =B45+I12 -> 105.645 | K12: =B45-I12 -> 98.355 | L12: =I12 -> 3.645
A13: 45581 | B13: 110.42 | C13: =(A14-A13)/B14 -> 0.0091116173 | D13: =LN(B13/B12) -> -0.010002336
A14: 45582 | B14: 109.75 | C14: =(A15-A14)/B15 -> 0.009199632 | D14: =LN(B14/B13) -> -0.0060862249
A15: 45583 | B15: 108.7 | C15: =(A16-A15)/B16 -> 0.028211397 | D15: =LN(B15/B14) -> -0.0096132578
A16: 45586 | B16: 106.34 | C16: =(A17-A16)/B17 -> 0.0093773443 | D16: =LN(B16/B15) -> -0.021950286
A17: 45587 | B17: 106.64 | C17: =(A18-A17)/B18 -> 0.0094002632 | D17: =LN(B17/B16) -> 0.0028171678
A18: 45588 | B18: 106.38 | C18: =(A19-A18)/B19 -> 0.0094446543 | D18: =LN(B18/B17) -> -0.0024410866
A19: 45589 | B19: 105.88 | C19: =(A20-A19)/B20 -> 0.0096172341 | D19: =LN(B19/B18) -> -0.004711212
A20: 45590 | B20: 103.98 | C20: =(A21-A20)/B21 -> 0.0287825 | D20: =LN(B20/B19) -> -0.018107804
A21: 45593 | B21: 104.23 | C21: =(A22-A21)/B22 -> 0.0096404126 | D21: =LN(B21/B20) -> 0.0024014228
A22: 45594 | B22: 103.73 | C22: =(A23-A22)/B23 -> 0.009539254 | D22: =LN(B22/B21) -> -0.0048086263
A23: 45595 | B23: 104.83 | C23: =(A24-A23)/B24 -> 0.0097732604 | D23: =LN(B23/B22) -> 0.010548621
A24: 45596 | B24: 102.32 | C24: =(A25-A24)/B25 -> 0.0098154692 | D24: =LN(B24/B23) -> -0.024234833
... A26: 45600 | B26: 101.87 | C26: =(A27-A26)/B27 -> 0.0098376783 | D26: =LN(B26/B25) -> -9.8159509e-05
A27: 45601 | B27: 101.65 | C27: =(A28-A27)/B28 -> 0.009927529 | D27: =LN(B27/B26) -> -0.0021619505 | E27: =_xlfn.STDEV.P(D5:D26) -> 0.010414177 | F27: =E27*SQRT(252) -> 0.16531993
A28: 45602 | B28: 100.73 | C28: =(A29-A28)/B29 -> 0.0098843531 | D28: =LN(B28/B27) -> -0.0090918701 | E28: =_xlfn.STDEV.P(D6:D27) -> 0.010178885 | F28: =E28*SQRT(252) -> 0.16158479
A29: 45603 | B29: 101.17 | C29: =(A30-A29)/B30 -> 0.0097162845 | D29: =LN(B29/B28) -> 0.0043586003 | E29: =_xlfn.STDEV.P(D7:D28) -> 0.010128985 | F29: =E29*SQRT(252) -> 0.16079265
A30: 45604 | B30: 102.92 | C30: =(A31-A30)/B31 -> 0.029782587 | D30: =LN(B30/B29) -> 0.017149717 | E30: =_xlfn.STDEV.P(D8:D29) -> 0.010244154 | F30: =E30*SQRT(252) -> 0.1626209
A31: 45607 | B31: 100.73 | C31: =(A32-A31)/B32 -> 0.010144045 | D31: =LN(B31/B30) -> -0.021508317 | E31: =_xlfn.STDEV.P(D9:D30) -> 0.010344566 | F31: =E31*SQRT(252) -> 0.16421489
A32: 45608 | B32: 98.58 | C32: =(A33-A32)/B33 -> 0.010152284 | D32: =LN(B32/B31) -> -0.021575269 | E32: =_xlfn.STDEV.P(D10:D31) -> 0.010996879 | F32: =E32*SQRT(252) -> 0.17457005
A33: 45609 | B33: 98.5 | C33: =(A34-A33)/B34 -> 0.010166734 | D33: =LN(B33/B32) -> -0.0008118531 | E33: =_xlfn.STDEV.P(D11:D32) -> 0.011490861 | F33: =E33*SQRT(252) -> 0.18241177
A34: 45610 | B34: 98.36 | C34: =(A35-A34)/B35 -> 0.010383138 | D34: =LN(B34/B33) -> -0.0014223308 | E34: =_xlfn.STDEV.P(D12:D33) -> 0.011483264 | F34: =E34*SQRT(252) -> 0.18229117
A35: 45611 | B35: 96.31 | C35: 0 | D35: =LN(B35/B34) -> -0.021062062 | E35: =_xlfn.STDEV.P(D13:D34) -> 0.010520245 | F35: =E35*SQRT(252) -> 0.16700371
A42: Long Straddle
A44: Stock Price on expiry | B44: 96.31
A45: ATM | B45: 102
A46: Call option | B46: 1.63
A47: Put Option | B47: 2.015
A48: Straddle Option | B48: =B46+B47 -> 3.645
A50: Payoff
A51: Stock price close | B51: Long call | C51: Long Put | D51: Long Straddle
A52: 82 | B52: =MAX(A52-$B$45, 0) -$B$46 -> -1.63 | C52: =MAX($B$45-A52,0)-$B$47 -> 17.985 | D52: =B52+C52 -> 16.355
A53: 83.5 | B53: =MAX(A53-$B$45, 0) -$B$46 -> -1.63 | C53: =MAX($B$45-A53,0)-$B$47 -> 16.485 | D53: =B53+C53 -> 14.855
A54: 85 | B54: =MAX(A54-$B$45, 0) -$B$46 -> -1.63 | C54: =MAX($B$45-A54,0)-$B$47 -> 14.985 | D54: =B54+C54 -> 13.355
A55: 86.5 | B55: =MAX(A55-$B$45, 0) -$B$46 -> -1.63 | C55: =MAX($B$45-A55,0)-$B$47 -> 13.485 | D55: =B55+C55 -> 11.855
A56: 88 | B56: =MAX(A56-$B$45, 0) -$B$46 -> -1.63 | C56: =MAX($B$45-A56,0)-$B$47 -> 11.985 | D56: =B56+C56 -> 10.355
A57: 89.5 | B57: =MAX(A57-$B$45, 0) -$B$46 -> -1.63 | C57: =MAX($B$45-A57,0)-$B$47 -> 10.485 | D57: =B57+C57 -> 8.855
A58: 91 | B58: =MAX(A58-$B$45, 0) -$B$46 -> -1.63 | C58: =MAX($B$45-A58,0)-$B$47 -> 8.985 | D58: =B58+C58 -> 7.355
A59: 92.5 | B59: =MAX(A59-$B$45, 0) -$B$46 -> -1.63 | C59: =MAX($B$45-A59,0)-$B$47 -> 7.485 | D59: =B59+C59 -> 5.855
A60: 94 | B60: =MAX(A60-$B$45, 0) -$B$46 -> -1.63 | C60: =MAX($B$45-A60,0)-$B$47 -> 5.985 | D60: =B60+C60 -> 4.355
A61: 95.5 | B61: =MAX(A61-$B$45, 0) -$B$46 -> -1.63 | C61: =MAX($B$45-A61,0)-$B$47 -> 4.485 | D61: =B61+C61 -> 2.855
A62: 97 | B62: =MAX(A62-$B$45, 0) -$B$46 -> -1.63 | C62: =MAX($B$45-A62,0)-$B$47 -> 2.985 | D62: =B62+C62 -> 1.355
A63: 98.5 | B63: =MAX(A63-$B$45, 0) -$B$46 -> -1.63 | C63: =MAX($B$45-A63,0)-$B$47 -> 1.485 | D63: =B63+C63 -> -0.145
... A78: 121 | B78: =MAX(A78-$B$45, 0) -$B$46 -> 17.37 | C78: =MAX($B$45-A78,0)-$B$47 -> -2.015 | D78: =B78+C78 -> 15.355
A81: Short Straddle
A83: Stock Price on expiry | B83: 96.31
A84: ATM | B84: 102
A85: Call option | B85: 1.63
A86: Put Option | B86: 2.355
A87: Straddle Option | B87: =B85+B86 -> 3.985
A89: Payoff
A90: Stock price close | B90: Short call | C90: Short Put | D90: Short Straddle
A91: 82 | B91: =-(MAX(A91-$B$84,0)-$B$85) -> 1.63 | C91: =-(MAX($B$84-A91, 0) - $B$86) -> -17.645 | D91: =B91+C91 -> -16.015
A92: 83.5 | B92: =-(MAX(A92-$B$84,0)-$B$85) -> 1.63 | C92: =-(MAX($B$84-A92, 0) - $B$86) -> -16.145 | D92: =B92+C92 -> -14.515
A93: 85 | B93: =-(MAX(A93-$B$84,0)-$B$85) -> 1.63 | C93: =-(MAX($B$84-A93, 0) - $B$86) -> -14.645 | D93: =B93+C93 -> -13.015
A94: 86.5 | B94: =-(MAX(A94-$B$84,0)-$B$85) -> 1.63 | C94: =-(MAX($B$84-A94, 0) - $B$86) -> -13.145 | D94: =B94+C94 -> -11.515
A95: 88 | B95: =-(MAX(A95-$B$84,0)-$B$85) -> 1.63 | C95: =-(MAX($B$84-A95, 0) - $B$86) -> -11.645 | D95: =B95+C95 -> -10.015
A96: 89.5 | B96: =-(MAX(A96-$B$84,0)-$B$85) -> 1.63 | C96: =-(MAX($B$84-A96, 0) - $B$86) -> -10.145 | D96: =B96+C96 -> -8.515
A97: 91 | B97: =-(MAX(A97-$B$84,0)-$B$85) -> 1.63 | C97: =-(MAX($B$84-A97, 0) - $B$86) -> -8.645 | D97: =B97+C97 -> -7.015
A98: 92.5 | B98: =-(MAX(A98-$B$84,0)-$B$85) -> 1.63 | C98: =-(MAX($B$84-A98, 0) - $B$86) -> -7.145 | D98: =B98+C98 -> -5.515
A99: 94 | B99: =-(MAX(A99-$B$84,0)-$B$85) -> 1.63 | C99: =-(MAX($B$84-A99, 0) - $B$86) -> -5.645 | D99: =B99+C99 -> -4.015
A100: 95.5 | B100: =-(MAX(A100-$B$84,0)-$B$85) -> 1.63 | C100: =-(MAX($B$84-A100, 0) - $B$86) -> -4.145 | D100: =B100+C100 -> -2.515
A101: 97 | B101: =-(MAX(A101-$B$84,0)-$B$85) -> 1.63 | C101: =-(MAX($B$84-A101, 0) - $B$86) -> -2.645 | D101: =B101+C101 -> -1.015
A102: 98.5 | B102: =-(MAX(A102-$B$84,0)-$B$85) -> 1.63 | C102: =-(MAX($B$84-A102, 0) - $B$86) -> -1.145 | D102: =B102+C102 -> 0.485
... A117: 121 | B117: =-(MAX(A117-$B$84,0)-$B$85) -> -17.37 | C117: =-(MAX($B$84-A117, 0) - $B$86) -> 2.355 | D117: =B117+C117 -> -15.015

Sheet Bloomberg Raw Data- all volumes
A1: Raw data collected from Bloomberg
B2: All data with volume as 0
B3: All data post expiration of stock
A5: Calls | H5: Put
A6: Strike | B6: Ticker | C6: Bid | D6: Ask | E6: Last | F6: IVM | G6: Volm | H6: Strike | I6: Ticker | J6: Bid | K6: Ask | L6: Last | M6: IVM | N6: Volm
A7: 15-Nov-24 (10d); CSize 100
A8: 60 | B8: MRK 11/15/24 C60 | C8: 39.699997 | D8: 43.650009 | E8: 0 | F8: 143.10562 | G8: 0 | H8: 60 | I8: MRK 11/15/24 P60 | J8: 0 | K8: 0.28000003 | L8: 0 | M8: 159.99619 | N8: 0
A9: 65 | B9: MRK 11/15/24 C65 | C9: 34.699997 | D9: 38.599991 | E9: 0 | F9: 119.01668 | G9: 0 | H9: 65 | I9: MRK 11/15/24 P65 | J9: 0 | K9: 0.28000003 | L9: 0 | M9: 138.66689 | N9: 0
A10: 70 | B10: MRK 11/15/24 C70 | C10: 31.149994 | D10: 32.149994 | E10: 0 | F10: 100.46087 | G10: 0 | H10: 70 | I10: MRK 11/15/24 P70 | J10: 0 | K10: 0.29000002 | L10: 0 | M10: 119.49909 | N10: 0
A11: 75 | B11: MRK 11/15/24 C75 | C11: 25.600006 | D11: 26.949997 | E11: 0 | F11: 0 | G11: 0 | H11: 75 | I11: MRK 11/15/24 P75 | J11: 0 | K11: 0.28999996 | L11: 0 | M11: 100.56729 | N11: 0
A12: 80 | B12: MRK 11/15/24 C80 | C12: 21.349991 | D12: 22 | E12: 0 | F12: 69.532822 | G12: 0 | H12: 80 | I12: MRK 11/15/24 P80 | J12: 0 | K12: 0.13 | L12: 0 | M12: 71.011055 | N12: 0
A13: 85 | B13: MRK 11/15/24 C85 | C13: 16.300003 | D13: 16.899994 | E13: 0 | F13: 44.811878 | G13: 0 | H13: 85 | I13: MRK 11/15/24 P85 | J13: 0 | K13: 0.10000002 | L13: 0 | M13: 52.984108 | N13: 0
A14: 89 | B14: MRK 11/15/24 C89 | C14: 11.65 | D14: 12.75 | E14: 0 | F14: 0 | G14: 0 | H14: 89 | I14: MRK 11/15/24 P89 | J14: 0.030000001 | K14: 0.10000002 | L14: 0 | M14: 38.303738 | N14: 0
A15: 90 | B15: MRK 11/15/24 C90 | C15: 11.5 | D15: 11.8 | E15: 0 | F15: 36.555439 | G15: 0 | H15: 90 | I15: MRK 11/15/24 P90 | J15: 0.0099999998 | K15: 0.090000033 | L15: 0.079999983 | M15: 34.066074 | N15: 5
A16: 91 | B16: MRK 11/15/24 C91 | C16: 10.55 | D16: 10.9 | E16: 0 | F16: 38.418758 | G16: 0 | H16: 91 | I16: MRK 11/15/24 P91 | J16: 0.079999983 | K16: 0.11000001 | L16: 0.10000002 | M16: 35.103302 | N16: 3
A17: 92 | B17: MRK 11/15/24 C92 | C17: 9.6000004 | D17: 9.8999996 | E17: 0 | F17: 36.480568 | G17: 0 | H17: 92 | I17: MRK 11/15/24 P92 | J17: 0.10000002 | K17: 0.16000003 | L17: 0 | M17: 34.281689 | N17: 0
A18: 93 | B18: MRK 11/15/24 C93 | C18: 8.3999996 | D18: 8.8500004 | E18: 0 | F18: 25.87026 | G18: 0 | H18: 93 | I18: MRK 11/15/24 P93 | J18: 0.010000002 | K18: 0.16000003 | L18: 0.15000004 | M18: 28.693621 | N18: 1
A19: 94 | B19: MRK 11/15/24 C94 | C19: 7.6500006 | D19: 7.9499998 | E19: 0 | F19: 31.964029 | G19: 0 | H19: 94 | I19: MRK 11/15/24 P94 | J19: 0.02 | K19: 0.19999999 | L19: 0.19 | M19: 27.217854 | N19: 32
... A57: 170 | B57: MRK 11/15/24 C170 | C57: 0 | D57: 0.28000003 | E57: 0 | F57: 144.01917 | G57: 0 | H57: 170 | I57: MRK 11/15/24 P170 | J57: 66.449997 | K57: 70.449997 | L57: 0 | M57: 0 | N57: 0
A58: 20-Dec-24 (45d); CSize 100
A59: 55 | B59: MRK 12/20/24 C55 | C59: 46.199997 | D59: 48.800003 | E59: 46.809998 | F59: 113.97512 | G59: 1 | H59: 55 | I59: MRK 12/20/24 P55 | J59: 0 | K59: 0.30000001 | L59: 0 | M59: 91.853699 | N59: 0
A60: 60 | B60: MRK 12/20/24 C60 | C60: 41.099991 | D60: 43.900009 | E60: 0 | F60: 99.508194 | G60: 0 | H60: 60 | I60: MRK 12/20/24 P60 | J60: 0 | K60: 0.31 | L60: 0 | M60: 80.793182 | N60: 0
A61: 65 | B61: MRK 12/20/24 C65 | C61: 36.599991 | D61: 37.049988 | E61: 37.199997 | F61: 52.473385 | G61: 9 | H61: 65 | I61: MRK 12/20/24 P65 | J61: 0 | K61: 0.33000004 | L61: 0 | M61: 70.86924 | N61: 0
A62: 70 | B62: MRK 12/20/24 C70 | C62: 30.099991 | D62: 33.949997 | E62: 0 | F62: 58.318485 | G62: 0 | H62: 70 | I62: MRK 12/20/24 P70 | J62: 0 | K62: 0.40000004 | L62: 0 | M62: 63.087574 | N62: 0
A63: 75 | B63: MRK 12/20/24 C75 | C63: 26.600006 | D63: 27.350006 | E63: 0 | F63: 45.521427 | G63: 0 | H63: 75 | I63: MRK 12/20/24 P75 | J63: 0.030000001 | K63: 0.49000001 | L63: 0.25 | M63: 48.777531 | N63: 1
A64: 80 | B64: MRK 12/20/24 C80 | C64: 20.549988 | D64: 23.75 | E64: 0 | F64: 42.967533 | G64: 0 | H64: 80 | I64: MRK 12/20/24 P80 | J64: 0.13 | K64: 0.19999999 | L64: 0.16000003 | M64: 36.628979 | N64: 1
A65: 85 | B65: MRK 12/20/24 C85 | C65: 15.65 | D65: 18.25 | E65: 0 | F65: 25.93729 | G65: 0 | H65: 85 | I65: MRK 12/20/24 P85 | J65: 0.050000001 | K65: 0.48000002 | L65: 0.25999999 | M65: 31.540991 | N65: 33
A66: 90 | B66: MRK 12/20/24 C90 | C66: 12.15 | D66: 12.55 | E66: 0 | F66: 28.038425 | G66: 0 | H66: 90 | I66: MRK 12/20/24 P90 | J66: 0.48000002 | K66: 0.55000001 | L66: 0.48000002 | M66: 27.534163 | N66: 64
A67: 95 | B67: MRK 12/20/24 C95 | C67: 7.8499994 | D67: 8 | E67: 7.9499998 | F67: 25.042513 | G67: 10 | H67: 95 | I67: MRK 12/20/24 P95 | J67: 1.1399994 | K67: 1.4499998 | L67: 1.1800003 | M67: 25.972647 | N67: 656
A68: 100 | B68: MRK 12/20/24 C100 | C68: 4.25 | D68: 4.4000006 | E68: 4.3000002 | F68: 23.473513 | G68: 46 | H68: 100 | I68: MRK 12/20/24 P100 | J68: 2.6800003 | K68: 2.75 | L68: 2.6999998 | M68: 23.470776 | N68: 910
A69: 105 | B69: MRK 12/20/24 C105 | C69: 1.8599997 | D69: 2.0499992 | E69: 1.8999996 | F69: 22.787363 | G69: 289 | H69: 105 | I69: MRK 12/20/24 P105 | J69: 5.0500002 | K69: 5.5 | L69: 5.3200006 | M69: 21.571854 | N69: 67
A70: 110 | B70: MRK 12/20/24 C110 | C70: 0.68000001 | D70: 0.69999999 | E70: 0.69 | F70: 22.093918 | G70: 720 | H70: 110 | I70: MRK 12/20/24 P110 | J70: 8 | K70: 9.75 | L70: 0 | M70: 17.797586 | N70: 0
... A83: 175 | B83: MRK 12/20/24 C175 | C83: 0 | D83: 0.27999997 | E83: 0 | F83: 75.171761 | G83: 0 | H83: 175 | I83: MRK 12/20/24 P175 | J83: 71.699997 | K83: 75.349991 | L83: 0 | M83: 0 | N83: 0
A86: Dates | B86: Strike | C86: Ticker | D86: Bid | E86: Ask | F86: Last | G86: IVM | H86: Volm | I86: Closing Stock Price
A87: 45601 | B87: 102 | C87: MRK 11/15/24 C102 | D87: 1.5999994 | E87: 1.6599998 | F87: 1.6900005 | G87: =25.2881336212158/100 -> 0.25288134 | H87: 41 | I87: 101.65
A88: 45602 | B88: 102 | C88: MRK 11/15/24 C102 | D88: 0.73000002 | E88: 0.91000003 | F88: 0.87 | G88: =17.9776229858398/100 -> 0.17977623 | H88: 667 | I88: 100.73
A89: 45603 | B89: 102 | C89: MRK 11/15/24 C102 | D89: 0.88 | E89: 1.5 | F89: 0.93000001 | G89: =23.8076725006104/100 -> 0.23807673 | H89: 697 | I89: 101.17
A90: 45604 | B90: 102 | C90: MRK 11/15/24 C102 | D90: 1.5799999 | E90: 2.1400003 | F90: 1.6999998 | G90: =22.6287307739258/100 -> 0.22628731 | H90: 796 | I90: 102.92
A91: 45605 | B91: 102 | C91: MRK 11/15/24 C102 | D91: 1.5799999 | E91: 2.1400003 | F91: 1.6999998 | G91: =22.6287307739258/100 -> 0.22628731 | H91: 796 | I91: 102.92
A92: 45606 | B92: 102 | C92: MRK 11/15/24 C102 | D92: 1.5799999 | E92: 2.1400003 | F92: 1.6999998 | G92: =22.6287307739258/100 -> 0.22628731 | H92: 796 | I92: 102.92
A93: 45607 | B93: 102 | C93: MRK 11/15/24 C102 | D93: 0.34000003 | E93: 0.56999999 | F93: 0.41000003 | G93: =19.94482421875/100 -> 0.19944824 | H93: 715 | I93: 100.73
A94: 45608 | B94: 102 | C94: MRK 11/15/24 C102 | D94: 0.079999983 | E94: 0.11000001 | F94: 0.079999983 | G94: =21.1003704071045/100 -> 0.2110037 | H94: 997 | I94: 98.58
A95: 45609 | B95: 102 | C95: MRK 11/15/24 C102 | D95: 0.030000001 | E95: 0.050000001 | F95: 0.050000001 | G95: =23.1497402191162/100 -> 0.2314974 | H95: 174 | I95: 98.5
A96: 45610 | B96: 102 | C96: MRK 11/15/24 C102 | D96: 0.0099999998 | E96: 0.039999999 | F96: 0.02 | G96: =32.4056549072266/100 -> 0.32405655 | H96: 779 | I96: 98.36
A97: 45611 | B97: 102 | C97: MRK 11/15/24 C102 | D97: 0 | E97: 0.010000002 | F97: 0.010000002 | G97: =467.474853515625/100 -> 4.6747485 | H97: 19 | I97: 96.31
A100: Dates | B100: Strike | C100: Ticker | D100: Bid | E100: Ask | F100: Last | G100: IVM | H100: Volm | I100: Closing Stock Price
A101: 45601 | B101: 102 | C101: MRK 11/15/24 P102 | D101: 1.9699993 | E101: 2.0600004 | F101: 2.0200005 | G101: =24.8180484771729/100 -> 0.24818048 | H101: 65 | I101: 101.65
A102: 45602 | B102: 102 | C102: MRK 11/15/24 P102 | D102: 1.7600002 | E102: 1.8999996 | F102: 1.7600002 | G102: =19.6807899475098/100 -> 0.1968079 | H102: 121 | I102: 100.73
A103: 45603 | B103: 102 | C103: MRK 11/15/24 P102 | D103: 1.4400005 | E103: 1.8999996 | F103: 1.6099997 | G103: =21.0366344451904/100 -> 0.21036634 | H103: 180 | I103: 101.17
A104: 45604 | B104: 102 | C104: MRK 11/15/24 P102 | D104: 0.57999998 | E104: 0.68000001 | F104: 0.61000001 | G104: =18.2637310028076/100 -> 0.18263731 | H104: 331 | I104: 102.92
A105: 45605 | B105: 102 | C105: MRK 11/15/24 P102 | D105: 0.57999998 | E105: 0.68000001 | F105: 0.61000001 | G105: =18.2637310028076/100 -> 0.18263731 | H105: 331 | I105: 102.92
A106: 45606 | B106: 102 | C106: MRK 11/15/24 P102 | D106: 0.57999998 | E106: 0.68000001 | F106: 0.61000001 | G106: =18.2637310028076/100 -> 0.18263731 | H106: 331 | I106: 102.92
A107: 45607 | B107: 102 | C107: MRK 11/15/24 P102 | D107: 1.6099997 | E107: 1.8999996 | F107: 1.79 | G107: =16.5353698730469/100 -> 0.1653537 | H107: 77 | I107: 100.73
A108: 45608 | B108: 102 | C108: MRK 11/15/24 P102 | D108: 2.8800001 | E108: 3.25 | F108: 2.4700003 | G108: 0 | H108: 46 | I108: 98.58
A109: 45609 | B109: 102 | C109: MRK 11/15/24 P102 | D109: 3.4000006 | E109: 3.6000004 | F109: 3.2200003 | G109: =16.8075084686279/100 -> 0.16807508 | H109: 43 | I109: 98.5
A110: 45610 | B110: 102 | C110: MRK 11/15/24 P102 | D110: 2.96 | E110: 4.0500002 | F110: 3 | G110: 0 | H110: 26 | I110: 98.36
A111: 45611 | B111: 102 | C111: MRK 11/15/24 P102 | D111: 5.5500002 | E111: 6.8999996 | F111: 5.3200006 | G111: =1095.548828125/100 -> 10.955488 | H111: 27 | I111: 96.31

Sheet Bloomberg Raw Data-5th(No zero)
A1: Raw data collected from Bloomberg- with no 0 volumes
A3: Calls | H3: Put
A4: Strike | B4: Ticker | C4: Bid | D4: Ask | E4: Last | F4: IVM | G4: Volm | H4: Strike | I4: Ticker | J4: Bid | K4: Ask | L4: Last | M4: IVM | N4: Volm
A5: 15-Nov-24 (10d); CSize 100
A6: 95 | B6: MRK 11/15/24 C95 | C6: 6.6500006 | D6: 6.9499998 | E6: 6.9499998 | F6: 28.584435 | G6: 12 | H6: 95 | I6: MRK 11/15/24 P95 | J6: 0.079999983 | K6: 0.25999999 | L6: 0.24000001 | M6: 26.781515 | N6: 24
A7: 98 | B7: MRK 11/15/24 C98 | C7: 4.1500006 | D7: 4.3000002 | E7: 4.1999998 | F7: 27.168388 | G7: 2 | H7: 98 | I7: MRK 11/15/24 P98 | J7: 0.56 | K7: 0.66000003 | L7: 0.60000002 | M7: 26.573425 | N7: 124
A8: 99 | B8: MRK 11/15/24 C99 | C8: 3.4000006 | D8: 3.5500002 | E8: 3.6700001 | F8: 26.825867 | G8: 10 | H8: 99 | I8: MRK 11/15/24 P99 | J8: 0.87 | K8: 0.88999999 | L8: 0.88 | M8: 26.641626 | N8: 56
A9: 100 | B9: MRK 11/15/24 C100 | C9: 2.7300005 | D9: 2.8400002 | E9: 2.8000002 | F9: 26.356119 | G9: 55 | H9: 100 | I9: MRK 11/15/24 P100 | J9: 1.0600004 | K9: 1.1999998 | L9: 1.1700001 | M9: 25.299459 | N9: 84
A10: 101 | B10: MRK 11/15/24 C101 | C10: 2.1099997 | D10: 2.21 | E10: 2.3299999 | F10: 25.734919 | G10: 28 | H10: 101 | I10: MRK 11/15/24 P101 | J10: 1.5099993 | K10: 1.5900002 | L10: 1.4800005 | M10: 25.354883 | N10: 100
A11: 102 | B11: MRK 11/15/24 C102 | C11: 1.5999994 | D11: 1.6599998 | E11: 1.6900005 | F11: 25.288134 | G11: 41 | H11: 102 | I11: MRK 11/15/24 P102 | J11: 1.9699993 | K11: 2.0600004 | L11: 2.0200005 | M11: 24.818048 | N11: 65
A12: 103 | B12: MRK 11/15/24 C103 | C12: 1.1700001 | D12: 1.2200003 | E12: 1.2799997 | F12: 24.961069 | G12: 89 | H12: 103 | I12: MRK 11/15/24 P103 | J12: 2.5500002 | K12: 2.6199999 | L12: 2.5900002 | M12: 24.502392 | N12: 28
A13: 104 | B13: MRK 11/15/24 C104 | C13: 0.81999999 | D13: 0.87 | E13: 0.87 | F13: 24.637125 | G13: 56 | H13: 104 | I13: MRK 11/15/24 P104 | J13: 3.1999998 | K13: 3.3500004 | L13: 3.3000002 | M13: 24.700979 | N13: 29
A14: 105 | B14: MRK 11/15/24 C105 | C14: 0.56999999 | D14: 0.61000001 | E14: 0.56999999 | F14: 24.601616 | G14: 660 | H14: 105 | I14: MRK 11/15/24 P105 | J14: 3.9499998 | K14: 4.0500002 | L14: 4.0500002 | M14: 24.196188 | N14: 69
A15: 106 | B15: MRK 11/15/24 C106 | C15: 0.38999999 | D15: 0.42000002 | E15: 0.40000004 | F15: 24.682907 | G15: 107 | H15: 106 | I15: MRK 11/15/24 P106 | J15: 4.8000002 | K15: 4.9000006 | L15: 4.8500004 | M15: 24.819933 | N15: 11
A16: 107 | B16: MRK 11/15/24 C107 | C16: 0.24000001 | D16: 0.29000002 | E16: 0.30000001 | F16: 24.602554 | G16: 36 | H16: 107 | I16: MRK 11/15/24 P107 | J16: 5.6500006 | K16: 5.8000002 | L16: 5.6999998 | M16: 24.942793 | N16: 6
A17: 110 | B17: MRK 11/15/24 C110 | C17: 0.090000033 | D17: 0.12 | E17: 0.090000033 | F17: 27.045614 | G17: 114 | H17: 110 | I17: MRK 11/15/24 P110 | J17: 8.5 | K17: 8.6999998 | L17: 8.4799995 | M17: 28.406557 | N17: 143
... A19: 130 | B19: MRK 11/15/24 C130 | C19: 0 | D19: 0.039999999 | E19: 0.010000002 | F19: 59.249893 | G19: 10 | H19: 130 | I19: MRK 11/15/24 P130 | J19: 27.399994 | K19: 30.399994 | L19: 28.850006 | M19: 88.830597 | N19: 4
J21: 0.079999983 | K21: 0.25999999
J22: 0.56 | K22: 0.66000003
J23: 0.87 | K23: 0.88999999
J24: 1.0600004 | K24: 1.1999998
J25: 1.5099993 | K25: 1.5900002
J26: 1.9699993 | K26: 2.0600004
J27: 2.5500002 | K27: 2.6199999
J28: 3.1999998 | K28: 3.3500004
J29: 3.9499998 | K29: 4.0500002
J30: 4.8000002 | K30: 4.9000006
J31: 5.6500006 | K31: 5.8000002
J32: 8.5 | K32: 8.6999998
... J34: 27.399994 | K34: 30.399994
A37: Contract Name
A38: CALL | B38: MRK241115C00102000
B40: Last Trade Date (EDT) | C40: Strike | D40: Last Price | E40: Bid | F40: Ask | G40: Change | H40: % Change | I40: Volume | J40: Open Interest | K40: Implied Volatility
B41: 45601.618 | C41: 102 | D41: 1.69 | E41: 1.6 | F41: 1.66 | G41: -0.57000005 | H41: -28.643217 | I41: 41 | J41: 790 | K41: 0.0078
K42: 101.87
B43: Dates | C43: Bid | D43: Ask | E43: Strike | F43: Expiry Date | G43: IVM | H43: Volume | I43: Closing Stock Price | J43: Daily Return | K43: Daily Ln Return
B44: 45601 | C44: 1.6 | D44: 1.66 | E44: 102 | F44: 45611 | G44: 25.28 | H44: 41 | I44: 101.65 | J44: -0.0021596152 | K44: -0.0021619505
B45: 45602 | C45: 0.73 | D45: 0.91 | E45: 102 | F45: 45611 | G45: 17.977 | H45: 667 | I45: 100.73 | J45: -0.009050664 | K45: -0.0090918701
B46: 45603 | C46: 0.88 | D46: 1.5 | E46: 102 | F46: 45611 | G46: 23.81 | H46: 697 | I46: 101.17 | J46: 0.0043681128 | K46: 0.0043586003
B47: 45604 | C47: 1.58 | D47: 2.14 | E47: 102 | F47: 45611 | G47: 21.46 | H47: 796 | I47: 102.92 | J47: 0.017297618 | K47: 0.017149717
B48: 45605 | C48: 1.58 | D48: 2.14 | E48: 102 | F48: 45611 | G48: 21.46 | H48: 796 | I48: 102.92 | J48: 0 | K48: 0
B49: 45606 | C49: 1.58 | D49: 2.14 | E49: 102 | F49: 45611 | G49: 21.46 | H49: 796 | I49: 102.92 | J49: 0 | K49: 0
B50: 45607 | C50: 0.34 | D50: 0.57 | E50: 102 | F50: 45611 | G50: 19.94 | H50: 715 | I50: 100.73 | J50: -0.021278663 | K50: -0.021508317
B51: 45608 | C51: 0.08 | D51: 0.11 | E51: 102 | F51: 45611 | G51: 21.1 | H51: 997 | I51: 98.58 | J51: -0.021344187 | K51: -0.021575269
B52: 45609 | C52: 0.03 | D52: 0.05 | E52: 102 | F52: 45611 | G52: 23.15 | H52: 174 | I52: 98.5 | J52: -0.00081152364 | K52: -0.0008118531
B53: 45610 | C53: 0.01 | D53: 0.04 | E53: 102 | F53: 45611 | G53: 32.405 | H53: 779 | I53: 98.36 | J53: -0.0014213198 | K53: -0.0014223308
B54: 45611 | C54: 0 | D54: 0.01 | E54: 102 | F54: 45611 | G54: 467.474 | H54: 19 | I54: 96.31 | J54: -0.020841806 | K54: -0.021062062
A57: Contract Name
A58: PUT | B58: MRK241115P00102000
B60: Last Trade Date (EDT) | C60: Strike | D60: Last Price | E60: Bid | F60: Ask | G60: Change | H60: % Change | I60: Volume | J60: Open Interest | K60: Implied Volatility
B61: 2024-11-05 2:13PM EST | C61: 102 | D61: 2.02 | E61: 1.9699 | F61: 2.06 | G61: 0.38 | H61: 0.18905 | I61: 65 | J61: 404 | K61: 0.0029
K62: 101.87
B63: Dates | C63: Bid | D63: Ask | E63: Strike | F63: Expiry Date | G63: IVM | H63: Volume | I63: Closing Stock Price | J63: Daily Return | K63: Daily Ln Return
B64: 45601 | C64: 1.9699 | D64: 2.06 | E64: 102 | F64: 45611 | G64: 24.818 | H64: 65 | I64: 101.65 | J64: -0.0021596152 | K64: -0.0021619505
B65: 45602 | C65: 1.76 | D65: 1.899 | E65: 102 | F65: 45611 | G65: 19.68 | H65: 121 | I65: 100.73 | J65: -0.009050664 | K65: -0.0090918701
B66: 45603 | C66: 1.44 | D66: 1.899 | E66: 102 | F66: 45611 | G66: 21.03 | H66: 180 | I66: 101.17 | J66: 0.0043681128 | K66: 0.0043586003
B67: 45604 | C67: 0.5799 | D67: 0.68 | E67: 102 | F67: 45611 | G67: 18.263 | H67: 331 | I67: 102.92 | J67: 0.017297618 | K67: 0.017149717
B68: 45605 | C68: 0.5799 | D68: 0.68 | E68: 102 | F68: 45611 | G68: 18.263 | H68: 331 | I68: 102.92 | J68: 0 | K68: 0
B69: 45606 | C69: 0.5799 | D69: 0.68 | E69: 102 | F69: 45611 | G69: 18.263 | H69: 331 | I69: 102.92 | J69: 0 | K69: 0
B70: 45607 | C70: 1.6099 | D70: 1.899 | E70: 102 | F70: 45611 | G70: 16.535 | H70: 77 | I70: 100.73 | J70: -0.021278663 | K70: -0.021508317
B71: 45608 | C71: 2.88 | D71: 3.25 | E71: 102 | F71: 45611 | G71: 0 | H71: 46 | I71: 98.58 | J71: -0.021344187 | K71: -0.021575269
B72: 45609 | C72: 3.4 | D72: 3.6 | E72: 102 | F72: 45611 | G72: 16.807 | H72: 43 | I72: 98.5 | J72: -0.00081152364 | K72: -0.0008118531
B73: 45610 | C73: 2.96 | D73: 4.05 | E73: 102 | F73: 45611 | G73: 0 | H73: 26 | I73: 98.36 | J73: -0.0014213198 | K73: -0.0014223308
B74: 45611 | C74: 5.55 | D74: 6.899 | E74: 102 | F74: 45611 | G74: 1095.5488 | H74: 27 | I74: 96.31 | J74: -0.020841806 | K74: -0.021062062

Sheet Historical Prices
A1: Date | B1: Stock Price | C1: Daily Return | D1: Log returns | E1: Standard Deviation | F1: Annualised Standard Deviation
A2: 45569 | B2: 109.77 | C2: =(A3-A2)/B3 -> 0.027626853
A3: 45572 | B3: 108.59 | C3: =(A4-A3)/B4 -> 0.0092148913 | D3: =LN(B3/B2) -> -0.010807945
A4: 45573 | B4: 108.52 | C4: =(A5-A4)/B5 -> 0.0090686497 | D4: =LN(B4/B3) -> -0.00064483444
A5: 45574 | B5: 110.27 | C5: =(A6-A5)/B6 -> 0.0091407678 | D5: =LN(B5/B4) -> 0.015997416
A6: 45575 | B6: 109.4 | C6: =(A7-A6)/B7 -> 0.009113278 | D6: =LN(B6/B5) -> -0.0079210138
A7: 45576 | B7: 109.73 | C7: =(A8-A7)/B8 -> 0.027349804 | D7: =LN(B7/B6) -> 0.003011913
A8: 45579 | B8: 109.69 | C8: =(A9-A8)/B9 -> 0.0089661974 | D8: =LN(B8/B7) -> -0.00036459758
A9: 45580 | B9: 111.53 | C9: =(A10-A9)/B10 -> 0.0090563304 | D9: =LN(B9/B8) -> 0.016635408
A10: 45581 | B10: 110.42 | C10: =(A11-A10)/B11 -> 0.0091116173 | D10: =LN(B10/B9) -> -0.010002336
A11: 45582 | B11: 109.75 | C11: =(A12-A11)/B12 -> 0.009199632 | D11: =LN(B11/B10) -> -0.0060862249
A12: 45583 | B12: 108.7 | C12: =(A13-A12)/B13 -> 0.028211397 | D12: =LN(B12/B11) -> -0.0096132578
A13: 45586 | B13: 106.34 | C13: =(A14-A13)/B14 -> 0.0093773443 | D13: =LN(B13/B12) -> -0.021950286
A14: 45587 | B14: 106.64 | C14: =(A15-A14)/B15 -> 0.0094002632 | D14: =LN(B14/B13) -> 0.0028171678
... A23: 45600 | B23: 101.87 | C23: =(A24-A23)/B24 -> 0.0098376783 | D23: =LN(B23/B22) -> -9.8159509e-05
A24: 45601 | B24: 101.65 | C24: =(A25-A24)/B25 -> 0.009927529 | D24: =LN(B24/B23) -> -0.0021619505 | E24: =_xlfn.STDEV.P(D2:D23) -> 0.010414177 | F24: =E24*SQRT(252) -> 0.16531993
A25: 45602 | B25: 100.73 | C25: =(A26-A25)/B26 -> 0.0098843531 | D25: =LN(B25/B24) -> -0.0090918701 | E25: =_xlfn.STDEV.P(D3:D24) -> 0.010178885 | F25: =E25*SQRT(252) -> 0.16158479
A26: 45603 | B26: 101.17 | C26: =(A27-A26)/B27 -> 0.0097162845 | D26: =LN(B26/B25) -> 0.0043586003 | E26: =_xlfn.STDEV.P(D4:D25) -> 0.010128985 | F26: =E26*SQRT(252) -> 0.16079265
A27: 45604 | B27: 102.92 | C27: =(A28-A27)/B28 -> 0.029782587 | D27: =LN(B27/B26) -> 0.017149717 | E27: =_xlfn.STDEV.P(D5:D26) -> 0.010244154 | F27: =E27*SQRT(252) -> 0.1626209
A28: 45607 | B28: 100.73 | C28: =(A29-A28)/B29 -> 0.010144045 | D28: =LN(B28/B27) -> -0.021508317 | E28: =_xlfn.STDEV.P(D6:D27) -> 0.010344566 | F28: =E28*SQRT(252) -> 0.16421489
A29: 45608 | B29: 98.58 | C29: =(A30-A29)/B30 -> 0.010152284 | D29: =LN(B29/B28) -> -0.021575269 | E29: =_xlfn.STDEV.P(D7:D28) -> 0.010996879 | F29: =E29*SQRT(252) -> 0.17457005
A30: 45609 | B30: 98.5 | C30: =(A31-A30)/B31 -> 0.010166734 | D30: =LN(B30/B29) -> -0.0008118531 | E30: =_xlfn.STDEV.P(D8:D29) -> 0.011490861 | F30: =E30*SQRT(252) -> 0.18241177
A31: 45610 | B31: 98.36 | C31: =(A32-A31)/B32 -> 0.010383138 | D31: =LN(B31/B30) -> -0.0014223308 | E31: =_xlfn.STDEV.P(D9:D30) -> 0.011483264 | F31: =E31*SQRT(252) -> 0.18229117
A32: 45611 | B32: 96.31 | C32: 0 | D32: =LN(B32/B31) -> -0.021062062 | E32: =_xlfn.STDEV.P(D10:D31) -> 0.010520245 | F32: =E32*SQRT(252) -> 0.16700371

Sheet Tracked Data - MRK
A3: (Data extracted using python)
A4: CALLS | R4: PUTS
A5: index | B5: contract Symbol | C5: lastTradeDate | D5: strike | E5: lastPrice | F5: bid | G5: ask | H5: change | I5: percentChange | J5: volume | K5: openInterest | L5: impliedVolatility | M5: inTheMoney | N5: contractSize | O5: currency | P5: Type | R5: index | S5: contract Symbol | T5: lastTradeDate | U5: strike | V5: lastPrice | W5: bid | X5: ask | Y5: change | Z5: percentChange | AA5: volume | AB5: openInterest | AC5: impliedVolatility | AD5: inTheMoney | AE5: contractSize | AF5: currency | AG5: Type
A6: 1 | B6: MRK241115C00060000 | C6: 45558.775 | D6: 60 | E6: 39.7 | F6: 39.7 | G6: 43.65 | H6: 0 | I6: 0 | J6: 0 | K6: 5 | L6: 3.5927745 | M6: TRUE | N6: REGULAR | O6: USD | P6: Call | R6: 1 | S6: MRK241115P00060000 | T6: 45589.762 | U6: 60 | V6: 0.02 | W6: 0 | X6: 0.28 | Y6: 0 | Z6: 0 | AA6: 2 | AB6: 3 | AC6: 1.4609402 | AD6: FALSE | AE6: REGULAR | AF6: USD | AG6: Put
A7: 2 | B7: MRK241115C00070000 | C7: 45574.588 | D7: 70 | E7: 39.45 | F7: 31.15 | G7: 32.15 | H7: 0 | I7: 0 | J7: 0 | K7: 73 | L7: 1.3837921 | M7: TRUE | N7: REGULAR | O7: USD | P7: Call | R7: 2 | S7: MRK241115P00070000 | T7: 45595.751 | U7: 70 | V7: 0.03 | W7: 0 | X7: 0.29 | Y7: 0 | Z7: 0 | AA7: 25 | AB7: 397 | AC7: 1.0820358 | AD7: FALSE | AE7: REGULAR | AF7: USD | AG7: Put
A8: 3 | B8: MRK241115C00080000 | C8: 45596.817 | D8: 80 | E8: 22.95 | F8: 21.35 | G8: 22 | H8: 0 | I8: 0 | J8: 111 | K8: 107 | L8: 1e-05 | M8: TRUE | N8: REGULAR | O8: USD | P8: Call | R8: 3 | S8: MRK241115P00080000 | T8: 45593.663 | U8: 80 | V8: 0.09 | W8: 0 | X8: 0.13 | Y8: 0 | Z8: 0 | AA8: 2 | AB8: 12 | AC8: 0.64844102 | AD8: FALSE | AE8: REGULAR | AF8: USD | AG8: Put
A9: 4 | B9: MRK241115C00085000 | C9: 45600.701 | D9: 85 | E9: 16.35 | F9: 16.3 | G9: 16.9 | H9: 0 | I9: 0 | J9: 1 | K9: 70 | L9: 1e-05 | M9: TRUE | N9: REGULAR | O9: USD | P9: Call | R9: 4 | S9: MRK241115P00085000 | T9: 45596.712 | U9: 85 | V9: 0.06 | W9: 0 | X9: 0.1 | Y9: 0 | Z9: 0 | AA9: 4 | AB9: 647 | AC9: 0.537114 | AD9: FALSE | AE9: REGULAR | AF9: USD | AG9: Put
A10: 5 | B10: MRK241115C00090000 | C10: 45589.61 | D10: 90 | E10: 16.5 | F10: 11.5 | G10: 11.8 | H10: 0 | I10: 0 | J10: 2 | K10: 206 | L10: 1e-05 | M10: TRUE | N10: REGULAR | O10: USD | P10: Call | R10: 5 | S10: MRK241115P00090000 | T10: 45601.605 | U10: 90 | V10: 0.39 | W10: 0.01 | X10: 0.09 | Y10: 0.29999998 | Z10: 333.3333 | AA10: 2 | AB10: 710 | AC10: 0.43945873 | AD10: FALSE | AE10: REGULAR | AF10: USD | AG10: Put
A11: 6 | B11: MRK241115C00095000 | C11: 45601.621 | D11: 95 | E11: 6.3 | F11: 6.65 | G11: 6.95 | H11: -0.9699998 | I11: -13.342501 | J11: 7 | K11: 68 | L11: 0.25391371 | M11: TRUE | N11: REGULAR | O11: USD | P11: Call | R11: 6 | S11: MRK241115P00095000 | T11: 45601.646 | U11: 95 | V11: 0.32 | W11: 0 | X11: 0.33 | Y11: -0.02000001 | Z11: -5.8823557 | AA11: 3 | AB11: 1531 | AC11: 0.31934274 | AD11: FALSE | AE11: REGULAR | AF11: USD | AG11: Put
A12: 7 | B12: MRK241115C00098000 | C12: 45597.675 | D12: 98 | E12: 5.5 | F12: 4.15 | G12: 4.3 | H12: 0 | I12: 0 | J12: 3 | K12: 54 | L12: 0.25733165 | M12: TRUE | N12: REGULAR | O12: USD | P12: Call | R12: 7 | S12: MRK241115P00098000 | T12: 45601.634 | U12: 98 | V12: 0.81 | W12: 0.08 | X12: 0.26 | Y12: 0.06999999 | Z12: 9.459458 | AA12: 1 | AB12: 386 | AC12: 0.29785858 | AD12: FALSE | AE12: REGULAR | AF12: USD | AG12: Put
A13: 8 | B13: MRK241115C00099000 | C13: 45600.629 | D13: 99 | E13: 3.25 | F13: 3.4 | G13: 3.55 | H13: -0.52 | I13: -13.793103 | J13: 7 | K13: 147 | L13: 0.26172613 | M13: TRUE | N13: REGULAR | O13: USD | P13: Call | R13: 8 | S13: MRK241115P00099000 | T13: 45600.78 | U13: 99 | V13: 1.08 | W13: 0.98 | X13: 1.08 | Y13: 0.060000062 | Z13: 5.882359 | AA13: 8 | AB13: 179 | AC13: 0.29248754 | AD13: FALSE | AE13: REGULAR | AF13: USD | AG13: Put
A14: 9 | B14: MRK241115C00100000 | C14: 45601.636 | D14: 100 | E14: 2.35 | F14: 2.73 | G14: 2.84 | H14: -0.37000012 | I14: -13.602945 | J14: 8 | K14: 357 | L14: 0.25220474 | M14: TRUE | N14: REGULAR | O14: USD | P14: Call | R14: 9 | S14: MRK241115P00100000 | T14: 45601.64 | U14: 100 | V14: 1.46 | W14: 1.38 | X14: 1.44 | Y14: 0.21000004 | Z14: 16.800003 | AA14: 38 | AB14: 27767 | AC14: 0.29102271 | AD14: FALSE | AE14: REGULAR | AF14: USD | AG14: Put
A15: 10 | B15: MRK241115C00101000 | C15: 45601.644 | D15: 101 | E15: 1.87 | F15: 2.11 | G15: 2.21 | H15: -0.6 | I15: -24.2915 | J15: 16 | K15: 1037 | L15: 0.26709717 | M15: TRUE | N15: REGULAR | O15: USD | P15: Call | R15: 10 | S15: MRK241115P00101000 | T15: 45601.644 | U15: 101 | V15: 1.82 | W15: 1.74 | X15: 1.88 | Y15: 0.29000008 | Z15: 18.954254 | AA15: 1 | AB15: 715 | AC15: 0.29004616 | AD15: FALSE | AE15: REGULAR | AF15: USD | AG15: Put
A16: 11 | B16: MRK241115C00102000 | C16: 45601.618 | D16: 102 | E16: 1.69 | F16: 1.6 | G16: 1.66 | H16: -0.57000005 | I16: -28.643217 | J16: 41 | K16: 789 | L16: 0.2634351 | M16: FALSE | N16: REGULAR | O16: USD | P16: Call | R16: 11 | S16: MRK241115P00102000 | T16: 45601.643 | U16: 102 | V16: 2.39 | W16: 2.3 | X16: 2.41 | Y16: 0.3800001 | Z16: 18.905478 | AA16: 6 | AB16: 380 | AC16: 0.29077858 | AD16: TRUE | AE16: REGULAR | AF16: USD | AG16: Put
A17: 12 | B17: MRK241115C00103000 | C17: 45601.642 | D17: 103 | E17: 1.27 | F17: 1.03 | G17: 1.17 | H17: -0.43000007 | I17: -29.452059 | J17: 19 | K17: 438 | L17: 0.25293716 | M17: FALSE | N17: REGULAR | O17: USD | P17: Call | R17: 12 | S17: MRK241115P00103000 | T17: 45600.866 | U17: 103 | V17: 3.3 | W17: 2.79 | X17: 3.1 | Y17: 0.78 | Z17: 30.952381 | AA17: 2 | AB17: 314 | AC17: 0.30396204 | AD17: TRUE | AE17: REGULAR | AF17: USD | AG17: Put
... A27: 22 | B27: MRK241115C00113000 | C27: 45600.657 | D27: 113 | E27: 0.03 | F27: 0.01 | G27: 0.4 | H27: 0 | I27: 0 | J27: 9 | K27: 416 | L27: 0.48096222 | M27: FALSE | N27: REGULAR | O27: USD | P27: Call | R27: 22 | S27: MRK241115P00113000 | T27: 45596.567 | U27: 113 | V27: 14.05 | W27: 12 | X27: 12.8 | Y27: 0 | Z27: 0 | AA27: 4 | AB27: 4 | AC27: 0.56738714 | AD27: TRUE | AE27: REGULAR | AF27: USD | AG27: Put
A28: 23 | B28: MRK241115C00114000 | C28: 45600.708 | D28: 114 | E28: 0.03 | F28: 0.01 | G28: 0.13 | H28: 0 | I28: 0 | J28: 68 | K28: 528 | L28: 0.39649041 | M28: FALSE | N28: REGULAR | O28: USD | P28: Call | R28: 23 | S28: MRK241115P00114000 | T28: 45587.606 | U28: 114 | V28: 8.27 | W28: 12.95 | X28: 13.25 | Y28: 0 | Z28: 0 | AB28: 0 | AC28: 0.51221191 | AD28: TRUE | AE28: REGULAR | AF28: USD | AG28: Put
A29: 24 | B29: MRK241115C00115000 | C29: 45601.64 | D29: 115 | E29: 0.03 | F29: 0.02 | G29: 0.03 | H29: 0 | I29: 0 | J29: 8 | K29: 5939 | L29: 0.33203793 | M29: FALSE | N29: REGULAR | O29: USD | P29: Call | R29: 24 | S29: MRK241115P00115000 | T29: 45600.851 | U29: 115 | V29: 13.33 | W29: 13.95 | X29: 14.2 | Y29: 0 | Z29: 0 | AA29: 84 | AB29: 2338 | AC29: 0.53125469 | AD29: TRUE | AE29: REGULAR | AF29: USD | AG29: Put
A30: 25 | B30: MRK241115C00116000 | C30: 45595.832 | D30: 116 | E30: 0.42 | F30: 0.01 | G30: 0.12 | H30: 0 | I30: 0 | J30: 13 | K30: 4833 | L30: 0.54102021 | M30: FALSE | N30: REGULAR | O30: USD | P30: Call | R30: 25 | S30: MRK241115P00116000 | T30: 45593.567 | U30: 116 | V30: 11.4 | W30: 14.95 | X30: 15.35 | Y30: 0 | Z30: 0 | AB30: 8 | AC30: 0.58301198 | AD30: TRUE | AE30: REGULAR | AF30: USD | AG30: Put
A31: 26 | B31: MRK241115C00117000 | C31: 45595.815 | D31: 117 | E31: 0.3 | F31: 0 | G31: 0.32 | H31: 0 | I31: 0 | J31: 3 | K31: 406 | L31: 0.55859816 | M31: FALSE | N31: REGULAR | O31: USD | P31: Call | R31: 26 | S31: MRK241115P00117000 | T31: 45596.577 | U31: 117 | V31: 16.32 | W31: 15.95 | X31: 17.8 | Y31: 0 | Z31: 0 | AA31: 1 | AB31: 0 | AC31: 0.80298049 | AD31: TRUE | AE31: REGULAR | AF31: USD | AG31: Put
A32: 27 | B32: MRK241115C00118000 | C32: 45595.808 | D32: 118 | E32: 0.24 | F32: 0 | G32: 0.1 | H32: 0 | I32: 0 | J32: 2 | K32: 118 | L32: 0.4648491 | M32: FALSE | N32: REGULAR | O32: USD | P32: Call | R32: 27 | S32: MRK241115P00118000 | T32: 45596.693 | U32: 118 | V32: 16 | W32: 16.4 | X32: 17.65 | Y32: 0 | Z32: 0 | AB32: 9 | AC32: 0.58984785 | AD32: TRUE | AE32: REGULAR | AF32: USD | AG32: Put
A33: 28 | B33: MRK241115C00119000 | C33: 45590.582 | D33: 119 | E33: 0.2 | F33: 0 | G33: 0.3 | H33: 0 | I33: 0 | J33: 10 | K33: 12 | L33: 0.52148916 | M33: FALSE | N33: REGULAR | O33: USD | P33: Call | R33: 28 | S33: MRK241115P00119000 | U33: 119 | V33: 0 | W33: 17.399994 | X33: 18.399994 | Y33: 0 | Z33: 0 | AB33: 0 | AC33: 0.58984785 | AD33: TRUE | AE33: REGULAR | AF33: USD | AG33: Put
A34: 29 | B34: MRK241115C00120000 | C34: 45600.843 | D34: 120 | E34: 0.01 | F34: 0 | G34: 0.18 | H34: 0 | I34: 0 | J34: 159 | K34: 7533 | L34: 0.56152782 | M34: FALSE | N34: REGULAR | O34: USD | P34: Call | R34: 29 | S34: MRK241115P00120000 | T34: 45600.851 | U34: 120 | V34: 18.5 | W34: 19.05 | X34: 19.25 | Y34: 0 | Z34: 0 | AA34: 27 | AB34: 23 | AC34: 0.68652657 | AD34: TRUE | AE34: REGULAR | AF34: USD | AG34: Put
A35: 30 | B35: MRK241115C00121000 | C35: 45601.605 | D35: 121 | E35: 0.01 | F35: 0 | G35: 0.27 | H35: -0.02 | I35: -66.66667 | J35: 1 | K35: 50 | L35: 0.55469195 | M35: FALSE | N35: REGULAR | O35: USD | P35: Call | R35: 30 | S35: MRK241115P00121000 | T35: 45600.685 | U35: 121 | V35: 19.4 | W35: 20 | X35: 20.3 | Y35: 0 | Z35: 0 | AA35: 2 | AB35: 0 | AC35: 0.71142867 | AD35: TRUE | AE35: REGULAR | AF35: USD | AG35: Put
A36: 31 | B36: MRK241115C00122000 | C36: 45590.648 | D36: 122 | E36: 0.1 | F36: 0 | G36: 0.29 | H36: 0 | I36: 0 | J36: 2 | K36: 5 | L36: 0.58203543 | M36: FALSE | N36: REGULAR | O36: USD | P36: Call | R36: 31 | S36: MRK241115P00122000 | U36: 122 | V36: 0 | W36: 19.050003 | X36: 20.850006 | Y36: 0 | Z36: 0 | AB36: 0 | AC36: 0.71142867 | AD36: TRUE | AE36: REGULAR | AF36: USD | AG36: Put
A37: 32 | B37: MRK241115C00125000 | C37: 45601.636 | D37: 125 | E37: 0.02 | F37: 0.01 | G37: 0.02 | H37: 0 | I37: 0 | J37: 30 | K37: 3922 | L37: 0.51172363 | M37: FALSE | N37: REGULAR | O37: USD | P37: Call | R37: 32 | S37: MRK241115P00125000 | T37: 45600.85 | U37: 125 | V37: 23.45 | W37: 23.95 | X37: 24.25 | Y37: 0 | Z37: 0 | AA37: 19 | AB37: 14 | AC37: 0.78613495 | AD37: TRUE | AE37: REGULAR | AF37: USD | AG37: Put
A38: 33 | B38: MRK241115C00130000 | C38: 45600.703 | D38: 130 | E38: 0.01 | F38: 0 | G38: 0.04 | H38: 0 | I38: 0 | J38: 7 | K38: 1660 | L38: 0.66797207 | M38: FALSE | N38: REGULAR | O38: USD | P38: Call | R38: 33 | S38: MRK241115P00130000 | T38: 45600.851 | U38: 130 | V38: 28.1 | W38: 28.6 | X38: 30.5 | Y38: 0 | Z38: 0 | AA38: 22 | AB38: 20 | AC38: 1.0625047 | AD38: TRUE | AE38: REGULAR | AF38: USD | AG38: Put
A39: 34 | B39: MRK241115C00135000 | C39: 45600.628 | D39: 135 | E39: 0.01 | F39: 0 | G39: 0.28 | H39: 0 | I39: 0 | J39: 2 | K39: 471 | L39: 0.82422051 | M39: FALSE | N39: REGULAR | O39: USD | P39: Call | R39: 34 | S39: MRK241115P00135000 | T39: 45595.832 | U39: 135 | V39: 30.38 | W39: 32.95 | X39: 35.55 | Y39: 0 | Z39: 0 | AB39: 0 | AC39: 1.0654344 | AD39: TRUE | AE39: REGULAR | AF39: USD | AG39: Put
A40: 35 | B40: MRK241115C00140000 | C40: 45560.831 | D40: 140 | E40: 0.08 | F40: 0 | G40: 0.29 | H40: 0 | I40: 0 | J40: 4 | K40: 17 | L40: 0.91406336 | M40: FALSE | N40: REGULAR | O40: USD | P40: Call | R40: 35 | S40: MRK241115P00140000 | U40: 140 | V40: 0 | W40: 36.799988 | X40: 40.5 | Y40: 0 | Z40: 0 | AB40: 0 | AC40: 1.0654344 | AD40: TRUE | AE40: REGULAR | AF40: USD | AG40: Put
A41: 36 | B41: MRK241115C00145000 | C41: 45558.609 | D41: 145 | E41: 0.04 | F41: 0 | G41: 0.28 | H41: 0 | I41: 0 | J41: 1 | K41: 23 | L41: 1.453616 | M41: FALSE | N41: REGULAR | O41: USD | P41: Call | R41: 36 | S41: MRK241115P00145000 | U41: 145 | V41: 0 | W41: 41.550003 | X41: 45.5 | Y41: 0 | Z41: 0 | AB41: 0 | AC41: 1.0654344 | AD41: TRUE | AE41: REGULAR | AF41: USD | AG41: Put
A42: 37 | B42: MRK241115C00150000 | C42: 45548.676 | D42: 150 | E42: 0.05 | F42: 0 | G42: 0.14 | H42: 0 | I42: 0 | J42: 1 | K42: 33 | L42: 0.9296882 | M42: FALSE | N42: REGULAR | O42: USD | P42: Call | R42: 37 | S42: MRK241115P00150000 | U42: 150 | V42: 0 | W42: 46.449997 | X42: 50.449997 | Y42: 0 | Z42: 0 | AB42: 0 | AC42: 1.0654344 | AD42: TRUE | AE42: REGULAR | AF42: USD | AG42: Put
A43: 38 | B43: MRK241115C00155000 | C43: 45551.761 | D43: 155 | E43: 0.08 | F43: 0 | G43: 0.28 | H43: 0 | I43: 0 | J43: 1 | K43: 1 | L43: 1.1406293 | M43: FALSE | N43: REGULAR | O43: USD | P43: Call | R43: 38 | S43: MRK241115P00155000 | U43: 155 | V43: 0 | W43: 51.699997 | X43: 55.449997 | Y43: 0 | Z43: 0 | AB43: 0 | AC43: 1.0654344 | AD43: TRUE | AE43: REGULAR | AF43: USD | AG43: Put
A44: 39 | B44: MRK241115C00160000 | C44: 45553.696 | D44: 160 | E44: 0.01 | F44: 0 | G44: 0.28 | H44: 0 | I44: 0 | J44: 16 | K44: 22 | L44: 1.3876984 | M44: FALSE | N44: REGULAR | O44: USD | P44: Call | R44: 39 | S44: MRK241115P00160000 | U44: 160 | V44: 0 | W44: 56.75 | X44: 60.399994 | Y44: 0 | Z44: 0 | AB44: 0 | AC44: 1.0654344 | AD44: TRUE | AE44: REGULAR | AF44: USD | AG44: Put
A45: 40 | B45: MRK241115C00170000 | C45: 45545.747 | D45: 170 | E45: 0.03 | F45: 0 | G45: 0.28 | H45: 0 | I45: 0 | J45: 0 | K45: 0 | L45: 1.3085972 | M45: FALSE | N45: REGULAR | O45: USD | P45: Call | R45: 40 | S45: MRK241115P00170000 | U45: 170 | V45: 0 | W45: 66.449997 | X45: 70.449997 | Y45: 0 | Z45: 0 | AB45: 0 | AC45: 1.0654344 | AD45: TRUE | AE45: REGULAR | AF45: USD | AG45: Put
A48: CALLS | R48: PUTS
A49: index | B49: Ticker | C49: lastTradeDate | D49: strike | E49: lastPrice | F49: bid | G49: ask | H49: change | I49: percentChange | J49: volume | K49: openInterest | L49: impliedVolatility | M49: inTheMoney | N49: contractSize | O49: currency | P49: Type | R49: index | S49: contract Symbol | T49: lastTradeDate | U49: strike | V49: lastPrice | W49: bid | X49: ask | Y49: change | Z49: percentChange | AA49: volume | AB49: openInterest | AC49: impliedVolatility | AD49: inTheMoney | AE49: contractSize | AF49: currency | AG49: Type
A50: 6 | B50: MRK241115C00095000 | C50: 45601.621 | D50: 95 | E50: 6.95 | F50: 6.65 | G50: 6.95 | H50: -0.9699998 | I50: -13.342501 | J50: 7 | K50: 68 | L50: 0.25391371 | M50: TRUE | N50: REGULAR | O50: USD | P50: Call | R50: 6 | S50: MRK241115P00095000 | T50: 45601.646 | U50: 95 | V50: 0.32 | W50: 0 | X50: 0.33 | Y50: -0.02000001 | Z50: -5.8823557 | AA50: 3 | AB50: 1531 | AC50: 0.31934274 | AD50: FALSE | AE50: REGULAR | AF50: USD | AG50: Put
A51: 7 | B51: MRK241115C00098000 | C51: 45597.675 | D51: 98 | E51: 4.2 | F51: 4.15 | G51: 4.3 | H51: 0 | I51: 0 | J51: 3 | K51: 54 | L51: 0.25733165 | M51: TRUE | N51: REGULAR | O51: USD | P51: Call | R51: 7 | S51: MRK241115P00098000 | T51: 45601.634 | U51: 98 | V51: 0.81 | W51: 0.08 | X51: 0.26 | Y51: 0.06999999 | Z51: 9.459458 | AA51: 1 | AB51: 386 | AC51: 0.29785858 | AD51: FALSE | AE51: REGULAR | AF51: USD | AG51: Put
