Workbook

Sheet Income Statement
A1: Company Fundamentals - Income Statement
A2: Company Name | B2: E W Scripps Co (SSP.O)
A3: Country of Exchange | B3: United States of America
A4: Country of Headquarters | B4: United States of America
A5: TRBC Industry Group | B5: Media & Publishing
A6: CF Template | B6: IND
A7: Consolidation Basis | B7: Consolidated
A8: Scaling | B8: Millions
A9: Period | B9: Annual
A10: Export Date | B10: 45835.823
A11: Statement Data | B11: 2024 | C11: 2023 | D11: 2022 | E11: 2021 | F11: 2020 | G11: 2019 | H11: 2018 | I11: 2017 | J11: 2016 | K11: 2015 | L11: 2014 | M11: 2013 | N11: 2012 | O11: 2011 | P11: 2010
A12: Period End Date | B12: 45657 | C12: 45291 | D12: 44926 | E12: 44561 | F12: 44196 | G12: 43830 | H12: 43465 | I12: 43100 | J12: 42735 | K12: 42369 | L12: 42004 | M12: 41639 | N12: 41274 | O12: 40908 | P12: 40543
A13: Statement Date | B13: 45657 | C13: 45291 | D13: 44926 | E13: 44561 | F13: 44196 | G13: 44196 | H13: 44196 | I13: 43465 | J13: 43465 | K13: 43100 | L13: 42369 | M13: 42369 | N13: 42004 | O13: 41274 | P13: 41274
A14: Standardized Currency | B14: USD | C14: USD | D14: USD | E14: USD | F14: USD | G14: USD | H14: USD | I14: USD | J14: USD | K14: USD | L14: USD | M14: USD | N14: USD | O14: USD | P14: USD
A15: Template Type | B15: Industrial - Operating | C15: Industrial - Operating | D15: Industrial - Operating | E15: Industrial - Operating | F15: Industrial - Operating | G15: Industrial - Operating | H15: Industrial - Operating | I15: Industrial - Operating | J15: Industrial - Operating | K15: Industrial - Operating | L15: Industrial - Operating | M15: Industrial - Operating | N15: Industrial - Operating | O15: Industrial - Operating | P15: Industrial - Operating
A17: Income Statement - Standardized (Currency: Standardized)
A18: Field Name | B18: 31-12-2024 | C18: 31-12-2023 | D18: 31-12-2022 | E18: 31-12-2021 | F18: 31-12-2020 | G18: 31-12-2019 | H18: 31-12-2018 | I18: 31-12-2017 | J18: 31-12-2016 | K18: 31-12-2015 | L18: 31-12-2014 | M18: 31-12-2013 | N18: 31-12-2012 | O18: 31-12-2011 | P18: 31-12-2010
A19: Revenues
A20: Revenue from Goods & Services | B20: 2477.29 | C20: 2257.22 | D20: 2417.71 | E20: 2229.71 | F20: 1776.47 | G20: 1274.69 | H20: 1130.23 | I20: 823.59 | J20: 829.47 | K20: 625.82 | L20: 477.73 | M20: 413.24 | N20: 859.71 | O20: 670.87 | P20: 722.69
A21: Sales of Goods & Services - Net - Unclassified | B21: 2477.29 | C21: 2257.22 | D21: 2417.71 | E21: 2229.71 | F21: 1776.47 | G21: 1274.69 | H21: 1130.23 | I21: 823.59 | J21: 829.47 | K21: 625.82 | L21: 477.73 | M21: 413.24 | N21: 859.71 | O21: 670.87 | P21: 722.69
A22: Revenue from Business-Related Activities - Other - Total | B22: 32.49 | C22: 35.7 | D22: 35.51 | E22: 53.83 | F22: 81.01 | G22: 76.71 | H22: 27.13 | I22: 53.38 | J22: 44.98 | K22: 28.36 | L22: 21.02 | M22: 19.12 | N22: 43.75 | O22: 57.79 | P22: 54.2
A23: Revenue from Business Activities - Total | B23: 2509.77 | C23: 2292.91 | D23: 2453.22 | E23: 2283.53 | F23: 1857.48 | G23: 1351.4 | H23: 1157.36 | I23: 876.97 | J23: 874.45 | K23: 654.17 | L23: 498.75 | M23: 432.36 | N23: 903.46 | O23: 728.66 | P23: 776.89
A24: Operating Expenses
A25: Cost of Operating Revenue | B25: 1476 | C25: 1438.43 | D25: 1394.2 | E25: 1268.15 | F25: 637.94 | G25: 482.66 | H25: 375.3 | I25: 284.95 | J25: 227.82 | K25: 161.96 | L25: 87.67 | M25: 84.35 | N25: 207.76 | O25: 200.1 | P25: 200.24
A26: Cost of Revenues - Total | B26: 1476 | C26: 1438.43 | D26: 1394.2 | E26: 1268.15 | F26: 637.94 | G26: 482.66 | H26: 375.3 | I26: 284.95 | J26: 227.82 | K26: 161.96 | L26: 87.67 | M26: 84.35 | N26: 207.76 | O26: 200.1 | P26: 200.24
A27: Cost of Revenues - Unclassified | B27: 1320.77 | C27: 1283.32 | D27: 1233.77 | E27: 1106.23 | F27: 530.79 | G27: 398.31 | H27: 314.59 | I27: 228.61 | J27: 172.62 | K27: 112.17 | L27: 55.49 | M27: 53.83 | N27: 158.43 | O27: 160.03 | P27: 155.35
A28: Amortization in Cost of Revenues | B28: 93.24 | C28: 94.38 | D28: 98.49 | E28: 103.57 | F28: 56.74 | G28: 44.35 | H28: 26.33 | I28: 22.29 | J28: 22.73 | K28: 16.98 | L28: 8.01 | M28: 6.38 | N28: 7.07 | O28: 1.25 | P28: 1.38
A29: Depreciation in Cost of Revenues | B29: 61.99 | C29: 60.73 | D29: 61.94 | E29: 58.36 | F29: 50.42 | G29: 40 | H29: 34.39 | I29: 34.05 | J29: 32.47 | K29: 32.81 | L29: 24.17 | M29: 24.14 | N29: 42.26 | O29: 38.82 | P29: 43.52
A30: Gross Profit - Industrials/Property - Total | B30: 1033.77 | C30: 854.48 | D30: 1059.01 | E30: 1015.38 | F30: 1219.54 | G30: 868.74 | H30: 782.07 | I30: 592.02 | J30: 646.63 | K30: 492.22 | L30: 411.09 | M30: 348.01 | N30: 695.7 | O30: 528.56 | P30: 576.65
A31: Selling, General & Administrative Expenses - Total | B31: 606.18 | C31: 614.77 | D31: 623.16 | E31: 595.11 | F31: 572.28 | G31: 476.97 | H31: 376.44 | I31: 367.74 | J31: 343.57 | K31: 316.42 | L31: 296.03 | M31: 259.48 | N31: 396.24 | O31: 410.86 | P31: 344.65
A32: Selling, General & Administrative Expenses - Unclassified | L32: 31.16 | M32: 26.27 | O32: 51.58
A33: Labor & Related Expenses including Stock-Based Compensation in Selling, General & Administrative Expenses | F33: 572.28 | G33: 476.97 | H33: 376.44 | I33: 367.74 | J33: 343.57 | K33: 316.42 | L33: 257.87 | M33: 225.64 | N33: 396.24 | O33: 348.18 | P33: 344.65
A34: Selling, General & Administrative Expenses - Other - Total | L34: 7 | M34: 7.56 | O34: 11.1
A35: Advertising Expense | L35: 7 | M35: 7.56 | O35: 11.1
A36: Other Operating Expense/(Income) - Net | F36: 324.43 | G36: 276.43 | H36: 233.94 | I36: 185.87 | J36: 173.8 | K36: 149.45 | L36: 82.69 | M36: 88.44 | N36: 209.92 | O36: 119.48 | P36: 186.52
A37: Other Operating Expense | F37: 324.43 | G37: 276.43 | H37: 233.94 | I37: 185.87 | J37: 173.8 | K37: 149.45 | L37: 82.69 | M37: 88.44 | N37: 209.92 | O37: 119.48 | P37: 186.52
A38: Operating Expenses - Total | B38: 2082.18 | C38: 2053.2 | D38: 2017.36 | E38: 1863.25 | F38: 1534.65 | G38: 1236.06 | H38: 985.67 | I38: 838.55 | J38: 745.19 | K38: 627.83 | L38: 466.38 | M38: 432.27 | N38: 813.92 | O38: 730.44 | P38: 731.42
A39: Operating Profit
A40: Operating Profit before Non-Recurring Income/Expense | B40: 427.59 | C40: 239.71 | D40: 435.85 | E40: 420.28 | F40: 322.83 | G40: 115.34 | H40: 171.69 | I40: 38.42 | J40: 129.26 | K40: 26.34 | L40: 32.37 | M40: 0.09 | N40: 89.54 | O40: -1.77 | P40: 45.47
A41: Non-Operating Expenses
A42: Financing Income/(Expense) - Net - Total | B42: -210.34 | C42: -213.51 | D42: -161.13 | E42: -165.16 | F42: -92.99 | G42: -80.6 | H42: -36.18 | I42: -26.7 | J42: -18.04 | K42: -15.1 | L42: -8.49 | M42: -10.44 | N42: -12.25 | O42: -1.64 | P42: -3.67
A43: Interest Expense - Net of (Interest Income) | B43: 210.34 | C43: 213.51 | D43: 161.13 | E43: 165.16 | F43: 92.99 | G43: 80.6 | H43: 36.18 | I43: 26.7 | J43: 18.04 | K43: 15.1 | L43: 8.49 | M43: 10.44 | N43: 12.25 | O43: 1.64 | P43: 3.67
A44: Interest Expense - Net of Capitalized Interest | B44: 210.34 | C44: 213.51 | D44: 161.13 | E44: 165.16 | F44: 92.99 | G44: 80.6 | H44: 36.18 | I44: 26.7 | J44: 18.04 | K44: 15.1 | L44: 8.49 | M44: 10.44 | N44: 12.25 | O44: 1.64 | P44: 3.67
A45: Sale of Tangible & Intangible Fixed Assets - Gain/(Loss) | B45: 18.42 | C45: -2.34 | D45: -5.87 | E45: 30.28 | F45: -0.66 | G45: 1.69 | H45: -1.25 | I45: -0.17 | J45: -0.48 | K45: -0.3 | L45: 2.87 | M45: -0.3 | N45: -0.47 | O45: 0.12 | P45: -1.22
A46: Equity Earnings/(Loss) - before Taxes including Non-Recurring | E46: -99.12
A47: Other Non-Operating Income/(Expense) - Total | B47: 7.83 | C47: -0.76 | D47: 0.66 | E47: -15.81 | F47: -1.47 | G47: -5.76 | H47: -19.63 | I47: -11.88 | J47: -16.98 | K47: -60.09 | L47: -7.69 | M47: -11.35 | N47: -4.75 | O47: -0.67 | P47: 1.8
A48: Normalized Pre-tax Profit | B48: 243.51 | C48: 23.1 | D48: 269.52 | E48: 170.46 | F48: 227.7 | G48: 30.68 | H48: 114.63 | I48: -0.32 | J48: 93.77 | K48: -49.15 | L48: 19.05 | M48: -21.99 | N48: 72.07 | O48: -3.97 | P48: 42.39
A49: Non-Recurring Income/Expense
A50: Non-Recurring Income/(Expense) - Total | B50: -33.52 | C50: -990.61 | D50: 6.95 | E50: 16.63 | F50: -18.68 | G50: -29.67 | H50: -21.95 | I50: -31.75 | J50: -0.58 | K50: -62.6 | L50: -9.71 | N50: -15.16 | O50: -21.72 | P50: -12.68
A51: Impairment - Tangible & Intangible Fixed Assets | C51: 952 | H51: 8.92 | I51: 35.73 | K51: 24.61 | O51: 9
A52: Impairment - Fixed Assets | H52: 8.92 | O52: 9
A53: Impairment - Goodwill | C53: 952 | I53: 35.73 | K53: 24.61
A54: Restructuring Charges | B54: 33.53 | C54: 38.61 | E54: 9.44 | G54: 3.37 | H54: 8.91 | I54: 4.42 | N54: 9.34 | O54: 9.94 | P54: 12.68
A55: Early Extinguishment of Lease Related Debts - Gain/(Loss) | D55: 8.59 | E55: -15.35
A56: Sale & Acquisition of Group Companies - Gain/(Loss) | D56: -1.64 | E56: 41.41 | F56: -18.68 | G56: -26.3 | H56: -4.12 | I56: 3 | J56: -0.58 | K56: -37.99 | L56: -9.71 | N56: -5.83 | O56: -2.79
A57: Non-Recurring Income/(Expense) - Other - Total | I57: 5.4
A58: Pre-Tax Income
A59: Income before Taxes | B59: 209.98 | C59: -967.51 | D59: 276.46 | E59: 187.09 | F59: 209.02 | G59: 1 | H59: 92.67 | I59: -32.08 | J59: 93.19 | K59: -111.76 | L59: 9.35 | M59: -21.99 | N59: 56.91 | O59: -25.69 | P59: 29.71
A60: Taxes
A61: Income Taxes | B61: 63.76 | C61: -19.73 | D61: 80.56 | E61: 71.19 | F61: 55.46 | G61: 2.92 | H61: 22.78 | I61: -15.85 | J61: 33.27 | K61: -37.88 | L61: -0.11 | M61: -11.91 | N61: 16.99 | O61: -10 | P61: 0.84
A62: Income Taxes for the Year - Current | B62: 77.23 | C62: 42.22 | D62: 67.65 | E62: 61.19 | F62: -10.65 | G62: 8.88 | H62: 6.2 | I62: -0.75 | J62: -0.72 | K62: -3.31 | L62: -6.41 | M62: -3.2 | N62: 8.69 | O62: -19.79 | P62: -24.75
A63: Income Taxes - Domestic - Current | B63: 76.18 | C63: 42.22 | D63: 67.65 | E63: 61.24 | F63: -10.76 | G63: 8.89 | H63: 6.2 | I63: -0.75 | J63: -0.72 | K63: -3.31 | L63: -6.41 | M63: -3.2 | N63: 8.69 | O63: -26.73 | P63: -38.74
A64: Income Taxes - Foreign - Current | B64: 1.05 | E64: -0.05 | F64: 0.11 | G64: -0.01 | H64: 0
A65: Income Taxes - Other (KFAS/NLST) - Current | O65: 6.95 | P65: 13.99
A66: Income Taxes - Deferred | B66: -13.47 | C66: -61.94 | D66: 12.91 | E66: 10 | F66: 66.11 | G66: -5.96 | H66: 16.58 | I66: -15.11 | J66: 33.99 | K66: -34.58 | L66: 6.3 | M66: -8.71 | N66: 8.3 | O66: 9.79 | P66: 25.59
A67: Income Taxes - Domestic - Deferred | B67: -13.44 | C67: -60.75 | D67: 13.65 | E67: 9.7 | F67: 66.66 | G67: -6.14 | H67: 16.59 | I67: -15.11 | J67: 33.99 | K67: -34.58 | L67: 6.4 | M67: -7.8 | N67: 7.19 | O67: 16.64 | P67: 28.27
A68: Income Taxes - Foreign - Deferred | B68: -0.03 | C68: -1.19 | D68: -0.74 | E68: 0.29 | F68: -0.55 | G68: 0.18 | H68: 0
A69: Income Taxes - Other - Deferred | L69: -0.1 | M69: -0.91 | N69: 1.11 | O69: -6.85 | P69: -2.68
A70: Net Income After Tax
A71: Net Income after Tax | B71: 146.22 | C71: -947.78 | D71: 195.9 | E71: 115.9 | F71: 153.56 | G71: -1.91 | H71: 69.89 | I71: -16.22 | J71: 59.92 | K71: -73.87 | L71: 9.46 | M71: -10.09 | N71: 39.92 | O71: -15.69 | P71: 28.87
A72: After Tax Income/Expense
A73: Income before Discontinued Operations & Extraordinary Items | B73: 146.22 | C73: -947.78 | D73: 195.9 | E73: 115.9 | F73: 153.56 | G73: -1.91 | H73: 69.89 | I73: -16.22 | J73: 59.92 | K73: -73.87 | L73: 9.46 | M73: -10.09 | N73: 39.92 | O73: -15.69 | P73: 28.87
A74: Extraordinary Activities - after Tax - Gain/(Loss) | E74: 6.81 | F74: 115.77 | G74: -16.46 | H74: -50.14 | I74: 1.61 | J74: 7.31 | K74: -8.6 | L74: 1.07 | M74: 9.61 | P74: 101.54
A75: Discontinued Operations - Net of Taxes - Total - Income/(Expense) | E75: 6.81 | F75: 115.77 | G75: -16.46 | H75: -50.14 | I75: -2.59 | J75: 7.31 | K75: -8.6 | L75: 1.07 | M75: 9.61 | P75: 101.54
A76: Discontinued Operations - Net - Income/(Expense) | G76: -16.46 | H76: -50.14 | K76: -8.6 | L76: 1.07 | M76: 9.61 | P76: 101.54
A77: Discontinued Operations before Tax - Total - Income/(Expense) | E77: 8.97 | F77: 150.23 | I77: 0.4 | J77: 12.78
A78: Discontinued Operations before Tax - Income/(Expense) | E78: 8.97 | F78: 150.23 | I78: 0.4 | J78: 12.78
A79: Discontinued Operations - Tax Impacts | E79: -2.16 | F79: -34.46 | I79: -3 | J79: -5.46
A80: Extraordinary Items | I80: 4.2
A81: Net Income before Minority Interest | B81: 146.22 | C81: -947.78 | D81: 195.9 | E81: 122.71 | F81: 269.33 | G81: -18.38 | H81: 19.75 | I81: -14.62 | J81: 67.24 | K81: -82.48 | L81: 10.53 | M81: -0.47 | N81: 39.92 | O81: -15.69 | P81: 130.41
A82: Minority Interest | H82: -0.63 | I82: -1.51 | N82: -0.27 | O82: -0.15 | P82: -0.1
A83: Net Income after Minority Interest | B83: 146.22 | C83: -947.78 | D83: 195.9 | E83: 122.71 | F83: 269.33 | G83: -18.38 | H83: 20.38 | I83: -13.11 | J83: 67.24 | K83: -82.48 | L83: 10.53 | M83: -0.47 | N83: 40.19 | O83: -15.54 | P83: 130.51
A84: Net Income
A85: Distribution for Preferred Shares | B85: 58.62 | C85: 50.31 | D85: 50.31 | E85: 49.37 | P85: 14.6
A86: Earnings Adjustments to Net Income - Other Expense/(Income) | D86: 3.66 | F86: 3.71 | H86: 1.13 | J86: 0.82
A87: Income Available to Common Shares | B87: 87.6 | C87: -998.09 | D87: 141.94 | E87: 73.34 | F87: 265.62 | G87: -18.38 | H87: 19.25 | I87: -13.11 | J87: 66.42 | K87: -82.48 | L87: 10.53 | M87: -0.47 | N87: 40.19 | O87: -15.54 | P87: 115.91
A88: Other Comprehensive Income
A89: Other Comprehensive Income - Starting Line | B89: 146.22 | C89: -947.78 | D89: 195.9 | E89: 122.71 | F89: 269.33 | G89: -18.38 | H89: 19.75 | I89: -14.62 | J89: 67.24 | K89: -82.48 | L89: 10.53 | M89: -0.47 | N89: 39.92 | O89: -15.69
A90: Other Comprehensive Income - Hedging Gain/(Loss) | J90: 0.24 | K90: 0.24 | L90: 0.24 | M90: 0.29 | N90: -1.01
A91: Other Comprehensive Income - Other | B91: -0.09 | C91: -0.12 | D91: 0.05 | E91: 0.13 | F91: -0.07 | G91: -0.22 | H91: -0.06 | I91: -0.35 | J91: 0.15 | K91: 0.25 | L91: -0.26 | M91: -0.18 | N91: -0.27 | O91: 0.73 | P91: 0.33
A92: Other Comprehensive Income - Pension Related | B92: 0.29 | C92: 2.08 | D92: -3.61 | E92: 26.08 | F92: -1.05 | G92: -3.37 | H92: 7.59 | I92: 10.15 | J92: -3.94 | K92: 33.83 | L92: -45.5 | M92: 35.81 | N92: -18.01 | O92: -16.73 | P92: 10.21
A93: Other Comprehensive Income - Net of Tax - Total | B93: 0.2 | C93: 1.96 | D93: -3.56 | E93: 26.21 | F93: -1.13 | G93: -3.59 | H93: 7.53 | I93: 9.8 | J93: -3.54 | K93: 34.32 | L93: -45.52 | M93: 35.92 | N93: -19.29 | O93: -16 | P93: 10.55
A94: Comprehensive Income before Minority Interest - Total | B94: 146.42 | C94: -945.82 | D94: 192.34 | E94: 148.92 | F94: 268.2 | G94: -21.97 | H94: 27.27 | I94: -4.82 | J94: 63.69 | K94: -48.16 | L94: -34.99 | M94: 35.44 | N94: 20.63 | O94: -31.69 | P94: 141.05
A95: Comprehensive Income - Attributable to Minority Interest - Total | H95: -0.63 | I95: -1.51 | N95: -0.27 | O95: -0.15 | P95: -0.1
A96: Comprehensive Income - Attributable to Parent Company Equity Holders - Total | B96: 146.42 | C96: -945.82 | D96: 192.34 | E96: 148.92 | F96: 268.2 | G96: -21.97 | H96: 27.91 | I96: -3.31 | J96: 63.69 | K96: -48.16 | L96: -34.99 | M96: 35.44 | N96: 20.9 | O96: -31.54 | P96: 141.05
A97: Share/Per Share - Basic
A98: Net Income - Basic - including Extraordinary Items Applicable to Common - Total | B98: 87.6 | C98: -998.09 | D98: 141.94 | E98: 73.34 | F98: 265.62 | G98: -18.38 | H98: 19.25 | I98: -13.11 | J98: 66.42 | K98: -82.48 | L98: 10.53 | M98: -0.47 | N98: 40.19 | O98: -15.54 | P98: 115.91
A99: Income available to Common excluding Extraordinary Items | B99: 87.6 | C99: -998.09 | D99: 141.94 | E99: 66.53 | F99: 149.85 | G99: -1.91 | H99: 69.39 | I99: -14.71 | J99: 59.11 | K99: -73.87 | L99: 9.46 | M99: -10.09 | N99: 40.19 | O99: -15.54 | P99: 14.37
A100: Shares used to calculate Basic EPS - Total | B100: 85.74 | C100: 84.27 | D100: 83.22 | E100: 82.33 | F100: 81.42 | G100: 80.83 | H100: 81.37 | I100: 82.05 | J100: 83.34 | K100: 77.37 | L100: 56.34 | M100: 56.52 | N100: 54.91 | O100: 57.22 | P100: 56.86
A101: EPS - Basic - including Extraordinary Items Applicable to Common - Total | B101: 1.02 | C101: -11.84 | D101: 1.71 | E101: 0.89 | F101: 3.26 | G101: -0.23 | H101: 0.24 | I101: -0.16 | J101: 0.8 | K101: -1.07 | L101: 0.19 | M101: -0.01 | N101: 0.73 | O101: -0.27 | P101: 2.04
...

Sheet Balance Sheet
A1: Company Fundamentals - Balance Sheet
A2: Company Name | B2: E W Scripps Co (SSP.O)
A3: Country of Exchange | B3: United States of America
A4: Country of Headquarters | B4: United States of America
A5: TRBC Industry Group | B5: Media & Publishing
A6: CF Template | B6: IND
A7: Consolidation Basis | B7: Consolidated
A8: Scaling | B8: Millions
A9: Period | B9: Annual
A10: Export Date | B10: 45835.823
A11: Statement Data | B11: 2024 | C11: 2023 | D11: 2022 | E11: 2021 | F11: 2020 | G11: 2019 | H11: 2018 | I11: 2017 | J11: 2016 | K11: 2015 | L11: 2014 | M11: 2013 | N11: 2012 | O11: 2011 | P11: 2010
A12: Period End Date | B12: 45657 | C12: 45291 | D12: 44926 | E12: 44561 | F12: 44196 | G12: 43830 | H12: 43465 | I12: 43100 | J12: 42735 | K12: 42369 | L12: 42004 | M12: 41639 | N12: 41274 | O12: 40908 | P12: 40543
A13: Statement Date | B13: 45657 | C13: 45291 | D13: 44926 | E13: 44561 | F13: 44196 | G13: 44012 | H13: 43465 | I13: 43100 | J13: 43100 | K13: 42369 | L13: 42369 | M13: 41639 | N13: 41364 | O13: 40908 | P13: 40908
A14: Standardized Currency | B14: USD | C14: USD | D14: USD | E14: USD | F14: USD | G14: USD | H14: USD | I14: USD | J14: USD | K14: USD | L14: USD | M14: USD | N14: USD | O14: USD | P14: USD
A15: Template Type | B15: Industrial - Differentiated | C15: Industrial - Differentiated | D15: Industrial - Differentiated | E15: Industrial - Differentiated | F15: Industrial - Differentiated | G15: Industrial - Differentiated | H15: Industrial - Differentiated | I15: Industrial - Differentiated | J15: Industrial - Differentiated | K15: Industrial - Differentiated | L15: Industrial - Differentiated | M15: Industrial - Differentiated | N15: Industrial - Differentiated | O15: Industrial - Differentiated | P15: Industrial - Differentiated
A17: Balance Sheet - Standardized (Currency: Standardized)
A18: Field Name | B18: 31-12-2024 | C18: 31-12-2023 | D18: 31-12-2022 | E18: 31-12-2021 | F18: 31-12-2020 | G18: 31-12-2019 | H18: 31-12-2018 | I18: 31-12-2017 | J18: 31-12-2016 | K18: 31-12-2015 | L18: 31-12-2014 | M18: 31-12-2013 | N18: 31-12-2012 | O18: 31-12-2011 | P18: 31-12-2010
A19: Current Assets
A20: Cash & Short-Term Investments | B20: 23.85 | C20: 35.32 | D20: 18.03 | E20: 66.22 | F20: 576.02 | G20: 32.97 | H20: 102.01 | I20: 148.7 | J20: 134.35 | K20: 108.06 | L20: 158.46 | M20: 221.26 | N20: 242.64 | O20: 127.89 | P20: 204.92
A21: Cash & Cash Equivalents | B21: 23.85 | C21: 35.32 | D21: 18.03 | E21: 66.22 | F21: 576.02 | G21: 32.97 | H21: 102.01 | I21: 148.7 | J21: 134.35 | K21: 108.06 | L21: 158.46 | M21: 221.26 | N21: 242.64 | O21: 127.89 | P21: 204.92
A22: Loans & Receivables - Net - Short-Term | B22: 568.19 | C22: 610.54 | D22: 600.1 | E22: 573.3 | F22: 441.38 | G22: 417.5 | H22: 300.57 | I22: 245.37 | J22: 178.54 | K22: 176.53 | L22: 99.61 | M22: 140.14 | N22: 128.57 | O22: 165.32 | P22: 130.16
A23: Trade Accounts & Trade Notes Receivable - Net | B23: 568.19 | C23: 610.54 | D23: 600.1 | E23: 572.53 | F23: 429.02 | G23: 387.85 | H23: 281.33 | I23: 245.37 | J23: 178.54 | K23: 171.9 | L23: 99.61 | M23: 139.7 | N23: 125.64 | O23: 135.54 | P23: 115.57
A24: Trade Accounts & Trade Notes Receivable - Gross | B24: 575.64 | C24: 615.58 | D24: 605.06 | E24: 576.78 | F24: 432.46 | G24: 391.19 | H24: 285.7 | I24: 247.31 | J24: 180.03 | K24: 173.51 | L24: 101 | M24: 141.73 | N24: 128.13 | O24: 137.42 | P24: 118.36
A25: Provision - Trade Accounts & Trade Notes Receivable | B25: 7.45 | C25: 5.04 | D25: 4.96 | E25: 4.26 | F25: 3.44 | G25: 3.35 | H25: 4.37 | I25: 1.95 | J25: 1.49 | K25: 1.61 | L25: 1.39 | M25: 2.03 | N25: 2.49 | O25: 1.89 | P25: 2.79
A26: Income Tax - Receivables - Short-Term | K26: 4.63 | L26: 0 | M26: 0.44 | N26: 2.93 | O26: 29.79 | P26: 14.6
A27: Receivables - Other - Total | D27: 0 | E27: 0.77 | F27: 12.36 | G27: 29.65 | H27: 19.24
A28: Inventories - Total | M28: 6.54 | N28: 6.44 | O28: 6.78 | P28: 7.86
A29: Assets Held for Sale/Discontinued Operations - Short-Term | F29: 0 | G29: 101.27 | H29: 0 | I29: 136 | J29: 14.22 | K29: 0 | L29: 44.43
A30: Other Current Assets - Total | B30: 37.97 | C30: 30.23 | D30: 25.82 | E30: 62.76 | F30: 1076.78 | G30: 92.19 | H30: 68.43 | I30: 75.47 | J30: 18.79 | K30: 18.04 | L30: 13.33 | M30: 34.12 | N30: 25.06 | O30: 25.42 | P30: 19.63
A31: Deferred Tax - Asset - Short-Term | M31: 17.86 | N31: 7.21 | O31: 7.23 | P31: 8.91
A32: Restricted Accounts - Short-Term | D32: 0 | E32: 34.26 | F32: 1050 | H32: 5.1 | K32: 6.56 | L32: 6.81 | M32: 8.21 | N32: 10.01 | O32: 10.01 | P32: 2.5
A33: Other Current Assets | B33: 37.97 | C33: 30.23 | D33: 25.82 | E33: 28.5 | F33: 26.78 | G33: 92.19 | H33: 63.33 | I33: 75.47 | J33: 18.79 | K33: 11.48 | L33: 6.52 | M33: 8.05 | N33: 7.84 | O33: 8.18 | P33: 8.22
A34: Total Current Assets | B34: 630.02 | C34: 676.09 | D34: 643.94 | E34: 702.28 | F34: 2094.19 | G34: 643.92 | H34: 471.02 | I34: 605.53 | J34: 345.9 | K34: 302.63 | L34: 315.82 | M34: 402.05 | N34: 402.7 | O34: 325.41 | P34: 362.58
A35: Non-Current Assets
A36: Investments - Long-Term | B36: 8.88 | C36: 23.27 | D36: 23.14 | E36: 21.63 | F36: 14.4 | G36: 8.38 | H36: 4.11 | I36: 4.6 | J36: 10.77 | K36: 10.65 | L36: 5.43 | M36: 16.57 | N36: 21.12 | O36: 15.3 | P36: 10.37
A37: Investments - Available for Sale/Held to Maturity - Long-Term | B37: 8.88 | C37: 23.27 | D37: 23.14 | E37: 21.63 | F37: 14.4 | G37: 8.38 | H37: 4.11 | I37: 4.6 | J37: 10.77 | K37: 10.65 | L37: 5.43 | M37: 16.57 | N37: 21.12 | O37: 15.3 | P37: 10.37
A38: Investments in Associates, Joint Ventures and Unconsolidated Subsidiaries | H38: 3.05 | I38: 3.1 | J38: 3.45 | K38: 3.2 | L38: 4.02 | O38: 7.92 | P38: 0.29
A39: Property, Plant & Equipment - Net - Total | B39: 544.04 | C39: 554.45 | D39: 576.47 | E39: 581.77 | F39: 395.39 | G39: 498.57 | H39: 237.93 | I39: 210 | J39: 225.44 | K39: 271.05 | L39: 157.84 | M39: 353.8 | N39: 374.93 | O39: 387.97 | P39: 389.65
A40: Property, Plant & Equipment - excluding Assets Leased Out - Net - Total | B40: 544.04 | C40: 554.45 | D40: 576.47 | E40: 581.77 | F40: 395.39 | G40: 498.57 | H40: 237.93 | I40: 210 | J40: 225.44 | K40: 271.05 | L40: 157.84 | M40: 353.8 | O40: 387.97 | P40: 389.65
A41: Right of Use Tangible Assets - Total - Net | G41: 128.19
A42: Right of Use Tangible Assets - Operating Lease - Net | G42: 128.19
A43: Property, Plant & Equipment - Other - Net | G43: 370.38
A44: Property, Plant & Equipment - Gross - Total | B44: 1111.27 | C44: 1070.37 | D44: 1038.66 | E44: 1000.15 | F44: 770.67 | H44: 560.55 | I44: 510.62 | J44: 498.54 | K44: 522.22 | L44: 384.83 | M44: 813.76 | O44: 819 | P44: 843.38
A45: Property, Plant & Equipment - excluding Assets Leased Out - Gross | B45: 1111.27 | C45: 1070.37 | D45: 1038.66 | E45: 1000.15 | F45: 770.67 | H45: 560.55 | I45: 510.62 | J45: 498.54 | K45: 522.22 | L45: 384.83 | M45: 813.76 | O45: 819 | P45: 843.38
A46: Land & Buildings - Gross | B46: 341.06 | C46: 317.8 | D46: 311.09 | E46: 270.38 | F46: 246.17 | H46: 196.21 | I46: 187.09 | J46: 184.42 | K46: 200.69 | L46: 131.3 | M46: 305.2 | O46: 297.77 | P46: 292.83
A47: Land/Improvements - Gross | B47: 65.21 | C47: 65.4 | D47: 65.56 | E47: 65.56 | F47: 62.66 | H47: 47.05 | I47: 47.41 | J47: 47.41 | K47: 59.18 | L47: 30.05 | M47: 73.98 | O47: 74.48 | P47: 72.73
A48: Buildings - Gross | B48: 275.84 | C48: 252.4 | D48: 245.53 | E48: 204.82 | F48: 183.52 | H48: 149.16 | I48: 139.69 | J48: 137.01 | K48: 141.51 | L48: 101.25 | M48: 231.22 | O48: 223.29 | P48: 220.1
A49: Plant, Machinery & Equipment - Gross | B49: 680.07 | C49: 653.38 | D49: 609.7 | E49: 604.95 | F49: 473.03 | H49: 364.34 | I49: 323.53 | J49: 314.12 | K49: 321.53 | L49: 253.53 | M49: 508.56 | O49: 521.23 | P49: 550.54
A50: Computer Software & Equipment - Gross | B50: 33.39 | C50: 30.4 | D50: 29.7 | E50: 29.03 | F50: 25.89 | H50: 17.49 | I50: 14.66 | J50: 14.58 | K50: 17.66 | L50: 17.82 | M50: 36.16 | O50: 34.56 | P50: 40.37
A51: Right of Use Tangible Assets - Total - Gross | B51: 90.14 | C51: 99.19 | D51: 117.87 | E51: 124.82 | F51: 51.47
A52: Right of Use Tangible Assets - Operating Lease - Gross | B52: 90.14 | C52: 99.19 | D52: 117.87 | E52: 124.82 | F52: 51.47
A53: Property, Plant & Equipment - Accumulated Depreciation & Impairment - Total | B53: 567.23 | C53: 515.92 | D53: 462.19 | E53: 418.38 | F53: 375.28 | H53: 322.63 | I53: 300.63 | J53: 273.1 | K53: 251.17 | L53: 226.99 | M53: 459.96 | O53: 431.03 | P53: 453.73
A54: Property, Plant & Equipment - excluding Assets Leased Out - Accumulated Depreciation & Impairment - Total | B54: 567.23 | C54: 515.92 | D54: 462.19 | E54: 418.38 | F54: 375.28 | H54: 322.63 | I54: 300.63 | J54: 273.1 | K54: 251.17 | L54: 226.99 | M54: 459.96 | O54: 431.03 | P54: 453.73
A55: Assets Held for Sale/Discontinued Operations - Long-Term | I55: 0 | J55: 131.82 | K55: 0 | L55: 174.98
A56: Other Non-Current Assets - Total | B56: 411.58 | C56: 460.56 | D56: 445.62 | E56: 528.94 | F56: 176.75 | G56: 125.64 | H56: 100.99 | I56: 124.4 | J56: 30.2 | K56: 28.35 | L56: 79.48 | M56: 27.88 | N56: 59.27 | O56: 53.48 | P56: 41.55
A57: Deferred Tax - Asset - Long-Term | F57: 0 | G57: 12.31 | H57: 9.14 | I57: 20.08 | J57: 16.61 | K57: 13.64 | L57: 65.37 | M57: 8.73 | N57: 36.1 | O57: 32.71 | P57: 30.84
A58: Other Non-Current Assets | B58: 411.58 | C58: 460.56 | D58: 445.62 | E58: 528.94 | F58: 176.75 | G58: 113.34 | H58: 91.85 | I58: 104.32 | J58: 13.59 | K58: 14.71 | L58: 14.12 | M58: 19.15 | N58: 23.18 | O58: 20.78 | P58: 10.71
A59: Intangible Assets - Total - Net | B59: 3604.06 | C59: 3695.75 | D59: 4741.83 | E59: 4823.7 | F59: 2178.66 | G59: 2285.35 | H59: 1312.97 | I59: 1181.92 | J59: 988.33 | K59: 1064.97 | L59: 293.52 | M59: 165.83 | N59: 172.75 | O59: 180.45 | P59: 23.11
A60: Goodwill/Cost in Excess of Assets Purchased - Net | B60: 1968.57 | C60: 1968.57 | D60: 2920.57 | E60: 2913.38 | F60: 1203.21 | G60: 1224.68 | H60: 834.01 | I60: 755.95 | J60: 575.78 | K60: 585.79 | L60: 106.26 | M60: 27.97 | N60: 27.97 | O60: 28.59 | P60: 0
A61: Intangible Assets - excluding Goodwill - Net - Total | B61: 1635.49 | C61: 1727.18 | D61: 1821.25 | E61: 1910.31 | F61: 975.44 | G61: 1060.68 | H61: 478.95 | I61: 425.98 | J61: 412.55 | K61: 479.19 | L61: 187.26 | M61: 137.86 | N61: 144.78 | O61: 151.86 | P61: 23.11
A62: Licenses, Franchises, Copyrights, Property Rights, Prototypes, Contract Based, Models & Designs - Net | B62: 779.42 | C62: 779.42 | D62: 779.82 | E62: 781.02 | F62: 356.82 | G62: 385.92 | H62: 157.22 | I62: 157.22 | J62: 157.22 | K62: 203.82 | L62: 92.22 | M62: 57.82 | N62: 57.82 | O62: 57.82 | P62: 13.2
A63: Intangible Assets - Other - Net | B63: 856.07 | C63: 947.76 | D63: 1041.44 | E63: 1129.3 | F63: 618.63 | G63: 674.76 | H63: 321.74 | I63: 268.76 | J63: 255.34 | K63: 275.37 | L63: 95.04 | M63: 80.05 | N63: 86.97 | O63: 94.04 | P63: 9.91
A64: Intangible Assets - Gross - Total | B64: 5357.14 | C64: 5355.6 | D64: 5355.64 | E64: 5340.22 | F64: 2621.53 | G64: 2672.01 | H64: 1695.88 | I64: 1535.49 | J64: 1291.78 | K64: 1346.48 | L64: 531.85 | M64: 1184.8 | N64: 1185.01
A65: Goodwill/Cost in Excess of Assets Purchased - Gross | B65: 3158.49 | C65: 3158.49 | D65: 3158.49 | E65: 3151.3 | F65: 1441.13 | G65: 1462.59 | H65: 1101.33 | I65: 1023.27 | J65: 813.69 | K65: 823.7 | L65: 321.68 | M65: 1022.28 | N65: 1022.28
A66: Intangible Assets - excluding Goodwill - Gross | B66: 2198.65 | C66: 2197.11 | D66: 2197.16 | E66: 2188.92 | F66: 1180.4 | G66: 1209.42 | H66: 594.55 | I66: 512.23 | J66: 478.08 | K66: 522.78 | L66: 210.18 | M66: 162.52 | N66: 162.73 | O66: 163.59 | P66: 38.25
A67: Licenses, Franchises, Copyrights, Property Rights, Prototypes, Contract Based, Models & Designs - Gross | B67: 779.42 | C67: 779.42 | D67: 779.82 | E67: 781.02 | F67: 356.82 | G67: 385.92 | H67: 157.22 | I67: 157.22 | J67: 157.22 | K67: 203.82 | L67: 92.22 | M67: 57.82 | N67: 57.82 | O67: 57.82 | P67: 13.2
A68: Intangible Assets - Other - Gross - Total | B68: 1419.24 | C68: 1417.69 | D68: 1417.34 | E68: 1407.91 | F68: 823.59 | G68: 823.5 | H68: 437.34 | I68: 355.01 | J68: 320.87 | K68: 318.97 | L68: 117.96 | M68: 104.71 | N68: 104.91 | O68: 105.77 | P68: 25.05
A69: Intangible Assets - Accumulated Amortization & Impairment - Total | B69: 1753.08 | C69: 1659.84 | D69: 613.82 | E69: 516.53 | F69: 442.87 | G69: 386.65 | H69: 382.92 | I69: 353.57 | J69: 303.45 | K69: 281.51 | L69: 238.33 | M69: 1018.98 | N69: 1012.26
A70: Goodwill - Accumulated Amortization & Impairment | B70: 1189.91 | C70: 1189.91 | D70: 237.91 | E70: 237.91 | F70: 237.91 | G70: 237.91 | H70: 267.32 | I70: 267.32 | J70: 237.91 | K70: 237.91 | L70: 215.41 | M70: 994.31 | N70: 994.31
A71: Intangible Assets - excluding Goodwill - Accumulated Amortization & Impairment - Total | B71: 563.17 | C71: 469.93 | D71: 375.9 | E71: 278.61 | F71: 204.96 | G71: 148.74 | H71: 115.6 | I71: 86.25 | J71: 65.53 | K71: 43.6 | L71: 22.92 | M71: 24.66 | N71: 17.95 | O71: 11.73 | P71: 15.14
A72: Intangible Assets - Other - Accumulated Amortization & Impairment | B72: 563.17 | C72: 469.93 | D72: 375.9 | E72: 278.61 | F72: 204.96 | G72: 148.74 | H72: 115.6 | I72: 86.25 | J72: 65.53 | K72: 43.6 | L72: 22.92 | M72: 24.66 | N72: 17.95 | O72: 11.73 | P72: 15.14
A73: Total Non-Current Assets | B73: 4568.56 | C73: 4734.03 | D73: 5787.06 | E73: 5956.03 | F73: 2765.2 | G73: 2917.94 | H73: 1659.04 | I73: 1524.01 | J73: 1390.01 | K73: 1378.23 | L73: 715.28 | M73: 564.08 | N73: 628.07 | O73: 645.12 | P73: 464.96
A74: Total Assets
A75: Total Assets | B75: 5198.58 | C75: 5410.12 | D75: 6431.01 | E75: 6658.31 | F75: 4859.39 | G75: 3561.86 | H75: 2130.06 | I75: 2129.55 | J75: 1735.91 | K75: 1680.86 | L75: 1031.1 | M75: 966.13 | N75: 1030.77 | O75: 970.53 | P75: 827.54
A76: Current Liabilities
A77: Trade Accounts Payable & Accruals - Short-Term | B77: 217.94 | C77: 181.19 | D77: 180.19 | E77: 203.14 | F77: 208.86 | G77: 113.39 | H77: 117.96 | I77: 109.98 | J77: 65.46 | K77: 90.67 | L77: 66.78 | M77: 72.44 | N77: 88.99 | O77: 74.51 | P77: 96.6
A78: Trade Accounts & Trade Notes Payable - Short-Term | B78: 100.67 | C78: 76.38 | D78: 82.71 | E78: 83.93 | F78: 68.14 | G78: 28.44 | H78: 26.92 | I78: 23.65 | J78: 15.98 | K78: 31.61 | L78: 13.99 | M78: 16.53 | N78: 23.33 | O78: 17.7 | P78: 34.09
A79: Accrued Expenses - Short-Term | B79: 117.27 | C79: 104.8 | D79: 97.48 | E79: 119.21 | F79: 140.72 | G79: 84.95 | H79: 91.04 | I79: 86.34 | J79: 49.48 | K79: 59.06 | L79: 52.79 | M79: 55.92 | N79: 65.66 | O79: 56.81 | P79: 62.51
A80: Short-Term Debt & Current Portion of Long-Term Debt | B80: 15.61 | C80: 15.61 | D80: 19.04 | E80: 18.61 | F80: 10.61 | G80: 10.61 | H80: 3 | I80: 5.66 | J80: 6.57 | K80: 6.66 | L80: 2 | M80: 2 | N80: 15.9 | O80: 15.9 | P80: 0
A81: Current Portion of Long-Term Debt including Capitalized Leases | B81: 15.61 | C81: 15.61 | D81: 19.04 | E81: 18.61 | F81: 10.61 | G81: 10.61 | H81: 3 | I81: 5.66 | J81: 6.57 | K81: 6.66 | L81: 2 | M81: 2 | N81: 15.9 | O81: 15.9 | P81: 0
A82: Current Portion of Long-Term Debt excluding Capitalized Leases | B82: 15.61 | C82: 15.61 | D82: 18.61 | E82: 18.61 | F82: 10.61 | G82: 10.61 | H82: 3 | I82: 5.66 | J82: 6.57 | K82: 6.66 | L82: 2 | M82: 2 | N82: 15.9 | O82: 15.9 | P82: 0
A83: Capitalized Leases - Current Portion | C83: 0 | D83: 0.43
A84: Liabilities Held for Sale/Discontinued Operations - Short-Term | G84: 22.73 | H84: 0 | I84: 19.54 | J84: 2.88 | K84: 0 | L84: 47.64
A85: Income Taxes - Payable - Short-Term | B85: 33.18 | O85: 0 | P85: 7.31
A86: Operating Lease Liabilities - Current Portion/Short-Term | B86: 18.09 | C86: 19.47 | D86: 19.6 | E86: 20.07 | F86: 9.62 | G86: 15.05
A87: Other Current Liabilities - Total | B87: 197.57 | C87: 261.56 | D87: 266.18 | E87: 270.06 | F87: 129.36 | G87: 150.25 | H87: 77.1 | I87: 75.61 | J87: 29.22 | K87: 22.5 | L87: 18.12 | M87: 38.68 | N87: 41.14 | O87: 34.64 | P87: 34.57
A88: Deferred Income - Short-Term | B88: 18.16 | C88: 12.18 | D88: 18.18 | E88: 20 | F88: 14.1 | G88: 10.7 | H88: 11.46
A89: Customer Advances - Short-Term | I89: 7.35 | J89: 6.41 | K89: 8.51 | L89: 8.81 | M89: 28.63 | N89: 26.24 | O89: 26.37 | P89: 26.07
A90: Other Current Liabilities | B90: 179.42 | C90: 249.37 | D90: 247.99 | E90: 250.06 | F90: 115.26 | G90: 139.54 | H90: 65.64 | I90: 68.26 | J90: 22.81 | K90: 13.99 | L90: 9.31 | M90: 10.04 | N90: 14.9 | O90: 8.27 | P90: 8.5
A91: Total Current Liabilities | B91: 482.39 | C91: 477.82 | D91: 485.01 | E91: 511.88 | F91: 358.46 | G91: 312.03 | H91: 198.06 | I91: 210.79 | J91: 104.13 | K91: 119.82 | L91: 134.54 | M91: 113.12 | N91: 146.03 | O91: 125.05 | P91: 138.48
A92: Non-Current Liabilities
A93: Debt - Long-Term - Total | B93: 2591.58 | C93: 2926.97 | D93: 2881.86 | E93: 3129.39 | F93: 2923.36 | G93: 1904.42 | H93: 685.76 | I93: 687.62 | J93: 386.61 | K93: 392.49 | L93: 194.37 | M93: 198 | N93: 180.2 | O93: 196.1 | P93: 0
A94: Long-Term Debt excluding Capitalized Leases | B94: 2560.56 | C94: 2896.82 | D94: 2853.79 | E94: 3129.39 | F94: 2923.36 | G94: 1904.42 | H94: 685.76 | I94: 687.62 | J94: 386.61 | K94: 392.49 | L94: 194.37 | M94: 198 | N94: 180.2 | O94: 196.1 | P94: 0
A95: Debt - Non-Convertible - Long-Term | B95: 2560.56 | C95: 2896.82 | D95: 2853.79 | E95: 3129.39 | F95: 2923.36 | G95: 1904.42 | H95: 685.76 | I95: 687.62 | J95: 386.61 | K95: 392.49 | L95: 194.37 | M95: 198 | N95: 180.2 | O95: 196.1 | P95: 0
A96: Capitalized Lease Obligations - Long-Term | B96: 31.02 | C96: 30.15 | D96: 28.06
A97: Liabilities Held for Sale/Discontinued Operations - Long-Term | I97: 0 | J97: 25.3 | K97: 0 | L97: 13.09
A98: Deferred Tax & Investment Tax Credits - Long-Term | B98: 293.63 | C98: 307.4 | D98: 370.46 | E98: 356.78 | F98: 85.84 | G98: 17.88 | H98: 25.53
A99: Deferred Tax - Liability - Long-Term | B99: 293.63 | C99: 307.4 | D99: 370.46 | E99: 356.78 | F99: 85.84 | G99: 17.88 | H99: 25.53
A100: Operating Lease Liabilities - Long-Term | B100: 79.4 | C100: 87.71 | D100: 106.87 | E100: 113.89 | F100: 42.1 | G100: 113.65
A101: Other Non-Current Liabilities - Total | B101: 433.55 | C101: 454.04 | D101: 456 | E101: 575.94 | F101: 286.37 | G101: 315.95 | H101: 294.54 | I101: 293.66 | J101: 273.93 | K101: 267.57 | L101: 169.17 | M101: 107.27 | N101: 164.63 | O101: 132.38 | P101: 97.53
...

Sheet Cash Flow
A1: Company Fundamentals - Cash Flow
A2: Company Name | B2: E W Scripps Co (SSP.O)
A3: Country of Exchange | B3: United States of America
A4: Country of Headquarters | B4: United States of America
A5: TRBC Industry Group | B5: Media & Publishing
A6: CF Template | B6: IND
A7: Consolidation Basis | B7: Consolidated
A8: Scaling | B8: Millions
A9: Period | B9: Annual
A10: Export Date | B10: 45835.823
A11: Statement Data | B11: 2024 | C11: 2023 | D11: 2022 | E11: 2021 | F11: 2020 | G11: 2019 | H11: 2018 | I11: 2017 | J11: 2016 | K11: 2015 | L11: 2014 | M11: 2013 | N11: 2012 | O11: 2011 | P11: 2010
A12: Period End Date | B12: 45657 | C12: 45291 | D12: 44926 | E12: 44561 | F12: 44196 | G12: 43830 | H12: 43465 | I12: 43100 | J12: 42735 | K12: 42369 | L12: 42004 | M12: 41639 | N12: 41274 | O12: 40908 | P12: 40543
A13: Statement Date | B13: 45657 | C13: 45291 | D13: 44926 | E13: 44561 | F13: 44196 | G13: 43830 | H13: 43465 | I13: 43100 | J13: 42735 | K13: 42735 | L13: 42735 | M13: 42369 | N13: 41274 | O13: 40908 | P13: 40543
A14: Standardized Currency | B14: USD | C14: USD | D14: USD | E14: USD | F14: USD | G14: USD | H14: USD | I14: USD | J14: USD | K14: USD | L14: USD | M14: USD | N14: USD | O14: USD | P14: USD
A15: Template Type | B15: Industrial - Indirect | C15: Industrial - Indirect | D15: Industrial - Indirect | E15: Industrial - Indirect | F15: Industrial - Indirect | G15: Industrial - Indirect | H15: Industrial - Indirect | I15: Industrial - Indirect | J15: Industrial - Indirect | K15: Industrial - Indirect | L15: Industrial - Indirect | M15: Industrial - Indirect | N15: Industrial - Indirect | O15: Industrial - Indirect | P15: Industrial - Indirect
A17: Cash Flow - Standardized (Currency: Standardized)
A18: Field Name | B18: 31-12-2024 | C18: 31-12-2023 | D18: 31-12-2022 | E18: 31-12-2021 | F18: 31-12-2020 | G18: 31-12-2019 | H18: 31-12-2018 | I18: 31-12-2017 | J18: 31-12-2016 | K18: 31-12-2015 | L18: 31-12-2014 | M18: 31-12-2013 | N18: 31-12-2012 | O18: 31-12-2011 | P18: 31-12-2010
A19: Operating Cash Flow - Indirect
A20: Profit/(Loss) - Starting Line - Cash Flow | B20: 146.22 | C20: -947.78 | D20: 195.9 | E20: 122.71 | F20: 269.33 | G20: -18.38 | H20: 19.75 | I20: -14.62 | J20: 67.24 | K20: -82.48 | L20: 10.53 | M20: -0.47 | N20: 39.92 | O20: -15.69 | P20: 130.41
A21: Non-cash Items & Reconciliation Adjustments - Cash Flow | B21: 163.81 | C21: 1096.17 | D21: 178.47 | E21: 171.68 | F21: 68.87 | G21: 90.47 | H21: 139.43 | I21: 65.31 | J21: 115.12 | K21: 135.1 | L21: 38.52 | M21: 38.45 | N21: 66.16 | O21: 67.41 | P21: -34.05
A22: Discontinued Operations - Gain/(Loss) - Net of Tax - Cash Flow - to Reconcile | E22: -6.81 | F22: -115.77 | H22: 36.33 | I22: 2.6 | K22: 15.84 | L22: -1.07 | M22: -9.61 | P22: -94.84
A23: Equity Income/(Loss) in Net Earnings - Cash Flow - to Reconcile | B23: -19.89
A24: Other Non-Cash Items & Reconciliation Adjustments - Cash Flow - to Reconcile | B24: 29.06 | C24: 24.79 | D24: -20.21 | E24: -6.18 | F24: -21.68 | G24: -4.14 | H24: 7.51 | I24: -23.21 | J24: 5.61 | K24: 58.91 | L24: -2.09 | M24: 12.8 | N24: -0.16 | O24: 10.49 | P24: -17.75
A25: Depreciation, Depletion & Amortization including Impairment - Cash Flow - to Reconcile | B25: 155.23 | C25: 1107.11 | D25: 160.43 | E25: 161.92 | F25: 107.16 | G25: 86.99 | H25: 63.99 | I25: 92.08 | J25: 58.58 | K25: 76.57 | L25: 32.18 | M25: 30.52 | N25: 49.33 | O25: 40.07 | P25: 44.89
A26: Depreciation & Depletion - Property, Plant & Equipment - Cash Flow - to Reconcile | B26: 155.23 | C26: 155.1 | D26: 160.43 | E26: 161.92 | F26: 107.16 | G26: 86.99 | H26: 63.99 | I26: 56.34 | J26: 58.58 | K26: 51.95 | L26: 32.18 | M26: 30.52 | N26: 49.33 | O26: 40.07 | P26: 44.89
A27: Impairment - Property, Plant & Equipment including Intangible Assets - Cash Flow - to Reconcile | C27: 952 | I27: 35.73 | K27: 24.61
A28: Deferred Income Taxes & Income Tax Credits - Cash Flow - to Reconcile | B28: -0.15 | C28: -63.7 | D28: 12.92 | E28: 9.73 | F28: 80.64 | G28: -4.66 | H28: 19.35 | I28: -16.08 | J28: 39.27 | K28: -26.83 | L28: 5.38 | M28: -4.34 | N28: 8.3 | O28: 9.79 | P28: 25.82
A29: Assets Sale - Gain/(Loss) - Cash Flow - to Reconcile | B29: -18.42 | C29: 2.34 | D29: 5.87 | E29: -112.06 | F29: 0.66 | G29: -2.62 | H29: 1.51 | I29: -5.94 | J29: 0.54 | K29: 0.48 | L29: -2.87 | M29: 3.3 | N29: 0.47 | O29: -0.12 | P29: -1.06
A30: Financial Assets - Unrealized Gain/(Loss) - Cash Flow - to Reconcile | E30: 99.12
A31: Share Based Payments - Cash Flow - to Reconcile | B31: 17.99 | C31: 25.63 | D31: 19.46 | E31: 25.96 | F31: 17.86 | G31: 14.91 | H31: 10.74 | I31: 15.87 | J31: 11.13 | K31: 10.13 | L31: 6.99 | M31: 5.78 | N31: 8.22 | O31: 7.2 | P31: 8.89
A32: Cash Flow from Operating Activities before Changes in Working Capital | B32: 310.03 | C32: 148.38 | D32: 374.37 | E32: 294.39 | F32: 338.2 | G32: 72.09 | H32: 159.18 | I32: 50.69 | J32: 182.36 | K32: 52.62 | L32: 49.05 | M32: 37.97 | N32: 106.09 | O32: 51.73 | P32: 96.36
A33: Working Capital - Increase/(Decrease) - Cash Flow | B33: 55.65 | C33: -36.78 | D33: -62.94 | E33: -63.45 | F33: 17.13 | G33: -99.55 | H33: -28.95 | I33: -20.51 | J33: -35.86 | K33: -43.79 | L33: 29.24 | M33: -31.21 | N33: 66.5 | O33: -36.94 | P33: -30.39
A34: Accounts Receivables - Decrease/(Increase) - Cash Flow | B34: 42.35 | C34: -10.44 | D34: -26.87 | E34: -31.62 | F34: -40.52 | G34: -104.96 | H34: -22.13 | I34: -22.52 | N34: 44.59 | O34: -25.58 | P34: -5.26
A35: Inventories - Decrease/(Increase) - Cash Flow | N35: 0.35 | O35: 1.08 | P35: -0.87
A36: Prepaid Expenses - Decrease/(Increase) - Cash Flow | N36: 5.9 | O36: 4.84 | P36: -62.77
A37: Other Assets - Decrease/(Increase) - Cash Flow | B37: -7.74 | C37: -4.63 | D37: 5.65 | E37: 12.49 | F37: 22.64 | G37: -11.35 | H37: -6.21
A38: Accounts Payable - Increase/(Decrease) - Cash Flow | B38: 13.18 | C38: -3.54 | D38: 7.31 | E38: 18.53 | F38: 19.52 | G38: 1.57 | H38: 0.97 | I38: -7.26 | N38: 5.63 | O38: -16.74 | P38: 12.07
A39: Accrued Expenses - Increase/(Decrease) - Cash Flow | B39: 10.01 | C39: 3.16 | D39: -22.97 | E39: 24.87 | F39: 7.16 | G39: 17.09 | H39: 7.69 | I39: 15.82 | N39: 2.72 | O39: -10.04 | P39: 8.43
A40: Other Liabilities - Increase/(Decrease) -Total - Cash Flow | B40: 3.3 | C40: -6 | D40: -3.11 | E40: -7.08 | F40: 3.4 | G40: 0.22 | H40: 2.92
A41: Other Assets & Liabilities - Increase/(Decrease) - Net - Cash Flow | B41: -5.44 | C41: -15.33 | D41: -22.94 | E41: -80.64 | F41: 4.93 | G41: -2.12 | H41: -12.18 | I41: -6.55 | J41: -35.86 | K41: -43.79 | L41: 29.24 | M41: -31.21 | N41: 7.3 | O41: 9.52 | P41: 18.02
A42: Net Cash Flow from Operating Activities | B42: 365.68 | C42: 111.6 | D42: 311.42 | E42: 230.94 | F42: 355.33 | G42: -27.45 | H42: 130.23 | I42: 30.19 | J42: 146.49 | K42: 8.83 | L42: 78.3 | M42: 6.76 | N42: 172.58 | O42: 14.79 | P42: 65.97
A43: Investing Cash Flow
A44: Capital Expenditures - Net - Cash Flow | B44: 44.79 | C44: 59.63 | D44: 43.12 | E44: 41.11 | F44: 18.47 | G44: 78.95 | H44: 58.95 | I44: 27.68 | J44: 27.89 | K44: 6.88 | L44: 10.44 | M44: 15.82 | N44: 30.21 | O44: 226.59 | P44: 18.33
A45: Property, Plant & Equipment - Purchased/(Sold) - Net - Cash Flow | B45: 44.79 | C45: 59.63 | D45: 43.12 | E45: 40.68 | F45: 16.58 | G45: 54.08 | H45: 51.72 | I45: 17.93 | J45: 27.89 | K45: 6.88 | L45: 10.44 | M45: 15.82 | N45: 30.21 | O45: 10.45 | P45: 17.48
A46: Property, Plant & Equipment - Purchased - Cash Flow | B46: 65.26 | C46: 59.63 | D46: 45.79 | E46: 60.74 | F46: 44.95 | G46: 61.04 | H46: 53.25 | I46: 17.93 | J46: 27.95 | K46: 23.11 | L46: 16.3 | M46: 15.86 | N46: 30.21 | O46: 12.18 | P46: 18.24
A47: Property, Plant & Equipment Sold - Cash Flow | B47: 20.46 | D47: 2.67 | E47: 20.06 | F47: 28.37 | G47: 6.96 | H47: 1.53 | J47: 0.06 | K47: 16.22 | L47: 5.86 | M47: 0.04 | O47: 1.74 | P47: 0.77
A48: Intangible Assets - Purchased/(Sold) - Net - Total - Cash Flow | E48: 0.43 | F48: 1.88 | G48: 24.86 | H48: 7.23 | I48: 9.74 | O48: 216.14 | P48: 0.85
A49: Intangible Assets - Purchased/Acquired - Cash Flow | E49: 0.43 | F49: 1.88 | G49: 24.86 | H49: 7.23 | I49: 9.74 | O49: 216.14 | P49: 0.85
A50: Capital Expenditures - Total | B50: 65.26 | C50: 59.63 | D50: 45.79 | E50: 61.17 | F50: 46.83 | G50: 85.91 | H50: 60.48 | I50: 27.68 | J50: 27.95 | K50: 23.11 | L50: 16.3 | M50: 15.86 | N50: 30.21 | O50: 228.33 | P50: 19.09
A51: Acquisition & Disposals of Business - Assets - Sold/(Acquired) - Net - Cash Flow | D51: -13.8 | E51: -2452.76 | F51: 76.64 | G51: -1190.42 | H51: -149.47 | I51: -280.94 | J51: -43.5 | K51: -46.84 | L51: -149.28 | N51: -0.27
A52: Acquisition of Business - Cash Flow | D52: 13.8 | E52: 2677.76 | F52: 7.1 | H52: 149.47
A53: Business - Sold - Cash Flow | E53: 224.99 | F53: 83.74
A54: Investments excluding Loans - Decrease/(Increase) - Cash Flow | B54: -1.73 | C54: -1 | D54: -7.37 | E54: -12.03 | F54: -8.31 | G54: -1.87 | H54: -0.56 | I54: -0.84 | J54: -2.13 | K54: -7.66 | L54: -2.65 | M54: -1.57 | N54: -5.07 | O54: -6.39 | P54: 10.51
A55: Investment Securities - Unclassified - Sold/(Purchased) - Net - Total - Cash Flow | B55: -1.73 | C55: -1 | D55: -7.37 | E55: -12.03 | F55: -8.31 | G55: -1.87 | H55: -0.56 | I55: -0.84 | J55: -2.13 | K55: -7.66 | L55: -2.65 | M55: -1.57 | N55: -5.07 | O55: -6.39 | P55: 10.51
A56: Investment Securities - Sold/Matured - Unclassified - Cash Flow | O56: 2.65 | P56: 12.18
A57: Investment Securities - Purchased - Unclassified - Cash Flow | B57: 1.73 | C57: 1 | D57: 7.37 | E57: 12.03 | F57: 8.31 | G57: 1.87 | H57: 0.56 | I57: 0.84 | J57: 2.13 | K57: 7.66 | L57: 2.65 | M57: 1.58 | N57: 5.07 | O57: 9.05 | P57: 1.67
A58: Investments - Associated Companies & Joint Ventures - Sold/(Purchased) - Cash Flow | B58: 19.99
A59: Other Investing Cash Flow - Decrease/(Increase) | C59: 0.02 | D59: 64.29 | E59: -2426.08 | F59: 60.5 | G59: -1257.77 | H59: -204.36 | I59: -283.68 | J59: -73.34 | K59: -58.22 | L59: -158.37 | M59: 1.87 | N59: 3.12 | O59: -248 | P59: -7.82
A60: Net Cash Flow from Investing Activities | B60: -26.54 | C60: -60.61 | E60: -4931.99 | F60: 110.36 | G60: -2529.01 | H60: -413.34 | I60: -593.13 | J60: -146.86 | K60: -119.6 | L60: -320.75 | M60: -15.52 | N60: -32.42 | O60: -480.99 | P60: -15.64
A61: Financing Cash Flow
A62: Dividends Paid - Cash - Total - Cash Flow | C62: 48 | D62: 48 | E62: 45.07 | F62: 16.57 | G62: 16.37 | H62: 16.4 | K62: 59.52
A63: Dividends - Common - Cash Paid | F63: 16.57 | G63: 16.37 | H63: 16.4 | K63: 59.52
A64: Dividends - Preferred - Cash Paid | C64: 48
A65: Stock - Total - Issuance/(Retirement) - Net - Cash Flow | E65: 600 | G65: -0.58 | H65: -30.47 | I65: -16.42 | J65: -39.76 | K65: -8.97 | L65: -4.66 | M65: -27.57 | N65: -5.35 | O65: -48.87 | P65: 8.39
A66: Stock - Issuance/(Retirement) - Net - Excluding Options/Warrants - Cash Flow | E66: 600 | G66: -0.58 | H66: -32.32 | I66: -17.89 | J66: -44.4 | K66: -16.22 | L66: -21.24 | M66: -74.2 | N66: -23.56 | O66: -51.38
A67: Stock - Common - Issuance/(Retirement) - Net - Cash Flow | G67: -0.58 | H67: -32.32 | I67: -17.89 | J67: -44.4 | K67: -16.22 | L67: -21.24 | M67: -74.2 | N67: -23.56 | O67: -51.38
A68: Stock - Common - Repurchased/Retired - Cash Flow | G68: 0.58 | H68: 32.32 | I68: 17.89 | J68: 44.4 | K68: 16.22 | L68: 21.24 | M68: 74.2 | N68: 23.56 | O68: 51.38
A69: Stock - Preferred - Issuance/(Retirement) - Net - Cash Flow | E69: 600
A70: Stock - Preferred - Issued/Sold - Cash Flow | E70: 600
A71: Options Exercised - Cash Flow | H71: 1.86 | I71: 1.46 | J71: 4.64 | K71: 7.25 | L71: 16.58 | M71: 46.62 | N71: 18.22 | O71: 2.51 | P71: 8.39
A72: Debt - Long-Term & Short-Term - Issuance/(Retirement) - Total - Cash Flow | B72: -345.61 | C72: 30.14 | D72: -278.1 | E72: 219 | F72: 1039.39 | G72: 1252.45 | H72: -5.66 | I72: 306.07 | J72: -6.63 | K72: 77.59 | L72: -2 | M72: 3.9 | N72: -15.9 | O72: 212 | P72: -34.9
A73: Debt - Issued/(Reduced) - Long-Term - Cash Flow | B73: -345.61 | C73: 30.14 | D73: -278.1 | E73: 219 | F73: 1039.39 | G73: 1252.45 | H73: -5.66 | I73: 306.07 | J73: -6.63 | K73: 77.59 | L73: -2 | M73: 3.9 | N73: -15.9 | O73: 212 | P73: -34.9
A74: Debt - Issued - Long-Term - Cash Flow | C74: 330 | E74: 800 | F74: 1050 | G74: 1261.18 | I74: 700 | K74: 200 | M74: 200 | O74: 212
A75: Debt - Reduced - Long-Term - Cash Flow | B75: 345.61 | C75: 299.86 | D75: 278.1 | E75: 581 | F75: 10.61 | G75: 8.73 | H75: 5.66 | I75: 393.93 | J75: 6.64 | K75: 122.41 | L75: 2 | M75: 196.1 | N75: 15.9 | P75: 34.9
A76: Other Financing Cash Flow - Increase/(Decrease) | B76: -5 | C76: -15.84 | D76: -1.39 | E76: -80.46 | F76: 973.54 | G76: 1200.16 | H76: -57.48 | I76: 255.48 | J76: -60.27 | K76: -5.41 | L76: -1.97 | M76: -11.22 | N76: -4.16 | O76: 134.21 | P76: -31.56
A77: Tax Payments or Benefits relating to Stock-based Compensation/Buyback/Withheld shares | B77: 1.88 | C77: 4.96 | D77: 8.87 | E77: 7.17 | F77: 2.88 | G77: 3.83 | H77: 3.8 | I77: 4.58 | J77: 2.68 | K77: 5.24 | L77: -4.09 | M77: 6.27 | N77: 3.45 | O77: 3.78 | P77: 2.51
A78: Net Cash Flow from Financing Activities | B78: -350.61 | C78: -33.71 | D78: -327.48 | E78: 693.48 | F78: 1996.36 | G78: 2435.65 | H78: -109.99 | I78: 545.12 | J78: -106.67 | K78: 3.69 | L78: -8.63 | M78: -34.9 | N78: -25.4 | O78: 297.34 | P78: -58.07
A79: Discontinued Cash Flow
A80: Net Cash Flow from Discontinued Operations - Operating Activities | E80: 6.06 | F80: -77.94 | H80: 10.68 | I80: 10.67 | K80: 0.04 | L80: 23.76 | M80: 26.74
A81: Net Cash Flow from Discontinued Operations - Investing Activities | E81: 10 | F81: 262.24 | H81: 79.19 | I81: -2.5 | K81: -1.56 | L81: -1.56 | M81: -4.36 | P81: 162.9
A82: Net Cash Flow from Discontinued Operations - Financing Activities | M82: -0.11
A83: Net Cash Flow from Discontinued Operations - Total | E83: 16.06 | F83: 184.31 | H83: 89.87 | I83: 8.17 | K83: -1.52 | L83: 22.2 | M83: 22.28 | P83: 162.9
A84: Foreign Exchange Effects
A85: Foreign Exchange Effects - Cash Flow | E85: -0.02 | F85: 0.06 | G85: -0.01 | H85: -0.01 | P85: 5.23
A86: Change in Cash
A87: Net Change in Cash - Total | B87: -11.47 | C87: 17.29 | D87: -82.45 | E87: -1525.54 | F87: 1593.05 | G87: -74.15 | H87: -41.58 | I87: 14.35 | J87: 19.73 | K87: -50.65 | L87: -64.2 | M87: -21.39 | N87: 114.75 | O87: -77.03 | P87: 197.24
A88: Net Cash from Continuing Operations | B88: -11.47 | C88: 17.29 | D88: -16.06 | E88: -4007.6 | F88: 2462.1 | G88: -120.83 | H88: -393.12 | I88: -17.82 | J88: -107.03 | K88: -107.09 | L88: -251.08 | M88: -43.66 | N88: 114.75 | O88: -168.86 | P88: -2.5
A89: Net Cash from Discontinued Operations | E89: 16.06 | F89: 184.31 | H89: 89.87 | I89: 8.17 | K89: -1.52 | L89: 22.2 | M89: 22.28 | P89: 162.9
A90: Net Cash - Beginning Balance | B90: 35.32 | C90: 18.03 | D90: 100.48 | E90: 1626.02 | F90: 32.97 | G90: 107.11 | H90: 148.7 | I90: 134.35 | J90: 114.62 | K90: 165.27 | L90: 229.47 | M90: 242.64 | N90: 127.89 | O90: 204.92 | P90: 7.68
A91: Net Cash - Ending Balance | B91: 23.85 | C91: 35.32 | D91: 18.03 | E91: 100.48 | F91: 1626.02 | G91: 32.97 | H91: 107.11 | I91: 148.7 | J91: 134.35 | K91: 114.62 | L91: 165.27 | M91: 221.26 | N91: 242.64 | O91: 127.89 | P91: 204.92
A92: Supplemental
A93: Income Taxes - Paid/(Reimbursed) - Cash Flow - Supplemental | B93: 71.81 | C93: 31.12 | D93: 61.74 | E93: 102.47 | F93: -13.22 | G93: 13.18 | H93: 3.73 | I93: 1.76 | J93: 1.1 | K93: 14.98 | L93: 0.46 | M93: 0.42 | N93: 7.09 | O93: 8.3 | P93: 40.49
A94: Interest Paid - Cash Flow - Supplemental | B94: 195.86 | C94: 195.83 | D94: 190.79 | E94: 126.26 | F94: 82.53 | G94: 61.3 | H94: 33.67 | I94: 18.96 | J94: 15.62 | K94: 13.44 | L94: 7.24 | M94: 8.07 | N94: 9.34 | O94: 0.29 | P94: 1.26
A95: CF from Optg Activities before Change in WC & Int Payments | B95: 310.03 | C95: 148.38 | D95: 374.37 | E95: 294.39 | F95: 338.2 | G95: 72.09 | H95: 159.18 | I95: 50.69 | J95: 182.36 | K95: 52.62 | L95: 49.05 | M95: 37.97 | N95: 106.09 | O95: 51.73 | P95: 96.36
A96: Cash Dividends Paid & Common Stock Buyback - Net | F96: 16.57 | G96: 16.96 | H96: 48.72 | I96: 17.89 | J96: 44.4 | K96: 75.75 | L96: 21.24 | M96: 74.2
A97: Common Stock Buyback - Net | G97: 0.58 | H97: 32.32 | I97: 17.89 | J97: 44.4 | K97: 16.22 | L97: 21.24 | M97: 74.2 | N97: 23.56 | O97: 51.38
A98: Depreciation, Depletion & Amortization - Cash Flow | B98: 155.23 | C98: 155.1 | D98: 160.43 | E98: 161.92 | F98: 107.16 | G98: 86.99 | H98: 63.99 | I98: 56.34 | J98: 58.58 | K98: 51.95 | L98: 32.18 | M98: 30.52 | N98: 49.33 | O98: 40.07 | P98: 44.89
A99: Free Cash Flow to Equity | B99: -24.72 | C99: 82.12 | D99: -9.79 | E99: 408.83 | F99: 1376.25 | G99: 1146.05 | H99: 65.62 | I99: 308.58 | J99: 111.97 | K99: 79.54 | L99: 65.85 | M99: -5.16 | N99: 126.47 | O99: 0.2 | P99: 12.75
A100: Free Cash Flow Net of Dividends | B100: 300.42 | C100: 3.98 | D100: 217.63 | E100: 124.7 | F100: 291.92 | G100: -129.73 | H100: 53.35 | I100: 2.51 | J100: 118.55 | K100: -73.8 | L100: 62 | M100: -9.1 | N100: 142.37 | O100: -213.54 | P100: 46.88
A101: Free Cash Flow | B101: 300.42 | C101: 51.98 | D101: 265.63 | E101: 169.76 | F101: 308.5 | G101: -113.36 | H101: 69.75 | I101: 2.51 | J101: 118.55 | K101: -14.28 | L101: 62 | M101: -9.1 | N101: 142.37 | O101: -213.54 | P101: 46.88
...

Sheet Operating Metrics
A1: Company Fundamentals - Operating Metrics
A2: Company Name | B2: E W Scripps Co (SSP.O)
A3: Country of Exchange | B3: United States of America
A4: Country of Headquarters | B4: United States of America
A5: TRBC Industry Group | B5: Media & Publishing
A6: CF Template | B6: IND
A7: Consolidation Basis | B7: Consolidated
A8: Scaling | B8: Millions
A9: Period | B9: Annual
A10: Measure system | B10: Metric
A11: Statement Data | B11: 2024 | C11: 2023 | D11: 2022 | E11: 2021 | F11: 2020 | G11: 2019 | H11: 2018 | I11: 2017 | J11: 2016
A12: Period End Date | B12: 45657 | C12: 45291 | D12: 44926 | E12: 44561 | F12: 44196 | G12: 43830 | H12: 43465 | I12: 43100 | J12: 42735
A13: Statement Date | B13: 45657 | C13: 45291 | D13: 44926 | E13: 44561 | F13: 44196 | G13: 44196 | H13: 43465 | I13: 43465 | J13: 43100
A14: Standardized Currency | B14: USD | C14: USD | D14: USD | E14: USD | F14: USD | G14: USD | H14: USD | I14: USD | J14: USD
A15: Template Type | B15: Industrial | C15: Industrial | D15: Industrial | E15: Industrial | F15: Industrial | G15: Industrial | H15: Industrial | I15: Industrial | J15: Industrial
A17: Operating Metrics - Standardized (Currency: Standardized)
A18: Field Name | B18: 31-12-2024 | C18: 31-12-2023 | D18: 31-12-2022 | E18: 31-12-2021 | F18: 31-12-2020 | G18: 31-12-2019 | H18: 31-12-2018 | I18: 31-12-2017 | J18: 31-12-2016
A19: Revenues, Costs & Other Measures
A20: Advertisement Revenue - Total | B20: 552253000 | C20: 598824000 | D20: 1549277000 | E20: 1592121000 | F20: 915515000 | G20: 861386000 | H20: 836049000 | I20: 563879000 | J20: 609612000
A21: Users & Payers
A22: Number of Subscribers - Media - Total | F22: 35000000

Sheet Financial Summary
A1: Company Fundamentals - Financial Summary
A2: Company Name | B2: E W Scripps Co (SSP.O)
A3: Country of Exchange | B3: United States of America
A4: Country of Headquarters | B4: United States of America
A5: TRBC Industry Group | B5: Media & Publishing
A6: CF Template | B6: IND
A7: Consolidation Basis | B7: Consolidated
A8: Scaling | B8: Millions
A9: Period | B9: Annual
A10: Export Date | B10: 45835.823
A11: Statement Data | B11: 2024 | C11: 2023 | D11: 2022 | E11: 2021 | F11: 2020 | G11: 2019 | H11: 2018 | I11: 2017 | J11: 2016 | K11: 2015 | L11: 2014 | M11: 2013 | N11: 2012 | O11: 2011 | P11: 2010
A12: Period End Date | B12: 45657 | C12: 45291 | D12: 44926 | E12: 44561 | F12: 44196 | G12: 43830 | H12: 43465 | I12: 43100 | J12: 42735 | K12: 42369 | L12: 42004 | M12: 41639 | N12: 41274 | O12: 40908 | P12: 40543
A13: Statement Date | B13: 45657 | C13: 45291 | D13: 44926 | E13: 44561 | F13: 44196 | G13: 44196 | H13: 44196 | I13: 43465 | J13: 43465 | K13: 43100 | L13: 42369 | M13: 42369 | N13: 42004 | O13: 41274 | P13: 41274
A14: Standardized Currency | B14: USD | C14: USD | D14: USD | E14: USD | F14: USD | G14: USD | H14: USD | I14: USD | J14: USD | K14: USD | L14: USD | M14: USD | N14: USD | O14: USD | P14: USD
A15: Template Type | B15: Industrial - Operating | C15: Industrial - Operating | D15: Industrial - Operating | E15: Industrial - Operating | F15: Industrial - Operating | G15: Industrial - Operating | H15: Industrial - Operating | I15: Industrial - Operating | J15: Industrial - Operating | K15: Industrial - Operating | L15: Industrial - Operating | M15: Industrial - Operating | N15: Industrial - Operating | O15: Industrial - Operating | P15: Industrial - Operating
A17: Financial Summary - Standardized (Currency: Standardized)
A18: Field Name | B18: 31-12-2024 | C18: 31-12-2023 | D18: 31-12-2022 | E18: 31-12-2021 | F18: 31-12-2020 | G18: 31-12-2019 | H18: 31-12-2018 | I18: 31-12-2017 | J18: 31-12-2016 | K18: 31-12-2015 | L18: 31-12-2014 | M18: 31-12-2013 | N18: 31-12-2012 | O18: 31-12-2011 | P18: 31-12-2010
A19: Selected Income Statement Items
A20: Revenue from Business Activities - Total | B20: 2509.77 | C20: 2292.91 | D20: 2453.22 | E20: 2283.53 | F20: 1857.48 | G20: 1351.4 | H20: 1157.36 | I20: 876.97 | J20: 874.45 | K20: 654.17 | L20: 498.75 | M20: 432.36 | N20: 903.46 | O20: 728.66 | P20: 776.89
A21: Gross Profit - Industrials/Property - Total | B21: 1033.77 | C21: 854.48 | D21: 1059.01 | E21: 1015.38 | F21: 1219.54 | G21: 868.74 | H21: 782.07 | I21: 592.02 | J21: 646.63 | K21: 492.22 | L21: 411.09 | M21: 348.01 | N21: 695.7 | O21: 528.56 | P21: 576.65
A22: Operating Profit before Non-Recurring Income/Expense | B22: 427.59 | C22: 239.71 | D22: 435.85 | E22: 420.28 | F22: 322.83 | G22: 115.34 | H22: 171.69 | I22: 38.42 | J22: 129.26 | K22: 26.34 | L22: 32.37 | M22: 0.09 | N22: 89.54 | O22: -1.77 | P22: 45.47
A23: Earnings before Interest, Taxes, Depreciation & Amortization (EBITDA) | B23: 582.82 | C23: 394.82 | D23: 596.29 | E23: 582.2 | F23: 429.98 | G23: 202.33 | H23: 235.68 | I23: 94.76 | J23: 187.84 | K23: 78.3 | L23: 64.55 | M23: 30.61 | N23: 138.87 | O23: 38.29 | P23: 90.37
A24: Income before Discontinued Operations & Extraordinary Items | B24: 146.22 | C24: -947.78 | D24: 195.9 | E24: 115.9 | F24: 153.56 | G24: -1.91 | H24: 69.89 | I24: -16.22 | J24: 59.92 | K24: -73.87 | L24: 9.46 | M24: -10.09 | N24: 39.92 | O24: -15.69 | P24: 28.87
A25: Selected Balance Sheet Items
A26: Cash & Cash Equivalents | B26: 23.85 | C26: 35.32 | D26: 18.03 | E26: 66.22 | F26: 576.02 | G26: 32.97 | H26: 102.01 | I26: 148.7 | J26: 134.35 | K26: 108.06 | L26: 158.46 | M26: 221.26 | N26: 242.64 | O26: 127.89 | P26: 204.92
A27: Cash & Short-Term Investments | B27: 23.85 | C27: 35.32 | D27: 18.03 | E27: 66.22 | F27: 576.02 | G27: 32.97 | H27: 102.01 | I27: 148.7 | J27: 134.35 | K27: 108.06 | L27: 158.46 | M27: 221.26 | N27: 242.64 | O27: 127.89 | P27: 204.92
A28: Total Assets | B28: 5198.58 | C28: 5410.12 | D28: 6431.01 | E28: 6658.31 | F28: 4859.39 | G28: 3561.86 | H28: 2130.06 | I28: 2129.55 | J28: 1735.91 | K28: 1680.86 | L28: 1031.1 | M28: 966.13 | N28: 1030.77 | O28: 970.53 | P28: 827.54
A29: Debt - Total | B29: 2607.19 | C29: 2942.58 | D29: 2900.89 | E29: 3148.01 | F29: 2933.97 | G29: 1915.03 | H29: 688.76 | I29: 693.28 | J29: 393.19 | K29: 399.14 | L29: 196.37 | M29: 200 | N29: 196.1 | O29: 212 | P29: 0
A30: Common Equity - Total | B30: 901.16 | C30: 741.63 | D30: 1718.58 | E30: 1560.5 | F30: 1163.27 | G30: 897.94 | H30: 926.17 | I30: 936.85 | J30: 945.94 | K30: 900.98 | L30: 518.28 | M30: 545.77 | N30: 537.7 | O30: 514.52 | P30: 588.9
A31: Selected Cash Flow Items
A32: Net Cash Flow from Operating Activities | B32: 365.68 | C32: 111.6 | D32: 311.42 | E32: 230.94 | F32: 355.33 | G32: -27.45 | H32: 130.23 | I32: 30.19 | J32: 146.49 | K32: 8.83 | L32: 78.3 | M32: 6.76 | N32: 172.58 | O32: 14.79 | P32: 65.97
A33: Depreciation, Depletion & Amortization including Impairment - Cash Flow - to Reconcile | B33: 155.23 | C33: 1107.11 | D33: 160.43 | E33: 161.92 | F33: 107.16 | G33: 86.99 | H33: 63.99 | I33: 92.08 | J33: 58.58 | K33: 76.57 | L33: 32.18 | M33: 30.52 | N33: 49.33 | O33: 40.07 | P33: 44.89
A34: Capital Expenditures - Net - Cash Flow | B34: 44.79 | C34: 59.63 | D34: 43.12 | E34: 41.11 | F34: 18.47 | G34: 78.95 | H34: 58.95 | I34: 27.68 | J34: 27.89 | K34: 6.88 | L34: 10.44 | M34: 15.82 | N34: 30.21 | O34: 226.59 | P34: 18.33
A35: Net Change in Cash - Total | B35: -11.47 | C35: 17.29 | D35: -82.45 | E35: -1525.54 | F35: 1593.05 | G35: -74.15 | H35: -41.58 | I35: 14.35 | J35: 19.73 | K35: -50.65 | L35: -64.2 | M35: -21.39 | N35: 114.75 | O35: -77.03 | P35: 197.24
A36: Free Cash Flow Net of Dividends | B36: 300.42 | C36: 3.98 | D36: 217.63 | E36: 124.7 | F36: 291.92 | G36: -129.73 | H36: 53.35 | I36: 2.51 | J36: 118.55 | K36: -73.8 | L36: 62 | M36: -9.1 | N36: 142.37 | O36: -213.54 | P36: 46.88
A37: Selected Per Share Data
A38: Dividend Yield - Common Stock - Gross - Issue Specific - % | B38: 0 | C38: 0 | D38: 0 | E38: 0 | F38: 1.31 | G38: 1.27 | H38: 1.27 | I38: 0 | J38: 0 | K38: 0 | L38: 0 | M38: 0 | N38: 0 | O38: 0 | P38: 0
A39: Dividend Yield - Common Stock - Net - Issue Specific - % | B39: 0 | C39: 0 | D39: 0 | E39: 0 | F39: 1.31 | G39: 1.27 | H39: 1.27 | I39: 0 | J39: 0 | K39: 0 | L39: 0 | M39: 0 | N39: 0 | O39: 0 | P39: 0
A40: EPS - Diluted - excluding Extraordinary Items Applicable to Common - Total | B40: 1.02 | C40: -11.84 | D40: 1.62 | E40: 1.39 | F40: 1.83 | G40: -0.02 | H40: 0.85 | I40: -0.18 | J40: 0.71 | K40: -0.95 | L40: 0.17 | M40: -0.18 | N40: 0.73 | O40: -0.27 | P40: 0.25
A41: Shares used to calculate Diluted EPS - Total | B41: 86.07 | C41: 84.27 | D41: 87.35 | E41: 87.98 | F41: 81.83 | G41: 80.83 | H41: 81.93 | I41: 82.05 | J41: 83.64 | K41: 77.37 | L41: 57.24 | M41: 56.52 | N41: 55.38 | O41: 57.22 | P41: 57
A42: Profitability / Return
A43: Gross Profit Margin - % | B43: 41.19 | C43: 37.27 | D43: 43.17 | E43: 44.47 | F43: 65.66 | G43: 64.28 | H43: 67.57 | I43: 67.51 | J43: 73.95 | K43: 75.24 | L43: 82.42 | M43: 80.49 | N43: 77 | O43: 72.54 | P43: 74.22
A44: EBITDA Margin - % | B44: 23.22 | C44: 17.22 | D44: 24.31 | E44: 25.5 | F44: 23.15 | G44: 14.97 | H44: 20.36 | I44: 10.81 | J44: 21.48 | K44: 11.97 | L44: 12.94 | M44: 7.08 | N44: 15.37 | O44: 5.26 | P44: 11.63
A45: Operating Margin - % | B45: 17.04 | C45: 10.45 | D45: 17.77 | E45: 18.4 | F45: 17.38 | G45: 8.53 | H45: 14.83 | I45: 4.38 | J45: 14.78 | K45: 4.03 | L45: 6.49 | M45: 0.02 | N45: 9.91 | O45: -0.24 | P45: 5.85
A46: Income before Tax Margin - % | B46: 8.37 | C46: -42.2 | D46: 11.27 | E46: 8.19 | F46: 11.25 | G46: 0.07 | H46: 8.01 | I46: -3.66 | J46: 10.66 | K46: -17.08 | L46: 1.87 | M46: -5.09 | N46: 6.3 | O46: -3.53 | P46: 3.82
A47: Income Tax Rate - % | B47: 30.37 | D47: 29.14 | E47: 38.05 | F47: 26.53 | G47: 290.54 | H47: 24.58 | J47: 35.7 | L47: -1.19 | N47: 29.85 | P47: 2.83
A48: Net Margin - % | B48: 5.83 | C48: -41.34 | D48: 7.99 | E48: 5.08 | F48: 8.27 | G48: -0.14 | H48: 6.04 | I48: -1.85 | J48: 6.85 | K48: -11.29 | L48: 1.9 | M48: -2.33 | N48: 4.42 | O48: -2.15 | P48: 3.72
A49: Free Cash Flow | B49: 300.42 | C49: 51.98 | D49: 265.63 | E49: 169.76 | F49: 308.5 | G49: -113.36 | H49: 69.75 | I49: 2.51 | J49: 118.55 | K49: -14.28 | L49: 62 | M49: -9.1 | N49: 142.37 | O49: -213.54 | P49: 46.88
A50: Return on Average Common Equity - % (Income available to Common excluding Extraordinary Items) | B50: 10.67 | C50: -81.14 | D50: 8.66 | E50: 4.88 | F50: 14.54 | G50: -0.21 | H50: 7.45 | I50: -1.56 | J50: 6.4 | K50: -10.41 | L50: 1.78 | M50: -1.86 | N50: 7.64 | O50: -2.82 | P50: 2.82
A51: Return on Average Total Assets - % (Income before Discontinued Operations & Extraordinary Items) | B51: 2.76 | C51: -16.01 | D51: 2.99 | F51: 3.65 | G51: -0.07 | H51: 3.28 | I51: -0.84 | J51: 3.51 | K51: -5.45 | L51: 0.95 | M51: -1.01 | N51: 3.99 | O51: -1.74 | P51: 3.58
A52: Return on Invested Capital - % | B52: 7.3 | D52: 6.11 | E52: 4.88 | F52: 9.77 | G52: -7.77 | H52: 2.94 | J52: 5.97 | L52: 2.61 | N52: 6.66 | P52: 25.27
A53: Growth
A54: Revenue from Business Activities - Total | B54: 2509.77 | C54: 2292.91 | D54: 2453.22 | E54: 2283.53 | F54: 1857.48 | G54: 1351.4 | H54: 1157.36 | I54: 876.97 | J54: 874.45 | K54: 654.17 | L54: 498.75 | M54: 432.36 | N54: 903.46 | O54: 728.66 | P54: 776.89
A55: Operating Profit before Non-Recurring Income/Expense | B55: 427.59 | C55: 239.71 | D55: 435.85 | E55: 420.28 | F55: 322.83 | G55: 115.34 | H55: 171.69 | I55: 38.42 | J55: 129.26 | K55: 26.34 | L55: 32.37 | M55: 0.09 | N55: 89.54 | O55: -1.77 | P55: 45.47
A56: Earnings before Interest, Taxes, Depreciation & Amortization (EBITDA) | B56: 582.82 | C56: 394.82 | D56: 596.29 | E56: 582.2 | F56: 429.98 | G56: 202.33 | H56: 235.68 | I56: 94.76 | J56: 187.84 | K56: 78.3 | L56: 64.55 | M56: 30.61 | N56: 138.87 | O56: 38.29 | P56: 90.37
A57: Income before Discontinued Operations & Extraordinary Items | B57: 146.22 | C57: -947.78 | D57: 195.9 | E57: 115.9 | F57: 153.56 | G57: -1.91 | H57: 69.89 | I57: -16.22 | J57: 59.92 | K57: -73.87 | L57: 9.46 | M57: -10.09 | N57: 39.92 | O57: -15.69 | P57: 28.87
A58: EPS - Diluted - excluding Extraordinary Items Applicable to Common - Total | B58: 1.02 | C58: -11.84 | D58: 1.62 | E58: 1.39 | F58: 1.83 | G58: -0.02 | H58: 0.85 | I58: -0.18 | J58: 0.71 | K58: -0.95 | L58: 0.17 | M58: -0.18 | N58: 0.73 | O58: -0.27 | P58: 0.25
A59: Common Shares - Outstanding - Total | B59: 86.63 | C59: 84.78 | D59: 83.58 | E59: 82.58 | F59: 81.73 | G59: 80.96 | H59: 80.67 | I59: 81.63 | J59: 81.98 | K59: 83.82 | L59: 57 | M59: 56.03 | N59: 55.53 | O59: 54.29 | P59: 58.34
A60: Financial Strength / Leverage
A61: Total Debt Percentage of Total Assets | B61: 50.15 | C61: 54.39 | D61: 45.11 | E61: 47.28 | F61: 60.38 | G61: 53.76 | H61: 32.34 | I61: 32.56 | J61: 22.65 | K61: 23.75 | L61: 19.04 | M61: 20.7 | N61: 19.02 | O61: 21.84 | P61: 0
A62: Total Debt Percentage of Total Capital | B62: 66.42 | C62: 71.79 | D62: 57.65 | E62: 61.5 | F62: 71.61 | G62: 68.08 | H62: 42.65 | I62: 42.51 | J62: 29.36 | K62: 30.7 | L62: 27.41 | M62: 26.75 | N62: 26.64 | O62: 29.08 | P62: 0
A63: Total Debt Percentage of Total Equity | B63: 197.81 | C63: 254.51 | D63: 136.14 | E63: 159.76 | F63: 252.22 | G63: 213.27 | H63: 74.37 | I63: 73.95 | J63: 41.57 | K63: 44.3 | L63: 37.77 | M63: 36.51 | N63: 36.32 | O63: 41.01 | P63: 0
A64: Debt Service | B64: 225.96 | C64: 230.84 | D64: 179.96 | F64: 103.61 | G64: 87.4 | H64: 40.51 | I64: 32.81 | J64: 24.65 | K64: 19.43 | L64: 10.49 | M64: 19.39 | N64: 28.15 | O64: 9.59 | P64: 3.67
A65: Debt Service Percentage of Normalized after Tax Profit | B65: 125.71 | C65: 538.99 | D65: 95.24 | E65: 181.1 | F65: 60.15 | G65: 314.84 | H65: 44.11 | I65: 211.24 | J65: 40.75 | L65: 54.76 | N65: 51.1 | O65: 158.91 | P65: 8.82
A66: Interest Coverage Ratio | B66: 2.03 | C66: 1.12 | D66: 2.7 | E66: 2.54 | F66: 3.47 | G66: 1.43 | H66: 4.75 | I66: 1.44 | J66: 7.17 | K66: 1.74 | L66: 3.81 | M66: 0.01 | N66: 7.31 | O66: -1.08 | P66: 12.4
A67: Dividend Coverage - % | F67: 904.15 | G67: -11.68 | H67: 423.25 | K67: -124.11
A68: Earnings Retention Rate | B68: 1 | D68: 1 | E68: 1 | F68: 0.89 | H68: 0.76 | J68: 1 | L68: 1 | N68: 1 | P68: 1
A69: Dividend Payout Ratio - % | B69: 0 | D69: 0 | E69: 0 | F69: 11.06 | H69: 23.63 | J69: 0 | L69: 0 | N69: 0 | P69: 0
A70: Enterprise Value Breakdown
A71: Market Capitalization | B71: 190.86 | C71: 674.98 | D71: 1101.25 | F71: 1247.66 | G71: 1271.17 | H71: 1268.98 | I71: 1280.1 | J71: 1602.42 | K71: 1593.53 | L71: 1081.65 | M71: 1033.82 | N71: 507.75 | O71: 374.6 | P71: 502.51
A72: Debt - Total | B72: 2607.19 | C72: 2942.58 | D72: 2900.89 | E72: 3148.01 | F72: 2933.97 | G72: 1915.03 | H72: 688.76 | I72: 693.28 | J72: 393.19 | K72: 399.14 | L72: 196.37 | M72: 200 | N72: 196.1 | O72: 212 | P72: 0
A73: Preferred Shareholders Equity | B73: 416.85 | C73: 414.55 | D73: 412.24 | E73: 409.94 | F73: 0 | G73: 0 | H73: 0 | I73: 0 | J73: 0
A74: Minority Interest - Total | H74: 0 | I74: 0.63 | J74: 0 | K74: 0 | L74: 1.66 | M74: 1.96 | N74: 2.21 | O74: 2.48 | P74: 2.63
A75: Cash & Short Term Investments - Total | B75: 23.85 | C75: 35.32 | D75: 18.03 | E75: 66.22 | F75: 576.02 | G75: 32.97 | H75: 102.01 | I75: 148.7 | J75: 134.35 | K75: 108.06 | L75: 158.46 | M75: 221.26 | N75: 242.64 | O75: 127.89 | P75: 204.92
A76: Enterprise Value | B76: 3191.06 | C76: 3996.8 | D76: 4396.36 | E76: 5088.57 | F76: 3605.61 | G76: 3153.23 | H76: 1855.73 | I76: 1825.31 | J76: 1861.25 | K76: 1884.61 | L76: 1121.22 | M76: 1014.52 | N76: 463.42 | O76: 461.2 | P76: 300.21
A77: Dupont / Earning Power
A78: Asset Turnover | B78: 0.47 | C78: 0.39 | D78: 0.37 | F78: 0.44 | G78: 0.47 | H78: 0.54 | I78: 0.45 | J78: 0.51 | K78: 0.48 | L78: 0.5 | M78: 0.43 | N78: 0.9 | O78: 0.81 | P78: 0.96
A79: Income before Tax Margin - % | B79: 8.37 | C79: -42.2 | D79: 11.27 | E79: 8.19 | F79: 11.25 | G79: 0.07 | H79: 8.01 | I79: -3.66 | J79: 10.66 | K79: -17.08 | L79: 1.87 | M79: -5.09 | N79: 6.3 | O79: -3.53 | P79: 3.82
A80: Pretax ROA - % | B80: 3.96 | C80: -16.34 | D80: 4.22 | E80: 3.25 | F80: 4.96 | G80: 0.04 | H80: 4.35 | I80: -1.66 | J80: 5.45 | K80: -8.24 | L80: 0.94 | M80: -2.2 | N80: 5.69 | O80: -2.86 | P80: 3.68
A81: Total Assets to Total Shareholders Equity - including Minority Interest & Hybrid Debt | B81: 4.29 | C81: 3.6 | D81: 3.19 | F81: 4.09 | G81: 3.12 | H81: 2.29 | I81: 2.05 | J81: 1.85 | K81: 1.91 | L81: 1.87 | M81: 1.84 | N81: 1.89 | O81: 1.62 | P81: 1.57
A82: Pretax ROE - % | B82: 16.97 | C82: -58.87 | D82: 13.48 | E82: 11.94 | F82: 20.28 | G82: 0.11 | H82: 9.95 | I82: -3.41 | J82: 10.09 | K82: -15.73 | L82: 1.75 | M82: -4.04 | N82: 10.77 | O82: -4.63 | P82: 5.8
A83: Tax Complement | B83: 0.7 | D83: 0.71 | E83: 0.62 | F83: 0.73 | G83: -1.91 | H83: 0.75 | J83: 0.64 | L83: 1.01 | N83: 0.7 | P83: 0.97
A84: Return on Average Common Equity - % (Income available to Common excluding Extraordinary Items) | B84: 10.67 | C84: -81.14 | D84: 8.66 | E84: 4.88 | F84: 14.54 | G84: -0.21 | H84: 7.45 | I84: -1.56 | J84: 6.4 | K84: -10.41 | L84: 1.78 | M84: -1.86 | N84: 7.64 | O84: -2.82 | P84: 2.82
A85: Earnings Retention Rate | B85: 1 | D85: 1 | E85: 1 | F85: 0.89 | H85: 0.76 | J85: 1 | L85: 1 | N85: 1 | P85: 1
A86: Reinvestment Rate - % | B86: 10.67 | C86: -81.14 | D86: 8.66 | E86: 4.88 | F86: 12.93 | G86: -2.01 | H86: 5.69 | I86: -1.56 | J86: 6.4 | K86: -18.8 | L86: 1.78 | M86: -1.86 | N86: 7.64 | O86: -2.82 | P86: 2.82
A87: Productivity
A88: Net Income after Tax per Employee | B88: 28670.2 | C88: -173905.32 | D88: 34672.92 | E88: 21072.55 | F88: 27179.47 | G88: -388.43 | H88: 17363.73 | I88: -3956.59 | J88: 15170.13 | K88: -17179.53 | L88: 1970.21 | M88: -2123.16 | N88: 8404.63 | O88: -3337.66
A89: Sales per Employee | B89: 492112.16 | C89: 420717.8 | D89: 434197.35 | E89: 415187.64 | F89: 328757.17 | G89: 274395.74 | H89: 287543.35 | I89: 213895.61 | J89: 221380 | K89: 152133.72 | L89: 103906.67 | M89: 91022.53 | N89: 190201.68 | O89: 155034.04
A90: Total Assets per Employee | B90: 1039715 | C90: 1040407.7 | D90: 1128246.5 | E90: 1188984.6 | F90: 899886.3 | G90: 603704.58 | H90: 539255.95 | I90: 519401.95 | J90: 423391.71 | K90: 442331.58 | L90: 214813.33 | M90: 201277.08 | N90: 219312.34 | O90: 202193.33 | P90: 179900.43
A91: Liquidity
A92: Current Ratio | B92: 1.31 | C92: 1.41 | D92: 1.33 | E92: 1.37 | F92: 5.84 | G92: 2.06 | H92: 2.38 | I92: 2.87 | J92: 3.32 | K92: 2.53 | L92: 2.35 | M92: 3.55 | N92: 2.76 | O92: 2.6 | P92: 2.62
A93: Quick Ratio | M93: 3.5 | N93: 2.71 | O93: 2.55 | P93: 2.56
A94: Working Capital to Total Assets | B94: 0.03 | C94: 0.04 | D94: 0.02 | E94: 0.03 | F94: 0.36 | G94: 0.09 | H94: 0.13 | I94: 0.19 | J94: 0.14 | K94: 0.11 | L94: 0.18 | M94: 0.3 | N94: 0.25 | O94: 0.21 | P94: 0.27
A95: Operating
A96: Accounts Receivable Turnover | B96: 4.26 | C96: 3.79 | D96: 4.18 | E96: 4.5 | F96: 4.33 | G96: 3.76 | H96: 4.24 | I96: 4.14 | J96: 4.93 | K96: 4.74 | L96: 4.16 | M96: 3.22 | N96: 6.15 | O96: 4.93 | P96: 5.05
A97: Average Receivables Collection Days | B97: 85.95 | C97: 96.62 | D97: 87.53 | E97: 81.32 | F97: 84.62 | G97: 97.24 | H97: 86.32 | I97: 88.46 | J97: 74.31 | K97: 77.25 | L97: 87.97 | M97: 113.73 | N97: 59.53 | O97: 74.21 | P97: 72.54
A98: Payables Turnover | B98: 16.67 | C98: 18.08 | D98: 16.73 | E98: 16.68 | F98: 13.21 | G98: 17.44 | H98: 14.84 | I98: 14.38 | J98: 9.58 | K98: 7.1 | L98: 5.75 | M98: 4.23 | N98: 10.13 | O98: 7.73 | P98: 6.76
A99: Average Payables Payment Days | B99: 21.95 | C99: 20.24 | D99: 21.87 | E99: 21.94 | F99: 27.71 | G99: 20.99 | H99: 24.66 | I99: 25.45 | J99: 38.22 | K99: 51.52 | L99: 63.7 | M99: 86.48 | N99: 36.14 | O99: 47.36 | P99: 54.16
A100: Inventory Turnover | M100: 13 | N100: 31.43 | O100: 27.33 | P100: 26.97
A101: Average Inventory Days | M101: 28.16 | N101: 11.64 | O101: 13.39 | P101: 13.57
...

Sheet Analysis
A1: Year | B1: 2014 | C1: 2015 | D1: 2016 | E1: 2017
A2: Revenue | B2: ='Income Statement'!L23 -> 498.75 | C2: ='Income Statement'!K23 -> 654.17 | D2: ='Income Statement'!J23 -> 874.45 | E2: ='Income Statement'!I23 -> 876.97
A3: CAGR(2014-2017) | B3: =(E2/B2)^(1/3)-1 -> 0.20698149
A4: Assumed Growth Rate | B4: 0.08 | F4: Although Scripps grew at a 21% CAGR from 2014 to 2017, structural industry changes such as cord-cutting, digital disruption, and advertising migration led analysts to project low-to-mid single-digit growth for traditional networks. (PwC Global E&M Outlook 2017–2021; Scripps 10-K 2016). Therefore, we apply a conservative but fair 8% annual revenue growth in our forecast.
A5: WACC | B5: =B89 -> 0.064350633 | F5: Aswath Damodaran – NYU Stern 2023 WACC Estimates
A6: g | B6: 0.025 | F6: ValueInvesting.io – Discovery WACC Breakdown
A7: Rf | B7: 0.0425 | F7: 10 Year Treasury
A8: Rm-Rf | B8: 0.055 | F8: Damodaran (NYU Stern Professor) publishes annual estimates, For U.S. in 2024/2025: ~5.5% Source: NYU Stern ERPs
A9: Beta | B9: 0.74 | F9: The beta of 0.74 used in this analysis is consistent with publicly available data from Reuters, representing the stock’s historical volatility relative to the market prior to its acquisition by Discovery.
A10: Rd | B10: ='Income Statement'!I177/Analysis!B51 -> 0.038512578
A11: Tc | B11: 0.25
A14: DCF Analysis
A16: Year | B16: 2014 | C16: 2015 | D16: 2016 | E16: 2017 | F16: 2018E | G16: 2019E | H16: 2020E | I16: 2021E | J16: 2022E | K16: 2023E | L16: 2024E | M16: 2025E
A17: Revenue | B17: =B2 -> 498.75 | C17: =C2 -> 654.17 | D17: =D2 -> 874.45 | E17: =E2 -> 876.97 | F17: =E17*(1+$B$4) -> 947.1276 | G17: =F17*(1+$B$4) -> 1022.8978 | H17: =G17*(1+$B$4) -> 1104.7296 | I17: =H17*(1+$B$4) -> 1193.108 | J17: =I17*(1+$B$4) -> 1288.5566 | K17: =J17*(1+$B$4) -> 1391.6412 | L17: =K17*(1+$B$4) -> 1502.9725 | M17: =L17*(1+$B$4) -> 1623.2103
A18: =A3 -> CAGR(2014-2017) | E18: =B3 -> 0.20698149
A19: =A4 -> Assumed Growth Rate | E19: =B4 -> 0.08
A21: Cost of Revenue | B21: ='Income Statement'!L26 -> 87.67 | C21: ='Income Statement'!K26 -> 161.96 | D21: ='Income Statement'!J26 -> 227.82 | E21: ='Income Statement'!I26 -> 284.95 | F21: =E17*$E$22 -> 284.95 | G21: =F17*$E$22 -> 307.746 | H21: =G17*$E$22 -> 332.36568 | I21: =H17*$E$22 -> 358.95493 | J21: =I17*$E$22 -> 387.67133 | K21: =J17*$E$22 -> 418.68504 | L21: =K17*$E$22 -> 452.17984 | M21: =L17*$E$22 -> 488.35423
A22: CoR % of Revenue | E22: =E21/E17 -> 0.3249256
A24: Other Op Exp | B24: ='Income Statement'!L36 -> 82.69 | C24: ='Income Statement'!K36 -> 149.45 | D24: ='Income Statement'!J36 -> 173.8 | E24: ='Income Statement'!I36 -> 185.87 | F24: =E17*$E$25 -> 185.87 | G24: =F17*$E$25 -> 200.7396 | H24: =G17*$E$25 -> 216.79877 | I24: =H17*$E$25 -> 234.14267 | J24: =I17*$E$25 -> 252.87408 | K24: =J17*$E$25 -> 273.10401 | L24: =K17*$E$25 -> 294.95233 | M24: =L17*$E$25 -> 318.54852
A25: Op Exp % of Revenue | E25: =E24/E17 -> 0.21194568
A27: EBIT | F27: =F17-F21-F24 -> 476.3076 | G27: =G17-G21-G24 -> 514.41221 | H27: =H17-H21-H24 -> 555.56518 | I27: =I17-I21-I24 -> 600.0104 | J27: =J17-J21-J24 -> 648.01123 | K27: =K17-K21-K24 -> 699.85213 | L27: =L17-L21-L24 -> 755.8403 | M27: =M17-M21-M24 -> 816.30752
A28: EBIT Margin % | F28: =F27/F17 -> 0.50289697 | G28: =G27/G17 -> 0.50289697 | H28: =H27/H17 -> 0.50289697 | I28: =I27/I17 -> 0.50289697 | J28: =J27/J17 -> 0.50289697 | K28: =K27/K17 -> 0.50289697 | L28: =L27/L17 -> 0.50289697 | M28: =M27/M17 -> 0.50289697
A30: Depreciation and Ammortization | B30: ='Cash Flow'!L98 -> 32.18 | C30: ='Cash Flow'!K98 -> 51.95 | D30: ='Cash Flow'!J98 -> 58.58 | E30: ='Cash Flow'!I98 -> 56.34 | F30: =F17*$E$31 -> 60.8472 | G30: =G17*$E$31 -> 65.714976 | H30: =H17*$E$31 -> 70.972174 | I30: =I17*$E$31 -> 76.649948 | J30: =J17*$E$31 -> 82.781944 | K30: =K17*$E$31 -> 89.404499 | L30: =L17*$E$31 -> 96.556859 | M30: =M17*$E$31 -> 104.28141
A31: D&A % of Revenue | E31: =E30/E17 -> 0.064243931
A33: CapEx | B33: ='Financial Summary'!L34 -> 10.44 | C33: ='Financial Summary'!K34 -> 6.88 | D33: ='Financial Summary'!J34 -> 27.89 | E33: ='Financial Summary'!I34 -> 27.68 | F33: =E17*$E$34 -> 27.68 | G33: =F17*$E$34 -> 29.8944 | H33: =G17*$E$34 -> 32.285952 | I33: =H17*$E$34 -> 34.868828 | J33: =I17*$E$34 -> 37.658334 | K33: =J17*$E$34 -> 40.671001 | L33: =K17*$E$34 -> 43.924681 | M33: =L17*$E$34 -> 47.438656
A34: Capex % of Revenue | E34: =E33/E17 -> 0.031563223
A37: NWC | B37: =('Balance Sheet'!L22+'Balance Sheet'!L23+'Balance Sheet'!L27+'Balance Sheet'!L28+'Balance Sheet'!L33)-('Balance Sheet'!L77+'Balance Sheet'!L89+'Balance Sheet'!L90) -> 120.84 | C37: =('Balance Sheet'!K22+'Balance Sheet'!K23+'Balance Sheet'!K27+'Balance Sheet'!K28+'Balance Sheet'!K33)-('Balance Sheet'!K77+'Balance Sheet'!K89+'Balance Sheet'!K90) -> 246.74 | D37: =('Balance Sheet'!J22+'Balance Sheet'!J23+'Balance Sheet'!J27+'Balance Sheet'!J28+'Balance Sheet'!J33)-('Balance Sheet'!J77+'Balance Sheet'!J89+'Balance Sheet'!J90) -> 281.19 | E37: =('Balance Sheet'!I22+'Balance Sheet'!I23+'Balance Sheet'!I27+'Balance Sheet'!I28+'Balance Sheet'!I33)-('Balance Sheet'!I77+'Balance Sheet'!I89+'Balance Sheet'!I90) -> 380.62
A38: ΔNWC | C38: =C37-B37 -> 125.9 | D38: =D37-C37 -> 34.45 | E38: =E37-D37 -> 99.43 | F38: =E17*$E$40 -> 100.91961 | G38: =F17*$E$40 -> 108.99318 | H38: =G17*$E$40 -> 117.71264 | I38: =H17*$E$40 -> 127.12965 | J38: =I17*$E$40 -> 137.30002 | K38: =J17*$E$40 -> 148.28402 | L38: =K17*$E$40 -> 160.14674 | M38: =L17*$E$40 -> 172.95848
A39: ΔNWC % of Revenue | C39: =C38/C17 -> 0.19245762 | D39: =D38/D17 -> 0.039396192 | E39: =E38/E17 -> 0.11337902
A40: Avg ΔNWC as % of Revenue | E40: =AVERAGE(C39:E39) -> 0.11507761
N42: Terminal Value | O42: PV of Terminal Value
A43: FCFF | F43: =F27*(1-$E$63)+F30-F33-F38 -> 289.47829 | G43: =G27*(1-$E$63)+G30-G33-G38 -> 312.63655 | H43: =H27*(1-$E$63)+H30-H33-H38 -> 337.64748 | I43: =I27*(1-$E$63)+I30-I33-I38 -> 364.65927 | J43: =J27*(1-$E$63)+J30-J33-J38 -> 393.83202 | K43: =K27*(1-$E$63)+K30-K33-K38 -> 425.33858 | L43: =L27*(1-$E$63)+L30-L33-L38 -> 459.36566 | M43: =M27*(1-$E$63)+M30-M33-M38 -> 496.11492 | N43: =M43*(1+$B$6)/($B$5-$B$6) -> 12922.734 | O43: =N43*M45 -> 7846.5119
A45: Discount Factor | F45: =1/(1+$B$5)^1 -> 0.93954001 | G45: =1/(1+$B$5)^2 -> 0.88273542 | H45: =1/(1+$B$5)^3 -> 0.82936524 | I45: =1/(1+$B$5)^4 -> 0.77922183 | J45: =1/(1+$B$5)^5 -> 0.73211008 | K45: =1/(1+$B$5)^6 -> 0.68784671 | L45: =1/(1+$B$5)^7 -> 0.6462595 | M45: =1/(1+$B$5)^8 -> 0.60718665
N46: Enterprise Value
A47: PV of FCFF | F47: =F43*F45 -> 271.97643 | G47: =G43*G45 -> 275.97536 | H47: =H43*H45 -> 280.03308 | I47: =I43*I45 -> 284.15046 | J47: =J43*J45 -> 288.32839 | K47: =K43*K45 -> 292.56774 | L47: =L43*L45 -> 296.86942 | M47: =M43*M45 -> 301.23435 | N47: =SUM(F47:M47) -> 2291.1352
A50: Year | B50: 2017
A51: Total Debt | B51: ='Financial Summary'!I29 -> 693.28
A52: Cash & Cash Equivalents | B52: ='Financial Summary'!I26 -> 148.7
A53: Net Debt | B53: =B51-B52 -> 544.58
A54: Equity Value | B54: =N47-B53 -> 1746.5552
A55: Shares Outstanding | B55: ='Financial Summary'!I59 -> 81.63
A56: Equity Value Per Share | B56: =B54/B55 -> 21.395997
A59: Sensitivity Analysis
A61: Annual Synergies | B61: Enterprise Value | C61: Deal Value | D61: Base EV | E61: =O43+N47 -> 10137.647
A62: 0 | B62: =$E$61+(A62*(1-$E$63)/$E$62) -> 10137.647 | C62: 14600 | D62: WACC | E62: =B5 -> 0.064350633
A63: 100 | B63: =$E$61+(A63*(1-$E$63)/$E$62) -> 11303.137 | C63: 14600 | D63: Tax Rate | E63: =B11 -> 0.25
A64: 200 | B64: =$E$61+(A64*(1-$E$63)/$E$62) -> 12468.627 | C64: 14600
A65: 300 | B65: =$E$61+(A65*(1-$E$63)/$E$62) -> 13634.116 | C65: 14600
A66: 400 | B66: =$E$61+(A66*(1-$E$63)/$E$62) -> 14799.606 | C66: 14600
A67: 500 | B67: =$E$61+(A67*(1-$E$63)/$E$62) -> 15965.096 | C67: 14600
A68: 600 | B68: =$E$61+(A68*(1-$E$63)/$E$62) -> 17130.585 | C68: 14600
A69: 700 | B69: =$E$61+(A69*(1-$E$63)/$E$62) -> 18296.075 | C69: 14600
A73: WACC Calulation
A75: Rf | B75: =B7 -> 0.0425
A76: Rm-Rf | B76: =B8 -> 0.055
A77: Beta | B77: =B9 -> 0.74
A78: Re | B78: =B75+B77*(B76) -> 0.0832
A79: Rd | B79: =B10 -> 0.038512578
A80: Tc | B80: =B11 -> 0.25
A81: After Tax Rd | B81: =B79*(1-B80) -> 0.028884433
A82: Price Per Share (pre merger) | B82: 15.98
A83: Outstanding Shares (2017) | B83: ='Financial Summary'!I59 -> 81.63
A84: E | B84: =B83*B82 -> 1304.4474
A85: D | B85: ='Financial Summary'!I29 -> 693.28
A86: V | B86: =B84+B85 -> 1997.7274
A87: E/V | B87: =B84/B86 -> 0.65296566
A88: D/V | B88: =B85/B86 -> 0.34703434
A89: WACC | B89: =(B87*B78)+(B88*B79*(1-B80)) -> 0.064350633

Sheet FCFF
B1: 2018E | C1: 2019E | D1: 2020E | E1: 2021E | F1: 2022E | G1: 2023E | H1: 2024E | I1: 2025E
A2: Free Cash Flow To The Firm (FCFF)
A3: EBIT*(1-Tax Rate) | B3: =Analysis!F27*(1-Analysis!$E$63) -> 357.2307 | C3: =Analysis!G27*(1-Analysis!$E$63) -> 385.80916 | D3: =Analysis!H27*(1-Analysis!$E$63) -> 416.67389 | E3: =Analysis!I27*(1-Analysis!$E$63) -> 450.0078 | F3: =Analysis!J27*(1-Analysis!$E$63) -> 486.00842 | G3: =Analysis!K27*(1-Analysis!$E$63) -> 524.8891 | H3: =Analysis!L27*(1-Analysis!$E$63) -> 566.88023 | I3: =Analysis!M27*(1-Analysis!$E$63) -> 612.23064
A4: [+] Depreciation | B4: =Analysis!F30 -> 60.8472 | C4: =Analysis!G30 -> 65.714976 | D4: =Analysis!H30 -> 70.972174 | E4: =Analysis!I30 -> 76.649948 | F4: =Analysis!J30 -> 82.781944 | G4: =Analysis!K30 -> 89.404499 | H4: =Analysis!L30 -> 96.556859 | I4: =Analysis!M30 -> 104.28141
A5: [-] Changes in Working Capital | B5: =Analysis!F38 -> 100.91961 | C5: =Analysis!G38 -> 108.99318 | D5: =Analysis!H38 -> 117.71264 | E5: =Analysis!I38 -> 127.12965 | F5: =Analysis!J38 -> 137.30002 | G5: =Analysis!K38 -> 148.28402 | H5: =Analysis!L38 -> 160.14674 | I5: =Analysis!M38 -> 172.95848
A6: [-] Capex | B6: =Analysis!F33 -> 27.68 | C6: =Analysis!G33 -> 29.8944 | D6: =Analysis!H33 -> 32.285952 | E6: =Analysis!I33 -> 34.868828 | F6: =Analysis!J33 -> 37.658334 | G6: =Analysis!K33 -> 40.671001 | H6: =Analysis!L33 -> 43.924681 | I6: =Analysis!M33 -> 47.438656
A7: Free Cashflow to the Firm (FCFF) | B7: =B3+B4-B5-B6 -> 289.47829 | C7: =C3+C4-C5-C6 -> 312.63655 | D7: =D3+D4-D5-D6 -> 337.64748 | E7: =E3+E4-E5-E6 -> 364.65927 | F7: =F3+F4-F5-F6 -> 393.83202 | G7: =G3+G4-G5-G6 -> 425.33858 | H7: =H3+H4-H5-H6 -> 459.36566 | I7: =I3+I4-I5-I6 -> 496.11492
